Workbook
Name Check1_1: #REF!
Name Check2_1: #REF!
Name Check3_1: #REF!
Name Check4_1: #REF!
Name check5: #REF!
Name Check5_1: #REF!
Name Check6_1: #REF!
Name Check7_1: #REF!
Name oijjjojoijpojpoi: #REF!
Name Plat_LastSaved: #REF!
Name Test: #REF!
Name Test4: #REF!

Sheet Overview
D3: Prospect Name/Number: | Q3: 32-11N-25W / Diversified
C5: Section | H5: 32 | L5: Township | R5: 11N | Y5: Range | AC5: 25W
D7: County | H7: Beckham | U7: State | X7: Oklahoma
B9: Containing 640.00 acres, more or less
X15: T1: N/2 NE/4 + SW/4 NE/4 120 ac
R22: T2: SE/4 NE/4 + E/2 SE/4 120 ac
E26: T4: SW/4 160 ac | M26: T3: NW/4 160 ac
X34: T5: W/2 SE/4 80 ac
B44: ATTACHMENTS: | I44: OWNERSHIP REPORT DATED: | Y44: LAST ENTRY:
I46: TITLE OPINION UPDATE DATED: | Y46: LAST ENTRY:
G48: x | I48: CURSORY REPORT DATED: | S48: 46218.208 | Y48: LAST ENTRY: | AC48: 2485/685
I50: COUNTY CERTIFICATION DATE:
B52: REMARKS: | F52: HOLD_NO_RELEASE — source-limited cursory update through 2026-07-15. Diversified Production LLC is supported only through the OK48147.001.1 identity path (2395/415–464; 2400/551–567); exact WI, NRI, ORRI and net acres remain NOT DETERMINED. 1697/236 is an assignment, not a proved base OGL. Carlson 32-11-25 7H carve (2183/174; 2185/639) remains unmapped to OK48147.001.1. Current tract display is gross reporting control only; mineral-title tract control remains OPEN. Local OCC RBDMS snapshot 2026-07-09 lists 11 Section 32 records. Historical OCC Cause CD 59995 / Order 156126 was reviewed, but current order effect, other orders, production continuity and lease-by-lease HBP remain NEEDS VERIFICATION.
B56: EXAMINER: | F56: NHE

Sheet Title 
B4: TRACT 1: | C4: N/2 NE/4 and SW/4 NE/4
B5: Containing: | C5: 120.00 acres, more or less
B7: Mineral Owner | C7: Net Acres | D7: OGL No. | E7: Royalty | F7: Expiration | G7: Comments
B8: Hanks, Darrell Lee, et al. | G8: SURFACE OWNER ONLY — MINERAL OWNERSHIP OPEN. Addr: 3704 S.E. 34th Ave., Amarillo, TX 79103. Assessor Acct. 050005625; Bk. 2290/P.494 (surface/current-owner lead only)
B9: Mineral / leasehold chain | G9: Historical Crook/Randel lease refs (264/345; 352/719; 352/721) — lessor chain OPEN. Diversified OK48147.001.1 path may burden leasehold but tract-level WI/NRI/net acres OPEN (2395/462; 2400/566).
B27: REPORT TOTAL | C27: =SUM(C8:C25) | G27: OPEN / SOURCE-LIMITED — REPORT TOTAL formula preserved; blank owner NMA ≠ zero proof.
B28: TOTAL | C28: =SUM(C8:C25)
B31: TRACT 2: | C31: SE/4 NE/4 and E/2 SE/4
B32: Containing: | C32: 120.00 acres, more or less
B34: Mineral Owner | C34: Net Acres | D34: OGL No. | E34: Royalty | F34: Expiration | G34: Comments
B35: Crook, Ola Mae | G35: SURFACE OWNER ONLY — MINERAL OWNERSHIP OPEN. Addr: 11277 N 1750 Rd., Sayre, OK 73662-4033. Assessor Accts. 050005631 / 050005630; Bk. 2111/P.585 (surface/current-owner lead only)
B36: Acciona Wind Energy USA LLC | G36: SURFACE OWNER ONLY — MINERAL OWNERSHIP OPEN. Addr: 55 E. Monroe St., Suite 1925, Chicago, IL 60603. Assessor Acct. 050020323; Bk. 2052/P.466 — SURFACE/WIND ONLY; no mineral interest attributed
B37: Mineral / leasehold chain | G37: Pearl wellbore/depth branch historical (845/47; 872/279) — not present WI. Diversified OK48147.001.1 path may burden leasehold but tract-level WI/NRI/net acres OPEN (2395/462; 2400/566).
B50: REPORT TOTAL | C50: =SUM(C35:C49) | G50: OPEN / SOURCE-LIMITED — REPORT TOTAL formula preserved; blank owner NMA ≠ zero proof.
B51: TOTAL | C51: =SUM(C35:C49)
B54: TRACT 3: | C54: NW/4
B55: Containing: | C55: 160.00 acres, more or less
B57: Mineral Owner | C57: Net Acres | D57: OGL No. | E57: Royalty | F57: Expiration | G57: Comments
B58: Maddoux, Gerry L., Living Trust | G58: SURFACE OWNER ONLY — MINERAL OWNERSHIP OPEN. Addr: 9055 N Morning Glory Rd., Paradise Valley, AZ 85253. Assessor Acct. 050005626 (surface/current-owner lead only)
B59: Sumpter, Elizabeth | G59: SURFACE OWNER ONLY — MINERAL OWNERSHIP OPEN. Addr: 11224 N 1740 Rd., Sweetwater, OK 73666. Assessor Acct. 050005628; Bk. 2302/P.166 (surface/current-owner lead only)
B60: Johnson, Abby Colleen | G60: SURFACE OWNER ONLY — MINERAL OWNERSHIP OPEN. Addr: 708 N State Ave., Apt. 5, Weatherford, OK 73096. Assessor Acct. 050024355; Bk. 2483/P.572 (surface/current-owner lead only)
B61: Mineral / leasehold chain | G61: Historical N/2 below-top-Hunton branch OPEN (502/265; 839/188; 1014/75). Diversified OK48147.001.1 path may burden leasehold but tract-level WI/NRI/net acres OPEN (2395/462; 2400/566).
B72: REPORT TOTAL | C72: =SUM(C58:C71) | G72: OPEN / SOURCE-LIMITED — REPORT TOTAL formula preserved; blank owner NMA ≠ zero proof.
B73: TOTAL | C73: =SUM(C58:C71)
B75: TRACT 4: | C75: SW/4
B76: Containing: | C76: 160.00 acres, more or less
B79: Mineral Owner | C79: Net Acres | D79: OGL No. | E79: Royalty | F79: Expiration | G79: Comments
B80: Maddoux, Gerry L., Living Trust | G80: SURFACE OWNER ONLY — MINERAL OWNERSHIP OPEN. Addr: 9055 N Morning Glory Rd., Paradise Valley, AZ 85253. Assessor Acct. 050005627 (surface/current-owner lead only)
B81: Maddoux, Gail, Trustee of Revocable Trust | G81: SURFACE OWNER ONLY — MINERAL OWNERSHIP OPEN. Addr: P.O. Box 111078, Naples, FL 34108-0000. Assessor Acct. 050005632; Bk. 1868/P.526 (surface/current-owner lead only)
B82: Sumpter, Elizabeth | G82: SURFACE OWNER ONLY — MINERAL OWNERSHIP OPEN. Addr: 11224 N 1740 Rd., Sweetwater, OK 73666. Assessor Acct. 050005629; Bk. 2391/P.68 (surface/current-owner lead only)
B83: Mineral / leasehold chain | G83: Overlapping historical OGL refs (307/31; 340/302 et seq.) — not additive NMA. Diversified OK48147.001.1 path may burden leasehold but tract-level WI/NRI/net acres OPEN (2395/462; 2400/566).
B89: REPORT TOTAL | C89: =SUM(C81:C88) | G89: OPEN / SOURCE-LIMITED — REPORT TOTAL formula preserved; blank owner NMA ≠ zero proof.
B90: TOTAL | C90: =SUM(C81:C88)
B92: TRACT 5: | C92: W/2 SE/4
B93: Containing: | C93: 80.00 acres, more or less
B96: Mineral Owner | C96: Net Acres | D96: OGL No. | E96: Royalty | F96: Expiration | G96: Comments
B97: Sumpter, Elizabeth | G97: SURFACE OWNER ONLY — MINERAL OWNERSHIP OPEN. Addr: 11224 N 1740 Rd., Sweetwater, OK 73666. Assessor parcel within Acct. 050005629; Bk. 2391/P.68 (surface/current-owner lead only)
B98: Mineral / leasehold chain | G98: Historical LeGrand/Union/Leede refs (307/31; 872/279) — base OGL terms OPEN. Diversified OK48147.001.1 path may burden leasehold but tract-level WI/NRI/net acres OPEN (2395/462; 2400/566).
B112: REPORT TOTAL | C112: =SUM(C97:C111) | G112: OPEN / SOURCE-LIMITED — REPORT TOTAL formula preserved; blank owner NMA ≠ zero proof.
B113: TOTAL | C113: =SUM(C97:C111)
B115: Working Interest: As to the Cherokee
B117: Owner | C117: Net Acres | D117: Base OGL's | E117: Royalty | F117: Expiration | G117: Comments
B118: Diversified Production LLC | D118: OK48147.001.1 | G118: Record-derived leasehold claimant via DP Sooner HoldCo (Bk 2395/415–464 schedule p.2395/462; Bk 2400/551–567 schedule p.2400/566). Addr of record: 1600 Corporate Drive, Birmingham, AL 35242. Exact WI/NRI/ORRI/net acres NOT DETERMINABLE. 1697/236 is Assignment (Staghorn→CHK), not base OGL. Carlson 7H wellbore carve 2183/174 + 2185/639. Do not use 48.75% or 51.25% residual as present WI.
B119: Historical CHK / Tapstone / OCM / wellbore branches | G119: See OGL / WI / Runsheet. Parallel FourPoint/Unbridled/MNR/Canvas/DP Ponies not merged into Diversified WI.
B127: REPORT TOTAL | C127: =SUM(C118:C126) | G127: OPEN / SOURCE-LIMITED — REPORT TOTAL formula preserved; blank owner NMA ≠ zero proof.
B128: TOTAL | C128: =SUM(C118:C126)
B131: Notes | C131: HOLD_NO_RELEASE — disclosed cursory update through 2026-07-15. Diversified Production LLC is supported on the OK48147.001.1 identity path (2395/415–464; 2400/551–567), but exact WI/NRI/ORRI/net acres are NOT DETERMINED. Base OGL is unproved; 1697/236 is an assignment. OCM Denali 48.75% at 2371/495 is NOT Diversified present WI. Carlson 7H carve (2183/174; 2185/639) is wellbore-limited and OK48147 is absent from its exhibit. Surface names are surface-only leads; fee minerals remain OPEN. Current five-tract display is gross reporting control, not proved mineral-title tract control. Index Page 48 and lease-by-lease HBP remain OPEN.
B132: Full 1,981-entry index: 03_INDEX_RECONCILIATION\SECTION_32_INDEX_MASTER.xlsx. Expanded Runsheet retained in donor/support workbooks — not forced into template A1:J145.

Sheet OGL
A1: OGL # | B1: LH | C1: Image # | D1: Instrument | E1: Bk./Pg. | F1: Execution Date | G1: Filing Date | H1: Grantor | I1: Grantee | J1: Legal Description | K1: Misc. Notes | L1: Term | M1: Gross Acres | N1: Tracts | O1: Exp Date | P1: Net Mineral Acres | Q1: Royalty | V1: Depth Clause | W1: Option to Extend | X1: No Warranty Clause | Y1: Top Lease Clause
A2: 1 | B2: 872/279 — lease exhibit reference | C2: L-007 imgs 4388–4393; L-001 imgs 1940–1943 where applicable | D2: LEASE REFERENCE ONLY | E2: 63/33 | F2: 17484 | H2: Garretts | I2: C.E. McKinley | J2: E/2 SE/4 | K2: Original lease not reviewed. Lease date/legal are exhibit references, not a lease-specific page isolation. Recording date, term, royalty, clauses, expiration, NMA and HBP remain open. Nominal acreage is an express aliquot assumption. | M2: 80 | N2: 2 | V2: Later assignment treatment only: Below 11,100 ft in later assignment exhibit; original lease depth clause OPEN
A3: 2 | B3: 872/279 — lease exhibit reference | C3: L-007 imgs 4388–4393; L-001 imgs 1940–1943 where applicable | D3: LEASE REFERENCE ONLY | E3: 264/345 | F3: 26334 | H3: Charlie B. and Ina Pearl Crook | I3: Union | J3: NE/4 | K3: Original lease not reviewed. Lease date/legal are exhibit references, not a lease-specific page isolation. Recording date, term, royalty, clauses, expiration, NMA and HBP remain open. Nominal acreage is an express aliquot assumption. | M3: 160 | N3: 1–2 | V3: Later assignment treatment only: Later deep assignment subject; original lease depth clause OPEN
A4: 3 | B4: 872/279 — lease exhibit reference | C4: L-007 imgs 4388–4393; L-001 imgs 1940–1943 where applicable | D4: LEASE REFERENCE ONLY | E4: 307/31 | F4: 27879 | H4: Cora B. LeGrand | I4: Union | J4: W/2 SE/4 and S/2 SW/4 | K4: Original lease not reviewed. Lease date/legal are exhibit references, not a lease-specific page isolation. Recording date, term, royalty, clauses, expiration, NMA and HBP remain open. Nominal acreage is an express aliquot assumption. | M4: 160 | N4: 4–5 | V4: Later assignment treatment only: Later deep assignment subject; original lease depth clause OPEN
A5: 4 | B5: 872/279 — lease exhibit reference | C5: L-007 imgs 4388–4393; L-001 imgs 1940–1943 where applicable | D5: LEASE REFERENCE ONLY | E5: 340/302 | F5: 28412 | H5: Gertrude L. LaFortune et al. | I5: Union | J5: N/2 SW/4 | K5: Original lease not reviewed. Lease date/legal are exhibit references, not a lease-specific page isolation. Recording date, term, royalty, clauses, expiration, NMA and HBP remain open. Nominal acreage is an express aliquot assumption. | M5: 80 | N5: 4 | V5: Later assignment treatment only: Later deep assignment subject; original lease depth clause OPEN
A6: 5 | B6: 872/279 — lease exhibit reference | C6: L-007 imgs 4388–4393; L-001 imgs 1940–1943 where applicable | D6: LEASE REFERENCE ONLY | E6: 340/304 | F6: 28412 | H6: Gertrude LaFortune, widow | I6: Union | J6: N/2 SW/4 | K6: Original lease not reviewed. Lease date/legal are exhibit references, not a lease-specific page isolation. Recording date, term, royalty, clauses, expiration, NMA and HBP remain open. Nominal acreage is an express aliquot assumption. | M6: 80 | N6: 4 | V6: Later assignment treatment only: Overlap/chain relationship must be read; original lease depth clause OPEN
A7: 6 | B7: 872/279 — lease exhibit reference | C7: L-007 imgs 4388–4393; L-001 imgs 1940–1943 where applicable | D7: LEASE REFERENCE ONLY | E7: 340/323 | F7: 28397 | H7: George T. Harrison Jr. and Renata Harrison | I7: Union | J7: N/2 NW/4 and N/2 SW/4 | K7: Original lease not reviewed. Lease date/legal are exhibit references, not a lease-specific page isolation. Recording date, term, royalty, clauses, expiration, NMA and HBP remain open. Nominal acreage is an express aliquot assumption. | M7: 160 | N7: 3–4 | V7: Later assignment treatment only: Later deep assignment subject; original lease depth clause OPEN
A8: 7 | B8: 872/279 — lease exhibit reference | C8: L-007 imgs 4388–4393; L-001 imgs 1940–1943 where applicable | D8: LEASE REFERENCE ONLY | E8: 342/564 | F8: 28397 | H8: Carol Seidenbach Leach | I8: Union | J8: N/2 SW/4 | K8: Original lease not reviewed. Lease date/legal are exhibit references, not a lease-specific page isolation. Recording date, term, royalty, clauses, expiration, NMA and HBP remain open. Nominal acreage is an express aliquot assumption. | M8: 80 | N8: 4 | V8: Later assignment treatment only: Later deep assignment subject; original lease depth clause OPEN
A9: 8 | B9: 872/279 — lease exhibit reference | C9: L-007 imgs 4388–4393; L-001 imgs 1940–1943 where applicable | D9: LEASE REFERENCE ONLY | E9: 342/566 | F9: 28430 | H9: Cynthia Seidenbach Kruse | I9: Union | J9: N/2 SW/4 | K9: Original lease not reviewed. Lease date/legal are exhibit references, not a lease-specific page isolation. Recording date, term, royalty, clauses, expiration, NMA and HBP remain open. Nominal acreage is an express aliquot assumption. | M9: 80 | N9: 4 | V9: Later assignment treatment only: Later deep assignment subject; original lease depth clause OPEN
A10: 9 | B10: 872/279 — lease exhibit reference | C10: L-007 imgs 4388–4393; L-001 imgs 1940–1943 where applicable | D10: LEASE REFERENCE ONLY | E10: 352/719 | F10: 28626 | H10: F.L. Randel | I10: Union | J10: NE/4 | K10: Original lease not reviewed. Lease date/legal are exhibit references, not a lease-specific page isolation. Recording date, term, royalty, clauses, expiration, NMA and HBP remain open. Nominal acreage is an express aliquot assumption. | M10: 160 | N10: 1–2 | V10: Later assignment treatment only: Later deep assignment subject; original lease depth clause OPEN
A11: 10 | B11: 872/279 — lease exhibit reference | C11: L-007 imgs 4388–4393; L-001 imgs 1940–1943 where applicable | D11: LEASE REFERENCE ONLY | E11: 352/721 | F11: 28626 | H11: J.L. Randel | I11: Union | J11: NE/4 | K11: Original lease not reviewed. Lease date/legal are exhibit references, not a lease-specific page isolation. Recording date, term, royalty, clauses, expiration, NMA and HBP remain open. Nominal acreage is an express aliquot assumption. | M11: 160 | N11: 1–2 | V11: Later assignment treatment only: Later deep assignment subject; original lease depth clause OPEN
A12: 11 | B12: 872/279 — lease exhibit reference | C12: L-007 imgs 4388–4393; L-001 imgs 1940–1943 where applicable | D12: LEASE REFERENCE ONLY | E12: 376/369 | F12: 28935 | H12: Great Western Oil & Gas | I12: Union | J12: NE/4 | K12: Original lease not reviewed. Lease date/legal are exhibit references, not a lease-specific page isolation. Recording date, term, royalty, clauses, expiration, NMA and HBP remain open. Nominal acreage is an express aliquot assumption. | M12: 160 | N12: 1–2 | V12: Later assignment treatment only: Later deep assignment subject; original lease depth clause OPEN
A13: OPEN | B13: OK48147.001.1 schedule cites 1697/236 — Assignment I-2001-004316 (Staghorn→CHK), NOT a base OGL. True base oil & gas lease for this modern lease ID remains OPEN.
A14: OPEN | B14: Carlson 32-11-25 7H wellbore carve: I-2015-000819 / I-2015-001373 (2185/639). Intersection with OK48147/Garrett leasehold unmapped; do not compute full-leasehold WI.
A15: OPEN | B15: CHK → Tapstone Energy → DP Legacy Tapstone facial bridge for OK48147.001.1 is not page-proven from available images (index/long-description cluster only).

Sheet PLAT
B22: SECTION 32-11N-25W TRACT CONTROL (GROSS ALIQUOTS; NOT OWNERSHIP)
B23: Tract 1 | C23: N/2 NE/4 + SW/4 NE/4 | G23: 120 ac
B24: Tract 2 | C24: SE/4 NE/4 + E/2 SE/4 | G24: 120 ac
B25: Tract 3 | C25: NW/4 | G25: 160 ac
B26: Tract 4 | C26: SW/4 | G26: 160 ac
B27: Tract 5 | C27: W/2 SE/4 | G27: 80 ac
B28: Total gross acres = 640
B29: Plat source: _PROJECT_FILES\01_SOURCE_READ_ONLY\PLAT_AND_TAX\Section_32_T11N_R25W_Original_GLO_Plat_Crop.png
B30: NOTE: Surface assessor names are NOT proved mineral ownership. Generic template Sec. 18 placeholder map removed.
B31: TRACT CONTROL CONFLICT — displayed aliquots are gross reporting control only and are not proved mineral-title tract control. A conflicting Template/tract-chain system remains documented and OPEN; examiner verification is required. Source: _PROJECT_FILES\03_QA_AND_SUPPORT\FINAL_COMPLETION_PACKAGE\TRACT_CONTROL_DECISION.md

Sheet Runsheet
B1: OGL | C1: Doc Type | D1: Bk/Pg. | E1: Effective Date | F1: Recorded Date | G1: Grantor | H1: Grantee | I1: Legal Description | J1: Notes
A2: 81 | C2: Confirmation of Division / Confirmatory Conveyance | D2: 2395/415–464 | F2: 44883 | G2: DP Legacy Tapstone LLC | H2: Diversified ABS VI Upstream LLC; DP Sooner HoldCo LLC | I2: All 16 Q-Q ticks; long description | J2: I-2022-004838 Confirmation of Division (ER-01 IMAGE). OK48147.001.1 on Exhibit E at 2395/462; interest columns blank. ABS VI — no Sec 32 well on 2395/450. Financing termination 2395/967 is separate.
A3: 86 | C3: Confirmation of Merger / Confirmatory Conveyance | D3: 2400/551–567 | F3: 44987 | G3: DP Sooner HoldCo LLC | H3: Diversified Production LLC | I3: Long description | J3: I-2023-000796 Confirmation of Merger (IMAGE). DP Sooner → Diversified Production LLC; Schedule B includes OK48147.001.1 at 2400/566; legal/interest blank. Quantum NOT YET CALCULABLE.
A4: 53 | C4: Wellbore Sale | D4: 2183/174 | F4: 42053 | G4: Chesapeake affiliates | H4: Linn Operating | I4: Section 32 index marks / extent varies | J4: CHK→Linn wellbore assignment/correction — Carlson 32-11-25 7H (API 35-009-2192300) carve; intersection with OK48147 OPEN.
A5: 54 | C5: Conveyance | D5: 2185/639 | F5: 42094 | G5: Chesapeake affiliates | H5: FourPoint Energy | I5: Section 32 index marks / extent varies | J5: CHK→Linn wellbore assignment/correction — Carlson 32-11-25 7H (API 35-009-2192300) carve; intersection with OK48147 OPEN.
A6: 65 | C6: Assignment | D6: 2371/495–513 | F6: 44573 | G6: Tapstone Energy; Tapstone Midstream | H6: OCM Denali Holdings LLC | I6: Section 32 | J6: Separate parallel instrument; schedule/estate open. | PUBLIC METADATA + INDEX | PHASE8: Tapstone→OCM Denali schedule lists OK48147.001.1 Sec32 (quantum OPEN).
A7: 75 | C7: Merger | D7: 2389/500–580 | F7: 44797 | G7: Diversified Production; DP Legacy Central; merger entities | H7: DP Legacy Tapstone LLC | I7: All Section 32 ticks | J7: Merger plan/certificate and title effect absent. | PUBLIC METADATA + INDEX
A8: 77 | C8: Amended Mortgage | D8: 2389/590–629 | F8: 44797 | G8: Diversified Production; DP Legacy Tapstone | H8: KeyBank | I8: Collateral schedule | J8: Direct Diversified encumbrance; references prior lien. | PUBLIC METADATA + INDEX — BURDEN | Financing/security — not WI vesting.
A9: 96 | C9: Wellbore Assignment | D9: 2434/751–760 | F9: 45526 | G9: Diversified Production; DP Legacy Central | H9: Teocalli Exploration | I9: Countywide long description | J9: Not indexed to subject section in supplied index; pull schedule before excluding. | COUNTYWIDE SCREEN
A10: 50 | C10: Assignment | D10: 1697/574 | F10: 37056 | G10: Staghorn Resources | H10: Chesapeake Exploration | I10: Section 32 index marks / extent varies | J10: Local Section 32 index reconciled; complete copy and schedules absent. Do not infer estate, quantum or operative effect. | INDEX ONLY S-002
A11: 58 | C11: Assignment | D11: 2340/403–433 | F11: 44179 | G11: Chesapeake affiliates | H11: Tapstone Energy LLC | I11: Section 32 index marks / extent varies | J11: Complete copy and schedules absent; county metadata proves only the facial record. Legal, estate, quantum and operative effect remain open. | PUBLIC METADATA + INDEX
A12: 64 | C12: Assignment | D12: 2371/470–494 | F12: 44573 | G12: KL CHK SPV LLC (local handwriting may read K3 CHK) | H12: Diversified Production LLC; OCM Denali Holdings LLC | I12: All 16 Q-Q ticks; long description | J12: County metadata supports KL CHK; local handwriting variant is preserved. Prior working materials reported 12/02/2021 as an instrument date, but it is not independently reconciled; fractions and schedules absent. | PUBLIC METADATA C-001 + INDEX
A13: 80 | C13: Release of Mortgage | D13: 2395/370–414 | F13: 44883 | G13: KeyBank | H13: DP Legacy Tapstone | I13: Collateral schedule | J13: Match collateral and released lien. | PUBLIC METADATA + INDEX | Financing/security — not WI vesting.
A14: 108 | C14: Assignment of OGL | D14: 244/432 | E14: 1969-11-25 exec / 1969-12-01 eff | F14: 1970-01 (day partially legible) | G14: Humble Oil & Refining Company | H14: Union Oil Company of California | I14: E/2 SE/4 Section 32-11N-25W | J14: DIRECT IMAGE 1062 (visually verified 2026-07-13). Assigns O&G lease L-91511 dated 1947-11-13, Cora B. Garrett & S.A. Garrett lessors, rec Bk 63/33. Confidence HIGH (parties/legal/books); MED recording day. Source: Images/1062.jpg
A15: 119 | C15: Assignment recital + Unit interest exhibit | D15: 792/096; also 809/241 | E15: OCC Order 156126 dated 1979-08-06 | F15: OPEN (books 792 & 809) | G15: OPEN — assignor on missing first page | H15: OPEN — assignee on missing first page | I15: Section 32-11N-25W (leases incl. Garrett Bk 63/33; INSOFAR AS cover Sec 32) | J15: [chron 1979-08-06] DIRECT IMAGE 3706 & 3952 (pixels verified, same recital in two recordings). References OCC Order 156126 / Cause CD 59995; Letter/Operating Agmt 1979-11-20 Leede/ENI; Farmout 1979-07-09 Union Oil/Leede. STATED Unit Operating Interest .0495703 (before payout)/.0371778 (after); Unit Net Revenue Interest .0371778/.0278833 — interest of the ASSIGNOR in that instrument, NOT attributed to any current owner. First page (parties/granting clause) NOT in local set. Confidence HIGH (text); assignor/assignee OPEN. Source: Images/3706.jpg, Images/3952.jpg
A16: 68 | C16: Mortgage | D16: 2371/554–588 | F16: 44573 | G16: Tapstone; Diversified Production | H16: KeyBank | I16: Collateral schedule | J16: Direct Diversified lien; applicability and release chain open. | PUBLIC METADATA + INDEX — BURDEN | Financing/security — not WI vesting.
A17: 69 | C17: Financing Statement | D17: 2371/589–625 | F17: 44573 | G17: Tapstone; Diversified Production | H17: KeyBank | I17: Collateral schedule | J17: Direct Diversified UCC/fixture filing; termination chain open. | PUBLIC METADATA + INDEX — BURDEN | Financing/security — not WI vesting.
A18: 78 | C18: Financing Statement | D18: 2389/630–671 | F18: 44797 | G18: DP Legacy Tapstone | H18: KeyBank | I18: Collateral schedule | J18: Collateral and termination must be matched. | PUBLIC METADATA + INDEX — BURDEN | Financing/security — not WI vesting.
A19: 82 | C19: Financing Statement Termination (NOT title conveyance) | D19: 2395/967–972 | F19: 44893 | G19: KeyBank National Association | H19: Tapstone Energy LLC; Diversified Production LLC | I19: Long description | J19: Financing-statement termination only (2395/967–972) — NOT a title conveyance. | PUBLIC METADATA + INDEX
A20: 83 | C20: Termination | D20: 2395/973–978 | F20: 44893 | G20: KeyBank | H20: DP Legacy Tapstone | I20: Financing/UCC | J20: Separate termination; do not treat 2395/967 as releasing it. | PUBLIC METADATA + INDEX
A21: 106 | C21: Affidavit | D21: 2480/824–883 | F21: 46091 | G21: DP Legacy Central; Diversified Production | H21: Public | I21: Countywide long description | J21: Sixty-page affidavit; subject applicability/effect open. | COUNTYWIDE SCREEN
A22: 128 | C22: Producing mineral-interest schedule | D22: 774/227 | E22: OPEN (schedule) | F22: OPEN (book 774) | G22: OPEN (schedule of an estate/owner) | H22: OPEN | I22: E/2 SE/4 (Cora Garrett lease) & N/2 NW/4 (Crook #1-32) Section 32-11N-25W | J22: [chron 1984-01-01] DIRECT IMAGE 3301 (pixels). Item 68: 5/640 int E/2 SE/4, Lease CORA GARRETT, Purchaser Union #19400, NRI .00175780. Item 70: 18/640 int N/2 NW/4, Lease CROOK #1-32, Purchaser Mesa #012600 (gas), NRI .00109870. Fractional owner NRI (NOT Diversified). Confidence HIGH. Source: Images/3301.jpg
A23: 100 | C23: Wellbore Assignment | D23: 2464/200–217 | F23: 45909 | G23: Stephens / Continental Properties affiliates | H23: Diversified Production LLC (metadata string) | I23: Countywide long description | J23: Potential acquisition; metadata parties ambiguous; schedule required. | COUNTYWIDE SCREEN
A24: 329 | C24: Wellbore Assignment | D24: 2151/865-869 | F24: 41698 | G24: BP AMERICA PRODUCTION COMPANY | H24: LINN ENERGY HOLDINGS LLC | I24: S32 T11N R25W | J24: OKCOUNTY API METADATA ONLY — indexed occurrence affecting Section 32. Document images and operative schedules were not purchased or reviewed; do not calculate title quantum from metadata alone.
A25: 14 | C25: Assignment/Reservation | D25: 987/159 | E25: 32113 | F25: 32115 | G25: TCW/Grantham/Carlson | H25: Leede Exploration | I25: McCall/Pearl/Crook table | J25: Historical Leede NRI/ORRI snapshot; corrected ending image. | DIRECT IMAGE L-009; imgs 4840–4852
A26: 51 | C26: Assignment | D26: 1783/118 | F26: 37830 | G26: Mobil Exploration Co. | H26: Chesapeake Exploration | I26: Section 32 index marks / extent varies | J26: Local Section 32 index reconciled; complete copy and schedules absent. Do not infer estate, quantum or operative effect. | INDEX ONLY S-002
A27: 52 | C27: Assignment | D27: 1784/959 | F27: 37851 | G27: Exxon Mobil Corp. | H27: Chesapeake Exploration | I27: Section 32 index marks / extent varies | J27: Local Section 32 index reconciled; complete copy and schedules absent. Do not infer estate, quantum or operative effect. | INDEX ONLY S-002
A28: 55 | C28: Assignment | D28: 2225/1 | F28: 42528 | G28: Chesapeake affiliates | H28: FourPoint Energy | I28: Section 32 index marks / extent varies | J28: Local Section 32 index reconciled; complete copy and schedules absent. Do not infer estate, quantum or operative effect. | INDEX ONLY S-002
A29: 59 | C29: Assignment | D29: 2340/490–519 | F29: 44179 | G29: Chesapeake affiliates | H29: KL CHK SPV LLC (local handwriting may read K3 CHK) | I29: Section 32 index marks / extent varies | J29: Complete copy and schedules absent; county metadata proves only the facial record. Legal, estate, quantum and operative effect remain open. | PUBLIC METADATA + INDEX
A30: 63 | C30: Release of Mortgage | D30: 2371/439–469 | F30: 44573 | G30: Bank of America | H30: Tapstone Energy LLC | I30: Blanket collateral | J30: Match released collateral to 2341/127–153. | PUBLIC METADATA + INDEX | Financing/security — not WI vesting.
A31: 79 | C31: Assignment | D31: 2393/1–698 | F31: 44851 | G31: ConocoPhillips; Louisiana Land & Exploration; Burlington Resources | H31: DP Legacy Central LLC | I31: 698-page schedule / Section 32 index entry | J31: Separate indexed acquisition branch; schedule must be searched for the subject. | PUBLIC METADATA + INDEX
A32: 97 | C32: Merger | D32: 2451/4–23 | F32: 45790 | G32: Diversified Energy Company PLC | H32: Public | I32: Long description / broad index ticks | J32: Merged/surviving entities and title effect absent. | PUBLIC METADATA C-005 + INDEX
A33: 107 | C33: Merger | D33: 2480/903–909 | F33: 46092 | G33: DP/Diversified/Canvas affiliates | H33: Public | I33: No indexed legal description | J33: Corporate effect may be global; plan/certificate required. | COUNTYWIDE SCREEN
A34: 120 | C34: Release and Agreement | D34: 395/618 | E34: 29180 | F34: 1979-12 (Beckham) | G34: Charlie B. Crook & Ima Pearl Crook | H34: Leede Exploration (released) | I34: NE/4 Section 32-11N-25W (Crook lease Bk 264/345) | J34: [chron 1979-11-21] DIRECT IMAGE 1575 (pixels verified). Crooks own surface + portion of minerals under NE/4 Sec 32. O&G lease 1972-02-05 rec Bk 264/345, Lessee Union Oil, covering SW/4 NW/4 & NW/4 SW/4 Sec 28 and NE/4 Sec 32; held by production from Number 1 Bruner Unit. Confidence HIGH. Source: Images/1575.jpg
A35: 141 | C35: Mineral Deed | D35: 1063/164-165 | E35: 32539 | F35: 32540 | G35: GARRETT, GERTRUDE | H35: FOWLER, JOHN; FOWLER, RUTH; GODWIN, JUANITA; KUYKENDALL, MILLARD E; ROBERTS, PAULINE; ROBERTS, ROYICE; STEWART, CARLENE | I35: S32 T11N R25W | J35: OKCOUNTY API METADATA ONLY — indexed occurrence affecting Section 32. Document images and operative schedules were not purchased or reviewed; do not calculate title quantum from metadata alone.
A36: 142 | C36: Mineral Deed | D36: 1063/166-167 | E36: 32520 | F36: 32540 | G36: GARRETT, CARL W | H36: STEWART, CARLENE | I36: S32 T11N R25W | J36: OKCOUNTY API METADATA ONLY — indexed occurrence affecting Section 32. Document images and operative schedules were not purchased or reviewed; do not calculate title quantum from metadata alone.
A37: 174 | C37: Mineral Deed | D37: 1283/4-5 | E37: 33903 | F37: 33904 | G37: GARRETT, CARL | H37: STEWART, CARLENE | I37: S32 T11N R25W | J37: OKCOUNTY API METADATA ONLY — indexed occurrence affecting Section 32. Document images and operative schedules were not purchased or reviewed; do not calculate title quantum from metadata alone.
A38: 256 | C38: Assignment Of Overriding Royalty Interest | D38: 1693/95-96 | E38: 36983 | F38: 37026 | G38: STAGHORN RESOURCES LLC | I38: 32-11N-25W | J38: OKCOUNTY API METADATA ONLY — indexed occurrence affecting Section 32. Document images and operative schedules were not purchased or reviewed; do not calculate title quantum from metadata alone.
A39: 327 | C39: Partial Release Of Mortgage | D39: 2146/23-39 | E39: 41628 | F39: 41646 | G39: UNION BANK N A | H39: CARMEN ACQUISITION LLC; CHESAPEAKE CLEMENTS ACQUISITION LLC; CHESAPEAKE EXPLORATION LIMITED PARTNERSHIP; CHESAPEAKE EXPLORATION LLC; CHESAPEAKE LOUISIANA L P; CHESAPEAKE ROYALTY LLC; EMPRESS LOUISIANA PROPERTIES L P; GOTHIC PRODUCTION LLC; MC LOUISIANA MINERALS LLC; MC MINERAL COMPANY LLC | I39: S32 T11N R25W | J39: OKCOUNTY API METADATA ONLY — indexed occurrence affecting Section 32. Document images and operative schedules were not purchased or reviewed; do not calculate title quantum from metadata alone. | Financing/security — not WI vesting.
A40: 56 | C40: Memorandum | D40: 2225/710 | F40: 42528 | G40: Chesapeake affiliates | H40: FourPoint Energy | I40: Section 32 index marks / extent varies | J40: Local Section 32 index reconciled; complete copy and schedules absent. Do not infer estate, quantum or operative effect. | INDEX ONLY S-002
A41: 60 | C41: Mortgage | D41: 2341/127–153 | F41: 44194 | G41: Tapstone Energy LLC | H41: Bank of America | I41: Blanket collateral / long description | J41: Collateral schedule and release chain open. | PUBLIC METADATA + INDEX | Financing/security — not WI vesting.
A42: 18 | C42: Assignment | D42: 1014/228 | G42: Mesa Operating Limited Partnership | H42: Leede Exploration | I42: Section 32 index marks / extent varies | J42: Local Section 32 index reconciled; complete copy and schedules absent. Do not infer estate, quantum or operative effect. | INDEX ONLY S-002
A43: 17 | C43: Assignment | D43: 1014/76 | G43: Union Oil & Chemical Co., Ltd. et al. | H43: Leede Exploration | I43: Section 32 index marks / extent varies | J43: Local Section 32 index reconciled; complete copy and schedules absent. Do not infer estate, quantum or operative effect. | INDEX ONLY S-002
A44: 29 | C44: Assignment of Liens | D44: 1022/800 | G44: Trust Company of the West, Trustee | H44: First City National Bank of Midland | I44: Section 32 index marks / extent varies | J44: Local Section 32 index reconciled; complete copy and schedules absent. Do not infer estate, quantum or operative effect. | INDEX ONLY S-002
A45: 30 | C45: Release of Liens | D45: 1022/802 | G45: Trust Company of the West, Trustee | H45: First City National Bank of Midland | I45: Section 32 index marks / extent varies | J45: Local Section 32 index reconciled; complete copy and schedules absent. Do not infer estate, quantum or operative effect. | INDEX ONLY S-002
A46: 20 | C46: Assignment | D46: 1016/13 | F46: 32268 | G46: Frazier, Robert H. | H46: Leede Exploration | I46: Section 32 index marks / extent varies | J46: Local Section 32 index reconciled; complete copy and schedules absent. Do not infer estate, quantum or operative effect. | INDEX ONLY S-002
A47: 21 | C47: Assignment | D47: 1016/18 | F47: 32268 | G47: Leede & Pine, Ltd. et al. | H47: Leede Exploration | I47: Section 32 index marks / extent varies | J47: Local Section 32 index reconciled; complete copy and schedules absent. Do not infer estate, quantum or operative effect. | INDEX ONLY S-002
A48: 22 | C48: Assignment | D48: 1016/25 | F48: 32268 | G48: Pine, Clyde A. et al. | H48: Leede Exploration | I48: Section 32 index marks / extent varies | J48: Local Section 32 index reconciled; complete copy and schedules absent. Do not infer estate, quantum or operative effect. | INDEX ONLY S-002
A49: 23 | C49: Assignment | D49: 1016/29 | F49: 32268 | G49: Consolidation of Leede Trusts | H49: Leede Exploration | I49: Section 32 index marks / extent varies | J49: Local Section 32 index reconciled; complete copy and schedules absent. Do not infer estate, quantum or operative effect. | INDEX ONLY S-002
A50: 24 | C50: Assignment | D50: 1016/33 | F50: 32268 | G50: McCall, Jack C. et al. | H50: Leede Exploration | I50: Section 32 index marks / extent varies | J50: Local Section 32 index reconciled; complete copy and schedules absent. Do not infer estate, quantum or operative effect. | INDEX ONLY S-002
A51: 25 | C51: Assignment | D51: 1016/38 | F51: 32268 | G51: Leede Exploration et al. | H51: Exxon Corp. | I51: Section 32 index marks / extent varies | J51: Local Section 32 index reconciled; complete copy and schedules absent. Do not infer estate, quantum or operative effect. | INDEX ONLY S-002
A52: 19 | C52: Assignment | D52: 1016/7 | F52: 32268 | G52: Ray, Charles E. | H52: Leede Exploration | I52: Section 32 index marks / extent varies | J52: Local Section 32 index reconciled; complete copy and schedules absent. Do not infer estate, quantum or operative effect. | INDEX ONLY S-002
A53: 26 | C53: Assignment | D53: 1016/90 | F53: 32268 | G53: Leede Exploration et al. | H53: Enco Gas Gathering Co. | I53: Section 32 index marks / extent varies | J53: Local Section 32 index reconciled; complete copy and schedules absent. Do not infer estate, quantum or operative effect. | INDEX ONLY S-002
A54: 28 | C54: Release of Liens | D54: 1017/328 | F54: 32310 | G54: First City National Bank of Midland | H54: Leede Exploration et al. | I54: Section 32 index marks / extent varies | J54: Local Section 32 index reconciled; complete copy and schedules absent. Do not infer estate, quantum or operative effect. | INDEX ONLY S-002
A55: 31 | C55: Release | D55: 1028/217 | F55: 32351 | G55: Tarco Oil & Gas Inc. | H55: Warlock Petroleum Corp. | I55: Section 32 index marks / extent varies | J55: Local Section 32 index reconciled; complete copy and schedules absent. Do not infer estate, quantum or operative effect. | INDEX ONLY S-002
A56: 32 | C56: Assignment | D56: 1137/65 | F56: 32878 | G56: Leede Exploration et al. | H56: TCW Royalty Co. et al. | I56: Section 32 index marks / extent varies | J56: Local Section 32 index reconciled; complete copy and schedules absent. Do not infer estate, quantum or operative effect. | INDEX ONLY S-002
A57: 35 | C57: Assignment | D57: 1217/304 | F57: 33444 | G57: Leede Exploration | H57: NICOR Exploration Co. | I57: Section 32 index marks / extent varies | J57: Local Section 32 index reconciled; complete copy and schedules absent. Do not infer estate, quantum or operative effect. | INDEX ONLY S-002
... A77: 105 | C77: Agreement | D77: 2476/121–130 | F77: 46045 | G77: Diversified Production; DP Ponies and four DP affiliates | H77: Same group; DP vs DE American Pharoah name variance | I77: All Section 32 ticks; long description | J77: Agreement only; not facially a conveyance; DP/DE American Pharoah source variance preserved; effect absent. | PUBLIC METADATA C-006 + INDEX
A78: 116 | C78: Release (O&G leases) | D78: 336/327 | E78: 28212 | F78: 1977-05 (Beckham) | G78: Texaco Inc. (f/k/a The Texas Company) | H78: Public (release of leasehold) | I78: S/2 SW/4 & W/2 SE/4 Section 32-11N-25W | J78: [chron 1977-03-28] DIRECT IMAGE 1399 (pixels verified). Releases Sec 32 leases: J.B. Palmer Bk 259/218 (renewal) and Bk 220/391. Confidence HIGH. Source: Images/1399.jpg
A79: 118 | C79: Release (O&G leases) | D79: 336/329 (rel #4669) | E79: 28244 | F79: 1977-05 (Beckham) | G79: Texaco Inc. | H79: Public (release of leasehold) | I79: S/2 SW/4 & W/2 SE/4 Section 32-11N-25W | J79: [chron 1977-04-29] DIRECT IMAGE 1436 (pixels verified). Releases Sec 32 leases: L. Frank Palmer Bk 259/184; Sharon Gail Key Bk 259/186; Betty Jean Ferguson Bk 259/407. Confidence HIGH. Source: Images/1436.jpg
A80: 132 | C80: Corrected Oil Lease | D80: 1039/20-23 | E80: 28935 | F80: 32402 | G80: GREAT WESTERN OIL AND GAS INC | H80: UNION OIL COMPANY OF CALIFORNIA | I80: S32 T11N R25W | J80: OKCOUNTY API METADATA ONLY — indexed occurrence affecting Section 32. Document images and operative schedules were not purchased or reviewed; do not calculate title quantum from metadata alone.
A81: 109 | C81: Mineral Deed (Exhibit A) | D81: 506/205 | E81: 29631 | F81: OPEN (exhibit page) | G81: Kevin Leede | H81: OPEN — grantee not on exhibit page | I81: N/2 NW/4 & N/2 SW/4; NE/4; W/2 SE/4 & S/2 SW/4 Section 32-11N-25W | J81: DIRECT IMAGE 1945 (visually verified). Exhibit A to Mineral Deed 1981-02-14. Tract1 11.6666 min ac (Bk444/65); Tract2 10.0 min ac (Bk442/4); Tract3 8.75 min ac (Bk446/202-203, Bk448/131). Confidence HIGH. Source: Images/1945.jpg
A82: 121 | C82: Assignment (wellbore + depth-limited) | D82: 471/330 | E82: 1981-05-28 (approx) | F82: 1981 (Beckham) | G82: Union Oil Company of California | H82: Leede Exploration | I82: Mesa-Leede #1 Crook wellbore, Section 32-11N-25W; Morrow-Springer interval 16,210-20,451 ft only | J82: [chron 1981-05-28] DIRECT IMAGE 1911 (pixels verified). Wellbore-only + depth-limited (Morrow-Springer 16,210-20,451 ft). Assignor RESERVES ORRI: 1/8 of 7/8 gas + 1/16 of 8/8 oil/casinghead. Adjacent to Bk 471/337 (superseded assignment corrected by 509/222). Confidence HIGH. Source: Images/1911.jpg
A83: 7 | C83: Correction Assignment | D83: 502/267 | E83: 29845 | F83: 29872 | G83: Union Oil Co. of California | H83: Leede Exploration | I83: Crook wellbore, 16,210–20,451 ft | J83: Corrects 471/330; original 05/28/1981; recording stamp reviewed. | DIRECT IMAGE L-001; imgs 1940–1943
A84: 6 | C84: Assignment of Interest | D84: 502/265 | E84: 29846 | F84: 29872 | G84: Leede Exploration | H84: Named royalty/ORRI owners | I84: Section 32 | J84: Royalty/ORRI allocation; after-payout Crook WI excluded; recording stamp reviewed. | DIRECT IMAGE L-004; imgs 1938–1939
A85: 8 | C85: Corrected ORRI Assignment | D85: 509/176 | E85: 29846 | F85: 29872 | G85: Leede Exploration | H85: Campbell/Park/Cone/Popham/Hickman | I85: Crook wellbore/depth | J85: 2.25% aggregate historical ORRI; recording stamp reviewed. | DIRECT IMAGE L-003; imgs 1946–1948
A86: 9 | C86: Correction Assignment | D86: 509/220 | E86: 29846 | F86: 29872 | G86: Leede Exploration | H86: Mesa/Petrofina/ENI/McCall/Midland/Sterling | I86: Crook wellbore/depth | J86: Historical participant allocation; payout/reversion; recording stamp reviewed. | DIRECT IMAGE L-002; imgs 1949–1952
A87: 127 | C87: Assignment of Interest (royalty/ORRI) | D87: 502/265 | E87: 1981-09-17 exec / eff first production | F87: 1981 (Beckham) | G87: Leede Exploration (a Partnership) | H87: Edward H. Leede 21.053%; Midland National Bank Trustee 52.632%; Pine/Hudgeons/Frazier/Ray/Morgan 5.263% each | I87: All of Section 32-11N-25W | J87: [chron 1981-09-17] DIRECT IMAGE 1938 (pixels). Assigns Leede's royalty + ORRI, all of Sec 32. Expressly does NOT cover the 'After Payout' WI Leede receives on payout of Mesa-Leede #1-32 Crook. Confidence HIGH. Source: Images/1938.jpg
A88: 110 | C88: Correction Assignment | D88: 509/222 | E88: 1981-09-17 exec / eff first runs Crook #1-32 | F88: OPEN | G88: Leede Exploration (Charles D. Ray, Partner-Land) | H88: OPEN — assignees per superseded assignment | I88: Section 32-11N-25W (Mesa-Leede Crook #1-32 well) | J88: DIRECT IMAGE 1951 (visually verified). Supersedes Assignment 1981-05-29 rec Bk 471/337. Effective as of first runs from Mesa-Leede Crook #1-32. Book 509/222 confirmed against pixels (was LOW, now HIGH). Confidence HIGH (content). Source: Images/1951.jpg
A89: 122 | C89: Mineral Deed (Exhibit A) | D89: 623/149 | E89: 30313 | F89: OPEN (exhibit page) | G89: Charles P. Walne | H89: Asher Land and Exploration Co. | I89: N/2 NW/4 & N/2 SW/4; NE/4; W/2 SE/4 & S/2 SW/4 Section 32-11N-25W | J89: [chron 1982-12-28] DIRECT IMAGE 2175 (pixels verified). Conveys 5% interest = 1.52083 net mineral acres. Same tracts as Bk 444/65, 442/4, 446/202-203, 448/131 (also referenced by Kevin Leede exhibit Bk 506/205). Confidence HIGH. Source: Images/2175.jpg
A90: 111 | C90: ORRI Conveyance/Assignment (recital) | D90: 987/160; 737/84,120,164,221 | E90: 1984-07-20 / 1984-07-24 | F90: 30893 | G90: Leede Exploration; Leede Oil & Gas Inc. | H90: Leede Oil & Gas Inc.; TCW Royalty Company | I90: Pearl #1-32 & Crook #1-32, Section 32-11N-25W (among multi-section wells) | J90: DIRECT IMAGE 4841 (visually verified). Recital of ORRI conveyances rec Bk 737 (Pg 84/120/164/221) 1984-07-30. Confidence HIGH. Source: Images/4841.jpg [cont. Image 4844 Bk 987/163 Leede NRI/ORRI table: Pearl #1-32 (Sec32,Lower Morrow) NRI 10.462093%, ORRI 0.052310%; Crook #1-32 (Sec32,Upper Morrow) NRI 0.000000%; McCall #1-29 (S/2 Sec29 & N/2 Sec32) NRI 8.629197%.]
A91: 113 | C91: Mortgage schedule (within Release 995/052) | D91: 995/053; 768/300; 962/016,046,115,152 | E91: 1984-11-13 / 1987-06-30 | F91: OPEN | G91: Leede Exploration Ltd. | H91: Vinson Supply Co.; First City National Bank of Midland | I91: Crook #1-32 & Pearl #1-32, Section 32-11N-25W | J91: DIRECT IMAGE 4869 (visually verified). Mortgage schedule within Release of Liens (995/052-053). Confidence HIGH. Source: Images/4869.jpg | Financing/security — not WI vesting.
A92: 133 | C92: Corrected Release Of Mortgage | D92: 1039/24-31 | E92: 31076 | F92: 32402 | G92: SEATTLE FIRST NATIONAL BANK | H92: ENI IDENTIFIED PROPERTIES PROGRAM 1979 IV; ENI JOINT VNTURE 1979 XII | I92: S32 T11N R25W | J92: OKCOUNTY API METADATA ONLY — indexed occurrence affecting Section 32. Document images and operative schedules were not purchased or reviewed; do not calculate title quantum from metadata alone. | Financing/security — not WI vesting.
A93: 11 | C93: Borehole Assignment | D93: 845/47 | E93: 31257 | F93: 31343 | G93: Cities Service Oil & Gas | H93: Leede Exploration | I93: E/2 SE/4; Pearl 11,100–19,480 ft | J93: 1/8 ORRI reservation; corrected source images. | DIRECT IMAGE L-006; imgs 4118–4119
A94: 10 | C94: Assignment | D94: 839/188 | E94: 31302 | F94: 31317 | G94: First City National Bank, Trustee | H94: Consolidation of Leede Trusts | I94: Royalty/ORRI under 502/265 | J94: Does not establish separate 1% participant WI transfer. | DIRECT IMAGE L-005; img 4103
A95: 12 | C95: Assignment | D95: 872/279 | E95: 31349 | F95: 31477 | G95: Union Oil Co. of California | H95: Leede Exploration | I95: Listed leases; top Morrow–19,480 ft | J95: Historical deep assignment; corrected source-image start. | DIRECT IMAGE L-007; imgs 4388–4393
A96: 124 | C96: Assignment of Liens | D96: 962/012 | E96: 31954 | F96: 1987 (Beckham) | G96: Trust Company of the West (Trustee, TCW Commingled Debt & Royalty Fund I) | H96: First City National Bank of Midland | I96: Pearl No. 1-32 & Crook No. 1-32, Section 32-11N-25W (among multi-section collateral) | J96: [chron 1987-06-26] DIRECT IMAGE 4613 (pixels verified). Assigns mortgages Bk 737/335, 738/29 (Pearl #1-32 Sec 32), 738/80 (Crook #1-32 Sec 32); $10MM note due 1991-03-31. Precedes Release Bk 995/052 (Image 4868). Confidence HIGH. Source: Images/4613.jpg
A97: 112 | C97: Release of Liens | D97: 995/052 | E97: 31954 | F97: OPEN | G97: First City National Bank of Midland | H97: Leede Exploration (mortgagor released) | I97: Pearl #1-32 & Crook #1-32, Section 32-11N-25W | J97: DIRECT IMAGE 4868 (visually verified). Releases Leede -> Trust Company of the West (TCW Commingled Debt & Royalty Fund I) mortgages rec Bk 962/012; collateral Bk 737/335, 738/29, 738/80. Confidence HIGH. Source: Images/4868.jpg
A98: 15 | C98: Release | D98: 995/52–54 | E98: 32155 | F98: 32161 | G98: First City National Bank | H98: Leede parties | I98: Enumerated Pearl/Crook/McCall liens | J98: Release limited to enumerated interests; execution and recording stamps reviewed. | DIRECT IMAGE L-010; imgs 4868–4870
A99: 16 | C99: Assignment | D99: 1014/75 | E99: 32191 | F99: 32259 | G99: Consolidation of Leede Trusts | H99: Leede Exploration | I99: N/2 below top Hunton | J99: Effective as of first production from McCall #1-29; assignor WI source defect. | DIRECT IMAGE L-011; img 4893
A100: 139 | C100: Assignment | D100: 1042/102-110 | E100: 32417 | F100: 32429 | G100: CHAMPLIN PETROLEUM COMPANY FKA; UNION PACIFIC RESOURCES COMPANY | H100: BRISTOL RESOURCES 1987 1 ACQUISITION PROGRAM | I100: S32 T11N R25W | J100: OKCOUNTY API METADATA ONLY — indexed occurrence affecting Section 32. Document images and operative schedules were not purchased or reviewed; do not calculate title quantum from metadata alone.
A101: 140 | C101: Release Of Mortgage | D101: 1052/78 | E101: 32479 | F101: 32483 | G101: LIBERTY NATIONAL BANK AND TRUST COMPANY OF OKLAHO | H101: CAMPBELL, DAVID G | I101: S32 T11N R25W | J101: OKCOUNTY API METADATA ONLY — indexed occurrence affecting Section 32. Document images and operative schedules were not purchased or reviewed; do not calculate title quantum from metadata alone. | Financing/security — not WI vesting.
A102: 143 | C102: Assignment | D102: 1064/223 | E102: 32531 | F102: 32549 | G102: POPHAM, DENNIS E | H102: LEEDE EXPLORATION | I102: S32 T11N R25W | J102: OKCOUNTY API METADATA ONLY — indexed occurrence affecting Section 32. Document images and operative schedules were not purchased or reviewed; do not calculate title quantum from metadata alone.
A103: 144 | C103: Release Of Oil Lease | D103: 1065/195-196 | E103: 32531 | F103: 32554 | G103: UNION OIL COMPANY OF CALIFORNIA | H103: CHUNN, FLORENCE JENKINS; FARISS, E A ESTATE OF; GENTRY, LOIS M; GILLESPIE, FLORENCE F; HARRISON, GEORGE T JR; HARRISON, RENATA; HELLER, HARVEY A; HELLER, HARVEY A JR; JACOBS, MYLON C; JENKINS, WILLIAM RUNDELL; LLOYD, GARTHALENE M; MADDOUX, A E; MADDOUX, D H; MADDOUX, L H; MCMAHAN, MAURINE B; MINTON, R L; NEWLAND, JEROME; RANDEL, F L; RANDEL, J L; SHEARER, JEAN JENKINS | I103: S32 T11N R25W | J103: OKCOUNTY API METADATA ONLY — indexed occurrence affecting Section 32. Document images and operative schedules were not purchased or reviewed; do not calculate title quantum from metadata alone.
A104: 150 | C104: Mineral Deed | D104: 1090/94 | E104: 32674 | F104: 32682 | G104: GODWIN, JUANITA | H104: GODWIN, JOSEPH ERVIN III | I104: S32 T11N R25W | J104: OKCOUNTY API METADATA ONLY — indexed occurrence affecting Section 32. Document images and operative schedules were not purchased or reviewed; do not calculate title quantum from metadata alone.
A105: 151 | C105: Mineral Deed | D105: 1090/95 | E105: 32674 | F105: 32682 | G105: GODWIN, JUANITA | H105: GODWIN, TIMOTHY ADRIAN | I105: S32 T11N R25W | J105: OKCOUNTY API METADATA ONLY — indexed occurrence affecting Section 32. Document images and operative schedules were not purchased or reviewed; do not calculate title quantum from metadata alone.
A106: 153 | C106: Assignment | D106: 1112/208-216 | E106: 32786 | F106: 32797 | G106: MOBIL EXPLORATION AND PRODUCING NORTH AMERICA INC | H106: SAMSON RESOURCES COMPANY | I106: S32 T11N R25W | J106: OKCOUNTY API METADATA ONLY — indexed occurrence affecting Section 32. Document images and operative schedules were not purchased or reviewed; do not calculate title quantum from metadata alone.
A107: 155 | C107: Partial Release Of Mortgage | D107: 1123/293-296 | E107: 32839 | F107: 32857 | G107: NCNB TEXAS NATIONAL BANK | H107: GREAT AMERICAN DRILLING PARTNERSHIP III; GREAT AMERICAN DRILLING PARTNERSHIP V; GREAT AMERICAN EXPLORATION CORPORATION | I107: S32 T11N R25W | J107: OKCOUNTY API METADATA ONLY — indexed occurrence affecting Section 32. Document images and operative schedules were not purchased or reviewed; do not calculate title quantum from metadata alone. | Financing/security — not WI vesting.
A108: 157 | C108: Assignment | D108: 1167/279-281 | E108: 33112 | F108: 33136 | G108: HAWK PETROLEUM INC LIQUIDATING TRUST | H108: BOYER, LYNDON B | I108: S32 T11N R25W | J108: OKCOUNTY API METADATA ONLY — indexed occurrence affecting Section 32. Document images and operative schedules were not purchased or reviewed; do not calculate title quantum from metadata alone.
A109: 158 | C109: Assignment | D109: 1167/282-284 | E109: 33112 | F109: 33136 | G109: HAWK PETROLEUM INC LIQUIDATING TRUST | H109: TBA PETROLEUM INC | I109: S32 T11N R25W | J109: OKCOUNTY API METADATA ONLY — indexed occurrence affecting Section 32. Document images and operative schedules were not purchased or reviewed; do not calculate title quantum from metadata alone.
... A141: 98 | C141: Release of Mortgage; I-2025-002299 | D141: 2453/389–1000 | E141: 45729 | F141: 45819 | G141: JPMorgan Chase Bank N.A. | H141: Breitburn Operating LP; Unbridled Resources LLC; Unbridled Agent Corp. | I141: LONG DESCRIPTION / 612-page collateral release | J141: Instrument date 03/13/2025. Metadata and range are reconciled, but the instrument and schedules were not reviewed; Section 32 coverage and the exact released mortgage/collateral remain open. | PUBLIC METADATA — BURDEN SCREEN | Financing/security — not WI vesting.
A142: 123 | C142: Final Decree / Probate distribution | D142: 845/150 | E142: decedent d. 1983-11-16 | F142: 1984 (Beckham) | G142: Estate of Charlie B. Crook | H142: Devisees (per decree) | I142: NE/4 Section 32-11N-25W (Tract 3: 7/13 interest; Tract 4: 7/52 minerals) | J142: [chron 1984-06-01] DIRECT IMAGE 4121 (pixels verified). Probate of Charlie B. Crook (testate). Sec 32 NE/4: undivided 7/13ths (Tract 3) and undivided 7/52nds minerals (Tract 4). Payments from Leede Oil & Gas noted. Confidence HIGH. Source: Images/4121.jpg
A143: 126 | C143: Partnership property statement (WI) | D143: 611/180 | E143: eff via Leede/ENI Letter+Operating Agmt 1979-11-20 | F143: OPEN | G143: ENI Joint Venture 1979 XII (the Partnership) | H143: n/a (statement of owned WI) | I143: Mesa No. 1-32 Crook spacing unit, CE/2 NE/4 Section 32-11N-25W | J143: [chron 1979-11-20] DIRECT IMAGE 2170 (pixels). STATED WI: 2.478516% of 8/8 before payout, 1.85889% after payout; revenue 1.85889% BPO / 1.394165% APO. Interest of ENI JV 1979 XII only (NOT Diversified). Gas Purchase Agmt 1981-02-15 Mesa/El Paso. Confidence HIGH. Source: Images/2170.jpg
A144: 115 | C144: Exhibit A (mineral/lease schedule) | D144: 293/507 | E144: filed 1975-04 | F144: 1975-04 (Beckham) | G144: OPEN (schedule page) | H144: OPEN (schedule page) | I144: W/2 SE/4 & S/2 SW/4 Section 32-11N-25W (tract A-1244) | J144: [chron 1975-04-01] DIRECT IMAGE 1362 (pixels verified). Tract A-1244: undivided 3/8 fully participating perpetual mineral interest, 160 ac. Other tracts on page are Sec 32-11N-22W (NOT ours). Confidence HIGH (A-1244 only). Source: Images/1362.jpg
A145: 114 | C145: Amendment of Oil & Gas Leases | D145: 253/308 | E145: leases 1966; amendment date OPEN | F145: OPEN | G145: Claud B. Hamill (lessor) | H145: W. W. Blair (lessee); now owned by Pan American Petroleum Corp. | I145: S/2 NW/4 Section 32-11N-25W (lease dated 1966-11-03, rec Bk 218/86) | J145: [chron 1966-11-03] DIRECT IMAGE 1102 (pixels verified). Only Tract 1 is Sec 32 (S/2 NW/4); tracts 2-3 are T10N. 1/6 royalty terms. Confidence HIGH. Source: Images/1102.jpg
A146: 330 | C146: Warranty Deed | D146: 9/418 | E146: October 11, 1906 | F146: March 12, 1907, 7:00 A.M. | G146: Velmore Biggs and Hettie A. Biggs, his wife | H146: Edward J. Gordon | I146: SE/4 of Section 32, Township 11 North, Range 25 West of the Indian Meridian | J146: SOURCE GROUP B01-G001 | Images 0001–0001 | $800 mortgage in favor of Oklahoma Farm Mortgage Company | Confidence: high
A147: 331 | C147: Warranty Deed | D147: 12 | E147: July 16, 1907 | F147: July 18, 1907, 1:00 P.M. | G147: Cornelius B. Cornelius and Margreta Cornelius, husband and wife | H147: Jacob Bollenbach | I147: NE/4 of Section 32, Township 11 North, Range 25 West of the Indian Meridian | J147: SOURCE GROUP B01-G002 | Images 0002–0002 | 1907 taxes | Confidence: high
A148: 332 | C148: Homestead Patent | D148: Patent Record/369 | E148: March 22, 1906 | G148: United States of America | H148: Cornelius B. Cornelius | I148: NE/4 of Section 32, Township 11 North, Range 25 West of the Indian Meridian | J148: SOURCE GROUP B01-G003 | Images 0003–0003 | Confidence: high
A149: 333 | C149: Final Receiver's Receipt / Homestead Entry | F149: August 8, 1908 | H149: Velmore Biggs | I149: SE/4 of Section 32, Township 11 North, Range 25 West of the Indian Meridian | J149: SOURCE GROUP B01-G005 | Images 0004–0004 | Confidence: medium
A150: 334 | C150: Final Receiver's Receipt / Homestead Entry | H150: Herman Stevens | I150: SW/4 of Section 32, Township 11 North, Range 25 West of the Indian Meridian | J150: SOURCE GROUP B01-G007 | Images 0005–0005 | Confidence: medium
...

Sheet Index runsheet
B1: OGL | C1: Doc Type | D1: Bk/Pg. | E1: Effective Date | F1: Recorded Date | G1: Grantor | H1: Grantee | I1: Legal Description | J1: Notes

Sheet Tract 1
A1: TRACT 1 — N/2 NE/4 AND SW/4 NE/4 — 120.00 ACRES — FEE MINERAL CHAIN OPEN | E1: Instrument
A2: 1 | B2: TRACT | D2: N/2 NE/4 and SW/4 NE/4, containing 120.00 acres | E2: Image Number
B3: DESCRIPTION | E3: Book / Page
E4: Date
B5: TRACT ACRES | D5: 120 | E5: Conveyance
B6: BASE OGL | D6: Tract 1 | E6: =SUBTOTAL(9,E9:E205) | F6: SURFACE | I6: =IF(I7=0,"","RECHECK") | M6: =IF(M7=0,"","RECHECK") | N6: =IF(N7=0,"","RECHECK") | O6: =IF(O7=0,"","RECHECK") | P6: =IF(P7=0,"","RECHECK") | Q6: =IF(Q7=0,"","RECHECK") | R6: =IF(R7=0,"","RECHECK") | T6: =IF(T7=0,"","RECHECK") | U6: =IF(U7=0,"","RECHECK") | V6: =IF(V7=0,"","RECHECK") | W6: =IF(W7=0,"","RECHECK") | X6: =IF(X7=0,"","RECHECK") | Y6: =IF(Y7=0,"","RECHECK") | Z6: =IF(Z7=0,"","RECHECK") | AA6: =IF(AA7=0,"","RECHECK") | ... AN6: =IF(AN7=0,"","RECHECK") | AR6: =IF(AR7=0,"","RECHECK") | AS6: =IF(AS7=0,"","RECHECK") | AT6: =IF(AT7=0,"","RECHECK") | AU6: =IF(AU7=0,"","RECHECK") | AX6: =IF(AX7=0,"","RECHECK") | AY6: =IF(AY7=0,"","RECHECK") | AZ6: =IF(AZ7=0,"","RECHECK") | BA6: =IF(BA7=0,"","RECHECK") | BB6: =IF(BB7=0,"","RECHECK") | BC6: =IF(BC7=0,"","RECHECK") | BD6: =IF(BD7=0,"","RECHECK") | BE6: =IF(BE7=0,"","RECHECK") | ... GF6: =IF(GF7=0,"","RECHECK")
G7: =SUBTOTAL(9,G10:G206) | H7: =SUBTOTAL(9,H10:H206) | J7: =SUBTOTAL(9,J10:J206) | K7: =SUBTOTAL(9,K10:K206) | L7: =SUBTOTAL(9,L10:L206) | M7: =SUBTOTAL(9,M10:M206) | N7: =SUBTOTAL(9,N10:N206) | O7: =SUBTOTAL(9,O10:O206) | P7: =SUBTOTAL(9,P10:P206) | Q7: =SUBTOTAL(9,Q10:Q206) | ... AR7: =SUBTOTAL(9,AR10:AR206) | AT7: =SUBTOTAL(9,AT10:AT206) | AU7: =SUBTOTAL(9,AU10:AU206) | AV7: =SUBTOTAL(9,AV10:AV201) | AW7: =SUBTOTAL(9,AW10:AW195) | AX7: =SUBTOTAL(9,AX10:AX195) | AY7: =SUBTOTAL(9,AY10:AY195) | AZ7: =SUBTOTAL(9,AZ10:AZ195) | BA7: =SUBTOTAL(9,BA10:BA206) | BB7: =SUBTOTAL(9,BB10:BB206) | BC7: =SUBTOTAL(9,BC10:BC206) | BD7: =SUBTOTAL(9,BD10:BD202) | BE7: =SUBTOTAL(9,BE10:BE206) | BF7: =SUBTOTAL(9,BF10:BF206) | BG7: =SUBTOTAL(9,BG10:BG206) | BH7: =SUBTOTAL(9,BH10:BH206) | BI7: =SUBTOTAL(9,BI10:BI206) | BJ7: =SUBTOTAL(9,BJ10:BJ206) | BK7: =SUBTOTAL(9,BK10:BK206) | BL7: =SUBTOTAL(9,BL10:BL206) | ... GF7: =SUBTOTAL(9,GF10:GF206)
A8: NOTES | D8: OWNERS | E8: TOTAL
A9: OPEN — NO BASE OGL PROVED | D9: Fee mineral ownership open — source-limited cursory; no tract-level mineral quantum established.
C10: =E10*D$5 | E10: =SUM(G10:HY10)
C11: =E11*D$5 | E11: =SUM(G11:HY11)
C12: =E12*D$5 | E12: =SUM(G12:HY12)
C13: =E13*D$5 | E13: =SUM(G13:HY13)
C14: =E14*D$5 | E14: =SUM(G14:HY14)
C15: =E15*D$5 | E15: =SUM(G15:HY15)
C16: =E16*D$5 | E16: =SUM(G16:HY16)
C17: =E17*D$5 | E17: =SUM(G17:HY17)
C18: =E18*D$5 | E18: =SUM(G18:HY18)
C19: =E19*D$5 | E19: =SUM(G19:HY19)
C20: =E20*D$5 | E20: =SUM(G20:HY20)
C21: =E21*D$5 | E21: =SUM(G21:HY21)
... C55: =E55*D$5 | E55: =SUM(G55:HY55)
C56: =E56*D$5 | E56: =SUM(G56:HL56)
C57: =E57*D$5 | E57: =SUM(G57:HL57)
C58: =E58*D$5 | E58: =SUM(G58:HL58)
C59: =E59*D$5 | E59: =SUM(G59:HL59)
C60: =E60*D$5 | E60: =SUM(G60:HL60)
C61: =E61*D$5 | E61: =SUM(G61:HY61)
C62: =E62*D$5 | E62: =SUM(G62:HY62)
C63: =E63*D$5 | E63: =SUM(G63:HY63)
C64: =E64*D$5 | E64: =SUM(G64:HP64)
C65: =E65*D$5 | E65: =SUM(G65:HY65)
C66: =E66*D$5 | E66: =SUM(G66:HY66)
C67: =E67*D$5 | E67: =SUM(G67:HY67)
C68: =E68*D$5 | E68: =SUM(G68:HY68)
C69: =E69*D$5 | E69: =SUM(G69:HY69)
C70: =E70*D$5 | E70: =SUM(G70:HY70)
C71: =E71*D$5 | E71: =SUM(G71:HY71)
C72: =E72*D$5 | E72: =SUM(G72:HY72)
C73: =E73*D$5 | E73: =SUM(G73:HY73)
C74: =E74*D$5 | E74: =SUM(G74:HY74)
C75: =E75*D$5 | E75: =SUM(G75:HY75)
C76: =E76*D$5 | E76: =SUM(G76:HY76)
... C205: =E205*D$5 | E205: =SUM(G205:HY205)

Sheet Tract 2
A1: TRACT 2 — SE/4 NE/4 AND E/2 SE/4 — 120.00 ACRES — FEE MINERAL CHAIN OPEN | E1: Instrument
A2: 2 | B2: TRACT | D2: SE/4 NE/4 and E/2 SE/4, containing 120.00 acres | E2: Image Number
B3: DESCRIPTION | E3: Book / Page
E4: Date
B5: TRACT ACRES | D5: 120 | E5: Conveyance
B6: BASE OGL | D6: Tract 2 | E6: =SUBTOTAL(9,E9:E205) | F6: SURFACE | I6: =IF(I7=0,"","RECHECK") | K6: =IF(K7=0,"","RECHECK") | M6: =IF(M7=0,"","RECHECK") | N6: =IF(N7=0,"","RECHECK") | O6: =IF(O7=0,"","RECHECK") | Q6: =IF(Q7=0,"","RECHECK") | R6: =IF(R7=0,"","RECHECK") | S6: =IF(S7=0,"","RECHECK") | T6: =IF(T7=0,"","RECHECK") | U6: =IF(U7=0,"","RECHECK") | V6: =IF(V7=0,"","RECHECK") | W6: =IF(W7=0,"","RECHECK") | X6: =IF(X7=0,"","RECHECK") | ... AA6: =IF(AA7=0,"","RECHECK") | AD6: =IF(AD7=0,"","RECHECK") | AE6: =IF(AE7=0,"","RECHECK") | AF6: =IF(AF7=0,"","RECHECK") | AG6: =IF(AG7=0,"","RECHECK") | AH6: =IF(AH7=0,"","RECHECK") | AI6: =IF(AI7=0,"","RECHECK") | AJ6: =IF(AJ7=0,"","RECHECK") | AK6: =IF(AK7=0,"","RECHECK") | ... GA6: =IF(GA7=0,"","RECHECK")
G7: =SUBTOTAL(9,G10:G206) | H7: =SUBTOTAL(9,H10:H206) | J7: =SUBTOTAL(9,J10:J206) | K7: =SUBTOTAL(9,K10:K206) | L7: =SUBTOTAL(9,L10:L206) | M7: =SUBTOTAL(9,M10:M206) | N7: =SUBTOTAL(9,N10:N206) | O7: =SUBTOTAL(9,O10:O206) | P7: =SUBTOTAL(9,P10:P206) | Q7: =SUBTOTAL(9,Q10:Q210) | R7: =SUBTOTAL(9,R10:R206) | S7: =SUBTOTAL(9,S10:S206) | T7: =SUBTOTAL(9,T10:T206) | U7: =SUBTOTAL(9,U10:U206) | V7: =SUBTOTAL(9,V10:V206) | W7: =SUBTOTAL(9,W10:W206) | X7: =SUBTOTAL(9,X10:X206) | Y7: =SUBTOTAL(9,Y10:Y206) | AA7: =SUBTOTAL(9,AA10:AA210) | AB7: =SUBTOTAL(9,AB10:AB207) | AC7: =SUBTOTAL(9,AC10:AC201) | AD7: =SUBTOTAL(9,AD10:AD201) | AE7: =SUBTOTAL(9,AE10:AE201) | AF7: =SUBTOTAL(9,AF10:AF201) | AG7: =SUBTOTAL(9,AG10:AG206) | AH7: =SUBTOTAL(9,AH10:AH202) | AI7: =SUBTOTAL(9,AI10:AI206) | AJ7: =SUBTOTAL(9,AJ10:AJ206) | AK7: =SUBTOTAL(9,AK10:AK206) | AL7: =SUBTOTAL(9,AL10:AL206) | AM7: =SUBTOTAL(9,AM10:AM206) | AN7: =SUBTOTAL(9,AN10:AN206) | AO7: =SUBTOTAL(9,AO10:AO206) | AP7: =SUBTOTAL(9,AP10:AP206) | ... GA7: =SUBTOTAL(9,GA10:GA206)
A8: NOTES | D8: OWNERS | E8: TOTAL
A9: OPEN — NO BASE OGL PROVED | D9: Fee mineral ownership open — source-limited cursory; no tract-level mineral quantum established.
C10: =E10*D$5 | E10: =SUM(G10:HT10)
C11: =E11*D$5 | E11: =SUM(G11:HT11)
C12: =E12*D$5 | E12: =SUM(G12:HT12)
C13: =E13*D$5 | E13: =SUM(G13:HT13)
C14: =E14*D$5 | E14: =SUM(G14:HT14)
C15: =E15*D$5 | E15: =SUM(G15:HT15)
C16: =E16*D$5 | E16: =SUM(G16:HT16)
C17: =E17*D$5 | E17: =SUM(G17:HT17)
C18: =E18*D$5 | E18: =SUM(G18:HT18)
C19: =E19*D$5 | E19: =SUM(G19:HP19)
C20: =E20*D$5 | E20: =SUM(G20:HP20)
C21: =E21*D$5 | E21: =SUM(G21:HT21)
C22: =E22*D$5 | E22: =SUM(G22:HT22)
C23: =E23*D$5 | E23: =SUM(G23:HT23)
C24: =E24*D$5 | E24: =SUM(G24:HT24)
C25: =E25*D$5 | E25: =SUM(G25:HT25)
C26: =E26*D$5 | E26: =SUM(G26:HT26)
C27: =E27*D$5 | E27: =SUM(G27:HT27)
C28: =E28*D$5 | E28: =SUM(G28:HT28)
C29: =E29*D$5 | E29: =SUM(G29:HT29)
C30: =E30*D$5 | E30: =SUM(G30:HT30)
C31: =E31*D$5 | E31: =SUM(G31:HT31)
C32: =E32*D$5 | E32: =SUM(G32:HT32)
... C34: =E34*D$5 | E34: =SUM(G34:HT34)
C35: =E35*D$5 | E35: =SUM(G35:HY35)
C36: =E36*D$5 | E36: =SUM(G36:HT36)
C37: =E37*D$5 | E37: =SUM(G37:HH37)
C38: =E38*D$5 | E38: =SUM(G38:HH38)
C39: =E39*D$5 | E39: =SUM(G39:HH39)
C40: =E40*D$5 | E40: =SUM(G40:HH40)
C41: =E41*D$5 | E41: =SUM(G41:HH41)
C42: =E42*D$5 | E42: =SUM(G42:HT42)
C43: =E43*D$5 | E43: =SUM(G43:HP43)
C44: =E44*D$5 | E44: =SUM(G44:HT44)
C45: =E45*D$5 | E45: =SUM(G45:HT45)
C46: =E46*D$5 | E46: =SUM(G46:HT46)
C47: =E47*D$5 | E47: =SUM(G47:HT47)
C48: =E48*D$5 | E48: =SUM(G48:HT48)
C49: =E49*D$5 | E49: =SUM(G49:HT49)
C50: =E50*D$5 | E50: =SUM(G50:HT50)
C51: =E51*D$5 | E51: =SUM(G51:HT51)
C52: =E52*D$5 | E52: =SUM(G52:HT52)
C53: =E53*D$5 | E53: =SUM(G53:HT53)
C54: =E54*D$5 | E54: =SUM(G54:HT54)
C55: =E55*D$5 | E55: =SUM(G55:HT55)
... C205: =E205*D$5 | E205: =SUM(G205:HT205)

Sheet Tract 3
A1: TRACT 3 — NW/4 — 160.00 ACRES — FEE MINERAL CHAIN OPEN | E1: Instrument
A2: 3 | B2: TRACT | D2: NW/4, containing 160.00 acres | E2: Image Number
B3: DESCRIPTION | E3: Book / Page
E4: Date
B5: TRACT ACRES | D5: 160 | E5: Conveyance
B6: BASE OGL | D6: Tract 3 | E6: =SUBTOTAL(9,E9:E203) | F6: SURFACE | H6: =IF(H7=0,"","RECHECK") | K6: =IF(K7=0,"","RECHECK") | M6: =IF(M7=0,"","RECHECK") | N6: =IF(N7=0,"","RECHECK") | O6: =IF(O7=0,"","RECHECK") | P6: =IF(P7=0,"","RECHECK") | R6: =IF(R7=0,"","RECHECK") | T6: =IF(T7=0,"","RECHECK") | U6: =IF(U7=0,"","RECHECK") | V6: =IF(V7=0,"","RECHECK") | W6: =IF(W7=0,"","RECHECK") | X6: =IF(X7=0,"","RECHECK") | Y6: =IF(Y7=0,"","RECHECK") | Z6: =IF(Z7=0,"","RECHECK") | AA6: =IF(AA7=0,"","RECHECK") | ... AF6: =IF(AF7=0,"","RECHECK") | AI6: =IF(AI7=0,"","RECHECK") | AJ6: =IF(AJ7=0,"","RECHECK") | AK6: =IF(AK7=0,"","RECHECK") | AL6: =IF(AL7=0,"","RECHECK") | AM6: =IF(AM7=0,"","RECHECK") | AN6: =IF(AN7=0,"","RECHECK") | AO6: =IF(AO7=0,"","RECHECK") | AP6: =IF(AP7=0,"","RECHECK") | ... GA6: =IF(GA7=0,"","RECHECK")
G7: =SUBTOTAL(9,G10:G204) | I7: =SUBTOTAL(9,I10:I204) | J7: =SUBTOTAL(9,J10:J204) | L7: =SUBTOTAL(9,L10:L204) | M7: =SUBTOTAL(9,M10:M204) | N7: =SUBTOTAL(9,N10:N204) | O7: =SUBTOTAL(9,O10:O204) | P7: =SUBTOTAL(9,P10:P204) | Q7: =SUBTOTAL(9,Q10:Q204) | R7: =SUBTOTAL(9,R10:R208) | S7: =SUBTOTAL(9,S10:S208) | T7: =SUBTOTAL(9,T10:T204) | U7: =SUBTOTAL(9,U10:U204) | V7: =SUBTOTAL(9,V10:V204) | W7: =SUBTOTAL(9,W10:W204) | X7: =SUBTOTAL(9,X10:X204) | Y7: =SUBTOTAL(9,Y10:Y204) | Z7: =SUBTOTAL(9,Z10:Z204) | AA7: =SUBTOTAL(9,AA10:AA204) | ... AD7: =SUBTOTAL(9,AD10:AD204) | AF7: =SUBTOTAL(9,AF10:AF208) | AG7: =SUBTOTAL(9,AG10:AG212) | AH7: =SUBTOTAL(9,AH10:AH206) | AI7: =SUBTOTAL(9,AI10:AI206) | AJ7: =SUBTOTAL(9,AJ10:AJ206) | AK7: =SUBTOTAL(9,AK10:AK206) | AL7: =SUBTOTAL(9,AL10:AL204) | AM7: =SUBTOTAL(9,AM10:AM203) | AN7: =SUBTOTAL(9,AN10:AN204) | AO7: =SUBTOTAL(9,AO10:AO206) | AP7: =SUBTOTAL(9,AP10:AP204) | AQ7: =SUBTOTAL(9,AQ10:AQ204) | AR7: =SUBTOTAL(9,AR10:AR204) | AS7: =SUBTOTAL(9,AS10:AS204) | AT7: =SUBTOTAL(9,AT10:AT204) | AU7: =SUBTOTAL(9,AU10:AU204) | AV7: =SUBTOTAL(9,AV10:AV204) | AW7: =SUBTOTAL(9,AW10:AW204) | ... GA7: =SUBTOTAL(9,GA10:GA204)
A8: NOTES | D8: OWNERS | E8: TOTAL
A9: OPEN — NO BASE OGL PROVED | D9: Fee mineral ownership open — source-limited cursory; no tract-level mineral quantum established.
C10: =E10*D$5 | E10: =SUM(G10:HT10)
C11: =E11*D$5 | E11: =SUM(G11:HT11)
C12: =E12*D$5 | E12: =SUM(G12:HT12)
C13: =E13*D$5 | E13: =SUM(G13:HT13)
C14: =E14*D$5 | E14: =SUM(G14:HT14)
C15: =E15*D$5 | E15: =SUM(G15:HT15)
C16: =E16*D$5 | E16: =SUM(G16:HT16)
C17: =E17*D$5 | E17: =SUM(G17:HT17)
C18: =E18*D$5 | E18: =SUM(G18:HT18)
C19: =E19*D$5 | E19: =SUM(G19:HT19)
C20: =E20*D$5 | E20: =SUM(G20:HT20)
C21: =E21*D$5 | E21: =SUM(G21:HT21)
... C36: =E36*D$5 | E36: =SUM(G36:HT36)
C37: =E37*D$5 | E37: =SUM(G37:HY37)
C38: =E38*D$5 | E38: =SUM(G38:HT38)
C39: =E39*D$5 | E39: =SUM(G39:HH39)
C40: =E40*D$5 | E40: =SUM(G40:HH40)
C41: =E41*D$5 | E41: =SUM(G41:HH41)
C42: =E42*D$5 | E42: =SUM(G42:HH42)
C43: =E43*D$5 | E43: =SUM(G43:HH43)
C44: =E44*D$5 | E44: =SUM(G44:HT44)
C45: =E45*D$5 | E45: =SUM(G45:HP45)
C46: =E46*D$5 | E46: =SUM(G46:HT46)
C47: =E47*D$5 | E47: =SUM(G47:HT47)
C48: =E48*D$5 | E48: =SUM(G48:HT48)
C49: =E49*D$5 | E49: =SUM(G49:HT49)
C50: =E50*D$5 | E50: =SUM(G50:HT50)
C51: =E51*D$5 | E51: =SUM(G51:HT51)
C52: =E52*D$5 | E52: =SUM(G52:HT52)
C53: =E53*D$5 | E53: =SUM(G53:HT53)
C54: =E54*D$5 | E54: =SUM(G54:HT54)
C55: =E55*D$5 | E55: =SUM(G55:HT55)
C56: =E56*D$5 | E56: =SUM(G56:HT56)
C57: =E57*D$5 | E57: =SUM(G57:HT57)
... C203: =E203*D$5 | E203: =SUM(G203:HT203)

Sheet Tract 4
A1: TRACT 4 — SW/4 — 160.00 ACRES — FEE MINERAL CHAIN OPEN | E1: Instrument
A2: 4 | B2: TRACT | D2: SW/4, containing 160.00 acres | E2: Image Number
B3: DESCRIPTION | E3: Book / Page
E4: Date
B5: TRACT ACRES | D5: 160 | E5: Conveyance
B6: BASE OGL | D6: Tract 4 | E6: =SUBTOTAL(9,E9:E186) | F6: SURFACE | I6: =IF(I7=0,"","RECHECK") | L6: =IF(L7=0,"","RECHECK") | M6: =IF(M7=0,"","RECHECK") | N6: =IF(N7=0,"","RECHECK") | O6: =IF(O7=0,"","RECHECK") | Q6: =IF(Q7=0,"","RECHECK") | R6: =IF(R7=0,"","RECHECK") | S6: =IF(S7=0,"","RECHECK") | T6: =IF(T7=0,"","RECHECK") | U6: =IF(U7=0,"","RECHECK") | V6: =IF(V7=0,"","RECHECK") | W6: =IF(W7=0,"","RECHECK") | X6: =IF(X7=0,"","RECHECK") | ... FN6: =IF(FN7=0,"","RECHECK")
G7: =SUBTOTAL(9,G10:G187) | H7: =SUBTOTAL(9,H10:H187) | J7: =SUBTOTAL(9,J10:J187) | K7: =SUBTOTAL(9,K10:K187) | L7: =SUBTOTAL(9,L10:L187) | M7: =SUBTOTAL(9,M10:M187) | N7: =SUBTOTAL(9,N10:N187) | O7: =SUBTOTAL(9,O10:O187) | P7: =SUBTOTAL(9,P10:P187) | Q7: =SUBTOTAL(9,Q10:Q187) | ... U7: =SUBTOTAL(9,U10:U187) | V7: =SUBTOTAL(9,V10:V190) | W7: =SUBTOTAL(9,W10:W187) | X7: =SUBTOTAL(9,X10:X187) | Y7: =SUBTOTAL(9,Y10:Y187) | Z7: =SUBTOTAL(9,Z10:Z187) | AA7: =SUBTOTAL(9,AA10:AA187) | AB7: =SUBTOTAL(9,AB10:AB187) | AC7: =SUBTOTAL(9,AC10:AC190) | AD7: =SUBTOTAL(9,AD10:AD190) | AE7: =SUBTOTAL(9,AE10:AE187) | AF7: =SUBTOTAL(9,AF10:AF187) | AG7: =SUBTOTAL(9,AG10:AG187) | AH7: =SUBTOTAL(9,AH10:AH187) | AI7: =SUBTOTAL(9,AI10:AI187) | AJ7: =SUBTOTAL(9,AJ10:AJ187) | AK7: =SUBTOTAL(9,AK10:AK187) | AL7: =SUBTOTAL(9,AL10:AL187) | ... FN7: =SUBTOTAL(9,FN10:FN187)
A8: NOTES | D8: OWNERS | E8: TOTAL
A9: OPEN — NO BASE OGL PROVED | D9: Fee mineral ownership open — source-limited cursory; no tract-level mineral quantum established.
E10: =SUM(G10:HG10)
E11: =SUM(G11:HG11)
E12: =SUM(G12:HG12)
E13: =SUM(G13:HG13)
E14: =SUM(G14:HG14)
E15: =SUM(G15:HG15)
E16: =SUM(G16:HH16)
E17: =SUM(G17:HH17)
E18: =SUM(G18:HH18)
E19: =SUM(G19:HH19)
E20: =SUM(G20:HH20)
E21: =SUM(G21:HG21)
E22: =SUM(G22:HG22)
E23: =SUM(G23:HG23)
E24: =SUM(G24:HG24)
E25: =SUM(G25:HG25)
E26: =SUM(G26:HG26)
E27: =SUM(G27:HK27)
E28: =SUM(G28:HK28)
E29: =SUM(G29:HK29)
E30: =SUM(G30:HG30)
E31: =SUM(G31:HG31)
C32: =E32*D$5 | E32: =SUM(G32:HG32)
C33: =E33*D$5 | E33: =SUM(G33:HG33)
C34: =E34*D$5 | E34: =SUM(G34:HG34)
C35: =E35*D$5 | E35: =SUM(G35:HG35)
C36: =E36*D$5 | E36: =SUM(G36:HG36)
C37: =E37*D$5 | E37: =SUM(G37:HG37)
C38: =E38*D$5 | E38: =SUM(G38:HG38)
C39: =E39*D$5 | E39: =SUM(G39:HG39)
C40: =E40*D$5 | E40: =SUM(G40:HG40)
C41: =E41*D$5 | E41: =SUM(G41:HG41)
C42: =E42*D$5 | E42: =SUM(G42:HG42)
C43: =E43*D$5 | E43: =SUM(G43:HG43)
... C186: =E186*D$5 | E186: =SUM(G186:HG186)

Sheet Tract 5
A1: TRACT 5 — W/2 SE/4 — 80.00 ACRES — FEE MINERAL CHAIN OPEN | E1: Instrument
A2: 5 | B2: TRACT | D2: W/2 SE/4, containing 80.00 acres | E2: Image Number
B3: DESCRIPTION | E3: Book / Page
E4: Date
B5: TRACT ACRES | D5: 80 | E5: Conveyance
B6: BASE OGL | D6: Tract 5 | E6: =SUBTOTAL(9,E9:E203) | F6: SURFACE | I6: =IF(I7=0,"","RECHECK") | L6: =IF(L7=0,"","RECHECK") | M6: =IF(M7=0,"","RECHECK") | N6: =IF(N7=0,"","RECHECK") | O6: =IF(O7=0,"","RECHECK") | Q6: =IF(Q7=0,"","RECHECK") | R6: =IF(R7=0,"","RECHECK") | S6: =IF(S7=0,"","RECHECK") | T6: =IF(T7=0,"","RECHECK") | U6: =IF(U7=0,"","RECHECK") | V6: =IF(V7=0,"","RECHECK") | W6: =IF(W7=0,"","RECHECK") | X6: =IF(X7=0,"","RECHECK") | ... AE6: =IF(AE7=0,"","RECHECK") | AH6: =IF(AH7=0,"","RECHECK") | AI6: =IF(AI7=0,"","RECHECK") | AJ6: =IF(AJ7=0,"","RECHECK") | AK6: =IF(AK7=0,"","RECHECK") | AL6: =IF(AL7=0,"","RECHECK") | AM6: =IF(AM7=0,"","RECHECK") | AN6: =IF(AN7=0,"","RECHECK") | AO6: =IF(AO7=0,"","RECHECK") | ... FW6: =IF(FW7=0,"","RECHECK")
G7: =SUBTOTAL(9,G10:G204) | H7: =SUBTOTAL(9,H10:H204) | J7: =SUBTOTAL(9,J10:J204) | K7: =SUBTOTAL(9,K10:K204) | L7: =SUBTOTAL(9,L10:L204) | M7: =SUBTOTAL(9,M10:M204) | N7: =SUBTOTAL(9,N10:N204) | O7: =SUBTOTAL(9,O10:O204) | P7: =SUBTOTAL(9,P10:P204) | Q7: =SUBTOTAL(9,Q10:Q204) | ... U7: =SUBTOTAL(9,U10:U204) | V7: =SUBTOTAL(9,V10:V207) | W7: =SUBTOTAL(9,W10:W204) | X7: =SUBTOTAL(9,X10:X204) | Y7: =SUBTOTAL(9,Y10:Y204) | Z7: =SUBTOTAL(9,Z10:Z204) | AA7: =SUBTOTAL(9,AA10:AA204) | AB7: =SUBTOTAL(9,AB10:AB204) | AC7: =SUBTOTAL(9,AC10:AC207) | AE7: =SUBTOTAL(9,AE10:AE209) | AF7: =SUBTOTAL(9,AF10:AF212) | AG7: =SUBTOTAL(9,AG10:AG206) | AH7: =SUBTOTAL(9,AH10:AH206) | AI7: =SUBTOTAL(9,AI10:AI206) | AJ7: =SUBTOTAL(9,AJ10:AJ206) | AK7: =SUBTOTAL(9,AK10:AK207) | AL7: =SUBTOTAL(9,AL10:AL203) | AM7: =SUBTOTAL(9,AM10:AM207) | AN7: =SUBTOTAL(9,AN10:AN206) | AO7: =SUBTOTAL(9,AO10:AO204) | AP7: =SUBTOTAL(9,AP10:AP204) | AQ7: =SUBTOTAL(9,AQ10:AQ204) | AR7: =SUBTOTAL(9,AR10:AR204) | AS7: =SUBTOTAL(9,AS10:AS204) | AT7: =SUBTOTAL(9,AT10:AT204) | AU7: =SUBTOTAL(9,AU10:AU204) | AV7: =SUBTOTAL(9,AV10:AV204) | ... FW7: =SUBTOTAL(9,FW10:FW204)
A8: NOTES | D8: OWNERS | E8: TOTAL
A9: OPEN — NO BASE OGL PROVED | D9: Fee mineral ownership open — source-limited cursory; no tract-level mineral quantum established.
C10: =E10*D$5 | E10: =SUM(G10:HP10)
C11: =E11*D$5 | E11: =SUM(G11:HP11)
C12: =E12*D$5 | E12: =SUM(G12:HP12)
C13: =E13*D$5 | E13: =SUM(G13:HP13)
C14: =E14*D$5 | E14: =SUM(G14:HP14)
C15: =E15*D$5 | E15: =SUM(G15:HP15)
C16: =E16*D$5 | E16: =SUM(G16:HQ16)
C17: =E17*D$5 | E17: =SUM(G17:HQ17)
C18: =E18*D$5 | E18: =SUM(G18:HQ18)
C19: =E19*D$5 | E19: =SUM(G19:HQ19)
C20: =E20*D$5 | E20: =SUM(G20:HQ20)
C21: =E21*D$5 | E21: =SUM(G21:HP21)
C22: =E22*D$5 | E22: =SUM(G22:HP22)
C23: =E23*D$5 | E23: =SUM(G23:HP23)
C24: =E24*D$5 | E24: =SUM(G24:HP24)
C25: =E25*D$5 | E25: =SUM(G25:HP25)
C26: =E26*D$5 | E26: =SUM(G26:HP26)
C27: =E27*D$5 | E27: =SUM(G27:HT27)
C28: =E28*D$5 | E28: =SUM(G28:HT28)
C29: =E29*D$5 | E29: =SUM(G29:HT29)
C30: =E30*D$5 | E30: =SUM(G30:HP30)
C31: =E31*D$5 | E31: =SUM(G31:HP31)
C32: =E32*D$5 | E32: =SUM(G32:HP32)
C33: =E33*D$5 | E33: =SUM(G33:HP33)
C34: =E34*D$5 | E34: =SUM(G34:HP34)
C35: =E35*D$5 | E35: =SUM(G35:HP35)
C36: =E36*D$5 | E36: =SUM(G36:HP36)
C37: =E37*D$5 | E37: =SUM(G37:HY37)
C38: =E38*D$5 | E38: =SUM(G38:HS38)
C39: =E39*D$5 | E39: =SUM(G39:HH39)
C40: =E40*D$5 | E40: =SUM(G40:HH40)
C41: =E41*D$5 | E41: =SUM(G41:HH41)
C42: =E42*D$5 | E42: =SUM(G42:HH42)
C43: =E43*D$5 | E43: =SUM(G43:HH43)
C44: =E44*D$5 | E44: =SUM(G44:HP44)
C45: =E45*D$5 | E45: =SUM(G45:HP45)
C46: =E46*D$5 | E46: =SUM(G46:HP46)
C47: =E47*D$5 | E47: =SUM(G47:HP47)
C48: =E48*D$5 | E48: =SUM(G48:HP48)
C49: =E49*D$5 | E49: =SUM(G49:HP49)
C50: =E50*D$5 | E50: =SUM(G50:HP50)
C51: =E51*D$5 | E51: =SUM(G51:HP51)
C52: =E52*D$5 | E52: =SUM(G52:HP52)
C53: =E53*D$5 | E53: =SUM(G53:HP53)
C54: =E54*D$5 | E54: =SUM(G54:HP54)
C55: =E55*D$5 | E55: =SUM(G55:HP55)
... C203: =E203*D$5 | E203: =SUM(G203:HP203)

Sheet WI 1
A1: OK48147.001.1 — DIVERSIFIED PATH; WI/NRI/NET ACRES OPEN; CARLSON 7H CARVE | E1: Instrument | H1: Confirmation of Division | I1: Confirmation of Merger | J1: Wellbore Sale | K1: Conveyance
A2: 1 | B2: TRACT | D2: All rights limited to the Cherokee Formation | E2: Image Number
B3: DESCRIPTION | E3: Book / Page | H3: =Runsheet!D2 | I3: =Runsheet!D3 | J3: =Runsheet!D4 | K3: =Runsheet!D5
E4: Date | H4: =Runsheet!F2 | I4: =Runsheet!F3 | J4: =Runsheet!F4 | K4: =Runsheet!F5
B5: TRACT ACRES | D5: 640 | E5: Conveyance | H5: IDENTITY PATH — OPEN | I5: IDENTITY PATH — OPEN | J5: WELLBORE CARVE | K5: WELLBORE CARVE
B6: BASE OGL | D6: Working Interest — source-limited | F6: SURFACE | K6: =IF(K7=0,"","RECHECK") | L6: =IF(L7=0,"","RECHECK") | M6: =IF(M7=0,"","RECHECK") | N6: =IF(N7=0,"","RECHECK") | O6: =IF(O7=0,"","RECHECK") | P6: =IF(P7=0,"","RECHECK") | R6: =IF(R7=0,"","RECHECK") | S6: =IF(S7=0,"","RECHECK") | T6: =IF(T7=0,"","RECHECK") | U6: =IF(U7=0,"","RECHECK") | V6: =IF(V7=0,"","RECHECK") | W6: =IF(W7=0,"","RECHECK") | X6: =IF(X7=0,"","RECHECK") | Y6: =IF(Y7=0,"","RECHECK") | Z6: =IF(Z7=0,"","RECHECK") | AB6: =IF(AB7=0,"","RECHECK") | AC6: =IF(AC7=0,"","RECHECK") | AD6: =IF(AD7=0,"","RECHECK") | AE6: =IF(AE7=0,"","RECHECK") | AF6: =IF(AF7=0,"","RECHECK") | AG6: =IF(AG7=0,"","RECHECK") | AH6: =IF(AH7=0,"","RECHECK") | AI6: =IF(AI7=0,"","RECHECK") | ... FQ6: =IF(FQ7=0,"","RECHECK")
G7: =SUBTOTAL(9,G10:G164) | H7: =SUBTOTAL(9,H10:H164) | I7: =SUBTOTAL(9,I10:I164) | J7: =SUBTOTAL(9,J10:J164) | K7: =SUBTOTAL(9,K10:K164) | L7: =SUBTOTAL(9,L10:L164) | M7: =SUBTOTAL(9,M10:M164) | N7: =SUBTOTAL(9,N10:N164) | ... FQ7: =SUBTOTAL(9,FQ10:FQ164)
A8: NOTES | D8: OWNERS
A9: OPEN — QUANTUM NOT DETERMINED | B9: OK48147.001.1 | D9: Diversified Production LLC — supported record-derived leasehold claimant
A10: IDENTITY PATH | B10: 2400/551–567 | D10: DP Sooner HoldCo LLC → Diversified Production LLC
A11: IDENTITY PATH | B11: 2395/415–464 | D11: DP Legacy Tapstone LLC → DP Sooner HoldCo LLC / Diversified ABS VI Upstream LLC
A12: BASE OGL OPEN | B12: 1697/236 | D12: Staghorn → Chesapeake assignment reference; not a proved base oil and gas lease
A13: WELLBORE CARVE OPEN | B13: 2183/174; 2185/639 | D13: Carlson 32-11-25 7H carve — intersection with OK48147 remains unmapped
C14: =E14*D$5 | E14: =SUM(G14:HJ14)
C15: =E15*D$5 | E15: =SUM(G15:HJ15)
C16: =E16*D$5 | E16: =SUM(G16:HJ16)
C17: =E17*D$5 | E17: =SUM(G17:HJ17)
C18: =E18*D$5 | E18: =SUM(G18:HJ18)
C19: =E19*D$5 | E19: =SUM(G19:HJ19)
C20: =E20*D$5 | E20: =SUM(G20:HJ20)
C21: =E21*D$5 | E21: =SUM(G21:HJ21)
C22: =E22*D$5 | E22: =SUM(G22:HJ22)
C23: =E23*D$5 | E23: =SUM(G23:HJ23)
C24: =E24*D$5 | E24: =SUM(G24:HJ24)
C25: =E25*D$5 | E25: =SUM(G25:HJ25)
... C163: =E163*D$5 | E163: =SUM(G163:HJ163)

Sheet WI 2
A1: NOT USED | B1: WI 2 | D1: No separate Springer Formation chain is supported within this Cherokee-limited cursory report | E1: Image Number
B2: DESCRIPTION | E2: Book / Page
E3: Date
B4: TRACT ACRES | E4: Conveyance
B5: STATUS | C5: N/A | D5: Working Interest 2 — NOT USED | E5: N/A | F5: OUT OF SCOPE | K5: =IF(K6=0,"","RECHECK") | L5: =IF(L6=0,"","RECHECK") | M5: =IF(M6=0,"","RECHECK") | N5: =IF(N6=0,"","RECHECK") | O5: =IF(O6=0,"","RECHECK") | P5: =IF(P6=0,"","RECHECK") | R5: =IF(R6=0,"","RECHECK") | S5: =IF(S6=0,"","RECHECK") | T5: =IF(T6=0,"","RECHECK") | U5: =IF(U6=0,"","RECHECK") | V5: =IF(V6=0,"","RECHECK") | W5: =IF(W6=0,"","RECHECK") | X5: =IF(X6=0,"","RECHECK") | Y5: =IF(Y6=0,"","RECHECK") | ... FQ5: =IF(FQ6=0,"","RECHECK")
G6: =SUBTOTAL(9,G9:G143) | H6: =SUBTOTAL(9,H9:H143) | I6: =SUBTOTAL(9,I9:I143) | J6: =SUBTOTAL(9,J9:J143) | K6: =SUBTOTAL(9,K9:K143) | L6: =SUBTOTAL(9,L9:L143) | M6: =SUBTOTAL(9,M9:M143) | N6: =SUBTOTAL(9,N9:N143) | ... FQ6: =SUBTOTAL(9,FQ9:FQ143)
A7: NOTES | D7: OWNERS
A9: NOT USED | D9: Unrelated inherited schedule removed; no separate Springer working-interest conclusion is stated.
C10: =E10*D$4 | E10: =SUM(G10:HJ10)
C11: =E11*D$4 | E11: =SUM(G11:HJ11)
C12: =E12*D$4 | E12: =SUM(G12:HJ12)
C13: =E13*D$4 | E13: =SUM(G13:HJ13)
C14: =E14*D$4 | E14: =SUM(G14:HJ14)
C15: =E15*D$4 | E15: =SUM(G15:HJ15)
C16: =E16*D$4 | E16: =SUM(G16:HJ16)
C17: =E17*D$4 | E17: =SUM(G17:HJ17)
C18: =E18*D$4 | E18: =SUM(G18:HJ18)
C19: =E19*D$4 | E19: =SUM(G19:HJ19)
C20: =E20*D$4 | E20: =SUM(G20:HJ20)
C21: =E21*D$4 | E21: =SUM(G21:HJ21)
... C142: =E142*D$4 | E142: =SUM(G142:HJ142)

Sheet Well 1
A1: Wells
A2: Well # | B2: API # | C2: Current Operator | D2: Well Name | E2: Formation | F2: Surface Location | G2: Bottom Hole Location | H2: Spud Date | I2: Perforated Interval(s) | J2: TD & TVD | K2: Spacing | L2: MU Order | M2: Type | N2: Completion Date | O2: Last Production | P2: Plugging | Q2: Allocation
A3: 1 | B3: 35-009-2192300 | C3: OPEN (regulatory) | D3: Carlson 32-11-25 7H | E3: OPEN | F3: Sec 32-11N-25W | G3: OPEN | M3: H | P3: OPEN | Q3: Wellbore carve 2183/174; correction 2185/639 → Linn Energy Holdings; API 35-009-2192300. OK48147 is absent from the carve exhibit (Garrett OK0005037-002 only). Overlap, current operator/status, orders, production and HBP remain NEEDS VERIFICATION. Source: _PROJECT_FILES\03_QA_AND_SUPPORT\FINAL_COMPLETION_PACKAGE\carlson_7h_carve_analysis.md
A4: 2 | B4: 35-009-20312 | C4: Complete Oil & Gas Services LLC | D4: Crook 1-32 | E4: Granite Wash Lower | F4: C W/2 NE/4 | G4: OPEN | M4: DRY | P4: DRY | Q4: OCC RBDMS filtered snapshot dated 2026-07-09 reports status code AC with well/status fields DRY/DRY — conflict preserved. Cause CD 59995 / Order 156126 dated 1979-08-06 was directly reviewed: it pools listed formations under all Section 32, names Leede as operator, and states a 180-day commencement condition. Current effect, production matching and HBP remain OPEN. Order source: _PROJECT_FILES\01_SOURCE_READ_ONLY\FROM_ROOT_00_EXTERNAL_EVIDENCE_INBOX\STAGING\ACCEPTED\OCC_PREEXISTING_ER_05\OCC_Order_156126_Cause_CD_59995_1979-08-06.pdf. Well source: _PROJECT_FILES\01_SOURCE_READ_ONLY\FROM_ROOT_00_EXTERNAL_EVIDENCE_INBOX\STAGING\ACCEPTED\OCC_PREEXISTING_ER_06_ctx\OCC_RBDMS_Section32_Filtered_2026-07-09.csv
A5: 3 | B5: 35-009-20605 | C5: SM ENERGY COMPANY | D5: Pearl 1-32 | E5: OPEN | F5: E/2 W/2 NE/4 | G5: OPEN | M5: GAS | P5: PLUGGED | Q5: OCC RBDMS filtered snapshot dated 2026-07-09 reports status code PA and PLUGGED. Regulatory context only — not present WI or HBP proof. Source: _PROJECT_FILES\01_SOURCE_READ_ONLY\FROM_ROOT_00_EXTERNAL_EVIDENCE_INBOX\STAGING\ACCEPTED\OCC_PREEXISTING_ER_06_ctx\OCC_RBDMS_Section32_Filtered_2026-07-09.csv
A6: 4 | B6: 35-009-00075 | C6: BP AMERICA PRODUCTION COMPANY | D6: CORA GARRETT #C-310 | E6: OPEN | F6: SE/4 SE/4 SE/4; 330' E, 330' S | G6: OPEN | K6: OPEN | L6: OPEN | M6: GAS | P6: PLUGGED | Q6: OCC snapshot code PA; regulatory context only — title, orders, production continuity and HBP NEED VERIFICATION. Source: _PROJECT_FILES\01_SOURCE_READ_ONLY\FROM_ROOT_00_EXTERNAL_EVIDENCE_INBOX\STAGING\ACCEPTED\OCC_PREEXISTING_ER_06_ctx\OCC_RBDMS_Section32_Filtered_2026-07-09.csv
A7: 5 | B7: 35-009-20738 | C7: LEEDE OIL & GAS INC | D7: LEGRAND #1-32 | E7: OPEN | F7: NW/4 SE/4 NW/4; 1,900' W, 1,220' S | G7: OPEN | K7: OPEN | L7: OPEN | M7: DRY | P7: PLUGGED | Q7: OCC snapshot code PA; regulatory context only — title, orders, production continuity and HBP NEED VERIFICATION. Source: _PROJECT_FILES\01_SOURCE_READ_ONLY\FROM_ROOT_00_EXTERNAL_EVIDENCE_INBOX\STAGING\ACCEPTED\OCC_PREEXISTING_ER_06_ctx\OCC_RBDMS_Section32_Filtered_2026-07-09.csv
A8: 6 | B8: 35-009-21072 | C8: BCE-MACH II LLC | D8: JGL #1-32 | E8: OPEN | F8: SW/4 NW/4 SW/4 NE/4; 240' W, 740' S | G8: OPEN | K8: OPEN | L8: OPEN | M8: GAS | P8: GAS | Q8: OCC snapshot code AC; regulatory context only — operator role is not title ownership and HBP NEEDS VERIFICATION. Source: _PROJECT_FILES\01_SOURCE_READ_ONLY\FROM_ROOT_00_EXTERNAL_EVIDENCE_INBOX\STAGING\ACCEPTED\OCC_PREEXISTING_ER_06_ctx\OCC_RBDMS_Section32_Filtered_2026-07-09.csv
A9: 7 | B9: 35-009-21085 | C9: BCE-MACH II LLC | D9: HANKS CROOK #1-32 | E9: OPEN | F9: C S/2 NE/4; 1,320' W, 660' S | G9: OPEN | K9: OPEN | L9: OPEN | M9: GAS | P9: GAS | Q9: OCC snapshot code AC; regulatory context only — operator role is not title ownership and HBP NEEDS VERIFICATION. Source: _PROJECT_FILES\01_SOURCE_READ_ONLY\FROM_ROOT_00_EXTERNAL_EVIDENCE_INBOX\STAGING\ACCEPTED\OCC_PREEXISTING_ER_06_ctx\OCC_RBDMS_Section32_Filtered_2026-07-09.csv
A10: 8 | B10: 35-009-21166 | C10: VASTAR RESOURCES INC | D10: CROOK-LEGRAND #1-32 | E10: OPEN | F10: S/2 N/2 N/2 SE/4 | G10: OPEN | K10: OPEN | L10: OPEN | M10: NT | P10: PLUGGED | Q10: OCC snapshot code PA; regulatory context only — title, orders, production continuity and HBP NEED VERIFICATION. Source: _PROJECT_FILES\01_SOURCE_READ_ONLY\FROM_ROOT_00_EXTERNAL_EVIDENCE_INBOX\STAGING\ACCEPTED\OCC_PREEXISTING_ER_06_ctx\OCC_RBDMS_Section32_Filtered_2026-07-09.csv
A11: 9 | B11: 35-009-21236 | C11: BCE-MACH II LLC | D11: LEGRAND #1-32 | E11: OPEN | F11: NW/4 NE/4 SE/4 SW/4; 2,200' W, 1,150' S | G11: OPEN | K11: OPEN | L11: OPEN | M11: GAS | P11: GAS | Q11: Distinct API from 35-009-20738. OCC snapshot code AC; regulatory context only — HBP NEEDS VERIFICATION. Source: _PROJECT_FILES\01_SOURCE_READ_ONLY\FROM_ROOT_00_EXTERNAL_EVIDENCE_INBOX\STAGING\ACCEPTED\OCC_PREEXISTING_ER_06_ctx\OCC_RBDMS_Section32_Filtered_2026-07-09.csv
A12: 10 | B12: 35-009-21245 | C12: BP AMERICA PRODUCTION COMPANY | D12: KATIE #1-32 | E12: OPEN | F12: N/2 N/2 S/2 NW/4 | G12: OPEN | K12: OPEN | L12: OPEN | M12: NT | P12: OTHER | Q12: OCC snapshot code EX; regulatory context only — title, orders, production continuity and HBP NEED VERIFICATION. Source: _PROJECT_FILES\01_SOURCE_READ_ONLY\FROM_ROOT_00_EXTERNAL_EVIDENCE_INBOX\STAGING\ACCEPTED\OCC_PREEXISTING_ER_06_ctx\OCC_RBDMS_Section32_Filtered_2026-07-09.csv
A13: 11 | B13: 35-009-21258 | C13: BCE-MACH II LLC | D13: LEGRAND #2-32 | E13: OPEN | F13: N/2 N/2 S/2 NW/4; 1,320' W, 1,070' S | G13: OPEN | K13: OPEN | L13: OPEN | M13: GAS | P13: GAS | Q13: OCC snapshot code AC; regulatory context only — operator role is not title ownership and HBP NEEDS VERIFICATION. Source: _PROJECT_FILES\01_SOURCE_READ_ONLY\FROM_ROOT_00_EXTERNAL_EVIDENCE_INBOX\STAGING\ACCEPTED\OCC_PREEXISTING_ER_06_ctx\OCC_RBDMS_Section32_Filtered_2026-07-09.csv
A14: 12 | B14: 35-009-21391 | C14: BCE-MACH II LLC | D14: TWIN #1-32 | E14: OPEN | F14: NW/4 NE/4 SE/4 SW/4; 2,000' W, 1,150' S | G14: OPEN | K14: OPEN | L14: OPEN | M14: GAS | P14: GAS | Q14: OCC snapshot code AC; regulatory context only — operator role is not title ownership and HBP NEEDS VERIFICATION. Source: _PROJECT_FILES\01_SOURCE_READ_ONLY\FROM_ROOT_00_EXTERNAL_EVIDENCE_INBOX\STAGING\ACCEPTED\OCC_PREEXISTING_ER_06_ctx\OCC_RBDMS_Section32_Filtered_2026-07-09.csv

Sheet IMAGE_INVENTORY_0001_0500
A1: Source position | B1: Exact filename | C1: Drive file ID or link | D1: Opened visually | E1: Review status | F1: Image quality | G1: Document-group ID | H1: First page or continuation | I1: Relevant to Section 32 | J1: Relevant to Diversified | K1: Extraction status | L1: Notes
A2: 1 | B2: 0001.jpg | C2: https://drive.google.com/file/d/1mY8YO0k5KwvNxInc1hTdEGBNg3OYM4Bk/view | D2: YES | E2: reviewed_instrument_page | F2: fair-to-good | G2: B01-G001 | H2: first_or_single_page | I2: True | J2: False | K2: extracted | L2: Visually inspected; OCR used only as an aid. Multiple groups listed where the page contains separate instruments.
A3: 2 | B3: 0002.jpg | C3: https://drive.google.com/file/d/1siMKLe61gqsnKVcTG_L-TYKk-21epkWE/view | D3: YES | E3: reviewed_instrument_page | F3: fair-to-good | G3: B01-G002 | H3: first_or_single_page | I3: True | J3: False | K3: extracted | L3: Visually inspected; OCR used only as an aid. Multiple groups listed where the page contains separate instruments.
A4: 3 | B4: 0003.jpg | C4: https://drive.google.com/file/d/19SOFVjSNOE5Kpc9dO8iXWtNAZ3jHkOjv/view | D4: YES | E4: reviewed_instrument_page | F4: fair-to-good | G4: B01-G003 | H4: first_or_single_page | I4: True | J4: False | K4: extracted | L4: Visually inspected; OCR used only as an aid. Multiple groups listed where the page contains separate instruments.
A5: 4 | B5: 0004.jpg | C5: https://drive.google.com/file/d/1GjILIn9DFyeHP-iu0xV-aY5j6f_56eDN/view | D5: YES | E5: reviewed_instrument_page | F5: fair-to-good | G5: B01-G004; B01-G005 | H5: first_or_single_page | I5: True | J5: False | K5: partial_or_multi_instrument_extracted | L5: Visually inspected; OCR used only as an aid. Multiple groups listed where the page contains separate instruments.
A6: 5 | B6: 0005.jpg | C6: https://drive.google.com/file/d/112DMLh6DeA8ECaVqN3_DLqrXjuKs6ECt/view | D6: YES | E6: reviewed_instrument_page | F6: fair-to-good | G6: B01-G006; B01-G007 | H6: first_or_single_page | I6: True | J6: False | K6: partial_or_multi_instrument_extracted | L6: Visually inspected; OCR used only as an aid. Multiple groups listed where the page contains separate instruments.
A7: 6 | B7: 0006.jpg | C7: https://drive.google.com/file/d/1BiI5GbY3m4ojKIPvyzApAwtu5L-tCXcc/view | D7: YES | E7: reviewed_instrument_page | F7: fair-to-good | G7: B01-G008; B01-G009 | H7: first_or_single_page | I7: True | J7: False | K7: partial_or_multi_instrument_extracted | L7: Visually inspected; OCR used only as an aid. Multiple groups listed where the page contains separate instruments.
A8: 7 | B8: 0007.jpg | C8: https://drive.google.com/file/d/1EzKyARydVQaTjiLzbxK5b_63_J-IDjor/view | D8: YES | E8: duplicate | F8: fair-to-good | G8: B01-G010 | H8: first_or_single_page | I8: True | J8: False | K8: duplicate_linked | L8: Duplicate exposure of 0008.jpg.
A9: 8 | B9: 0008.jpg | C9: https://drive.google.com/file/d/14ab5mC2Rs-CGpLmamoxuosbqhdpRxn4A/view | D9: YES | E9: reviewed_instrument_page | F9: fair-to-good | G9: B01-G010 | H9: first_or_single_page | I9: True | J9: False | K9: extracted | L9: Visually inspected; OCR used only as an aid. Multiple groups listed where the page contains separate instruments.
A10: 9 | B10: 0009.jpg | C10: https://drive.google.com/file/d/1zS4kMxokKsha7PQxemTfaaBSHMwqg0bY/view | D10: YES | E10: reviewed_instrument_page | F10: fair-to-good | G10: B01-G011 | H10: first_or_single_page | I10: True | J10: False | K10: extracted | L10: Visually inspected; OCR used only as an aid. Multiple groups listed where the page contains separate instruments.
A11: 10 | B11: 0010.jpg | C11: https://drive.google.com/file/d/1cXtfmzroHg-7uzj7PZh3bdKNao327mgw/view | D11: YES | E11: continuation_or_mixed_page | F11: fair-to-good | G11: B01-G011 | H11: continuation | I11: True | J11: False | K11: partial_or_multi_instrument_extracted | L11: Visually inspected; OCR used only as an aid. Multiple groups listed where the page contains separate instruments.
A12: 11 | B12: 0011.jpg | C12: https://drive.google.com/file/d/1AZlWYkrrpMAddT7Uzs3lQN3AkswMTERA/view | D12: YES | E12: continuation_or_mixed_page | F12: fair-to-good | G12: B01-G011 | H12: continuation | I12: True | J12: False | K12: partial_or_multi_instrument_extracted | L12: Visually inspected; OCR used only as an aid. Multiple groups listed where the page contains separate instruments.
A13: 12 | B13: 0012.jpg | C13: https://drive.google.com/file/d/1GIEyB4F5gEM0OgFYbFgxGzfQjDD7SHBV/view | D13: YES | E13: reviewed_instrument_page | F13: fair-to-good | G13: B01-G012 | H13: first_or_single_page | I13: True | J13: False | K13: extracted | L13: Visually inspected; OCR used only as an aid. Multiple groups listed where the page contains separate instruments.
... A501: 500 | B501: 0500.jpg | C501: https://drive.google.com/file/d/1Go1VbgdqihqzLynoyo-pyaygR1poaSiX/view | D501: YES | E501: continuation_or_mixed_page | F501: fair-negative | G501: B10-G032 | H501: continuation | I501: False | J501: False | K501: partial_boundary_instrument | L501: Indenture pages 10-11 photographed as spread; bond form inspected. Text plainly continues past the scoped boundary.

Sheet RAW_IMAGE_EXTRACTION
A1: Group Id | B1: Image Start | C1: Image End | D1: Exact Filenames | E1: Page Count | F1: Doc Type Abbrev | G1: Full Title | H1: Instrument Number | I1: Book | J1: Beginning Page | K1: Ending Page | L1: Recording Date/Time | M1: Execution Date | N1: Effective Date | O1: Acknowledgment Date | P1: Grantor | Q1: Grantee | R1: Assignor | S1: Assignee | T1: Lessor | U1: Lessee | V1: Mortgagor | W1: Mortgagee | X1: Releasor | Y1: Releasee | Z1: Decedent | AA1: Other Capacities | AB1: Mailing Addresses | AC1: Legal Description Raw | AD1: Legal Description Normalized | AE1: Section | AF1: Township | AG1: Range | AH1: County | AI1: State | AJ1: Quarter | AK1: Quarter Quarter | AL1: Lots | AM1: Stated Acreage | AN1: Mineral Acreage | AO1: Fractions | AP1: Percentages | AQ1: Royalty | AR1: Wi | AS1: Nri | AT1: Orri | AU1: Production Payment | AV1: Depth | AW1: Formation | AX1: Wellbore | AY1: Surface Limitations | AZ1: Lease References | BA1: Base Lease References | BB1: Prior References | BC1: Reservations | BD1: Exceptions | BE1: Subject To | BF1: Term | BG1: Extensions | BH1: Consideration | BI1: Wells | BJ1: Api | BK1: Unit | BL1: Material Title Notes | BM1: Interest Before | BN1: Interest After | BO1: Relevance To Diversified | BP1: Confidence Classification | BQ1: Assumptions | BR1: Human Review Status
A2: B01-G001 | B2: 1 | C2: 1 | D2: 0001.jpg | E2: 1 | F2: WD | G2: Warranty Deed | I2: 9 | J2: 418 | L2: March 12, 1907, 7:00 A.M. | M2: October 11, 1906 | O2: October 11, 1906 | P2: Velmore Biggs and Hettie A. Biggs, his wife | Q2: Edward J. Gordon | AC2: South east quarter of section thirty two (32) township eleven (11), range twenty five (25), consisting of 160 acres | AD2: SE/4 of Section 32, Township 11 North, Range 25 West of the Indian Meridian | AE2: 32 | AF2: 11 North | AG2: 25 West | AH2: Beckham (formerly Roger Mills) | AI2: Oklahoma | AJ2: SE/4 | AM2: 160 | BE2: $800 mortgage in favor of Oklahoma Farm Mortgage Company | BH2: $2,150.00 | BO2: No chain basis identified in Batch 01. | BP2: high | BR2: not_required
A3: B01-G002 | B3: 2 | C3: 2 | D3: 0002.jpg | E3: 1 | F3: WD | G3: Warranty Deed | I3: 12 | L3: July 18, 1907, 1:00 P.M. | M3: July 16, 1907 | O3: July 16, 1907 | P3: Cornelius B. Cornelius and Margreta Cornelius, husband and wife | Q3: Jacob Bollenbach | AC3: The North-east quarter (NE) of Section Thirty-two (32) in Township Eleven (11) North of Range Twenty-five (25) West containing One Hundred and Sixty (160) acres | AD3: NE/4 of Section 32, Township 11 North, Range 25 West of the Indian Meridian | AE3: 32 | AF3: 11 North | AG3: 25 West | AH3: Beckham (formerly Roger Mills) | AI3: Oklahoma | AJ3: NE/4 | AM3: 160 | BD3: 1907 taxes | BH3: $2,000.00 | BO3: No chain basis identified in Batch 01. | BP3: high | BR3: not_required
A4: B01-G003 | B4: 3 | C4: 3 | D4: 0003.jpg | E4: 1 | F4: PAT | G4: Homestead Patent | I4: Patent Record | J4: 369 | M4: March 22, 1906 | P4: United States of America | Q4: Cornelius B. Cornelius | AC4: North-east quarter of Section thirty-two in Township Eleven, North of Range Twenty-five, West of Indian Meridian in Oklahoma, containing One Hundred and Sixty acres | AD4: NE/4 of Section 32, Township 11 North, Range 25 West of the Indian Meridian | AE4: 32 | AF4: 11 North | AG4: 25 West | AH4: Beckham (formerly Roger Mills) | AI4: Oklahoma | AJ4: NE/4 | AM4: 160 | BO4: No chain basis identified in Batch 01. | BP4: high | BR4: not_required
A5: B01-G004 | B5: 4 | C5: 4 | D5: 0004.jpg | E5: 1 | F5: FRR | G5: Final Receiver's Receipt / Homestead Entry | H5: Final Receiver's Receipt No. 4668 | L5: July 12, 1908 | Q5: Alfred R. Harris | AC5: N 1/2 W 1/2; SW 1/4 and SE 1/4 SW 1/4 (section number unclear) | AI5: Oklahoma | BL5: Not shown as Section 32; handwriting and abbreviations require review. | BO5: No chain basis identified in Batch 01. | BP5: medium | BQ5: Treated as a separate receipt on the upper portion of image 0004. | BR5: required
A6: B01-G005 | B6: 4 | C6: 4 | D6: 0004.jpg | E6: 1 | F6: FRR | G6: Final Receiver's Receipt / Homestead Entry | H6: Final Receiver's Receipt No. 128 | L6: August 8, 1908 | Q6: Velmore Biggs | AC6: S.E. 1/4 of Section 32, Township 11 N., Range 25 W. | AD6: SE/4 of Section 32, Township 11 North, Range 25 West of the Indian Meridian | AE6: 32 | AF6: 11 North | AG6: 25 West | AH6: Beckham (formerly Roger Mills) | AI6: Oklahoma | AJ6: SE/4 | AM6: 160 | BO6: No chain basis identified in Batch 01. | BP6: medium | BR6: required
A7: B01-G006 | B7: 5 | C7: 5 | D7: 0005.jpg | E7: 1 | F7: FRR | G7: Final Receiver's Receipt / Homestead Entry | H7: Final Receiver's Receipt No. 3895 | Q7: Albertus B. Hardison | AC7: W 1/2 SE 1/4 and E 1/2 SE 1/4; Section 23, Township 10 N., Range 22 W. | AE7: 23 | AF7: 10 North | AG7: 22 West | AI7: Oklahoma | BO7: No chain basis identified in Batch 01. | BP7: medium | BR7: required
A8: B01-G007 | B8: 5 | C8: 5 | D8: 0005.jpg | E8: 1 | F8: FRR | G8: Final Receiver's Receipt / Homestead Entry | H8: Application No. 16018 | Q8: Herman Stevens | AC8: SW 1/4 of Section 32, Township 11 N., Range 25 W. | AD8: SW/4 of Section 32, Township 11 North, Range 25 West of the Indian Meridian | AE8: 32 | AF8: 11 North | AG8: 25 West | AH8: Beckham (formerly Roger Mills) | AI8: Oklahoma | AJ8: SW/4 | AM8: 160 | BO8: No chain basis identified in Batch 01. | BP8: medium | BR8: required
A9: B01-G008 | B9: 6 | C9: 6 | D9: 0006.jpg | E9: 1 | F9: FRR | G9: Final Receiver's Receipt / Homestead Entry | H9: Final Receiver's Receipt No. 3895; Application No. 16126 | L9: May 12, 1908 | Q9: Augustus P. Stevens | AC9: SW 1/4, Section 32, Township 11 N., Range 25 W. | AD9: SW/4 of Section 32, Township 11 North, Range 25 West of the Indian Meridian | AE9: 32 | AF9: 11 North | AG9: 25 West | AH9: Beckham (formerly Roger Mills) | AI9: Oklahoma | AJ9: SW/4 | AM9: 160 | BO9: No chain basis identified in Batch 01. | BP9: medium | BR9: required
A10: B01-G009 | B10: 6 | C10: 6 | D10: 0006.jpg | E10: 1 | F10: FRR | G10: Final Receiver's Receipt / Homestead Entry | H10: Final Receiver's Receipt No. 3876; Application No. 13662 | Q10: John J. Armstrong | AC10: W 1/2 SE 1/4 and NE 1/4 SE 1/4, Section 20, Township 11 N., Range 22 W. | AE10: 20 | AF10: 11 North | AG10: 22 West | AI10: Oklahoma | BO10: No chain basis identified in Batch 01. | BP10: medium | BR10: required
A11: B01-G010 | B11: 8 | C11: 8 | D11: 0008.jpg | E11: 1 | F11: MTG | G11: Real Estate and Chattel Mortgage | J11: 173 | L11: April 17, 1907, 8:00 A.M. | M11: April 5, 1907 | O11: April 15, 1907 | V11: A. P. Stevens | W11: The Cotton Exchange State Bank | AC11: The South-west quarter of Section 32 Township 11, Range 25, W.I.M. | AD11: SW/4 of Section 32, Township 11 North, Range 25 West of the Indian Meridian | AE11: 32 | AF11: 11 North | AG11: 25 West | AH11: Beckham (formerly Roger Mills) | AI11: Oklahoma | AJ11: SW/4 | AM11: 160 | BH11: $613.00 | BL11: 0007.jpg is a duplicate image of this recorded page; exact source retained as 0008.jpg. | BO11: No chain basis identified in Batch 01. | BP11: medium | BQ11: Party initials and some chattel-note details are difficult. | BR11: required
A12: B01-G011 | B12: 9 | C12: 11 | D12: 0009.jpg 0010.jpg 0011.jpg | E12: 3 | F12: MTG | G12: Real Estate Mortgage | J12: 249 | K12: 251 | L12: May 12, 1905, 6:30 P.M. | M12: May 10, 1905 | O12: May 12, 1905 | V12: Augustus P. Stevens and Herman Stevens, single men | W12: C. J. Weiser | AC12: The southwest quarter and northwest quarter of section thirty-two, township eleven north, range twenty-five west | AD12: SW/4 and NW/4 of Section 32, Township 11 North, Range 25 West of the Indian Meridian | AE12: 32 | AF12: 11 North | AG12: 25 West | AH12: Beckham (formerly Roger Mills) | AI12: Oklahoma | AJ12: SW/4; NW/4 | AM12: 320 | BF12: Due May 10, 1908; 6% before maturity; 12% after maturity | BH12: $817.00 | BO12: No chain basis identified in Batch 01. | BP12: high | BR12: not_required
A13: B01-G012 | B13: 12 | C13: 12 | D13: 0012.jpg | E13: 1 | F13: MTG | G13: Oklahoma Farm Mortgage | I13: 12 | J13: 117 | L13: July 31, 1906 | M13: July 27, 1906 | V13: Velmore Biggs and Hettie Biggs, husband and wife | W13: Oklahoma Farm Mortgage Company | AC13: The south east quarter of section thirty two (32) in township eleven (11) north of range twenty five (25) west | AD13: SE/4 of Section 32, Township 11 North, Range 25 West of the Indian Meridian | AE13: 32 | AF13: 11 North | AG13: 25 West | AH13: Beckham (formerly Roger Mills) | AI13: Oklahoma | AJ13: SE/4 | AM13: 160 | BH13: $500.00 | BL13: 0013.jpg is a duplicate image of this recorded page. | BO13: No chain basis identified in Batch 01. | BP13: high | BR13: not_required
A14: B01-G013 | B14: 14 | C14: 14 | D14: 0014.jpg | E14: 1 | F14: AOM | G14: Assignment of Mortgage | L14: August 31, 1906 | M14: August 29, 1906 | R14: Oliver L. Johnson | S14: First National Bank, Elk City, Oklahoma | AC14: Lots 9-14, Block 45, Elk City, Oklahoma | AH14: Roger Mills | AI14: Oklahoma | AL14: Lots 9-14, Block 45 | BH14: $5,000.00 | BO14: No chain basis identified in Batch 01. | BP14: high | BR14: not_required
A15: B01-G014 | B15: 14 | C15: 14 | D15: 0014.jpg | E15: 1 | F15: AOM | G15: Assignment of Mortgage | I15: 1 | J15: 3 | L15: September 10, 1906 | M15: September 10, 1906 | R15: Oklahoma Farm Mortgage Company | S15: Miss Mabel G. Allen | AC15: The South-east Quarter of Section Thirty-two (32) in Township Eleven (11), North of Range Twenty-five (25) West, containing 160 acres | AD15: SE/4 of Section 32, Township 11 North, Range 25 West of the Indian Meridian | AE15: 32 | AF15: 11 North | AG15: 25 West | AH15: Beckham (formerly Roger Mills) | AI15: Oklahoma | AJ15: SE/4 | AM15: 160 | BB15: Mortgage dated July 27, 1906 | BH15: $500.00 | BO15: No chain basis identified in Batch 01. | BP15: high | BR15: not_required
A16: B01-G015 | B16: 15 | C16: 15 | D16: 0015.jpg | E16: 1 | F16: AOM | G16: Assignment of Mortgage | I16: 1 | J16: 4 | L16: September 24, 1906 | M16: September 10, 1906 | R16: Mabel G. Allen | S16: Dr. S. E. Denbois | AC16: The South-east Quarter of Section Thirty-two (32), Township Eleven (11) North, Range Twenty-five (25) West, containing 160 acres | AD16: SE/4 of Section 32, Township 11 North, Range 25 West of the Indian Meridian | AE16: 32 | AF16: 11 North | AG16: 25 West | AH16: Beckham (formerly Roger Mills) | AI16: Oklahoma | AJ16: SE/4 | AM16: 160 | BH16: $500.00 | BO16: No chain basis identified in Batch 01. | BP16: medium | BR16: required
A17: B01-G016 | B17: 15 | C17: 15 | D17: 0015.jpg | E17: 1 | F17: AOM | G17: Assignment of Mortgage | L17: September 26, 1906 | R17: Name unclear | S17: Mr. Poole | AC17: South half of the Northeast Quarter and north half of the Southeast Quarter, Section 13, Township 8 North, Range 22 West | AE17: 13 | AF17: 8 North | AG17: 22 West | AH17: Roger Mills | AI17: Oklahoma | BH17: $300.00 | BO17: No chain basis identified in Batch 01. | BP17: medium | BQ17: Assignor is illegible. | BR17: required
A18: B01-G017 | B18: 16 | C18: 16 | D18: 0016.jpg | E18: 1 | F18: PAT | G18: Homestead Patent | J18: 75 | P18: United States of America | Q18: Name appears to be Velmore Biggs | AC18: Southwest quarter of Section 31, Township 11 North, Range 24 West, containing 160 acres | AE18: 31 | AF18: 11 North | AG18: 24 West | AI18: Oklahoma | AM18: 160 | BO18: No chain basis identified in Batch 01. | BP18: low | BQ18: Handwritten patentee and legal description are faint; not treated as Section 32. | BR18: required
A19: B01-G018 | B19: 17 | C19: 17 | D19: 0017.jpg | E19: 1 | F19: AOM | G19: Assignment of Mortgage | I19: 12 | J19: 17 | L19: April 8, 1908, 6:00 P.M. | M19: April 3, 1908 | R19: W. S. P. [surname unclear] | S19: Jacob Guda [name uncertain] | AC19: The northeast quarter of Section thirty-two (32), Township eleven (11) North, Range twenty-five (25) West, containing 160 acres | AD19: NE/4 of Section 32, Township 11 North, Range 25 West of the Indian Meridian | AE19: 32 | AF19: 11 North | AG19: 25 West | AH19: Beckham (formerly Roger Mills) | AI19: Oklahoma | AJ19: NE/4 | AM19: 160 | BH19: $500.00 | BO19: No chain basis identified in Batch 01. | BP19: low | BQ19: Handwritten party names are uncertain. | BR19: required
A20: B01-G019 | B20: 17 | C20: 17 | D20: 0017.jpg | E20: 1 | F20: AOM | G20: Assignment of Mortgage | L20: April 9, 1908 | M20: April 2, 1908 | R20: Martin H. G. | S20: John L. [surname unclear] | AC20: North half of the Southeast quarter and North half of the Southwest quarter, Section 19, Township 8 North, Range 23 West | AE20: 19 | AF20: 8 North | AG20: 23 West | AH20: Beckham | AI20: Oklahoma | BH20: $700.00 | BO20: No chain basis identified in Batch 01. | BP20: low | BQ20: Party names require human reading. | BR20: required
A21: B01-G020 | B21: 18 | C21: 18 | D21: 0018.jpg | E21: 1 | F21: MTG | G21: Oklahoma Mortgage | J21: 316 | L21: December 9, 1908 | M21: December 1, 1908 | V21: Paul [surname unclear] and wife | W21: Oklahoma Farm Mortgage Company | AC21: The South East Quarter of Section Thirty-two in Township Eleven North of Range Twenty-five West | AD21: SE/4 of Section 32, Township 11 North, Range 25 West of the Indian Meridian | AE21: 32 | AF21: 11 North | AG21: 25 West | AH21: Beckham (formerly Roger Mills) | AI21: Oklahoma | AJ21: SE/4 | AM21: 160 | BH21: $1,000.00 | BL21: 0019.jpg appears to be a duplicate exposure of the same form/page. | BO21: No chain basis identified in Batch 01. | BP21: low | BQ21: Mortgagor names are too faint for reliable transcription. | BR21: required
A22: B01-G021 | B22: 20 | C22: 20 | D22: 0020.jpg | E22: 1 | F22: MTG | G22: First Real Estate Mortgage | J22: 101 | L22: December 10, 1908 | M22: December 1, 1908 | V22: Augustus P. Stevens, a single man | W22: W. B. [surname unclear] | AC22: The southwest quarter of Section Thirty-two, Township Eleven North, Range Twenty-five West | AD22: SW/4 of Section 32, Township 11 North, Range 25 West of the Indian Meridian | AE22: 32 | AF22: 11 North | AG22: 25 West | AH22: Beckham (formerly Roger Mills) | AI22: Oklahoma | AJ22: SW/4 | AM22: 160 | BO22: No chain basis identified in Batch 01. | BP22: low | BQ22: Mortgagee and monetary terms are faint. | BR22: required
A23: B01-G022 | B23: 21 | C23: 21 | D23: 0021.jpg | E23: 1 | F23: REL | G23: Release of Mortgage | J23: 476 | L23: June 21, 1912 | M23: June 11, 1912 | X23: P. W. Gunn | Y23: J. Adam and wife | AC23: SE 1/4 NE 1/4 and SE 1/4 NW 1/4, Section 33, Township 9 North, Range 22 West | AE23: 33 | AF23: 9 North | AG23: 22 West | AH23: Beckham | AI23: Oklahoma | BB23: Mortgage Book 3, page 111 | BO23: No chain basis identified in Batch 01. | BP23: low | BR23: required
A24: B01-G023 | B24: 21 | C24: 21 | D24: 0021.jpg | E24: 1 | F24: REL | G24: Release of Mortgage | L24: June 21, 1912 | M24: June 20, 1912 | X24: King [initials unclear] | Y24: Philip H. S. | AC24: Lots and blocks in Elk City, Oklahoma | AH24: Beckham | AI24: Oklahoma | BO24: No chain basis identified in Batch 01. | BP24: low | BQ24: Names and lot description are handwritten and uncertain. | BR24: required
A25: B01-G024 | B25: 22 | C25: 23 | D25: 0022.jpg 0023.jpg | E25: 2 | F25: MTG | G25: Mortgage | J25: 328 | K25: 329 | L25: January 18, 1909, 9:00 A.M. | M25: January 13, 1909 | O25: January 16, 1909 | V25: Jacob Bollenbach and Katharina Bollenbach, his wife | W25: Union Central Life Insurance Company | AC25: North East Quarter of Section Thirty-two (32), Township Eleven (11) North, Range Twenty-five (25) West | AD25: NE/4 of Section 32, Township 11 North, Range 25 West of the Indian Meridian | AE25: 32 | AF25: 11 North | AG25: 25 West | AH25: Beckham (formerly Roger Mills) | AI25: Oklahoma | AJ25: NE/4 | AM25: 160 | BH25: $400.00 | BO25: No chain basis identified in Batch 01. | BP25: high | BR25: not_required
A26: B01-G025 | B26: 24 | C26: 24 | D26: 0024.jpg | E26: 1 | F26: MTG | G26: Mortgage | J26: 330 | L26: January 20, 1909, 9:00 A.M. | M26: January 13, 1909 | V26: Joshua P. Hill and Sallie C. Hill, his wife | W26: Union Central Life Insurance Company | AC26: South one-half of Section 17, Township 7 North, Range 24 West | AE26: 17 | AF26: 7 North | AG26: 24 West | AH26: Beckham | AI26: Oklahoma | AM26: 320 | BH26: $3,000.00 | BO26: No chain basis identified in Batch 01. | BP26: high | BR26: not_required
A27: B01-G026 | B27: 25 | C27: 25 | D27: 0025.jpg | E27: 1 | F27: PAT | G27: Homestead Patent | H27: Homestead Certificate No. 3815; Application No. 16126 | J27: 295 | M27: November 3, 1909 | P27: United States of America | Q27: Augustus P. Stevens | AC27: South West quarter of Section thirty-two in Township Eleven North of Range twenty-five West of Indian Meridian, containing one hundred and sixty acres | AD27: SW/4 of Section 32, Township 11 North, Range 25 West of the Indian Meridian | AE27: 32 | AF27: 11 North | AG27: 25 West | AH27: Beckham (formerly Roger Mills) | AI27: Oklahoma | AJ27: SW/4 | AM27: 160 | BO27: No chain basis identified in Batch 01. | BP27: high | BR27: not_required
A28: B01-G027 | B28: 26 | C28: 26 | D28: 0026.jpg | E28: 1 | F28: REL | G28: Release of Mortgage | J28: 200 | L28: January 19, 1909 | X28: Name unclear | Y28: Name unclear | AC28: South half of the South east quarter and Southeast quarter of Southwest quarter, Section 30, Township 10 North, Range 22 West | AE28: 30 | AF28: 10 North | AG28: 22 West | AH28: Beckham | AI28: Oklahoma | BO28: No chain basis identified in Batch 01. | BP28: low | BQ28: Handwriting prevents reliable party transcription. | BR28: required
A29: B01-G028 | B29: 26 | C29: 26 | D29: 0026.jpg | E29: 1 | F29: REL | G29: Release of Mortgage | J29: 200 | L29: January 19, 1909 | X29: Oklahoma Farm Mortgage Company | Y29: Mortgagor name unclear | AC29: The southwest quarter of Section thirty-two (32), Township eleven North, Range twenty-five West | AD29: SW/4 of Section 32, Township 11 North, Range 25 West of the Indian Meridian | AE29: 32 | AF29: 11 North | AG29: 25 West | AH29: Beckham (formerly Roger Mills) | AI29: Oklahoma | AJ29: SW/4 | AM29: 160 | BO29: No chain basis identified in Batch 01. | BP29: low | BQ29: Party names and prior mortgage page require review. | BR29: required
A30: B01-G029 | B30: 27 | C30: 27 | D30: 0027.jpg | E30: 1 | F30: REL | G30: Release of Mortgage | J30: 201 | L30: January 19, 1909 | X30: Oklahoma Farm Mortgage Company | Y30: Mortgagor name unclear | AC30: Southwest quarter of Section 33, Township 8 North, Range 21 West | AE30: 33 | AF30: 8 North | AG30: 21 West | AH30: Beckham | AI30: Oklahoma | BO30: No chain basis identified in Batch 01. | BP30: low | BR30: required
A31: B01-G030 | B31: 27 | C31: 27 | D31: 0027.jpg | E31: 1 | F31: REL | G31: Release of Mortgage | J31: 201 | L31: January 19, 1909 | X31: Charles E. Davis | Y31: R. [surname unclear] | AC31: Lots 1, 2, 3, 4 and 5 in Block 15, Doffey Addition to Elk City, Oklahoma | AH31: Beckham | AI31: Oklahoma | AL31: Lots 1-5, Block 15 | BO31: No chain basis identified in Batch 01. | BP31: low | BR31: required
A32: B01-G031 | B32: 28 | C32: 28 | D32: 0028.jpg | E32: 1 | F32: MTG | G32: Mortgage of Real Estate | J32: 212 | L32: February 9, 1909, 3:00 P.M. | M32: February 6, 1909 | O32: February 6, 1909 | V32: Augustus P. Stevens, a single man | W32: The Cotton Exchange State Bank | AC32: The North West Quarter of section thirty two (32), Township Eleven (11), Range Twenty Five (25) W.I.M. containing 160 acres | AD32: NW/4 of Section 32, Township 11 North, Range 25 West of the Indian Meridian | AE32: 32 | AF32: 11 North | AG32: 25 West | AH32: Beckham (formerly Roger Mills) | AI32: Oklahoma | AJ32: NW/4 | AM32: 160 | BH32: $370.00 | BO32: No chain basis identified in Batch 01. | BP32: medium | BR32: required
A33: B01-G032 | B33: 29 | C33: 29 | D33: 0029.jpg | E33: 1 | F33: WD | G33: Warranty Deed | J33: 393 | L33: January 31, 1909 | P33: E. D. Gordon and Annie A. Gordon, his wife | Q33: Edward [surname unclear] | AC33: The South West Quarter of Section Thirty-two in Township Eleven North, Range Twenty-five West, containing one hundred and sixty acres | AD33: SW/4 of Section 32, Township 11 North, Range 25 West of the Indian Meridian | AE33: 32 | AF33: 11 North | AG33: 25 West | AH33: Beckham (formerly Roger Mills) | AI33: Oklahoma | AJ33: SW/4 | AM33: 160 | BO33: No chain basis identified in Batch 01. | BP33: low | BQ33: Grantee surname and consideration are difficult. | BR33: required
A34: B01-G033 | B34: 30 | C34: 30 | D34: 0030.jpg | E34: 1 | F34: AOM | G34: Assignment of Mortgage | J34: 70 | R34: Oklahoma Farm Mortgage Company | S34: Mary [surname unclear] | AC34: The East half of the South west quarter of Section thirty-two and other land | AD34: E/2 SW/4 of Section 32, Township 11 North, Range 25 West of the Indian Meridian | AE34: 32 | AF34: 11 North | AG34: 25 West | AH34: Beckham (formerly Roger Mills) | AI34: Oklahoma | AJ34: E/2 SW/4 | BO34: No chain basis identified in Batch 01. | BP34: low | BQ34: Party name, recording date, and full multi-tract legal require review. | BR34: required
A35: B01-G034 | B35: 30 | C35: 30 | D35: 0030.jpg | E35: 1 | F35: AOM | G35: Assignment of Mortgage | J35: 70 | R35: Jacob Bollenbach | S35: Name unclear | AC35: The North East quarter of Section thirty-two (32), Township Eleven North, Range Twenty-five West | AD35: NE/4 of Section 32, Township 11 North, Range 25 West of the Indian Meridian | AE35: 32 | AF35: 11 North | AG35: 25 West | AH35: Beckham (formerly Roger Mills) | AI35: Oklahoma | AJ35: NE/4 | AM35: 160 | BB35: Mortgage Book 11, page 111 | BO35: No chain basis identified in Batch 01. | BP35: low | BQ35: Assignee name is illegible. | BR35: required
A36: B01-G035 | B36: 31 | C36: 31 | D36: 0031.jpg | E36: 1 | F36: JDG | G36: Judgment (continuation only) | J36: 323 | AA36: A. T. Hoblin, Justice of the Peace | AH36: Beckham | AI36: Oklahoma | BL36: Only the concluding text of an out-of-scope prior-page judgment is visible. | BO36: No chain basis identified in Batch 01. | BP36: low | BQ36: Instrument begins before Batch 01 and cannot be fully identified. | BR36: required
A37: B01-G036 | B37: 31 | C37: 31 | D37: 0031.jpg | E37: 1 | F37: AOM | G37: Assignment of Mortgage | J37: 323 | L37: February 22, 1908, 8:00 P.M. | M37: February 22, 1908 | R37: Beers & Co. | S37: Stevens, A. P. | AC37: South west quarter of Section thirty-two (32), Township eleven North, Range 25 West | AD37: SW/4 of Section 32, Township 11 North, Range 25 West of the Indian Meridian | AE37: 32 | AF37: 11 North | AG37: 25 West | AH37: Beckham (formerly Roger Mills) | AI37: Oklahoma | AJ37: SW/4 | BB37: Mortgage record Book 13, page 234; $300 indebtedness | BO37: No chain basis identified in Batch 01. | BP37: medium | BR37: required
A38: B01-G037 | B38: 32 | C38: 32 | D38: 0032.jpg | E38: 1 | F38: WD | G38: Warranty Deed | J38: 235 | L38: June 21, 1910 | M38: June 18, 1910 | O38: June 18, 1910 | P38: Jacob Bollenbach and Katharina Bollenbach, husband and wife | Q38: Adolf Bollenbach and Ena Bollenbach | AC38: The North East quarter of Section thirty-two (32), Township Eleven North, Range Twenty-five West, containing 160 acres | AD38: NE/4 of Section 32, Township 11 North, Range 25 West of the Indian Meridian | AE38: 32 | AF38: 11 North | AG38: 25 West | AH38: Beckham (formerly Roger Mills) | AI38: Oklahoma | AJ38: NE/4 | AM38: 160 | BC38: Grantors reserve an interest stated on the deed; exact fraction is faint. | BO38: No chain basis identified in Batch 01. | BP38: medium | BQ38: Reserved fraction requires human confirmation. | BR38: required
A39: B01-G038 | B39: 33 | C39: 33 | D39: 0033.jpg | E39: 1 | F39: MTG | G39: Mortgage of Real Estate | J39: 410 | L39: January 31, 1910 | M39: January 18, 1910 | V39: Adolf Bollenbach and Ena Bollenbach, husband and wife | W39: Jacob Bollenbach | AC39: The North East quarter (NE 1/4) of Section thirty-two (32), Township eleven North, Range twenty-five West, containing 160 acres | AD39: NE/4 of Section 32, Township 11 North, Range 25 West of the Indian Meridian | AE39: 32 | AF39: 11 North | AG39: 25 West | AH39: Beckham (formerly Roger Mills) | AI39: Oklahoma | AJ39: NE/4 | AM39: 160 | BH39: $2,800.00 | BO39: No chain basis identified in Batch 01. | BP39: medium | BR39: required
A40: B01-G039 | B40: 34 | C40: 34 | D40: 0034.jpg | E40: 1 | F40: AOM | G40: Assignment of Mortgage (continuation) | M40: June 15, 1910 | R40: Merchants State Bank of Waterville, Kansas | S40: Clara W. Clingman | AC40: Legal begins on a prior image; visible ending says Range 22 West | AG40: 22 West | AI40: Oklahoma | BB40: Mortgage volume 14, page 234 | BH40: $660.00 | BL40: Continuation from a prior, unavailable page. | BO40: No chain basis identified in Batch 01. | BP40: medium | BR40: required
A41: B01-G040 | B41: 34 | C41: 34 | D41: 0034.jpg | E41: 1 | F41: REL | G41: Release of Mortgage | I41: 4 Misc. | J41: 155 | L41: July 21, 1910, 2:00 P.M. | M41: July 16, 1910 | O41: July 18, 1910 | X41: Jacob Bollenbach | Y41: Adolf Bollenbach and Ena Bollenbach | AC41: The North East Quarter of Section Thirty-Two in Township Eleven North Range Twenty Five W.I.M. containing one hundred sixty acres | AD41: NE/4 of Section 32, Township 11 North, Range 25 West of the Indian Meridian | AE41: 32 | AF41: 11 North | AG41: 25 West | AH41: Beckham (formerly Roger Mills) | AI41: Oklahoma | AJ41: NE/4 | AM41: 160 | BB41: Mortgage Record No. 4, page 410; mortgage dated January 18, 1910 | BO41: No chain basis identified in Batch 01. | BP41: high | BR41: not_required
A42: B01-G041 | B42: 35 | C42: 35 | D42: 0035.jpg | E42: 1 | F42: MTG | G42: Mortgage of Real Estate | J42: 515 | L42: July 21, 1910, 2:00 P.M. | M42: July 20, 1910 | O42: July 20, 1910 | V42: Adolf Bollenbach and Ena Bollenbach, husband and wife | W42: Jacob Bollenbach | AC42: The North East quarter of Section thirty-two (32), Township Eleven (11) North, Range twenty-five (25) West, containing one hundred and sixty acres | AD42: NE/4 of Section 32, Township 11 North, Range 25 West of the Indian Meridian | AE42: 32 | AF42: 11 North | AG42: 25 West | AH42: Beckham (formerly Roger Mills) | AI42: Oklahoma | AJ42: NE/4 | AM42: 160 | BF42: One note due January 18, 1915; 7% interest | BH42: $2,800.00 | BO42: No chain basis identified in Batch 01. | BP42: medium | BR42: required
A43: B01-G042 | B43: 36 | C43: 36 | D43: 0036.jpg | E43: 1 | F43: REL | G43: Corporation Release of Mortgage | I43: 4 Misc. | J43: 483 | L43: February 25, 1911, 2:00 P.M. | M43: June 11, 1910 | X43: Cotton Exchange State Bank of Elk City, Oklahoma | Y43: Augustus P. Stevens | AC43: South West quarter of Section thirty-two (32), Township Eleven (11), Range Twenty-five (25) W.I.M. | AD43: SW/4 of Section 32, Township 11 North, Range 25 West of the Indian Meridian | AE43: 32 | AF43: 11 North | AG43: 25 West | AH43: Beckham (formerly Roger Mills) | AI43: Oklahoma | AJ43: SW/4 | BB43: Mortgage Book 4, page 212 | BO43: No chain basis identified in Batch 01. | BP43: high | BR43: not_required
A44: B01-G043 | B44: 36 | C44: 36 | D44: 0036.jpg | E44: 1 | F44: REL | G44: Release of Mortgage | I44: 4 Misc. | J44: 483 | L44: February 27, 1911, 8:00 A.M. | M44: February 24, 1911 | X44: The Jefferson Trust Company | Y44: John W. Jacobs | AC44: South West quarter of Section 24, Township 10 North, Range 26 West | AE44: 24 | AF44: 10 North | AG44: 26 West | AH44: Beckham | AI44: Oklahoma | BB44: Mortgage Book 14, page 436 | BH44: $125.00 | BO44: No chain basis identified in Batch 01. | BP44: high | BR44: not_required
A45: B01-G044 | B45: 37 | C45: 37 | D45: 0037.jpg | E45: 1 | F45: AOM | G45: Assignment of Mortgage | I45: 6 Misc. | J45: 254 | L45: February 24, 1913, 8:00 A.M. | M45: August 9, 1910 | R45: Jacob Bollenbach | S45: Hulda Hahn | AC45: North East Quarter of Section Thirty-two (32), Township Eleven (11) North, Range Twenty-five (25) West of Indian Meridian, containing 160 acres | AD45: NE/4 of Section 32, Township 11 North, Range 25 West of the Indian Meridian | AE45: 32 | AF45: 11 North | AG45: 25 West | AH45: Beckham (formerly Roger Mills) | AI45: Oklahoma | AJ45: NE/4 | AM45: 160 | BB45: Mortgage Book 4, page 515; mortgage dated July 20, 1910 | BO45: No chain basis identified in Batch 01. | BP45: high | BR45: not_required
A46: B01-G045 | B46: 38 | C46: 38 | D46: 0038.jpg | E46: 1 | F46: PAT | G46: Homestead Patent | H46: Homestead Certificate No. 6011 | J46: 124 | M46: May 4, 1912 | P46: United States of America | Q46: William B. Farrar | AC46: North West quarter of Section thirty-two in Township Eleven North of Range Twenty-five West of the Indian Meridian, containing one hundred and sixty acres | AD46: NW/4 of Section 32, Township 11 North, Range 25 West of the Indian Meridian | AE46: 32 | AF46: 11 North | AG46: 25 West | AH46: Beckham (formerly Roger Mills) | AI46: Oklahoma | AJ46: NW/4 | AM46: 160 | BO46: No chain basis identified in Batch 01. | BP46: medium | BR46: required
A47: B01-G046 | B47: 39 | C47: 39 | D47: 0039.jpg | E47: 1 | F47: CERT | G47: Land Office Certificate of Cancellation | I47: 6 Misc. | J47: 441 | L47: July 21, 1913, 9:00 A.M. | M47: July 19, 1913 | AA47: Hugh Scott, Receiver, United States Land Office | AC47: SW 1/4 Sec. 32, T. 11 N., R. 25 W.I.M. | AD47: SW/4 of Section 32, Township 11 North, Range 25 West of the Indian Meridian | AE47: 32 | AF47: 11 North | AG47: 25 West | AH47: Beckham (formerly Roger Mills) | AI47: Oklahoma | AJ47: SW/4 | BB47: Commissioner's Letter H, July 9, 1907 | BL47: Certifies Herman Stephens Homestead Entry No. 16112 / Final Certificate No. 3694 was cancelled by Commissioner's letter of July 9, 1907. | BO47: No chain basis identified in Batch 01. | BP47: high | BR47: not_required
A48: B01-G047 | B48: 39 | C48: 39 | D48: 0039.jpg | E48: 1 | F48: REL | G48: Release of Mortgage | I48: 6 Misc. | J48: 441 | L48: July 21, 1913, 9:00 A.M. | M48: June 17, 1913 | X48: Charles E. Davis | Y48: J. W. Deering and Mattie E. Deering | AC48: Lots 13 through 21, Block 12, Shores Addition to Elk City | AH48: Beckham | AI48: Oklahoma | AL48: Lots 13-21, Block 12 | BB48: Mortgage Record No. 23, page 180 | BO48: No chain basis identified in Batch 01. | BP48: high | BR48: not_required
A49: B01-G048 | B49: 40 | C49: 40 | D49: 0040.jpg | E49: 1 | F49: MTG | G49: Oklahoma Mortgage | J49: 368 | L49: June 29, 1913 | M49: June 26, 1913 | V49: William B. Farrar and Emma Farrar, husband and wife | W49: The Martin Loan and Investment Company | AC49: The North West quarter of Section Thirty-two (32), Township Eleven (11) North, Range Twenty-five (25) West | AD49: NW/4 of Section 32, Township 11 North, Range 25 West of the Indian Meridian | AE49: 32 | AF49: 11 North | AG49: 25 West | AH49: Beckham (formerly Roger Mills) | AI49: Oklahoma | AJ49: NW/4 | AM49: 160 | BH49: $1,025.00 | BO49: No chain basis identified in Batch 01. | BP49: low | BQ49: Some monetary terms and recording details are faint. | BR49: required
A50: B01-G049 | B50: 41 | C50: 41 | D50: 0041.jpg | E50: 1 | F50: AOM | G50: Assignment of Mortgage | J50: 20 | M50: October 16, 1913 | R50: Martin Loan and Investment Company | S50: Mary Florence | AC50: Lots in Elk City, Oklahoma | AH50: Beckham | AI50: Oklahoma | BH50: $4,000.00 | BO50: No chain basis identified in Batch 01. | BP50: medium | BR50: required
A51: B01-G050 | B51: 41 | C51: 41 | D51: 0041.jpg | E51: 1 | F51: AOM | G51: Assignment of Mortgage | J51: 20 | L51: August 14, 1913 | M51: July 28, 1913 | R51: Martin Loan and Investment Company | S51: Mabel L. Benton | AC51: The North West Quarter of Section Thirty-two (32), Township Eleven (11) North, Range Twenty-five (25) West of the Indian Meridian | AD51: NW/4 of Section 32, Township 11 North, Range 25 West of the Indian Meridian | AE51: 32 | AF51: 11 North | AG51: 25 West | AH51: Beckham (formerly Roger Mills) | AI51: Oklahoma | AJ51: NW/4 | BB51: Mortgage Book 12, page 368 | BH51: $825.00 | BO51: No chain basis identified in Batch 01. | BP51: medium | BR51: required
A52: B01-G051 | B52: 42 | C52: 43 | D52: 0042.jpg 0043.jpg | E52: 2 | F52: MTG | G52: Second Mortgage | I52: 24 Mortgages | J52: 451 | K52: 452 | L52: December 12, 1913, 1:00 P.M. | M52: November 28, 1912 | O52: November 28, 1913 | V52: A. P. Stevens, a single man | W52: Garretson & Woodward | AC52: The south west quarter of Section Thirty-two (32), Township Eleven (11) North, Range Twenty-five (25) West of the Indian Meridian | AD52: SW/4 of Section 32, Township 11 North, Range 25 West of the Indian Meridian | AE52: 32 | AF52: 11 North | AG52: 25 West | AH52: Beckham (formerly Roger Mills) | AI52: Oklahoma | AJ52: SW/4 | BE52: Prior mortgage of same date between same parties for $1,100.00 | BF52: Matures June 1, 1914; 6% until maturity, 10% after maturity | BH52: $137.50 | BL52: Acknowledgment year appears inconsistent with execution year and requires review. | BO52: No chain basis identified in Batch 01. | BP52: high | BR52: not_required
A53: B01-G052 | B53: 43 | C53: 43 | D53: 0043.jpg | E53: 1 | F53: MTG | G53: Mortgage and Refunding Bond (partial) | I53: 24 Mortgages | J53: 452 | L53: December 15, 1913, 10:00 A.M. | M53: December 3, 1913 | V53: L. M. McMillan, O. C. Hartzog, and M. M. Allen, Trustees of Carter Methodist Episcopal Church, South | W53: Board of Church Extension of the Methodist Episcopal Church, South | AH53: Beckham | AI53: Oklahoma | BH53: $200.00 | BL53: Instrument continues beyond Batch 01; legal description not visible. | BO53: No chain basis identified in Batch 01. | BP53: medium | BQ53: Only the first page portion is in scope. | BR53: required
A54: B01-G053 | B54: 44 | C54: 44 | D54: 0044.jpg | E54: 1 | F54: MTG | G54: Oklahoma Mortgage | J54: 426 | L54: February 26, 1915, 10:00 A.M. | M54: January 26, 1915 | O54: January 26, 1915 | V54: William B. Farrar and Emma Farrar, husband and wife | W54: The Martin Loan and Investment Company | AC54: The North West quarter of Section thirty-two (32), Township Eleven (11) North, Range Twenty-five (25) West | AD54: NW/4 of Section 32, Township 11 North, Range 25 West of the Indian Meridian | AE54: 32 | AF54: 11 North | AG54: 25 West | AH54: Beckham (formerly Roger Mills) | AI54: Oklahoma | AJ54: NW/4 | AM54: 160 | BH54: $1,000.00 | BO54: No chain basis identified in Batch 01. | BP54: medium | BR54: required
A55: B01-G054 | B55: 45 | C55: 45 | D55: 0045.jpg | E55: 1 | F55: REL | G55: Release of Mortgage | J55: 150 | L55: July 10, 1914 | M55: February 3, 1914 | X55: State S. Benton | Y55: William B. Farrar and Emma Farrar | AC55: The Northwest quarter of Section thirty-two (32), Township Eleven (11) North, Range twenty-five (25) West | AD55: NW/4 of Section 32, Township 11 North, Range 25 West of the Indian Meridian | AE55: 32 | AF55: 11 North | AG55: 25 West | AH55: Beckham (formerly Roger Mills) | AI55: Oklahoma | AJ55: NW/4 | BB55: Mortgage volume 12, page 368 | BO55: No chain basis identified in Batch 01. | BP55: low | BQ55: Releasor given name may be Mabel/State; handwriting requires confirmation. | BR55: required
A56: B01-G055 | B56: 45 | C56: 45 | D56: 0045.jpg | E56: 1 | F56: REL | G56: Release of Mortgage | L56: February 12, 1914 | M56: January 9, 1914 | X56: H. L. Parks | Y56: Evelyn E. [surname unclear] and husband | AC56: The southwest quarter of Section 30, Township 10 North, Range 22 West, containing 160 acres | AE56: 30 | AF56: 10 North | AG56: 22 West | AH56: Beckham | AI56: Oklahoma | AM56: 160 | BO56: No chain basis identified in Batch 01. | BP56: low | BR56: required
A57: B01-G056 | B57: 46 | C57: 46 | D57: 0046.jpg | E57: 1 | F57: AOM | G57: Assignment of Mortgage | J57: 82 | L57: December 19, 1913 | M57: December 18, 1913 | R57: Martin Loan and Investment Company | S57: Goldwin, Alice P. [reading uncertain] | AC57: The northwest quarter of Section thirty-two (32), Township Eleven (11) North, Range Twenty-five (25) West | AD57: NW/4 of Section 32, Township 11 North, Range 25 West of the Indian Meridian | AE57: 32 | AF57: 11 North | AG57: 25 West | AH57: Beckham (formerly Roger Mills) | AI57: Oklahoma | AJ57: NW/4 | BH57: $500.00 | BO57: No chain basis identified in Batch 01. | BP57: low | BQ57: Assignee name requires confirmation. | BR57: required
A58: B01-G057 | B58: 46 | C58: 46 | D58: 0046.jpg | E58: 1 | F58: AOM | G58: Assignment of Mortgage | J58: 82 | L58: February 24, 1914 | M58: February 22, 1914 | R58: Martin Loan and Investment Company | S58: Kate S. Genter | AC58: The North West quarter of Section thirty-two (32), Township Eleven (11) North, Range Twenty-five (25) West | AD58: NW/4 of Section 32, Township 11 North, Range 25 West of the Indian Meridian | AE58: 32 | AF58: 11 North | AG58: 25 West | AH58: Beckham (formerly Roger Mills) | AI58: Oklahoma | AJ58: NW/4 | BH58: $1,000.00 | BO58: No chain basis identified in Batch 01. | BP58: medium | BR58: required
A59: B01-G058 | B59: 47 | C59: 47 | D59: 0047.jpg | E59: 1 | F59: MTG | G59: Oklahoma Mortgage | J59: 428 | L59: February 26, 1915 | M59: January 26, 1915 | V59: William B. Farrar and Emma Farrar | W59: The Martin Loan and Investment Company | AC59: The North West quarter of Section thirty-two (32), Township Eleven (11) North, Range Twenty-five (25) West | AD59: NW/4 of Section 32, Township 11 North, Range 25 West of the Indian Meridian | AE59: 32 | AF59: 11 North | AG59: 25 West | AH59: Beckham (formerly Roger Mills) | AI59: Oklahoma | AJ59: NW/4 | AM59: 160 | BL59: Separate recorded mortgage from the page-426 instrument on 0044; secures three notes. | BO59: No chain basis identified in Batch 01. | BP59: low | BQ59: Principal amount is faint. | BR59: required
A60: B01-G059 | B60: 48 | C60: 48 | D60: 0048.jpg | E60: 1 | F60: MTG | G60: Real Estate Mortgage | I60: 27 Mortgages | J60: 64 | L60: September 10, 1915 | M60: September 8, 1915 | O60: September 8, 1915 | V60: Austin J. Coffey and Nancy J. Coffey | W60: P. E. Carroll | AC60: All of the Northwest Quarter of Section 32 in Township 11 North of Range 25 West of the Indian Meridian, containing 160 acres | AD60: NW/4 of Section 32, Township 11 North, Range 25 West of the Indian Meridian | AE60: 32 | AF60: 11 North | AG60: 25 West | AH60: Beckham (formerly Roger Mills) | AI60: Oklahoma | AJ60: NW/4 | AM60: 160 | BD60: Subject to prior mortgage executed by William B. Farrar and wife | BH60: $600.00 | BO60: No chain basis identified in Batch 01. | BP60: medium | BR60: required
A61: B01-G060 | B61: 49 | C61: 49 | D61: 0049.jpg | E61: 1 | F61: WD | G61: Warranty Deed | J61: 52 | L61: September 10, 1915, 9:00 A.M. | M61: September 4, 1915 | O61: September 4, 1915 | P61: William B. Farrar and Emma Farrar, husband and wife | Q61: Austin J. Coffey | AC61: The Northwest quarter of Section 32, Township 11 North, Range 25 West of the Indian Meridian, containing 160 acres more or less | AD61: NW/4 of Section 32, Township 11 North, Range 25 West of the Indian Meridian | AE61: 32 | AF61: 11 North | AG61: 25 West | AH61: Beckham (formerly Roger Mills) | AI61: Oklahoma | AJ61: NW/4 | AM61: 160 | BE61: Mortgage for $1,000 payable to Martin Loan and Investment Company | BH61: $2,250.00 | BO61: No chain basis identified in Batch 01. | BP61: medium | BR61: required
A62: B01-G061 | B62: 50 | C62: 50 | D62: 0050.jpg | E62: 1 | F62: REL | G62: Release of Mortgage | J62: 8 | L62: September 16, 1915, 10:00 A.M. | M62: September 10, 1915 | X62: The Martin Loan and Investment Company | Y62: William B. Farrar and Emma Farrar | AC62: Section 32, Township 11 North, Range 25 West; quarter appears to be Northwest Quarter | AD62: NW/4 of Section 32, Township 11 North, Range 25 West of the Indian Meridian | AE62: 32 | AF62: 11 North | AG62: 25 West | AH62: Beckham (formerly Roger Mills) | AI62: Oklahoma | AJ62: NW/4 | AM62: 160 | BB62: Mortgage volume 27, page 64; prior page reference appears as Book 12/page 368 | BO62: No chain basis identified in Batch 01. | BP62: medium | BQ62: Quarter designation and prior-reference handwriting should be checked. | BR62: required
A63: B01-G062 | B63: 50 | C63: 50 | D63: 0050.jpg | E63: 1 | F63: REL | G63: Release of Mortgage | J63: 8 | L63: December 30, 1915 | M63: December 28, 1915 | X63: The Martin Loan and Investment Company | Y63: H. B. Moore and wife | AC63: The North west quarter of Section Twenty-three (23), Township Eleven (11) North, Range Twenty-three (23) West | AE63: 23 | AF63: 11 North | AG63: 23 West | AH63: Beckham | AI63: Oklahoma | BB63: Mortgage page 362, volume 12 | BO63: No chain basis identified in Batch 01. | BP63: medium | BR63: required
A64: B02-G001 | B64: 51 | C64: 51 | D64: 0051.jpg | E64: 1 | F64: REL | G64: Release of Mortgage | I64: 8 Miscellaneous | J64: 101 | L64: October 16, 1916, 9:00 A.M. | M64: October 11, 1916 | X64: M. Carter | Y64: S. H. Carter, J. Carter, husband and wife, and P. M. Carter | AC64: North half of the northwest quarter and the southeast quarter of the northwest quarter of Section 19, Township 10 North, Range 21 West | AE64: 19 | AF64: 10 North | AG64: 21 West | AH64: Beckham | AJ64: N/2 NW/4; SE/4 NW/4 | BB64: Mortgage Record No. 27, page 80 | BM64: Mortgage lien held by M. Carter. | BN64: Mortgage declared satisfied and released. | BO64: No Diversified party or supported Diversified chain link appears in this instrument. | BP64: high | BR64: not_required
A65: B02-G002 | B65: 51 | C65: 53 | D65: 0051.jpg 0052.jpg 0053.jpg | E65: 3 | F65: LSE | G65: Agricultural Lease | I65: 8 Miscellaneous | J65: 101 | K65: 103 | L65: October 16, 1916, 9:00 A.M. | M65: October 14, 1916 | O65: October 14, 1916 | T65: Charles Sing | U65: T. K. Ross | AC65: One hundred sixty acres described as the Southeast quarter of Section 32, Township 11 North, Range 25 West | AD65: SE/4 of Section 32, Township 11 North, Range 25 West of the Indian Meridian | AE65: 32 | AF65: 11 North | AG65: 25 West | AH65: Beckham | AI65: Oklahoma | AJ65: SE/4 | AM65: 160 | BF65: Five years beginning January 1, 1917 and ending January 1, 1922 | BH65: $1,500 evidenced by five $300 annual notes; crop-sharing and farming covenants | BM65: Charles Sing held the lessor's interest in the described premises. | BN65: T. K. Ross received a five-year agricultural leasehold, subject to the stated covenants. | BO65: No Diversified party or supported Diversified chain link appears in this instrument. | BP65: high | BR65: not_required
A66: B02-G003 | B66: 54 | C66: 54 | D66: 0054.jpg | E66: 1 | F66: REL | G66: Release of Mortgage | I66: Release Record No. 4 | J66: 516 | X66: Oklahoma Farm Mortgage Company | Y66: Velmore Biggs and wife | AC66: Southeast quarter of Section 32, Township 11 North, Range 25 West, containing 160 acres | AD66: SE/4 of Section 32, Township 11 North, Range 25 West of the Indian Meridian | AE66: 32 | AF66: 11 North | AG66: 25 West | AH66: Beckham | AI66: Oklahoma | AJ66: SE/4 | AM66: 160 | BL66: Upper release on the page; handwriting is faint. | BM66: Recorded mortgage lien against the SE/4. | BN66: Mortgage lien released. | BO66: No Diversified party or supported Diversified chain link appears in this instrument. | BP66: medium | BR66: required
A67: B02-G004 | B67: 54 | C67: 54 | D67: 0054.jpg | E67: 1 | F67: REL | G67: Release of Mortgage | I67: Release Record No. 4 | J67: 516 | M67: January 18, 1912 | X67: Phil Allen, Jr. | Y67: Velmore Biggs and wife | AC67: Southeast quarter of Section 32, Township 11 North, Range 25 West, containing 160 acres | AD67: SE/4 of Section 32, Township 11 North, Range 25 West of the Indian Meridian | AE67: 32 | AF67: 11 North | AG67: 25 West | AH67: Beckham | AI67: Oklahoma | AJ67: SE/4 | AM67: 160 | BB67: Mortgage Book 12, page 117 | BL67: Lower release; mortgage was originally payable to Oklahoma Farm Mortgage Company and assigned to Phil Allen, Jr. | BM67: Phil Allen, Jr. held the assigned mortgage lien. | BN67: Mortgage lien released. | BO67: No Diversified party or supported Diversified chain link appears in this instrument. | BP67: medium | BR67: required
A68: B02-G005 | B68: 55 | C68: 55 | D68: 0055.jpg | E68: 1 | F68: WD | G68: Warranty Deed | I68: Warranty Deed Record No. 26 | J68: 294 | L68: December 4, 1916 | M68: September 23, 1916 | P68: Sing, Charles, and wife | Q68: Garratt, S. A. | AC68: Southeast quarter of Section 32, Township 11 North, Range 25 West of the Indian Meridian, Beckham County, Oklahoma | AD68: SE/4 of Section 32, Township 11 North, Range 25 West of the Indian Meridian | AE68: 32 | AF68: 11 North | AG68: 25 West | AH68: Beckham | AI68: Oklahoma | AJ68: SE/4 | BH68: $2,100.00 | BM68: Charles Sing and wife held the grantor interest shown. | BN68: S. A. Garratt received the described tract by warranty deed. | BO68: No Diversified party or supported Diversified chain link appears in this instrument. | BP68: medium | BR68: required
A69: B02-G006 | B69: 56 | C69: 56 | D69: 0056.jpg | E69: 1 | F69: MTG | G69: Real Estate Mortgage | I69: Mortgage Record No. 27 | J69: 277 | M69: November 24, 1917 | O69: November 24, 1917 | V69: S. A. Garrett and Cora Garrett, husband and wife | W69: Sing, Charles | AC69: Southeast quarter of Section 32, Township 11 North, Range 25 West of the Indian Meridian | AD69: SE/4 of Section 32, Township 11 North, Range 25 West of the Indian Meridian | AE69: 32 | AF69: 11 North | AG69: 25 West | AH69: Beckham | AI69: Oklahoma | AJ69: SE/4 | BH69: $2,015.00 | BM69: S. A. Garrett and Cora Garrett held the mortgagor interest shown. | BN69: Charles Sing received a mortgage lien on the SE/4. | BO69: No Diversified party or supported Diversified chain link appears in this instrument. | BP69: medium | BR69: required
A70: B02-G007 | B70: 57 | C70: 58 | D70: 0057.jpg 0058.jpg | E70: 2 | F70: OGL | G70: Oil and Gas Lease | I70: 8 Miscellaneous | J70: 471 | K70: 472 | L70: June 20, 1917, 9:00 A.M. | M70: May 2, 1917 | O70: May 2, 1917 | T70: Austin J. Coffey and Nancy L. Coffey, husband and wife | U70: Empire Oil and Fuel Company | AC70: Northwest quarter of Section 32, Township 11 North, Range 25 West, containing 160 acres | AD70: NW/4 of Section 32, Township 11 North, Range 25 West of the Indian Meridian | AE70: 32 | AF70: 11 North | AG70: 25 West | AH70: Beckham | AI70: Oklahoma | AJ70: NW/4 | AM70: 160 | AQ70: 1/8 of oil; customary gas and casinghead-gas consideration | BF70: Drilling to begin on or before May 1, 1918; thereafter maintained by operations, production, or stated delay rental provisions | BM70: Austin J. and Nancy L. Coffey held the lessor interest shown. | BN70: Empire Oil and Fuel Company received the oil-and-gas leasehold, subject to the lease terms. | BO70: No Diversified party or supported Diversified chain link appears in this instrument. | BP70: high | BR70: not_required
A71: B02-G008 | B71: 59 | C71: 59 | D71: 0059.jpg | E71: 1 | F71: REL | G71: Release of Mortgage | I71: Release Record No. 7 | J71: 40 | M71: November 16, 1917 | X71: D. H. Cunnelly, guardian | Y71: Martha W. Hollen and Charles Hollen, husband and wife | AC71: Southwest quarter of Section 29 and eastern half of the southwest quarter of Section 21, Township 11 North, Range 21 West | AE71: 29; 21 | AF71: 11 North | AG71: 21 West | AH71: Beckham | BL71: Upper instrument; party spellings and legal description are handwritten. | BM71: Recorded mortgage lien. | BN71: Mortgage lien released. | BO71: No Diversified party or supported Diversified chain link appears in this instrument. | BP71: medium | BR71: required
A72: B02-G009 | B72: 59 | C72: 59 | D72: 0059.jpg | E72: 1 | F72: REL | G72: Release of Mortgage | I72: Release Record No. 7 | J72: 40 | M72: November 12, 1917 | X72: Riley S. Butler | Y72: William B. Tarver and Emma Tarver, husband and wife | AC72: Northwest quarter of Section 32, Township 11 North, Range 25 West, containing 160 acres | AD72: NW/4 of Section 32, Township 11 North, Range 25 West of the Indian Meridian | AE72: 32 | AF72: 11 North | AG72: 25 West | AH72: Beckham | AI72: Oklahoma | AJ72: NW/4 | AM72: 160 | BB72: Mortgage Book 12, page 426 | BM72: Riley S. Butler held the mortgage lien shown. | BN72: Mortgage lien released. | BO72: No Diversified party or supported Diversified chain link appears in this instrument. | BP72: medium | BR72: required
A73: B02-G010 | B73: 60 | C73: 60 | D73: 0060.jpg | E73: 1 | F73: OGL | G73: Oil and Gas Lease | I73: 9 Miscellaneous | J73: 108 | M73: May 1, 1917 | T73: S. E. Brumley and wife | U73: Eolian Oil Company | AC73: East half of the southeast quarter of Section 32, Township 11 North, Range 25 West, containing 80 acres | AD73: E/2 SE/4 of Section 32, Township 11 North, Range 25 West of the Indian Meridian | AE73: 32 | AF73: 11 North | AG73: 25 West | AH73: Beckham | AI73: Oklahoma | AJ73: SE/4 | AK73: E/2 SE/4 | AM73: 80 | AQ73: 1/8 | BM73: S. E. Brumley and wife held the lessor interest shown. | BN73: Eolian Oil Company received the oil-and-gas leasehold. | BO73: No Diversified party or supported Diversified chain link appears in this instrument. | BP73: medium | BR73: required
A74: B02-G011 | B74: 61 | C74: 61 | D74: 0061.jpg | E74: 1 | F74: OGL | G74: Oil and Gas Lease | I74: 9 Miscellaneous | J74: 128 | M74: May 1, 1917 | T74: S. A. Garrett and Cora Garrett, husband and wife | U74: Eolian Oil Company | AC74: Southeast quarter of Section 32, Township 11 North, Range 25 West, containing 160 acres | AD74: SE/4 of Section 32, Township 11 North, Range 25 West of the Indian Meridian | AE74: 32 | AF74: 11 North | AG74: 25 West | AH74: Beckham | AI74: Oklahoma | AJ74: SE/4 | AM74: 160 | AQ74: 1/8 | BM74: S. A. Garrett and Cora Garrett held the lessor interest shown. | BN74: Eolian Oil Company received the oil-and-gas leasehold. | BO74: No Diversified party or supported Diversified chain link appears in this instrument. | BP74: medium | BR74: required
A75: B02-G012 | B75: 62 | C75: 62 | D75: 0062.jpg | E75: 1 | F75: WD | G75: Warranty Deed | I75: Warranty Deed Record No. 29 | J75: 398 | L75: April 1, 1918, 9:00 A.M. | M75: March 18, 1918 | P75: Austin J. Coffey and Nancy L. Coffey, husband and wife | Q75: W. H. Kelley | AC75: Northwest quarter of Section 32, Township 11 North, Range 25 West | AD75: NW/4 of Section 32, Township 11 North, Range 25 West of the Indian Meridian | AE75: 32 | AF75: 11 North | AG75: 25 West | AH75: Beckham | AI75: Oklahoma | AJ75: NW/4 | BC75: One-half revenue reservation noted in the deed | BH75: $1.00 and other consideration | BM75: Austin J. and Nancy L. Coffey held the grantor interest shown. | BN75: W. H. Kelley received the described tract subject to the stated reservation. | BO75: No Diversified party or supported Diversified chain link appears in this instrument. | BP75: medium | BR75: required
A76: B02-G013 | B76: 63 | C76: 63 | D76: 0063.jpg | E76: 1 | F76: MTG | G76: Real Estate Mortgage | I76: Mortgage Record No. 27 | J76: 345 | V76: W. H. Kelley and wife | W76: S. A. Coffey | AC76: Northwest quarter of Section 32, Township 11 North, Range 25 West | AD76: NW/4 of Section 32, Township 11 North, Range 25 West of the Indian Meridian | AE76: 32 | AF76: 11 North | AG76: 25 West | AH76: Beckham | AI76: Oklahoma | AJ76: NW/4 | BL76: Image is extremely faint; dates, amount, and exact spouse name require human verification. | BM76: W. H. Kelley and wife held the mortgagor interest shown. | BN76: S. A. Coffey received a mortgage lien. | BO76: No Diversified party or supported Diversified chain link appears in this instrument. | BP76: low | BR76: required
A77: B02-G014 | B77: 64 | C77: 64 | D77: 0064.jpg | E77: 1 | F77: ASN | G77: Assignment | I77: 10 Miscellaneous | J77: 98 | L77: April 23, 1918, 9:00 A.M. | M77: April 25, 1918 | O77: April 23, 1918 | R77: A. J. Coffey | S77: J. M. Aubury | AC77: All of the Northwest Quarter (NW/4) of Section 32, Township 11 North, Range 25 West of the Indian Meridian | AD77: NW/4 of Section 32, Township 11 North, Range 25 West of the Indian Meridian | AE77: 32 | AF77: 11 North | AG77: 25 West | AH77: Beckham | AI77: Oklahoma | AJ77: NW/4 | BB77: Mortgage Book 27, page 648 | BH77: $1,500.00 | BM77: A. J. Coffey held the note and mortgage interest described. | BN77: J. M. Aubury received the assigned note and mortgage interest. | BO77: No Diversified party or supported Diversified chain link appears in this instrument. | BP77: high | BR77: not_required
A78: B02-G015 | B78: 65 | C78: 65 | D78: 0065.jpg | E78: 1 | F78: AOL | G78: Assignment of Oil and Gas Lease | I78: 10 Miscellaneous | J78: 325 | L78: November 6, 1918, 2:00 P.M. | M78: October 22, 1918 | R78: Empire Gas & Fuel Company | S78: Midland Oil Company | T78: Tillman Albert Stone and Mary E. Stone, husband and wife | AC78: Southeast quarter, Section 19, Township 11 North, Range 26 West, containing 160 acres | AE78: 19 | AF78: 11 North | AG78: 26 West | AH78: Beckham | AJ78: SE/4 | AM78: 160 | AZ78: Lease dated May 2, 1917; Book 8 Miscellaneous, page 497 | BM78: Empire Gas & Fuel Company held the leasehold. | BN78: Midland Oil Company received the assigned leasehold. | BO78: No Diversified party or supported Diversified chain link appears in this instrument. | BP78: medium | BR78: required
A79: B02-G016 | B79: 65 | C79: 66 | D79: 0065.jpg 0066.jpg | E79: 2 | F79: AOL | G79: Assignment of Oil and Gas Lease | I79: 10 Miscellaneous | J79: 325 | K79: 326 | L79: November 6, 1918, 2:00 P.M. | M79: October 22, 1918 | R79: Empire Gas & Fuel Company | S79: Midland Oil Company | T79: Green A. Crook and Ellen W. Crook, husband and wife | AC79: Northeast quarter of Section 32, Township 11 North, Range 25 West, containing 160 acres | AD79: NE/4 of Section 32, Township 11 North, Range 25 West of the Indian Meridian | AE79: 32 | AF79: 11 North | AG79: 25 West | AH79: Beckham | AI79: Oklahoma | AJ79: NE/4 | AM79: 160 | AZ79: Lease dated May 4, 1917; Book 9 Miscellaneous, page 108 | BM79: Empire Gas & Fuel Company held the leasehold. | BN79: Midland Oil Company received the assigned leasehold. | BO79: No Diversified party or supported Diversified chain link appears in this instrument. | BP79: high | BR79: not_required
A80: B02-G017 | B80: 66 | C80: 66 | D80: 0066.jpg | E80: 1 | F80: AOL | G80: Assignment of Oil and Gas Lease | I80: 10 Miscellaneous | J80: 326 | L80: November 6, 1918, 2:00 P.M. | M80: October 22, 1918 | R80: Empire Gas & Fuel Company | S80: Midland Oil Company | T80: Richard O. Bradley and Bell Bradley, husband and wife | AC80: East half of Northwest quarter, Section 30, Township 11 North, Range 25 West, containing 80 acres | AE80: 30 | AF80: 11 North | AG80: 25 West | AH80: Beckham | AJ80: NW/4 | AK80: E/2 NW/4 | AM80: 80 | AZ80: Lease dated May 4, 1917; Book 8 Miscellaneous, page 469 | BL80: Instrument continues beyond the photographed page. | BM80: Empire Gas & Fuel Company held the leasehold. | BN80: Midland Oil Company received the assigned leasehold. | BO80: No Diversified party or supported Diversified chain link appears in this instrument. | BP80: medium | BR80: required
A81: B02-G018 | B81: 67 | C81: 67 | D81: 0067.jpg | E81: 1 | F81: MTG | G81: Mortgage (continuation only) | J81: 28 | K81: 29 | L81: November 1918 | V81: David F. Denton and Arvilla Denton | BL81: Only the concluding portion is visible; the first page and legal description are outside this batch. | BO81: No Diversified party or supported Diversified chain link appears in this instrument. | BP81: low | BQ81: Consolidated only the visible concluding portion; no unsupported land description supplied. | BR81: required
A82: B02-G019 | B82: 67 | C82: 69 | D82: 0067.jpg 0068.jpg 0069.jpg | E82: 3 | F82: MTG | G82: Oklahoma Real Estate Mortgage | I82: Mortgage Book 33 | J82: 29 | K82: 31 | L82: December 9, 1918, 3:00 P.M. | M82: December 2, 1918 | O82: December 9, 1918 | V82: Jerry W. Kelley and Margaret I. Kelley, husband and wife | W82: The Inter-State Mortgage Trust Company | AC82: All of the Southwest quarter of Section 32, Township 11 North, Range 25 West of the Indian Meridian, containing 160 acres | AD82: SW/4 of Section 32, Township 11 North, Range 25 West of the Indian Meridian | AE82: 32 | AF82: 11 North | AG82: 25 West | AH82: Beckham | AI82: Oklahoma | AJ82: SW/4 | AM82: 160 | BH82: $2,000.00 | BM82: Jerry W. and Margaret I. Kelley held the mortgagor interest shown. | BN82: The Inter-State Mortgage Trust Company received a mortgage lien on the SW/4. | BO82: No Diversified party or supported Diversified chain link appears in this instrument. | BP82: high | BR82: not_required
A83: B02-G020 | B83: 69 | C83: 70 | D83: 0069.jpg 0070.jpg | E83: 2 | F83: MTG | G83: Mortgage | I83: Mortgage Book 33 | J83: 31 | K83: 32 | L83: December 9, 1918, 3:15 P.M. | M83: December 2, 1918 | O83: December 9, 1918 | V83: Jerry W. Kelley and Margaret I. Kelley, husband and wife | W83: Inter-State Mortgage Trust Company | AC83: All of the Southwest quarter of Section 32, Township 11 North, Range 25 West of the Indian Meridian, containing 160 acres | AD83: SW/4 of Section 32, Township 11 North, Range 25 West of the Indian Meridian | AE83: 32 | AF83: 11 North | AG83: 25 West | AH83: Beckham | AI83: Oklahoma | AJ83: SW/4 | AM83: 160 | BH83: $280.00 | BM83: Jerry W. and Margaret I. Kelley held the mortgagor interest shown. | BN83: Inter-State Mortgage Trust Company received a separate $280 mortgage lien on the SW/4. | BO83: No Diversified party or supported Diversified chain link appears in this instrument. | BP83: high | BR83: not_required
A84: B02-G021 | B84: 71 | C84: 71 | D84: 0071.jpg | E84: 1 | F84: REL | G84: Release of Mortgage | I84: Release Record No. 7 | J84: 222 | X84: First National Bank | Y84: W. E. Dephart | AC84: Lots and town property described in the upper release | AH84: Beckham | BL84: Upper handwritten release is faint and is not a Section 32 tract. | BN84: Mortgage lien released. | BO84: No Diversified party or supported Diversified chain link appears in this instrument. | BP84: low | BR84: required
A85: B02-G022 | B85: 71 | C85: 71 | D85: 0071.jpg | E85: 1 | F85: REL | G85: Release of Mortgage | I85: Release Record No. 7 | J85: 222 | M85: December 12, 1918 | X85: M. D. Garretson | Y85: Augustus P. Stevens | AC85: Southwest quarter of Section 32, Township 11 North, Range 25 West of the Indian Meridian | AD85: SW/4 of Section 32, Township 11 North, Range 25 West of the Indian Meridian | AE85: 32 | AF85: 11 North | AG85: 25 West | AH85: Beckham | AI85: Oklahoma | AJ85: SW/4 | BM85: M. D. Garretson held the mortgage lien shown. | BN85: Mortgage lien released. | BO85: No Diversified party or supported Diversified chain link appears in this instrument. | BP85: medium | BR85: required
A86: B02-G023 | B86: 72 | C86: 72 | D86: 0072.jpg | E86: 1 | F86: AOM | G86: Assignment of Mortgage | I86: 10 Miscellaneous | J86: 387 | L86: December 16, 1918, 9:00 A.M. | M86: December 14, 1918 | R86: T. A. Haines | S86: John M. Haines | V86: W. H. Gibson and Maggie Gibson, husband and wife | AC86: Southeast quarter of Section 31, Township 11 North, Range 25 West | AE86: 31 | AF86: 11 North | AG86: 25 West | AH86: Beckham | AJ86: SE/4 | BB86: Mortgage Volume 27, page 237 | BH86: $328.50 | BM86: T. A. Haines held the mortgage and debt. | BN86: John M. Haines received the assigned mortgage and debt. | BO86: No Diversified party or supported Diversified chain link appears in this instrument. | BP86: high | BR86: not_required
A87: B02-G024 | B87: 72 | C87: 72 | D87: 0072.jpg | E87: 1 | F87: REL | G87: Satisfaction of Mortgage | I87: 10 Miscellaneous | J87: 387 | L87: December 16, 1918, 2:00 P.M. | M87: December 15, 1918 | X87: Garretson & Woodward, by M. P. Garretson | Y87: Augustus P. Stevens | AC87: Southwest quarter of Section 32, Township 11 North, Range 25 West of the Indian Meridian | AD87: SW/4 of Section 32, Township 11 North, Range 25 West of the Indian Meridian | AE87: 32 | AF87: 11 North | AG87: 25 West | AH87: Beckham | AI87: Oklahoma | AJ87: SW/4 | BB87: Mortgage Book 24, page 451 | BM87: Garretson & Woodward held the mortgage lien shown. | BN87: Mortgage lien satisfied and released. | BO87: No Diversified party or supported Diversified chain link appears in this instrument. | BP87: high | BR87: not_required
A88: B02-G025 | B88: 73 | C88: 73 | D88: 0073.jpg | E88: 1 | F88: WD | G88: Warranty Deed | I88: Warranty Deed Record No. 31 | J88: 257 | L88: December 16, 1918, 3:00 P.M. | M88: December 13, 1918 | P88: Augustus P. Stevens, a single man | Q88: Jerry W. Kelley | AC88: Southwest quarter of Section 32, Township 11 North, Range 25 West of the Indian Meridian, containing 160 acres | AD88: SW/4 of Section 32, Township 11 North, Range 25 West of the Indian Meridian | AE88: 32 | AF88: 11 North | AG88: 25 West | AH88: Beckham | AI88: Oklahoma | AJ88: SW/4 | AM88: 160 | BH88: $3,000.00 | BM88: Augustus P. Stevens held the grantor interest shown. | BN88: Jerry W. Kelley received the SW/4 by warranty deed. | BO88: No Diversified party or supported Diversified chain link appears in this instrument. | BP88: medium | BR88: required
A89: B02-G026 | B89: 74 | C89: 74 | D89: 0074.jpg | E89: 1 | F89: ROL | G89: Release of Oil and Gas Lease | I89: 10 Miscellaneous | J89: 444 | L89: January 30, 1919, 1:00 P.M. | M89: December 31, 1918 | X89: Midland Oil Company | Y89: Richard C. Bradley and wife | AC89: East half of Northwest quarter, Section 30, Township 11 North, Range 25 West, containing 80 acres | AE89: 30 | AF89: 11 North | AG89: 25 West | AH89: Beckham | AJ89: NW/4 | AK89: E/2 NW/4 | AM89: 80 | AZ89: Lease dated May 4, 1917; Book 8 Miscellaneous, page 469 | BM89: Midland Oil Company held the leasehold. | BN89: Oil-and-gas lease released. | BO89: No Diversified party or supported Diversified chain link appears in this instrument. | BP89: high | BR89: not_required
A90: B02-G027 | B90: 74 | C90: 74 | D90: 0074.jpg | E90: 1 | F90: ROL | G90: Release of Oil and Gas Lease | I90: 10 Miscellaneous | J90: 444 | L90: January 30, 1919, 1:00 P.M. | M90: December 31, 1918 | X90: Midland Oil Company | Y90: Green A. Crook and Ellen W. Crook, husband and wife | AC90: Northeast quarter of Section 32, Township 11 North, Range 25 West, containing 160 acres | AD90: NE/4 of Section 32, Township 11 North, Range 25 West of the Indian Meridian | AE90: 32 | AF90: 11 North | AG90: 25 West | AH90: Beckham | AI90: Oklahoma | AJ90: NE/4 | AM90: 160 | AZ90: Lease dated May 4, 1917; Book 9 Miscellaneous, page 108 | BM90: Midland Oil Company held the leasehold. | BN90: Oil-and-gas lease released. | BO90: No Diversified party or supported Diversified chain link appears in this instrument. | BP90: medium | BR90: required
A91: B02-G028 | B91: 75 | C91: 75 | D91: 0075.jpg | E91: 1 | F91: ROL | G91: Release of Oil and Gas Lease | I91: 10 Miscellaneous | J91: 445 | L91: January 30, 1919, 1:00 P.M. | M91: December 31, 1918 | X91: Midland Oil Company | Y91: Stone, husband and wife | AC91: Tract outside Section 32; exact legal is faint | AH91: Beckham | BL91: Upper release; exact names and legal require review. | BO91: No Diversified party or supported Diversified chain link appears in this instrument. | BP91: low | BR91: required
A92: B02-G029 | B92: 75 | C92: 75 | D92: 0075.jpg | E92: 1 | F92: ROL | G92: Release of Oil and Gas Lease | I92: 10 Miscellaneous | J92: 445 | L92: January 30, 1919, 1:00 P.M. | M92: December 31, 1918 | X92: Midland Oil Company | Y92: Coffey, husband and wife | AC92: Tract outside Section 32; exact legal is faint | AH92: Beckham | BL92: Middle release; exact names and legal require review. | BO92: No Diversified party or supported Diversified chain link appears in this instrument. | BP92: low | BR92: required
A93: B02-G030 | B93: 75 | C93: 75 | D93: 0075.jpg | E93: 1 | F93: ROL | G93: Release of Oil and Gas Lease | I93: 10 Miscellaneous | J93: 445 | L93: January 30, 1919, 1:00 P.M. | M93: December 31, 1918 | X93: Midland Oil Company | Y93: Coffey, husband and wife | AC93: Tract in Section 23, Township 11 North, Range 25 West | AE93: 23 | AF93: 11 North | AG93: 25 West | AH93: Beckham | BL93: Lower release; exact party initials and subdivision require review. | BO93: No Diversified party or supported Diversified chain link appears in this instrument. | BP93: low | BR93: required
A94: B02-G031 | B94: 76 | C94: 76 | D94: 0076.jpg | E94: 1 | F94: AFF | G94: Affidavit of Identity | I94: 10 Miscellaneous | J94: 461 | L94: February 6, 1919, 1:00 P.M. | M94: February 4, 1919 | AA94: E. L. Martin, affiant; identifies Crawford Bohannan as the grantee named J. R. Bohannan | BB94: Warranty deed Book 27, page 533; warranty deed Book 27, page 532 | BL94: Identity affidavit; referenced land is not stated as Section 32. | BM94: Record contained variant grantee names. | BN94: Affidavit links Crawford Bohannan with J. R. Bohannan. | BO94: No Diversified party or supported Diversified chain link appears in this instrument. | BP94: high | BR94: not_required
A95: B02-G032 | B95: 76 | C95: 76 | D95: 0076.jpg | E95: 1 | F95: REL | G95: Release of Mortgage | I95: 10 Miscellaneous | J95: 461 | L95: February 7, 1919, 9:00 A.M. | M95: January 16, 1919 | X95: The Union Central Life Insurance Company of Cincinnati, Ohio | Y95: Jacob Bollenbach and Katharina Bollenbach, his wife | AC95: South East Quarter of Section 32, Township 11 North, Range 25 West | AD95: SE/4 of Section 32, Township 11 North, Range 25 West of the Indian Meridian | AE95: 32 | AF95: 11 North | AG95: 25 West | AH95: Beckham | AI95: Oklahoma | AJ95: SE/4 | BB95: Mortgage Book 8, page 326 | BM95: Union Central Life Insurance Company held the mortgage lien. | BN95: Mortgage lien released. | BO95: No Diversified party or supported Diversified chain link appears in this instrument. | BP95: high | BR95: not_required
A96: B02-G033 | B96: 77 | C96: 77 | D96: 0077.jpg | E96: 1 | F96: ASN | G96: Assignment | I96: 10 Miscellaneous | J96: 481 | L96: February 21, 1919, 1:00 P.M. | M96: February 6, 1919 | R96: E. B. Farrar | S96: J. M. Aubury | AC96: Northeast quarter of Section 32, Township 11 North, Range 25 West, containing 160 acres | AD96: NE/4 of Section 32, Township 11 North, Range 25 West of the Indian Meridian | AE96: 32 | AF96: 11 North | AG96: 25 West | AH96: Beckham | AI96: Oklahoma | AJ96: NE/4 | AM96: 160 | BB96: Mortgage Book 27, page 64 | BH96: $500.00 | BM96: E. B. Farrar held the mortgage-secured interest. | BN96: J. M. Aubury received the assigned interest. | BO96: No Diversified party or supported Diversified chain link appears in this instrument. | BP96: high | BR96: not_required
A97: B02-G034 | B97: 77 | C97: 77 | D97: 0077.jpg | E97: 1 | F97: AOM | G97: Assignment of Mortgage | H97: No. 5601 | I97: 10 Miscellaneous | J97: 481 | L97: February 24, 1919, 9:00 A.M. | M97: August 23, 1916 | R97: Scotts & Blackmer, a partnership consisting of D. A. Scotts and R. C. Blackmer | S97: Manhattan Life Insurance Company | V97: E. M. Bower and Lillie Bower, husband and wife | BB97: Mortgage/Deed of Trust Volume 31, page 608 | BH97: $5,000.00 | BL97: No Section 32 legal description appears in the visible assignment. | BM97: Scotts & Blackmer held the mortgage and secured debt. | BN97: Manhattan Life Insurance Company received the assigned mortgage and debt. | BO97: No Diversified party or supported Diversified chain link appears in this instrument. | BP97: high | BR97: not_required
A98: B02-G035 | B98: 78 | C98: 78 | D98: 0078.jpg | E98: 1 | F98: REL | G98: Release of Mortgage | I98: Release Record No. 7 | J98: 398 | M98: March 22, 1919 | X98: J. M. Aubury | Y98: Jerry W. Kelley and M. I. Kelley, husband and wife | AC98: Northwest quarter of Section 32, Township 11 North, Range 25 West | AD98: NW/4 of Section 32, Township 11 North, Range 25 West of the Indian Meridian | AE98: 32 | AF98: 11 North | AG98: 25 West | AH98: Beckham | AI98: Oklahoma | AJ98: NW/4 | BB98: Mortgage Book 27, page 548 | BM98: J. M. Aubury held the mortgage lien. | BN98: Mortgage lien released. | BO98: No Diversified party or supported Diversified chain link appears in this instrument. | BP98: medium | BR98: required
A99: B02-G036 | B99: 78 | C99: 78 | D99: 0078.jpg | E99: 1 | F99: REL | G99: Release of Mortgage | I99: Release Record No. 7 | J99: 398 | M99: March 22, 1919 | X99: J. M. Aubury | Y99: Austin J. Coffey and Nancy L. Coffey, husband and wife | AC99: Northwest quarter of Section 32, Township 11 North, Range 25 West, containing 160 acres | AD99: NW/4 of Section 32, Township 11 North, Range 25 West of the Indian Meridian | AE99: 32 | AF99: 11 North | AG99: 25 West | AH99: Beckham | AI99: Oklahoma | AJ99: NW/4 | AM99: 160 | BB99: Mortgage Book 27, page 644 | BM99: J. M. Aubury held the mortgage lien. | BN99: Mortgage lien released. | BO99: No Diversified party or supported Diversified chain link appears in this instrument. | BP99: medium | BR99: required
A100: B02-G037 | B100: 79 | C100: 79 | D100: 0079.jpg | E100: 1 | F100: WD | G100: Warranty Deed | I100: Warranty Deed Record No. 34 | J100: 117 | L100: May 14, 1921, 2:00 P.M. | M100: June 30, 1916 | P100: Hilda M. Liscomb | Q100: Joseph H. Liscomb and another grantee whose name is faint | AC100: West half of Section 32, Township 11 North, Range 25 West | AD100: W/2 of Section 32, Township 11 North, Range 25 West of the Indian Meridian | AE100: 32 | AF100: 11 North | AG100: 25 West | AH100: Beckham | AI100: Oklahoma | AJ100: W/2 | BH100: $2,400.00 | BL100: One grantee name and a margin note are difficult to read. | BM100: Hilda M. Liscomb held the grantor interest shown. | BN100: The named grantees received the W/2 by warranty deed. | BO100: No Diversified party or supported Diversified chain link appears in this instrument. | BP100: medium | BR100: required
...

Sheet DOCUMENT_GROUPS
A1: Group Id | B1: Image Start | C1: Image End | D1: Exact Filenames | E1: Page Count | F1: Doc Type Abbrev | G1: Full Title | H1: Instrument Number | I1: Book | J1: Beginning Page | K1: Ending Page | L1: Recording Date/Time | M1: Execution Date | N1: Effective Date | O1: Acknowledgment Date | P1: Grantor | Q1: Grantee | R1: Assignor | S1: Assignee | T1: Lessor | U1: Lessee | V1: Mortgagor | W1: Mortgagee | X1: Releasor | Y1: Releasee | Z1: Decedent | AA1: Other Capacities | AB1: Mailing Addresses | AC1: Legal Description Raw | AD1: Legal Description Normalized | AE1: Section | AF1: Township | AG1: Range | AH1: County | AI1: State | AJ1: Quarter | AK1: Quarter Quarter | AL1: Lots | AM1: Stated Acreage | AN1: Mineral Acreage | AO1: Fractions | AP1: Percentages | AQ1: Royalty | AR1: Wi | AS1: Nri | AT1: Orri | AU1: Production Payment | AV1: Depth | AW1: Formation | AX1: Wellbore | AY1: Surface Limitations | AZ1: Lease References | BA1: Base Lease References | BB1: Prior References | BC1: Reservations | BD1: Exceptions | BE1: Subject To | BF1: Term | BG1: Extensions | BH1: Consideration | BI1: Wells | BJ1: Api | BK1: Unit | BL1: Material Title Notes | BM1: Interest Before | BN1: Interest After | BO1: Relevance To Diversified | BP1: Confidence Classification | BQ1: Assumptions | BR1: Human Review Status
A2: B01-G001 | B2: 1 | C2: 1 | D2: 0001.jpg | E2: 1 | F2: WD | G2: Warranty Deed | I2: 9 | J2: 418 | L2: March 12, 1907, 7:00 A.M. | M2: October 11, 1906 | O2: October 11, 1906 | P2: Velmore Biggs and Hettie A. Biggs, his wife | Q2: Edward J. Gordon | AC2: South east quarter of section thirty two (32) township eleven (11), range twenty five (25), consisting of 160 acres | AD2: SE/4 of Section 32, Township 11 North, Range 25 West of the Indian Meridian | AE2: 32 | AF2: 11 North | AG2: 25 West | AH2: Beckham (formerly Roger Mills) | AI2: Oklahoma | AJ2: SE/4 | AM2: 160 | BE2: $800 mortgage in favor of Oklahoma Farm Mortgage Company | BH2: $2,150.00 | BO2: No chain basis identified in Batch 01. | BP2: high | BR2: not_required
A3: B01-G002 | B3: 2 | C3: 2 | D3: 0002.jpg | E3: 1 | F3: WD | G3: Warranty Deed | I3: 12 | L3: July 18, 1907, 1:00 P.M. | M3: July 16, 1907 | O3: July 16, 1907 | P3: Cornelius B. Cornelius and Margreta Cornelius, husband and wife | Q3: Jacob Bollenbach | AC3: The North-east quarter (NE) of Section Thirty-two (32) in Township Eleven (11) North of Range Twenty-five (25) West containing One Hundred and Sixty (160) acres | AD3: NE/4 of Section 32, Township 11 North, Range 25 West of the Indian Meridian | AE3: 32 | AF3: 11 North | AG3: 25 West | AH3: Beckham (formerly Roger Mills) | AI3: Oklahoma | AJ3: NE/4 | AM3: 160 | BD3: 1907 taxes | BH3: $2,000.00 | BO3: No chain basis identified in Batch 01. | BP3: high | BR3: not_required
A4: B01-G003 | B4: 3 | C4: 3 | D4: 0003.jpg | E4: 1 | F4: PAT | G4: Homestead Patent | I4: Patent Record | J4: 369 | M4: March 22, 1906 | P4: United States of America | Q4: Cornelius B. Cornelius | AC4: North-east quarter of Section thirty-two in Township Eleven, North of Range Twenty-five, West of Indian Meridian in Oklahoma, containing One Hundred and Sixty acres | AD4: NE/4 of Section 32, Township 11 North, Range 25 West of the Indian Meridian | AE4: 32 | AF4: 11 North | AG4: 25 West | AH4: Beckham (formerly Roger Mills) | AI4: Oklahoma | AJ4: NE/4 | AM4: 160 | BO4: No chain basis identified in Batch 01. | BP4: high | BR4: not_required
A5: B01-G004 | B5: 4 | C5: 4 | D5: 0004.jpg | E5: 1 | F5: FRR | G5: Final Receiver's Receipt / Homestead Entry | H5: Final Receiver's Receipt No. 4668 | L5: July 12, 1908 | Q5: Alfred R. Harris | AC5: N 1/2 W 1/2; SW 1/4 and SE 1/4 SW 1/4 (section number unclear) | AI5: Oklahoma | BL5: Not shown as Section 32; handwriting and abbreviations require review. | BO5: No chain basis identified in Batch 01. | BP5: medium | BQ5: Treated as a separate receipt on the upper portion of image 0004. | BR5: required
A6: B01-G005 | B6: 4 | C6: 4 | D6: 0004.jpg | E6: 1 | F6: FRR | G6: Final Receiver's Receipt / Homestead Entry | H6: Final Receiver's Receipt No. 128 | L6: August 8, 1908 | Q6: Velmore Biggs | AC6: S.E. 1/4 of Section 32, Township 11 N., Range 25 W. | AD6: SE/4 of Section 32, Township 11 North, Range 25 West of the Indian Meridian | AE6: 32 | AF6: 11 North | AG6: 25 West | AH6: Beckham (formerly Roger Mills) | AI6: Oklahoma | AJ6: SE/4 | AM6: 160 | BO6: No chain basis identified in Batch 01. | BP6: medium | BR6: required
A7: B01-G006 | B7: 5 | C7: 5 | D7: 0005.jpg | E7: 1 | F7: FRR | G7: Final Receiver's Receipt / Homestead Entry | H7: Final Receiver's Receipt No. 3895 | Q7: Albertus B. Hardison | AC7: W 1/2 SE 1/4 and E 1/2 SE 1/4; Section 23, Township 10 N., Range 22 W. | AE7: 23 | AF7: 10 North | AG7: 22 West | AI7: Oklahoma | BO7: No chain basis identified in Batch 01. | BP7: medium | BR7: required
A8: B01-G007 | B8: 5 | C8: 5 | D8: 0005.jpg | E8: 1 | F8: FRR | G8: Final Receiver's Receipt / Homestead Entry | H8: Application No. 16018 | Q8: Herman Stevens | AC8: SW 1/4 of Section 32, Township 11 N., Range 25 W. | AD8: SW/4 of Section 32, Township 11 North, Range 25 West of the Indian Meridian | AE8: 32 | AF8: 11 North | AG8: 25 West | AH8: Beckham (formerly Roger Mills) | AI8: Oklahoma | AJ8: SW/4 | AM8: 160 | BO8: No chain basis identified in Batch 01. | BP8: medium | BR8: required
A9: B01-G008 | B9: 6 | C9: 6 | D9: 0006.jpg | E9: 1 | F9: FRR | G9: Final Receiver's Receipt / Homestead Entry | H9: Final Receiver's Receipt No. 3895; Application No. 16126 | L9: May 12, 1908 | Q9: Augustus P. Stevens | AC9: SW 1/4, Section 32, Township 11 N., Range 25 W. | AD9: SW/4 of Section 32, Township 11 North, Range 25 West of the Indian Meridian | AE9: 32 | AF9: 11 North | AG9: 25 West | AH9: Beckham (formerly Roger Mills) | AI9: Oklahoma | AJ9: SW/4 | AM9: 160 | BO9: No chain basis identified in Batch 01. | BP9: medium | BR9: required
A10: B01-G009 | B10: 6 | C10: 6 | D10: 0006.jpg | E10: 1 | F10: FRR | G10: Final Receiver's Receipt / Homestead Entry | H10: Final Receiver's Receipt No. 3876; Application No. 13662 | Q10: John J. Armstrong | AC10: W 1/2 SE 1/4 and NE 1/4 SE 1/4, Section 20, Township 11 N., Range 22 W. | AE10: 20 | AF10: 11 North | AG10: 22 West | AI10: Oklahoma | BO10: No chain basis identified in Batch 01. | BP10: medium | BR10: required
A11: B01-G010 | B11: 8 | C11: 8 | D11: 0008.jpg | E11: 1 | F11: MTG | G11: Real Estate and Chattel Mortgage | J11: 173 | L11: April 17, 1907, 8:00 A.M. | M11: April 5, 1907 | O11: April 15, 1907 | V11: A. P. Stevens | W11: The Cotton Exchange State Bank | AC11: The South-west quarter of Section 32 Township 11, Range 25, W.I.M. | AD11: SW/4 of Section 32, Township 11 North, Range 25 West of the Indian Meridian | AE11: 32 | AF11: 11 North | AG11: 25 West | AH11: Beckham (formerly Roger Mills) | AI11: Oklahoma | AJ11: SW/4 | AM11: 160 | BH11: $613.00 | BL11: 0007.jpg is a duplicate image of this recorded page; exact source retained as 0008.jpg. | BO11: No chain basis identified in Batch 01. | BP11: medium | BQ11: Party initials and some chattel-note details are difficult. | BR11: required
A12: B01-G011 | B12: 9 | C12: 11 | D12: 0009.jpg 0010.jpg 0011.jpg | E12: 3 | F12: MTG | G12: Real Estate Mortgage | J12: 249 | K12: 251 | L12: May 12, 1905, 6:30 P.M. | M12: May 10, 1905 | O12: May 12, 1905 | V12: Augustus P. Stevens and Herman Stevens, single men | W12: C. J. Weiser | AC12: The southwest quarter and northwest quarter of section thirty-two, township eleven north, range twenty-five west | AD12: SW/4 and NW/4 of Section 32, Township 11 North, Range 25 West of the Indian Meridian | AE12: 32 | AF12: 11 North | AG12: 25 West | AH12: Beckham (formerly Roger Mills) | AI12: Oklahoma | AJ12: SW/4; NW/4 | AM12: 320 | BF12: Due May 10, 1908; 6% before maturity; 12% after maturity | BH12: $817.00 | BO12: No chain basis identified in Batch 01. | BP12: high | BR12: not_required
A13: B01-G012 | B13: 12 | C13: 12 | D13: 0012.jpg | E13: 1 | F13: MTG | G13: Oklahoma Farm Mortgage | I13: 12 | J13: 117 | L13: July 31, 1906 | M13: July 27, 1906 | V13: Velmore Biggs and Hettie Biggs, husband and wife | W13: Oklahoma Farm Mortgage Company | AC13: The south east quarter of section thirty two (32) in township eleven (11) north of range twenty five (25) west | AD13: SE/4 of Section 32, Township 11 North, Range 25 West of the Indian Meridian | AE13: 32 | AF13: 11 North | AG13: 25 West | AH13: Beckham (formerly Roger Mills) | AI13: Oklahoma | AJ13: SE/4 | AM13: 160 | BH13: $500.00 | BL13: 0013.jpg is a duplicate image of this recorded page. | BO13: No chain basis identified in Batch 01. | BP13: high | BR13: not_required
A14: B01-G013 | B14: 14 | C14: 14 | D14: 0014.jpg | E14: 1 | F14: AOM | G14: Assignment of Mortgage | L14: August 31, 1906 | M14: August 29, 1906 | R14: Oliver L. Johnson | S14: First National Bank, Elk City, Oklahoma | AC14: Lots 9-14, Block 45, Elk City, Oklahoma | AH14: Roger Mills | AI14: Oklahoma | AL14: Lots 9-14, Block 45 | BH14: $5,000.00 | BO14: No chain basis identified in Batch 01. | BP14: high | BR14: not_required
A15: B01-G014 | B15: 14 | C15: 14 | D15: 0014.jpg | E15: 1 | F15: AOM | G15: Assignment of Mortgage | I15: 1 | J15: 3 | L15: September 10, 1906 | M15: September 10, 1906 | R15: Oklahoma Farm Mortgage Company | S15: Miss Mabel G. Allen | AC15: The South-east Quarter of Section Thirty-two (32) in Township Eleven (11), North of Range Twenty-five (25) West, containing 160 acres | AD15: SE/4 of Section 32, Township 11 North, Range 25 West of the Indian Meridian | AE15: 32 | AF15: 11 North | AG15: 25 West | AH15: Beckham (formerly Roger Mills) | AI15: Oklahoma | AJ15: SE/4 | AM15: 160 | BB15: Mortgage dated July 27, 1906 | BH15: $500.00 | BO15: No chain basis identified in Batch 01. | BP15: high | BR15: not_required
A16: B01-G015 | B16: 15 | C16: 15 | D16: 0015.jpg | E16: 1 | F16: AOM | G16: Assignment of Mortgage | I16: 1 | J16: 4 | L16: September 24, 1906 | M16: September 10, 1906 | R16: Mabel G. Allen | S16: Dr. S. E. Denbois | AC16: The South-east Quarter of Section Thirty-two (32), Township Eleven (11) North, Range Twenty-five (25) West, containing 160 acres | AD16: SE/4 of Section 32, Township 11 North, Range 25 West of the Indian Meridian | AE16: 32 | AF16: 11 North | AG16: 25 West | AH16: Beckham (formerly Roger Mills) | AI16: Oklahoma | AJ16: SE/4 | AM16: 160 | BH16: $500.00 | BO16: No chain basis identified in Batch 01. | BP16: medium | BR16: required
A17: B01-G016 | B17: 15 | C17: 15 | D17: 0015.jpg | E17: 1 | F17: AOM | G17: Assignment of Mortgage | L17: September 26, 1906 | R17: Name unclear | S17: Mr. Poole | AC17: South half of the Northeast Quarter and north half of the Southeast Quarter, Section 13, Township 8 North, Range 22 West | AE17: 13 | AF17: 8 North | AG17: 22 West | AH17: Roger Mills | AI17: Oklahoma | BH17: $300.00 | BO17: No chain basis identified in Batch 01. | BP17: medium | BQ17: Assignor is illegible. | BR17: required
A18: B01-G017 | B18: 16 | C18: 16 | D18: 0016.jpg | E18: 1 | F18: PAT | G18: Homestead Patent | J18: 75 | P18: United States of America | Q18: Name appears to be Velmore Biggs | AC18: Southwest quarter of Section 31, Township 11 North, Range 24 West, containing 160 acres | AE18: 31 | AF18: 11 North | AG18: 24 West | AI18: Oklahoma | AM18: 160 | BO18: No chain basis identified in Batch 01. | BP18: low | BQ18: Handwritten patentee and legal description are faint; not treated as Section 32. | BR18: required
A19: B01-G018 | B19: 17 | C19: 17 | D19: 0017.jpg | E19: 1 | F19: AOM | G19: Assignment of Mortgage | I19: 12 | J19: 17 | L19: April 8, 1908, 6:00 P.M. | M19: April 3, 1908 | R19: W. S. P. [surname unclear] | S19: Jacob Guda [name uncertain] | AC19: The northeast quarter of Section thirty-two (32), Township eleven (11) North, Range twenty-five (25) West, containing 160 acres | AD19: NE/4 of Section 32, Township 11 North, Range 25 West of the Indian Meridian | AE19: 32 | AF19: 11 North | AG19: 25 West | AH19: Beckham (formerly Roger Mills) | AI19: Oklahoma | AJ19: NE/4 | AM19: 160 | BH19: $500.00 | BO19: No chain basis identified in Batch 01. | BP19: low | BQ19: Handwritten party names are uncertain. | BR19: required
A20: B01-G019 | B20: 17 | C20: 17 | D20: 0017.jpg | E20: 1 | F20: AOM | G20: Assignment of Mortgage | L20: April 9, 1908 | M20: April 2, 1908 | R20: Martin H. G. | S20: John L. [surname unclear] | AC20: North half of the Southeast quarter and North half of the Southwest quarter, Section 19, Township 8 North, Range 23 West | AE20: 19 | AF20: 8 North | AG20: 23 West | AH20: Beckham | AI20: Oklahoma | BH20: $700.00 | BO20: No chain basis identified in Batch 01. | BP20: low | BQ20: Party names require human reading. | BR20: required
A21: B01-G020 | B21: 18 | C21: 18 | D21: 0018.jpg | E21: 1 | F21: MTG | G21: Oklahoma Mortgage | J21: 316 | L21: December 9, 1908 | M21: December 1, 1908 | V21: Paul [surname unclear] and wife | W21: Oklahoma Farm Mortgage Company | AC21: The South East Quarter of Section Thirty-two in Township Eleven North of Range Twenty-five West | AD21: SE/4 of Section 32, Township 11 North, Range 25 West of the Indian Meridian | AE21: 32 | AF21: 11 North | AG21: 25 West | AH21: Beckham (formerly Roger Mills) | AI21: Oklahoma | AJ21: SE/4 | AM21: 160 | BH21: $1,000.00 | BL21: 0019.jpg appears to be a duplicate exposure of the same form/page. | BO21: No chain basis identified in Batch 01. | BP21: low | BQ21: Mortgagor names are too faint for reliable transcription. | BR21: required
A22: B01-G021 | B22: 20 | C22: 20 | D22: 0020.jpg | E22: 1 | F22: MTG | G22: First Real Estate Mortgage | J22: 101 | L22: December 10, 1908 | M22: December 1, 1908 | V22: Augustus P. Stevens, a single man | W22: W. B. [surname unclear] | AC22: The southwest quarter of Section Thirty-two, Township Eleven North, Range Twenty-five West | AD22: SW/4 of Section 32, Township 11 North, Range 25 West of the Indian Meridian | AE22: 32 | AF22: 11 North | AG22: 25 West | AH22: Beckham (formerly Roger Mills) | AI22: Oklahoma | AJ22: SW/4 | AM22: 160 | BO22: No chain basis identified in Batch 01. | BP22: low | BQ22: Mortgagee and monetary terms are faint. | BR22: required
A23: B01-G022 | B23: 21 | C23: 21 | D23: 0021.jpg | E23: 1 | F23: REL | G23: Release of Mortgage | J23: 476 | L23: June 21, 1912 | M23: June 11, 1912 | X23: P. W. Gunn | Y23: J. Adam and wife | AC23: SE 1/4 NE 1/4 and SE 1/4 NW 1/4, Section 33, Township 9 North, Range 22 West | AE23: 33 | AF23: 9 North | AG23: 22 West | AH23: Beckham | AI23: Oklahoma | BB23: Mortgage Book 3, page 111 | BO23: No chain basis identified in Batch 01. | BP23: low | BR23: required
A24: B01-G023 | B24: 21 | C24: 21 | D24: 0021.jpg | E24: 1 | F24: REL | G24: Release of Mortgage | L24: June 21, 1912 | M24: June 20, 1912 | X24: King [initials unclear] | Y24: Philip H. S. | AC24: Lots and blocks in Elk City, Oklahoma | AH24: Beckham | AI24: Oklahoma | BO24: No chain basis identified in Batch 01. | BP24: low | BQ24: Names and lot description are handwritten and uncertain. | BR24: required
A25: B01-G024 | B25: 22 | C25: 23 | D25: 0022.jpg 0023.jpg | E25: 2 | F25: MTG | G25: Mortgage | J25: 328 | K25: 329 | L25: January 18, 1909, 9:00 A.M. | M25: January 13, 1909 | O25: January 16, 1909 | V25: Jacob Bollenbach and Katharina Bollenbach, his wife | W25: Union Central Life Insurance Company | AC25: North East Quarter of Section Thirty-two (32), Township Eleven (11) North, Range Twenty-five (25) West | AD25: NE/4 of Section 32, Township 11 North, Range 25 West of the Indian Meridian | AE25: 32 | AF25: 11 North | AG25: 25 West | AH25: Beckham (formerly Roger Mills) | AI25: Oklahoma | AJ25: NE/4 | AM25: 160 | BH25: $400.00 | BO25: No chain basis identified in Batch 01. | BP25: high | BR25: not_required
A26: B01-G025 | B26: 24 | C26: 24 | D26: 0024.jpg | E26: 1 | F26: MTG | G26: Mortgage | J26: 330 | L26: January 20, 1909, 9:00 A.M. | M26: January 13, 1909 | V26: Joshua P. Hill and Sallie C. Hill, his wife | W26: Union Central Life Insurance Company | AC26: South one-half of Section 17, Township 7 North, Range 24 West | AE26: 17 | AF26: 7 North | AG26: 24 West | AH26: Beckham | AI26: Oklahoma | AM26: 320 | BH26: $3,000.00 | BO26: No chain basis identified in Batch 01. | BP26: high | BR26: not_required
A27: B01-G026 | B27: 25 | C27: 25 | D27: 0025.jpg | E27: 1 | F27: PAT | G27: Homestead Patent | H27: Homestead Certificate No. 3815; Application No. 16126 | J27: 295 | M27: November 3, 1909 | P27: United States of America | Q27: Augustus P. Stevens | AC27: South West quarter of Section thirty-two in Township Eleven North of Range twenty-five West of Indian Meridian, containing one hundred and sixty acres | AD27: SW/4 of Section 32, Township 11 North, Range 25 West of the Indian Meridian | AE27: 32 | AF27: 11 North | AG27: 25 West | AH27: Beckham (formerly Roger Mills) | AI27: Oklahoma | AJ27: SW/4 | AM27: 160 | BO27: No chain basis identified in Batch 01. | BP27: high | BR27: not_required
A28: B01-G027 | B28: 26 | C28: 26 | D28: 0026.jpg | E28: 1 | F28: REL | G28: Release of Mortgage | J28: 200 | L28: January 19, 1909 | X28: Name unclear | Y28: Name unclear | AC28: South half of the South east quarter and Southeast quarter of Southwest quarter, Section 30, Township 10 North, Range 22 West | AE28: 30 | AF28: 10 North | AG28: 22 West | AH28: Beckham | AI28: Oklahoma | BO28: No chain basis identified in Batch 01. | BP28: low | BQ28: Handwriting prevents reliable party transcription. | BR28: required
A29: B01-G028 | B29: 26 | C29: 26 | D29: 0026.jpg | E29: 1 | F29: REL | G29: Release of Mortgage | J29: 200 | L29: January 19, 1909 | X29: Oklahoma Farm Mortgage Company | Y29: Mortgagor name unclear | AC29: The southwest quarter of Section thirty-two (32), Township eleven North, Range twenty-five West | AD29: SW/4 of Section 32, Township 11 North, Range 25 West of the Indian Meridian | AE29: 32 | AF29: 11 North | AG29: 25 West | AH29: Beckham (formerly Roger Mills) | AI29: Oklahoma | AJ29: SW/4 | AM29: 160 | BO29: No chain basis identified in Batch 01. | BP29: low | BQ29: Party names and prior mortgage page require review. | BR29: required
A30: B01-G029 | B30: 27 | C30: 27 | D30: 0027.jpg | E30: 1 | F30: REL | G30: Release of Mortgage | J30: 201 | L30: January 19, 1909 | X30: Oklahoma Farm Mortgage Company | Y30: Mortgagor name unclear | AC30: Southwest quarter of Section 33, Township 8 North, Range 21 West | AE30: 33 | AF30: 8 North | AG30: 21 West | AH30: Beckham | AI30: Oklahoma | BO30: No chain basis identified in Batch 01. | BP30: low | BR30: required
A31: B01-G030 | B31: 27 | C31: 27 | D31: 0027.jpg | E31: 1 | F31: REL | G31: Release of Mortgage | J31: 201 | L31: January 19, 1909 | X31: Charles E. Davis | Y31: R. [surname unclear] | AC31: Lots 1, 2, 3, 4 and 5 in Block 15, Doffey Addition to Elk City, Oklahoma | AH31: Beckham | AI31: Oklahoma | AL31: Lots 1-5, Block 15 | BO31: No chain basis identified in Batch 01. | BP31: low | BR31: required
A32: B01-G031 | B32: 28 | C32: 28 | D32: 0028.jpg | E32: 1 | F32: MTG | G32: Mortgage of Real Estate | J32: 212 | L32: February 9, 1909, 3:00 P.M. | M32: February 6, 1909 | O32: February 6, 1909 | V32: Augustus P. Stevens, a single man | W32: The Cotton Exchange State Bank | AC32: The North West Quarter of section thirty two (32), Township Eleven (11), Range Twenty Five (25) W.I.M. containing 160 acres | AD32: NW/4 of Section 32, Township 11 North, Range 25 West of the Indian Meridian | AE32: 32 | AF32: 11 North | AG32: 25 West | AH32: Beckham (formerly Roger Mills) | AI32: Oklahoma | AJ32: NW/4 | AM32: 160 | BH32: $370.00 | BO32: No chain basis identified in Batch 01. | BP32: medium | BR32: required
A33: B01-G032 | B33: 29 | C33: 29 | D33: 0029.jpg | E33: 1 | F33: WD | G33: Warranty Deed | J33: 393 | L33: January 31, 1909 | P33: E. D. Gordon and Annie A. Gordon, his wife | Q33: Edward [surname unclear] | AC33: The South West Quarter of Section Thirty-two in Township Eleven North, Range Twenty-five West, containing one hundred and sixty acres | AD33: SW/4 of Section 32, Township 11 North, Range 25 West of the Indian Meridian | AE33: 32 | AF33: 11 North | AG33: 25 West | AH33: Beckham (formerly Roger Mills) | AI33: Oklahoma | AJ33: SW/4 | AM33: 160 | BO33: No chain basis identified in Batch 01. | BP33: low | BQ33: Grantee surname and consideration are difficult. | BR33: required
A34: B01-G033 | B34: 30 | C34: 30 | D34: 0030.jpg | E34: 1 | F34: AOM | G34: Assignment of Mortgage | J34: 70 | R34: Oklahoma Farm Mortgage Company | S34: Mary [surname unclear] | AC34: The East half of the South west quarter of Section thirty-two and other land | AD34: E/2 SW/4 of Section 32, Township 11 North, Range 25 West of the Indian Meridian | AE34: 32 | AF34: 11 North | AG34: 25 West | AH34: Beckham (formerly Roger Mills) | AI34: Oklahoma | AJ34: E/2 SW/4 | BO34: No chain basis identified in Batch 01. | BP34: low | BQ34: Party name, recording date, and full multi-tract legal require review. | BR34: required
A35: B01-G034 | B35: 30 | C35: 30 | D35: 0030.jpg | E35: 1 | F35: AOM | G35: Assignment of Mortgage | J35: 70 | R35: Jacob Bollenbach | S35: Name unclear | AC35: The North East quarter of Section thirty-two (32), Township Eleven North, Range Twenty-five West | AD35: NE/4 of Section 32, Township 11 North, Range 25 West of the Indian Meridian | AE35: 32 | AF35: 11 North | AG35: 25 West | AH35: Beckham (formerly Roger Mills) | AI35: Oklahoma | AJ35: NE/4 | AM35: 160 | BB35: Mortgage Book 11, page 111 | BO35: No chain basis identified in Batch 01. | BP35: low | BQ35: Assignee name is illegible. | BR35: required
A36: B01-G035 | B36: 31 | C36: 31 | D36: 0031.jpg | E36: 1 | F36: JDG | G36: Judgment (continuation only) | J36: 323 | AA36: A. T. Hoblin, Justice of the Peace | AH36: Beckham | AI36: Oklahoma | BL36: Only the concluding text of an out-of-scope prior-page judgment is visible. | BO36: No chain basis identified in Batch 01. | BP36: low | BQ36: Instrument begins before Batch 01 and cannot be fully identified. | BR36: required
A37: B01-G036 | B37: 31 | C37: 31 | D37: 0031.jpg | E37: 1 | F37: AOM | G37: Assignment of Mortgage | J37: 323 | L37: February 22, 1908, 8:00 P.M. | M37: February 22, 1908 | R37: Beers & Co. | S37: Stevens, A. P. | AC37: South west quarter of Section thirty-two (32), Township eleven North, Range 25 West | AD37: SW/4 of Section 32, Township 11 North, Range 25 West of the Indian Meridian | AE37: 32 | AF37: 11 North | AG37: 25 West | AH37: Beckham (formerly Roger Mills) | AI37: Oklahoma | AJ37: SW/4 | BB37: Mortgage record Book 13, page 234; $300 indebtedness | BO37: No chain basis identified in Batch 01. | BP37: medium | BR37: required
A38: B01-G037 | B38: 32 | C38: 32 | D38: 0032.jpg | E38: 1 | F38: WD | G38: Warranty Deed | J38: 235 | L38: June 21, 1910 | M38: June 18, 1910 | O38: June 18, 1910 | P38: Jacob Bollenbach and Katharina Bollenbach, husband and wife | Q38: Adolf Bollenbach and Ena Bollenbach | AC38: The North East quarter of Section thirty-two (32), Township Eleven North, Range Twenty-five West, containing 160 acres | AD38: NE/4 of Section 32, Township 11 North, Range 25 West of the Indian Meridian | AE38: 32 | AF38: 11 North | AG38: 25 West | AH38: Beckham (formerly Roger Mills) | AI38: Oklahoma | AJ38: NE/4 | AM38: 160 | BC38: Grantors reserve an interest stated on the deed; exact fraction is faint. | BO38: No chain basis identified in Batch 01. | BP38: medium | BQ38: Reserved fraction requires human confirmation. | BR38: required
A39: B01-G038 | B39: 33 | C39: 33 | D39: 0033.jpg | E39: 1 | F39: MTG | G39: Mortgage of Real Estate | J39: 410 | L39: January 31, 1910 | M39: January 18, 1910 | V39: Adolf Bollenbach and Ena Bollenbach, husband and wife | W39: Jacob Bollenbach | AC39: The North East quarter (NE 1/4) of Section thirty-two (32), Township eleven North, Range twenty-five West, containing 160 acres | AD39: NE/4 of Section 32, Township 11 North, Range 25 West of the Indian Meridian | AE39: 32 | AF39: 11 North | AG39: 25 West | AH39: Beckham (formerly Roger Mills) | AI39: Oklahoma | AJ39: NE/4 | AM39: 160 | BH39: $2,800.00 | BO39: No chain basis identified in Batch 01. | BP39: medium | BR39: required
A40: B01-G039 | B40: 34 | C40: 34 | D40: 0034.jpg | E40: 1 | F40: AOM | G40: Assignment of Mortgage (continuation) | M40: June 15, 1910 | R40: Merchants State Bank of Waterville, Kansas | S40: Clara W. Clingman | AC40: Legal begins on a prior image; visible ending says Range 22 West | AG40: 22 West | AI40: Oklahoma | BB40: Mortgage volume 14, page 234 | BH40: $660.00 | BL40: Continuation from a prior, unavailable page. | BO40: No chain basis identified in Batch 01. | BP40: medium | BR40: required
A41: B01-G040 | B41: 34 | C41: 34 | D41: 0034.jpg | E41: 1 | F41: REL | G41: Release of Mortgage | I41: 4 Misc. | J41: 155 | L41: July 21, 1910, 2:00 P.M. | M41: July 16, 1910 | O41: July 18, 1910 | X41: Jacob Bollenbach | Y41: Adolf Bollenbach and Ena Bollenbach | AC41: The North East Quarter of Section Thirty-Two in Township Eleven North Range Twenty Five W.I.M. containing one hundred sixty acres | AD41: NE/4 of Section 32, Township 11 North, Range 25 West of the Indian Meridian | AE41: 32 | AF41: 11 North | AG41: 25 West | AH41: Beckham (formerly Roger Mills) | AI41: Oklahoma | AJ41: NE/4 | AM41: 160 | BB41: Mortgage Record No. 4, page 410; mortgage dated January 18, 1910 | BO41: No chain basis identified in Batch 01. | BP41: high | BR41: not_required
A42: B01-G041 | B42: 35 | C42: 35 | D42: 0035.jpg | E42: 1 | F42: MTG | G42: Mortgage of Real Estate | J42: 515 | L42: July 21, 1910, 2:00 P.M. | M42: July 20, 1910 | O42: July 20, 1910 | V42: Adolf Bollenbach and Ena Bollenbach, husband and wife | W42: Jacob Bollenbach | AC42: The North East quarter of Section thirty-two (32), Township Eleven (11) North, Range twenty-five (25) West, containing one hundred and sixty acres | AD42: NE/4 of Section 32, Township 11 North, Range 25 West of the Indian Meridian | AE42: 32 | AF42: 11 North | AG42: 25 West | AH42: Beckham (formerly Roger Mills) | AI42: Oklahoma | AJ42: NE/4 | AM42: 160 | BF42: One note due January 18, 1915; 7% interest | BH42: $2,800.00 | BO42: No chain basis identified in Batch 01. | BP42: medium | BR42: required
A43: B01-G042 | B43: 36 | C43: 36 | D43: 0036.jpg | E43: 1 | F43: REL | G43: Corporation Release of Mortgage | I43: 4 Misc. | J43: 483 | L43: February 25, 1911, 2:00 P.M. | M43: June 11, 1910 | X43: Cotton Exchange State Bank of Elk City, Oklahoma | Y43: Augustus P. Stevens | AC43: South West quarter of Section thirty-two (32), Township Eleven (11), Range Twenty-five (25) W.I.M. | AD43: SW/4 of Section 32, Township 11 North, Range 25 West of the Indian Meridian | AE43: 32 | AF43: 11 North | AG43: 25 West | AH43: Beckham (formerly Roger Mills) | AI43: Oklahoma | AJ43: SW/4 | BB43: Mortgage Book 4, page 212 | BO43: No chain basis identified in Batch 01. | BP43: high | BR43: not_required
A44: B01-G043 | B44: 36 | C44: 36 | D44: 0036.jpg | E44: 1 | F44: REL | G44: Release of Mortgage | I44: 4 Misc. | J44: 483 | L44: February 27, 1911, 8:00 A.M. | M44: February 24, 1911 | X44: The Jefferson Trust Company | Y44: John W. Jacobs | AC44: South West quarter of Section 24, Township 10 North, Range 26 West | AE44: 24 | AF44: 10 North | AG44: 26 West | AH44: Beckham | AI44: Oklahoma | BB44: Mortgage Book 14, page 436 | BH44: $125.00 | BO44: No chain basis identified in Batch 01. | BP44: high | BR44: not_required
A45: B01-G044 | B45: 37 | C45: 37 | D45: 0037.jpg | E45: 1 | F45: AOM | G45: Assignment of Mortgage | I45: 6 Misc. | J45: 254 | L45: February 24, 1913, 8:00 A.M. | M45: August 9, 1910 | R45: Jacob Bollenbach | S45: Hulda Hahn | AC45: North East Quarter of Section Thirty-two (32), Township Eleven (11) North, Range Twenty-five (25) West of Indian Meridian, containing 160 acres | AD45: NE/4 of Section 32, Township 11 North, Range 25 West of the Indian Meridian | AE45: 32 | AF45: 11 North | AG45: 25 West | AH45: Beckham (formerly Roger Mills) | AI45: Oklahoma | AJ45: NE/4 | AM45: 160 | BB45: Mortgage Book 4, page 515; mortgage dated July 20, 1910 | BO45: No chain basis identified in Batch 01. | BP45: high | BR45: not_required
A46: B01-G045 | B46: 38 | C46: 38 | D46: 0038.jpg | E46: 1 | F46: PAT | G46: Homestead Patent | H46: Homestead Certificate No. 6011 | J46: 124 | M46: May 4, 1912 | P46: United States of America | Q46: William B. Farrar | AC46: North West quarter of Section thirty-two in Township Eleven North of Range Twenty-five West of the Indian Meridian, containing one hundred and sixty acres | AD46: NW/4 of Section 32, Township 11 North, Range 25 West of the Indian Meridian | AE46: 32 | AF46: 11 North | AG46: 25 West | AH46: Beckham (formerly Roger Mills) | AI46: Oklahoma | AJ46: NW/4 | AM46: 160 | BO46: No chain basis identified in Batch 01. | BP46: medium | BR46: required
A47: B01-G046 | B47: 39 | C47: 39 | D47: 0039.jpg | E47: 1 | F47: CERT | G47: Land Office Certificate of Cancellation | I47: 6 Misc. | J47: 441 | L47: July 21, 1913, 9:00 A.M. | M47: July 19, 1913 | AA47: Hugh Scott, Receiver, United States Land Office | AC47: SW 1/4 Sec. 32, T. 11 N., R. 25 W.I.M. | AD47: SW/4 of Section 32, Township 11 North, Range 25 West of the Indian Meridian | AE47: 32 | AF47: 11 North | AG47: 25 West | AH47: Beckham (formerly Roger Mills) | AI47: Oklahoma | AJ47: SW/4 | BB47: Commissioner's Letter H, July 9, 1907 | BL47: Certifies Herman Stephens Homestead Entry No. 16112 / Final Certificate No. 3694 was cancelled by Commissioner's letter of July 9, 1907. | BO47: No chain basis identified in Batch 01. | BP47: high | BR47: not_required
A48: B01-G047 | B48: 39 | C48: 39 | D48: 0039.jpg | E48: 1 | F48: REL | G48: Release of Mortgage | I48: 6 Misc. | J48: 441 | L48: July 21, 1913, 9:00 A.M. | M48: June 17, 1913 | X48: Charles E. Davis | Y48: J. W. Deering and Mattie E. Deering | AC48: Lots 13 through 21, Block 12, Shores Addition to Elk City | AH48: Beckham | AI48: Oklahoma | AL48: Lots 13-21, Block 12 | BB48: Mortgage Record No. 23, page 180 | BO48: No chain basis identified in Batch 01. | BP48: high | BR48: not_required
A49: B01-G048 | B49: 40 | C49: 40 | D49: 0040.jpg | E49: 1 | F49: MTG | G49: Oklahoma Mortgage | J49: 368 | L49: June 29, 1913 | M49: June 26, 1913 | V49: William B. Farrar and Emma Farrar, husband and wife | W49: The Martin Loan and Investment Company | AC49: The North West quarter of Section Thirty-two (32), Township Eleven (11) North, Range Twenty-five (25) West | AD49: NW/4 of Section 32, Township 11 North, Range 25 West of the Indian Meridian | AE49: 32 | AF49: 11 North | AG49: 25 West | AH49: Beckham (formerly Roger Mills) | AI49: Oklahoma | AJ49: NW/4 | AM49: 160 | BH49: $1,025.00 | BO49: No chain basis identified in Batch 01. | BP49: low | BQ49: Some monetary terms and recording details are faint. | BR49: required
A50: B01-G049 | B50: 41 | C50: 41 | D50: 0041.jpg | E50: 1 | F50: AOM | G50: Assignment of Mortgage | J50: 20 | M50: October 16, 1913 | R50: Martin Loan and Investment Company | S50: Mary Florence | AC50: Lots in Elk City, Oklahoma | AH50: Beckham | AI50: Oklahoma | BH50: $4,000.00 | BO50: No chain basis identified in Batch 01. | BP50: medium | BR50: required
A51: B01-G050 | B51: 41 | C51: 41 | D51: 0041.jpg | E51: 1 | F51: AOM | G51: Assignment of Mortgage | J51: 20 | L51: August 14, 1913 | M51: July 28, 1913 | R51: Martin Loan and Investment Company | S51: Mabel L. Benton | AC51: The North West Quarter of Section Thirty-two (32), Township Eleven (11) North, Range Twenty-five (25) West of the Indian Meridian | AD51: NW/4 of Section 32, Township 11 North, Range 25 West of the Indian Meridian | AE51: 32 | AF51: 11 North | AG51: 25 West | AH51: Beckham (formerly Roger Mills) | AI51: Oklahoma | AJ51: NW/4 | BB51: Mortgage Book 12, page 368 | BH51: $825.00 | BO51: No chain basis identified in Batch 01. | BP51: medium | BR51: required
A52: B01-G051 | B52: 42 | C52: 43 | D52: 0042.jpg 0043.jpg | E52: 2 | F52: MTG | G52: Second Mortgage | I52: 24 Mortgages | J52: 451 | K52: 452 | L52: December 12, 1913, 1:00 P.M. | M52: November 28, 1912 | O52: November 28, 1913 | V52: A. P. Stevens, a single man | W52: Garretson & Woodward | AC52: The south west quarter of Section Thirty-two (32), Township Eleven (11) North, Range Twenty-five (25) West of the Indian Meridian | AD52: SW/4 of Section 32, Township 11 North, Range 25 West of the Indian Meridian | AE52: 32 | AF52: 11 North | AG52: 25 West | AH52: Beckham (formerly Roger Mills) | AI52: Oklahoma | AJ52: SW/4 | BE52: Prior mortgage of same date between same parties for $1,100.00 | BF52: Matures June 1, 1914; 6% until maturity, 10% after maturity | BH52: $137.50 | BL52: Acknowledgment year appears inconsistent with execution year and requires review. | BO52: No chain basis identified in Batch 01. | BP52: high | BR52: not_required
A53: B01-G052 | B53: 43 | C53: 43 | D53: 0043.jpg | E53: 1 | F53: MTG | G53: Mortgage and Refunding Bond (partial) | I53: 24 Mortgages | J53: 452 | L53: December 15, 1913, 10:00 A.M. | M53: December 3, 1913 | V53: L. M. McMillan, O. C. Hartzog, and M. M. Allen, Trustees of Carter Methodist Episcopal Church, South | W53: Board of Church Extension of the Methodist Episcopal Church, South | AH53: Beckham | AI53: Oklahoma | BH53: $200.00 | BL53: Instrument continues beyond Batch 01; legal description not visible. | BO53: No chain basis identified in Batch 01. | BP53: medium | BQ53: Only the first page portion is in scope. | BR53: required
A54: B01-G053 | B54: 44 | C54: 44 | D54: 0044.jpg | E54: 1 | F54: MTG | G54: Oklahoma Mortgage | J54: 426 | L54: February 26, 1915, 10:00 A.M. | M54: January 26, 1915 | O54: January 26, 1915 | V54: William B. Farrar and Emma Farrar, husband and wife | W54: The Martin Loan and Investment Company | AC54: The North West quarter of Section thirty-two (32), Township Eleven (11) North, Range Twenty-five (25) West | AD54: NW/4 of Section 32, Township 11 North, Range 25 West of the Indian Meridian | AE54: 32 | AF54: 11 North | AG54: 25 West | AH54: Beckham (formerly Roger Mills) | AI54: Oklahoma | AJ54: NW/4 | AM54: 160 | BH54: $1,000.00 | BO54: No chain basis identified in Batch 01. | BP54: medium | BR54: required
A55: B01-G054 | B55: 45 | C55: 45 | D55: 0045.jpg | E55: 1 | F55: REL | G55: Release of Mortgage | J55: 150 | L55: July 10, 1914 | M55: February 3, 1914 | X55: State S. Benton | Y55: William B. Farrar and Emma Farrar | AC55: The Northwest quarter of Section thirty-two (32), Township Eleven (11) North, Range twenty-five (25) West | AD55: NW/4 of Section 32, Township 11 North, Range 25 West of the Indian Meridian | AE55: 32 | AF55: 11 North | AG55: 25 West | AH55: Beckham (formerly Roger Mills) | AI55: Oklahoma | AJ55: NW/4 | BB55: Mortgage volume 12, page 368 | BO55: No chain basis identified in Batch 01. | BP55: low | BQ55: Releasor given name may be Mabel/State; handwriting requires confirmation. | BR55: required
A56: B01-G055 | B56: 45 | C56: 45 | D56: 0045.jpg | E56: 1 | F56: REL | G56: Release of Mortgage | L56: February 12, 1914 | M56: January 9, 1914 | X56: H. L. Parks | Y56: Evelyn E. [surname unclear] and husband | AC56: The southwest quarter of Section 30, Township 10 North, Range 22 West, containing 160 acres | AE56: 30 | AF56: 10 North | AG56: 22 West | AH56: Beckham | AI56: Oklahoma | AM56: 160 | BO56: No chain basis identified in Batch 01. | BP56: low | BR56: required
A57: B01-G056 | B57: 46 | C57: 46 | D57: 0046.jpg | E57: 1 | F57: AOM | G57: Assignment of Mortgage | J57: 82 | L57: December 19, 1913 | M57: December 18, 1913 | R57: Martin Loan and Investment Company | S57: Goldwin, Alice P. [reading uncertain] | AC57: The northwest quarter of Section thirty-two (32), Township Eleven (11) North, Range Twenty-five (25) West | AD57: NW/4 of Section 32, Township 11 North, Range 25 West of the Indian Meridian | AE57: 32 | AF57: 11 North | AG57: 25 West | AH57: Beckham (formerly Roger Mills) | AI57: Oklahoma | AJ57: NW/4 | BH57: $500.00 | BO57: No chain basis identified in Batch 01. | BP57: low | BQ57: Assignee name requires confirmation. | BR57: required
A58: B01-G057 | B58: 46 | C58: 46 | D58: 0046.jpg | E58: 1 | F58: AOM | G58: Assignment of Mortgage | J58: 82 | L58: February 24, 1914 | M58: February 22, 1914 | R58: Martin Loan and Investment Company | S58: Kate S. Genter | AC58: The North West quarter of Section thirty-two (32), Township Eleven (11) North, Range Twenty-five (25) West | AD58: NW/4 of Section 32, Township 11 North, Range 25 West of the Indian Meridian | AE58: 32 | AF58: 11 North | AG58: 25 West | AH58: Beckham (formerly Roger Mills) | AI58: Oklahoma | AJ58: NW/4 | BH58: $1,000.00 | BO58: No chain basis identified in Batch 01. | BP58: medium | BR58: required
A59: B01-G058 | B59: 47 | C59: 47 | D59: 0047.jpg | E59: 1 | F59: MTG | G59: Oklahoma Mortgage | J59: 428 | L59: February 26, 1915 | M59: January 26, 1915 | V59: William B. Farrar and Emma Farrar | W59: The Martin Loan and Investment Company | AC59: The North West quarter of Section thirty-two (32), Township Eleven (11) North, Range Twenty-five (25) West | AD59: NW/4 of Section 32, Township 11 North, Range 25 West of the Indian Meridian | AE59: 32 | AF59: 11 North | AG59: 25 West | AH59: Beckham (formerly Roger Mills) | AI59: Oklahoma | AJ59: NW/4 | AM59: 160 | BL59: Separate recorded mortgage from the page-426 instrument on 0044; secures three notes. | BO59: No chain basis identified in Batch 01. | BP59: low | BQ59: Principal amount is faint. | BR59: required
A60: B01-G059 | B60: 48 | C60: 48 | D60: 0048.jpg | E60: 1 | F60: MTG | G60: Real Estate Mortgage | I60: 27 Mortgages | J60: 64 | L60: September 10, 1915 | M60: September 8, 1915 | O60: September 8, 1915 | V60: Austin J. Coffey and Nancy J. Coffey | W60: P. E. Carroll | AC60: All of the Northwest Quarter of Section 32 in Township 11 North of Range 25 West of the Indian Meridian, containing 160 acres | AD60: NW/4 of Section 32, Township 11 North, Range 25 West of the Indian Meridian | AE60: 32 | AF60: 11 North | AG60: 25 West | AH60: Beckham (formerly Roger Mills) | AI60: Oklahoma | AJ60: NW/4 | AM60: 160 | BD60: Subject to prior mortgage executed by William B. Farrar and wife | BH60: $600.00 | BO60: No chain basis identified in Batch 01. | BP60: medium | BR60: required
A61: B01-G060 | B61: 49 | C61: 49 | D61: 0049.jpg | E61: 1 | F61: WD | G61: Warranty Deed | J61: 52 | L61: September 10, 1915, 9:00 A.M. | M61: September 4, 1915 | O61: September 4, 1915 | P61: William B. Farrar and Emma Farrar, husband and wife | Q61: Austin J. Coffey | AC61: The Northwest quarter of Section 32, Township 11 North, Range 25 West of the Indian Meridian, containing 160 acres more or less | AD61: NW/4 of Section 32, Township 11 North, Range 25 West of the Indian Meridian | AE61: 32 | AF61: 11 North | AG61: 25 West | AH61: Beckham (formerly Roger Mills) | AI61: Oklahoma | AJ61: NW/4 | AM61: 160 | BE61: Mortgage for $1,000 payable to Martin Loan and Investment Company | BH61: $2,250.00 | BO61: No chain basis identified in Batch 01. | BP61: medium | BR61: required
A62: B01-G061 | B62: 50 | C62: 50 | D62: 0050.jpg | E62: 1 | F62: REL | G62: Release of Mortgage | J62: 8 | L62: September 16, 1915, 10:00 A.M. | M62: September 10, 1915 | X62: The Martin Loan and Investment Company | Y62: William B. Farrar and Emma Farrar | AC62: Section 32, Township 11 North, Range 25 West; quarter appears to be Northwest Quarter | AD62: NW/4 of Section 32, Township 11 North, Range 25 West of the Indian Meridian | AE62: 32 | AF62: 11 North | AG62: 25 West | AH62: Beckham (formerly Roger Mills) | AI62: Oklahoma | AJ62: NW/4 | AM62: 160 | BB62: Mortgage volume 27, page 64; prior page reference appears as Book 12/page 368 | BO62: No chain basis identified in Batch 01. | BP62: medium | BQ62: Quarter designation and prior-reference handwriting should be checked. | BR62: required
A63: B01-G062 | B63: 50 | C63: 50 | D63: 0050.jpg | E63: 1 | F63: REL | G63: Release of Mortgage | J63: 8 | L63: December 30, 1915 | M63: December 28, 1915 | X63: The Martin Loan and Investment Company | Y63: H. B. Moore and wife | AC63: The North west quarter of Section Twenty-three (23), Township Eleven (11) North, Range Twenty-three (23) West | AE63: 23 | AF63: 11 North | AG63: 23 West | AH63: Beckham | AI63: Oklahoma | BB63: Mortgage page 362, volume 12 | BO63: No chain basis identified in Batch 01. | BP63: medium | BR63: required
A64: B02-G001 | B64: 51 | C64: 51 | D64: 0051.jpg | E64: 1 | F64: REL | G64: Release of Mortgage | I64: 8 Miscellaneous | J64: 101 | L64: October 16, 1916, 9:00 A.M. | M64: October 11, 1916 | X64: M. Carter | Y64: S. H. Carter, J. Carter, husband and wife, and P. M. Carter | AC64: North half of the northwest quarter and the southeast quarter of the northwest quarter of Section 19, Township 10 North, Range 21 West | AE64: 19 | AF64: 10 North | AG64: 21 West | AH64: Beckham | AJ64: N/2 NW/4; SE/4 NW/4 | BB64: Mortgage Record No. 27, page 80 | BM64: Mortgage lien held by M. Carter. | BN64: Mortgage declared satisfied and released. | BO64: No Diversified party or supported Diversified chain link appears in this instrument. | BP64: high | BR64: not_required
A65: B02-G002 | B65: 51 | C65: 53 | D65: 0051.jpg 0052.jpg 0053.jpg | E65: 3 | F65: LSE | G65: Agricultural Lease | I65: 8 Miscellaneous | J65: 101 | K65: 103 | L65: October 16, 1916, 9:00 A.M. | M65: October 14, 1916 | O65: October 14, 1916 | T65: Charles Sing | U65: T. K. Ross | AC65: One hundred sixty acres described as the Southeast quarter of Section 32, Township 11 North, Range 25 West | AD65: SE/4 of Section 32, Township 11 North, Range 25 West of the Indian Meridian | AE65: 32 | AF65: 11 North | AG65: 25 West | AH65: Beckham | AI65: Oklahoma | AJ65: SE/4 | AM65: 160 | BF65: Five years beginning January 1, 1917 and ending January 1, 1922 | BH65: $1,500 evidenced by five $300 annual notes; crop-sharing and farming covenants | BM65: Charles Sing held the lessor's interest in the described premises. | BN65: T. K. Ross received a five-year agricultural leasehold, subject to the stated covenants. | BO65: No Diversified party or supported Diversified chain link appears in this instrument. | BP65: high | BR65: not_required
A66: B02-G003 | B66: 54 | C66: 54 | D66: 0054.jpg | E66: 1 | F66: REL | G66: Release of Mortgage | I66: Release Record No. 4 | J66: 516 | X66: Oklahoma Farm Mortgage Company | Y66: Velmore Biggs and wife | AC66: Southeast quarter of Section 32, Township 11 North, Range 25 West, containing 160 acres | AD66: SE/4 of Section 32, Township 11 North, Range 25 West of the Indian Meridian | AE66: 32 | AF66: 11 North | AG66: 25 West | AH66: Beckham | AI66: Oklahoma | AJ66: SE/4 | AM66: 160 | BL66: Upper release on the page; handwriting is faint. | BM66: Recorded mortgage lien against the SE/4. | BN66: Mortgage lien released. | BO66: No Diversified party or supported Diversified chain link appears in this instrument. | BP66: medium | BR66: required
