Workbook
Name Check1_1: #REF!
Name Check2_1: #REF!
Name Check3_1: #REF!
Name Check4_1: #REF!
Name check5: '[1]Tract Plat Map '!$C$65
Name Check5_1: #REF!
Name Check6_1: #REF!
Name Check7_1: #REF!
Name oijjjojoijpojpoi: #REF!
Name Plat_LastSaved: #REF!
Name Test: #REF!
Name Test4: #REF!
Name XXXXXX: '[2]Well Plat Map '!$B$60

Sheet Overview
D3: Prospect | Q3: 25-004
C5: Section | H5: 31 | L5: Township | R5: 12N | Y5: Range | AC5: 24W
D7: County | H7: Roger Mills | U7: State | X7: Oklahoma
B9: Containing 640.00 acres, more or less
Y14: Tract 1
M18: Tract 4
U22: Tract 2 | AC22: Tract 3
E26: Tract 5
AC30: Tract 7
M34: Tract 6
U36: Tract 8
B44: ATTACHMENTS: | I44: OWNERSHIP REPORT DATED: | Y44: LAST ENTRY:
I46: TITLE OPINION UPDATE DATED: | Y46: LAST ENTRY:
G48: x | I48: CURSORY REPORT DATED: | S48: 6/16/2026 | Y48: LAST ENTRY: | AC48: 2704/142
I50: COUNTY CERTIFICATION DATE:
B52: REMARKS:
B53: REPORT IS A CURSORY REPORT
B56: EXAMINER: | F56: RG

Sheet Title 
B4: TRACT 1: | C4: N/2 NE/4
B5: Containing: | C5: 80 acres, more or less
B7: Mineral Owner | C7: Net Acres | D7: OGL No. | E7: Royalty | F7: Expiration | G7: Comments
B8: Gena Mitchell a/k/a Gena Williams a/k/a Gena Moore | C8: TBD | D8: 2702/0505 | E8: Not stated | F8: Recent Silver Oak lease | G8: N/2 NE/4, SE/4 NE/4; lease terms and ownership require full image.
B9: Mitchell-Buonaccorsi Living Trust trustees | C9: TBD | D9: 2693/0337 | E9: Not stated | F9: Recent Silver Oak lease | G9: N/2 NE/4, SE/4 NE/4; full lease image needed.
B10: Keri Lee Daigle Tucker Trust | C10: TBD | D10: 2697/0520 | E10: Not stated | F10: PDF expanded legal | G10: S31 T12N R24W N2 NE SW; NE SE; SE NE from PDF page 88.
B11: Ronald Paul Dold | C11: TBD | D11: 2697/0524 | E11: Not stated | F11: PDF expanded legal | G11: Covers E2 NW/N2/NE and SW tracts per PDF page 88; full lease needed.
B12: Mark Ashley Daigle Trust | C12: TBD | D12: 2693/0349 | E12: Not stated | F12: Recent Silver Oak lease | G12: SE/4 NE/4, NE/4 SE/4; full lease needed.
B13: Kevin Warner Johnson Trust | C13: TBD | D13: 2693/0345 | E13: Not stated | F13: Recent Silver Oak lease | G13: SE/4 NE/4, NE/4 SE/4; full lease needed.
B14: Carrie Leeann Mitchell / Nancy Susan Mitchell | C14: TBD | D14: 001608/0541; 001608/0543 | E14: Not stated | F14: Historic EOG lease rows | G14: Historic PDF page 24 additions; release/HBP not determined.
B16: REPORT TOTAL | C16: =SUM(C8:C15) -> 0
B17: TOTAL | C17: =SUM(C8:C15) -> 0
B20: TRACT 2: | C20: SW/4 NE/4
B21: Containing: | C21: 40 acres, more or less
B23: Mineral Owner | C23: Net Acres | D23: OGL No. | E23: Royalty | F23: Expiration | G23: Comments
B24: EDR, LLC -> Del Monte Royalty Partners, LLC PO BOX 18876, Oklahoma City, OK | C24: TBD | D24: 2625/0233 | E24: N/A | F24: Mineral deed | G24: SW/4 NE/4; exact fraction/net acres not in index.
B25: EDR, LLC -> Okki Industries, LLC PO BOX 54859, Oklahoma City, OK | C25: TBD | D25: 2625/0231 | E25: N/A | F25: Mineral deed | G25: SW/4 NE/4; exact fraction/net acres not in index.
B26: Greystone Energy & Minerals -> Cardinal Land Co. / EDR | C26: TBD | D26: 2481/0287 | E26: N/A | F26: Mineral deed | G26: SW/4 NE/4; full deed needed.
B27: Paul R. Deutsch / Deborah A. Deutsch | C27: TBD | D27: 2561/0142 | E27: N/A | F27: Address/notice item | G27: SW/4 NE/4; no conveyance inferred.
B28: Matthew Lucas / Katie Lucas | C28: TBD | D28: 2541/0100; 2488/0370 | E28: N/A | F28: Mortgage/release match needed | G28: SE/4 SW/4/Lot 4 partial; collateral/release scope TBD.
B30: REPORT TOTAL | C30: =SUM(C24:C29) -> 0
B31: TOTAL | C31: =SUM(C24:C29) -> 0
B34: TRACT 3: | C34: SE/4 NE/4
B35: Containing: | C35: 40 acres, more or less
B37: Mineral Owner | C37: Net Acres | D37: OGL No. | E37: Royalty | F37: Expiration | G37: Comments
B38: Gena Mitchell a/k/a Williams / Gena W. Moore | C38: TBD | D38: 2702/0505 | E38: 3/16 (0.1875) | F38: Top lease; 5-yr primary; exp 02/11/2031 (springs on prior-lease termination) | G38: N/2 NE/4, SE/4 NE/4; lease terms and ownership require full image. TOP LEASE subordinate to prior 2004-era lease; springs on its termination. Prior Lease: (Mitchell family) to R. Michael Lortz, dtd 01/14/2004, Bk 1736. Term resolved from non-watermarked page-1 image, OKCountyRecords API print 6/12/2026.
B39: Mitchell-Buonaccorsi Living Trust trustees | C39: TBD | D39: 2693/0337 | E39: 3/16 (0.1875) | F39: Top lease; 3-yr primary; exp 02/23/2029 (springs on prior-lease termination) | G39: N/2 NE/4, SE/4 NE/4; full lease image needed. TOP LEASE subordinate to prior 2004-era lease; springs on its termination. Prior Lease: Carrie Leeann Mitchell to R. Michael Lortz, dtd 01/14/2004, Bk 1736 Pg 0594. Term resolved from non-watermarked page-1 image, OKCountyRecords API print 6/12/2026.
B40: Keri Lee Daigle Tucker Trust | C40: TBD | D40: 2697/0520 | E40: 3/16 (0.1875) | F40: Top lease; 5-yr primary term; exp 02/17/2031 | G40: S31 T12N R24W N2 NE SW; NE SE; SE NE from PDF page 88. TOP LEASE subordinate to prior 2004-era lease; springs on its termination. Prior Lease: Sorenson Daigle/Johnson trustees to R. Michael Lortz (2004).
B41: Ronald Paul Dold | C41: TBD | D41: 2697/0524 | E41: 3/16 (0.1875) | F41: Top lease; 3-yr primary term; exp 03/31/2029 | G41: Covers E2 NW/N2/NE and SW tracts per PDF page 88; full lease needed. TOP LEASE subordinate to prior 2004-era lease; springs on its termination. Prior Lease: Nancy S. Mitchell to R. Michael Lortz, dtd 01/14/2004.
B42: Mark Ashley Daigle Trust | C42: TBD | D42: 2693/0349 | E42: 3/16 (0.1875) | F42: Top lease; 5-yr primary; exp 02/23/2031 (springs on prior-lease termination) | G42: SE/4 NE/4, NE/4 SE/4; full lease needed. TOP LEASE subordinate to prior 2004-era lease; springs on its termination. Prior Lease: Sorenson Oil and Gas Trust (Daigle/Johnson, TTEEs) to N/G Discovery, L.L.C.. Term resolved from non-watermarked page-1 image, OKCountyRecords API print 6/12/2026.
B43: Kevin Warner Johnson Trust | C43: TBD | D43: 2693/0345 | E43: 3/16 (0.1875) | F43: Top lease; 5-yr primary; exp 02/27/2031 (springs on prior-lease termination) | G43: SE/4 NE/4, NE/4 SE/4; full lease needed. TOP LEASE subordinate to prior 2004-era lease; springs on its termination. Prior Lease: Sorenson Oil and Gas Trust (Daigle/Johnson, TTEEs) to R. Michael Lortz, dtd 2004. Term resolved from non-watermarked page-1 image, OKCountyRecords API print 6/12/2026.
B44: Carrie Leeann Mitchell / Nancy Susan Mitchell | C44: TBD | D44: 001608/0541; 001608/0543 | E44: Not stated | F44: Historic EOG lease rows | G44: Historic PDF page 24 additions; release/HBP not determined.
B46: REPORT TOTAL | C46: =SUM(C38:C45) -> 0
B47: TOTAL | C47: =SUM(C38:C45) -> 0
B50: TRACT 4: | C50: E/2 NW/4
B51: Containing: | C51: 80 acres, more or less
B53: Mineral Owner | C53: Net Acres | D53: OGL No. | E53: Royalty | F53: Expiration | G53: Comments
B54: Ronald Paul Dold | C54: TBD | D54: 2697/0524 | E54: 3/16 (0.1875) | F54: Top lease; 3-yr primary term; exp 03/31/2029 | G54: Covers E2 NW/N2/NE and SW tracts per PDF page 88; full lease needed. TOP LEASE subordinate to prior 2004-era lease; springs on its termination. Prior Lease: Nancy S. Mitchell to R. Michael Lortz, dtd 01/14/2004.
B55: Colt Development / Roca Development -> Dustin Deal, LLC | C55: TBD | D55: 2426/0154 | E55: N/A | F55: Mineral deed | G55: E/2 NW/4; exact quantum not stated.
B56: Cindy Lou Vignal Trustee -> Gary Wayne Vignal Trustee | C56: TBD | D56: 2406/0228 | E56: N/A | F56: Quit Claim Mineral Deed | G56: E/2 NW/4; full deed needed.
B57: Ella Pearl Kirk -> Calvin Wayne Kirk | C57: TBD | D57: 2365/0338 | E57: N/A | F57: Mineral deed | G57: NW/4 partial; exact legal/quantum TBD.
B58: William Bryant / Kathy Bryant | C58: TBD | D58: 2379/0142; 2511/0016; 2511/0018 | E58: N/A | F58: Mortgage/release match needed | G58: Lot 1 tract/partial; confirm releases.
B59: Ronald Paul Dold -> Silver Oak Natural Resources 5030 N May Ave Ste 125, Oklahoma City, OK | C59: TBD | D59: 2697/0524 | E59: 3/16 (0.1875) | F59: Top lease; 3-yr primary term; exp 03/31/2029 | G59: E/2 NW and other tracts per PDF page 88. TOP LEASE subordinate to prior 2004-era lease; springs on its termination. Prior Lease: Nancy S. Mitchell to R. Michael Lortz, dtd 01/14/2004.
B61: REPORT TOTAL | C61: =SUM(C54:C60) -> 0
B62: TOTAL | C62: =SUM(C54:C60) -> 0
B64: TRACT 5: | C64: NW/4 partial, Lots 1 & 4, SE/4 SW/4 partial
B65: Containing: | C65: Acreage not determined — VERIFY (irregular lots; confirm from plat/survey)
B67: Mineral Owner | C67: Net Acres | D67: OGL No. | E67: Royalty | F67: Expiration | G67: Comments
B68: Ella Pearl Kirk -> Calvin Wayne Kirk | C68: TBD | D68: 2365/0338 | E68: N/A | F68: Mineral deed | G68: NW/4 partial; exact legal/quantum TBD.
B69: William Bryant / Kathy Bryant | C69: TBD | D69: 2379/0142; 2511/0016; 2511/0018 | E69: N/A | F69: Mortgage/release match needed | G69: Lot 1 tract/partial; confirm releases.
B71: REPORT TOTAL | C71: =SUM(C68:C70) -> 0
B72: TOTAL | C72: =SUM(C68:C70) -> 0
B74: TRACT 6: | C74: W/2 SW/4
B75: Containing: | C75: 80 acres, more or less (nominal — VERIFY against plat)
B78: Mineral Owner | C78: Net Acres | D78: OGL No. | E78: Royalty | F78: Expiration | G78: Comments
B79: Ronald Paul Dold | C79: 80 | D79: 2697/0524 | E79: 3/16 (0.1875) | F79: Top lease; 3-yr primary term; exp 03/31/2029 | G79: Covers E2 NW/N2/NE and SW tracts per PDF page 88; full lease needed. TOP LEASE subordinate to prior 2004-era lease; springs on its termination. Prior Lease: Nancy S. Mitchell to R. Michael Lortz, dtd 01/14/2004.
B81: REPORT TOTAL | C81: =SUM(C79:C80) -> 80
B82: TOTAL | C82: =SUM(C79:C80) -> 80
B84: TRACT 7: | C84: NE/4 SE/4
B85: Containing: | C85: 40 acres, more or less (nominal — VERIFY against plat)
B88: Mineral Owner | C88: Net Acres | D88: OGL No. | E88: Royalty | F88: Expiration | G88: Comments
B89: Keri Lee Daigle Tucker Trust | C89: TBD | D89: 2697/0520 | E89: 3/16 (0.1875) | F89: Top lease; 5-yr primary term; exp 02/17/2031 | G89: S31 T12N R24W N2 NE SW; NE SE; SE NE from PDF page 88. TOP LEASE subordinate to prior 2004-era lease; springs on its termination. Prior Lease: Sorenson Daigle/Johnson trustees to R. Michael Lortz (2004).
B90: Mark Ashley Daigle Trust | C90: TBD | D90: 2693/0349 | E90: 3/16 (0.1875) | F90: Top lease; 5-yr primary; exp 02/23/2031 (springs on prior-lease termination) | G90: SE/4 NE/4, NE/4 SE/4; full lease needed. TOP LEASE subordinate to prior 2004-era lease; springs on its termination. Prior Lease: Sorenson Oil and Gas Trust (Daigle/Johnson, TTEEs) to N/G Discovery, L.L.C.. Term resolved from non-watermarked page-1 image, OKCountyRecords API print 6/12/2026.
B91: Kevin Warner Johnson Trust | C91: TBD | D91: 2693/0345 | E91: 3/16 (0.1875) | F91: Top lease; 5-yr primary; exp 02/27/2031 (springs on prior-lease termination) | G91: SE/4 NE/4, NE/4 SE/4; full lease needed. TOP LEASE subordinate to prior 2004-era lease; springs on its termination. Prior Lease: Sorenson Oil and Gas Trust (Daigle/Johnson, TTEEs) to R. Michael Lortz, dtd 2004. Term resolved from non-watermarked page-1 image, OKCountyRecords API print 6/12/2026.
B93: REPORT TOTAL | C93: =SUM(C89:C92) -> 0
B94: TOTAL | C94: =SUM(C89:C92) -> 0
B96: TRACT 8: | C96: W/2 SE/4, SE/4 SE/4
B97: Containing: | C97: 120 acres, more or less (nominal — VERIFY against plat)
B100: Mineral Owner | C100: Net Acres | D100: OGL No. | E100: Royalty | F100: Expiration | G100: Comments
B101: Del Monte Royalty Partners, LLC | C101: TBD | D101: 2625/233 | G101: EDR, LLC mineral deeds (Bk 2625); see note on owner cell.
B102: Okki Industries, LLC | C102: TBD | D102: 2625/231
B103: Cardinal Land Company, LLC | C103: TBD
B104: Longreach Energy 2, LLC | C104: TBD
B105: Royfin Natural Gas, LLC | C105: TBD
B106: Paul M. Bain | C106: TBD
B107: Anna T. Bain Gibson | C107: TBD
B108: Brian Herman Kortright | C108: TBD
B109: Gregory J. Winneke | C109: TBD
B110: Smith, William A. and Isa May Family Revocable Trust | C110: TBD
B111: Jinkee D. Acuero Fuchs, Trustee | C111: TBD
B112: Eric Jansen | C112: TBD
B113: REPORT TOTAL | C113: =SUM(C101:C112) -> 0
B114: TOTAL | C114: =SUM(C101:C112) -> 0
B116: Working Interest: | C116: Insofar as the Lalexander 1-31 / wellbore and all-section leasehold items; exact WI/NRI TBD
B118: Owner | C118: Net Acres | D118: Base OGL's | E118: Royalty | F118: Expiration | G118: Comments
B119: Martin's Empire, LLC -> Stride Bank Trustee | C119: TBD | D119: 2698/0069 / 2026-002547 | E119: N/A | F119: Wellbore assignment; corrected target legal | G119: ORRI assignment, NOT working interest: Martin's Empire, LLC assigns 2% of 8/8ths overriding royalty from the Exhibit A wellbores to Stride Bank, N.A., TTEE of the Umbrella Trust dtd 12/30/2025; eff 01/01/2026, rec 05/04/2026 (2698/0069, 7 pgs). S31 index legal NW NW; OCC surface location is C NW SE. Abstracted from watermarked county image via OKCountyRecords API 6/12/2026 (free to view).
B120: Cheyenne Resources -> Templar Energy, LLC | C120: TBD | D120: 2385/0072 | E120: N/A | F120: Assignment | G120: Lalexander 1-31; well/exhibit review needed.
B121: Hani Tabally -> Santos J. Dominguez | C121: TBD | D121: 2455/0446 | E121: N/A | F121: Assignment | G121: Lalexander of 31-12N-24W; full assignment needed.
B122: Geodyne/Samson -> Fairway Resources III, LLC | C122: TBD | D122: 2356/0399 | E122: N/A | F122: Public snippet assignment | G122: S31 T12N R24W Lalexander; full image needed.
B123: Fairway Resources III, LLC -> JPMorgan Chase Bank P O Box 25848 OK1-1097, Oklahoma City, OK | C123: TBD | D123: 2357/0001 | E123: N/A | F123: Public snippet mortgage | G123: Collateral/release status open.
B124: Deutsche/JPMorgan releases to Samson/Geodyne | C124: TBD | D124: 2356/0001; 2356/0200 | E124: N/A | F124: Public snippet releases | G124: Release effect on target requires full images.
B126: REPORT TOTAL | C126: =SUM(C119:C125) -> 0
B127: TOTAL | C127: =SUM(C119:C125) -> 0
B130: Working Interest:
B132: Owner | C132: Net Acres | D132: Base OGL's | E132: Royalty | F132: Expiration | G132: Comments
B133: Historic Chesapeake/EOG/Lortz/Devon/Jess Harris/TODCO leasehold | C133: TBD | D133: OGLs 1-30 | E133: Mixed/unknown | F133: Expired/HBP status not concluded | G133: Primary terms alone are not enough; check production, pooling, shut-in, extensions and releases.
B134: Silver Oak Natural Resources, LLC 5030 N May Ave Ste 125, Oklahoma City, OK | C134: TBD | D134: 2693/0337; 0345; 0349; 2697/0520; 0524; 2702/0505 | E134: 3/16 (0.1875) | F134: Top leases; 3-to-5-yr primaries; exps 2029-2031 | G134: All six 2026 Silver Oak leases are PAID-UP TOP LEASES at 3/16 royalty, subordinate to 2004-era prior leases and effective only upon their termination. Terms verified from instrument images 6/12/2026: 2693/337 3-yr exp 02/23/2029; 2693/345 5-yr exp 02/27/2031; 2693/349 5-yr exp 02/23/2031; 2697/520 5-yr exp 02/17/2031; 2697/524 3-yr exp 03/31/2029; 2702/505 5-yr exp 02/11/2031.
B135: Lalexander 1-31 / wellbore chain | C135: TBD | D135: 2385/0072; 2455/0446; 2698/0069 | E135: N/A | F135: Well/OCC check required | G135: OCC RBDMS 6/12/2026: Alexander #1-31, API 35-129-22925, status ACTIVE (oil), operator Martin's Resources LLC, surface C NW SE (660' FWL x 1980' FSL). Active status supports HBP for wellbore-tied leasehold; OTC gross-production confirmation still required. | HBP PENDING — Client describes this as an INACTIVE well; OCC RBDMS shows status ACTIVE (oil). Reconcile active/inactive status and confirm OTC gross production before treating the section as HBP.
B136: Mortgage/lien burden chain | C136: TBD | D136: 2356/0001; 2356/0200; 2357/0001; 2357/0474 | E136: N/A | F136: Open until matched to releases | G136: Full images/exhibits needed for release scope and collateral.
B138: REPORT TOTAL | C138: =SUM(C133:C137) -> 0
...

Sheet PLAT
B2: SECTION 31 — T12N R24W, Roger Mills County, OK
B3: Tract / Aliquot Plat — nominal 40-acre quarter-quarter diagram (North up). Not a survey.
C5: N ↑
B6: W | C6: NW/4 NW/4 Tract 5 | E6: NE/4 NW/4 Tract 4 | G6: NW/4 NE/4 Tract 1 | I6: NE/4 NE/4 Tract 1 | K6: E
C9: SW/4 NW/4 Tract 5 | E9: SE/4 NW/4 Tract 4 | G9: SW/4 NE/4 Tract 2 | I9: SE/4 NE/4 Tract 3
C12: NW/4 SW/4 Tract 6 | E12: NE/4 SW/4 NOT ASSIGNED | G12: NW/4 SE/4 Tract 8 | I12: NE/4 SE/4 Tract 7
C15: SW/4 SW/4 Tract 6 | E15: SE/4 SW/4 Tract 5 (part) | G15: SW/4 SE/4 Tract 8 | I15: SE/4 SE/4 Tract 8
C18: S
B20: LEGEND
C21: Tract | D21: Legal description | G21: Nom. ac. | H21: Notes
C22: Tract 1 | D22: N/2 NE/4 | G22: 80
C23: Tract 2 | D23: SW/4 NE/4 | G23: 40
C24: Tract 3 | D24: SE/4 NE/4 | G24: 40
C25: Tract 4 | D25: E/2 NW/4 | G25: 80
C26: Tract 5 | D26: NW/4 partial (W/2, Lots 1 & 4) + SE/4 SW/4 partial | G26: Irregular — VERIFY | H26: Boundary section; W & S tiers are government lots with non-40 acreage.
C27: Tract 6 | D27: W/2 SW/4 | G27: 80 (nom.) | H27: SW tier lotted — confirm acreage vs plat.
C28: Tract 7 | D28: NE/4 SE/4 | G28: 40
C29: Tract 8 | D29: W/2 SE/4, SE/4 SE/4 | G29: 120 (nom.)
C30: — | D30: NE/4 SW/4 | G30: 40 | H30: NOT in any subject tract per current legals — verify (may fall in lots).
B32: Diagram derived from the tract legal descriptions on the Title sheet (data already in this workbook). Aliquot positions are nominal; Section 31 is a township-boundary section, so the west and south tiers are government lots whose true acreage differs from 40. Not a survey — confirm boundaries and acreage against the recorded plat/survey.
B35: Aerial / plat reference — attach recorded plat/survey image here when available.

Sheet OGLs
A1: OGL # | B1: LH | C1: Image # | D1: Instrument | E1: Bk./Pg. | F1: Execution Date | G1: Filing Date | H1: Grantor | I1: Grantee | J1: Legal Description | K1: Misc. Notes | L1: Term | M1: Gross Acres | N1: Tracts | O1: Exp Date | P1: Net Mineral Acres | Q1: Royalty | R1: Depth Clause | S1: Option to Extend | T1: No Warranty Clause | U1: Top Lease Clause | V1: Notes
A2: 29 | D2: Oil and Gas Lease | E2: 4/61 | F2: 6333 | G2: 6333 | H2: H. E. Rupp, L. M. Rupp | I2: Reo Oil and Gas Company | J2: All of 31-12N-24W aol
A3: 30 | D3: Oil and Gas Lease | E3: 4/64 | F3: 6333 | G3: 6333 | H3: M. Hambrook | I3: Reo Oil and Gas Company | J3: All of 31-12N-24W
A4: 33 | D4: Oil and Gas Lease | E4: 4/401 | F4: 7090 | G4: 7090 | H4: Susie Danforth, W. C. Danforth | I4: John R. Williams | J4: All of 31-12N-24W
A5: 34 | D5: Oil and Gas Lease | E5: 4/445 | F5: 7116 | G5: 7116 | H5: H. E. Rupp, Lulu M. Rupp | I5: J. G. Queman | J5: All of 31-12N-24W
A6: 35 | D6: Oil and Gas Lease | E6: 4/556 | F6: 7341 | G6: 7341 | H6: Margaret V. Black, William G. Black | I6: W. E. Thomas | J6: All of 31-12N-24W aol
A7: 31 | D7: Oil and Gas Lease | E7: 5/320 | F7: 6399 | G7: 6399 | H7: Claude J. Mcguire, Herbert E. Mcguire | I7: Empire Gas and Fuel Company | J7: All of 31-12N-24W
A8: 32 | D8: Oil and Gas Lease | E8: 5/332 | F8: 6399 | G8: 6399 | H8: C. S. Repass, Sarah Repass | I8: Empire Gas and Fuel Company | J8: All of 31-12N-24W
A9: 36 | D9: Oil and Gas Lease | E9: 6/484 | F9: 8513 | G9: 8513 | H9: E. T. Gamble, Zella Gamble | I9: Calvin M. Rosser | J9: All of 31-12N-24W
A10: 37 | D10: Oil and Gas Lease | E10: 8/649 | F10: 11164 | G10: 11164 | H10: Louis E. Jaques, Virginia Jaques | I10: Roy M. Johnson | J10: All of 31-12N-24W aol
A11: 39 | D11: Oil and Gas Lease | E11: 9/30 | F11: 11177 | G11: 11177 | H11: Mark Hambrook | I11: Roy M. Johnson | J11: All of 31-12N-24W
A12: 38 | D12: Oil and Gas Lease | E12: 9/32 | F12: 11174 | G12: 11174 | H12: Lee Aulbert, Mollie Aulbert | I12: Roy M. Johnson | J12: All of 31-12N-24W
A13: 40 | D13: Oil and Gas Lease | E13: 9/62 | F13: 11223 | G13: 11223 | H13: Eula Bain, William C. Bain | I13: Roy M. Johnson | J13: All of 31-12N-24W
... A311: 204 | D311: Oil and Gas Lease | E311: 1676/377 | F311: 37347 | G311: 37372 | H311: Myron V. Slobin | I311: Chesapeake Exploration Ltd. PTN | J311: NW/4 SE/4, S/2 SE/4, SW/4 NE/4 of 31-12N-24W
A312: 1 | D312: Oil and Gas Lease | E312: 1676/377 | F312: 37347 | G312: 37372 | H312: Myron V. Slobin | I312: Chesapeake Exploration, Ltd. Partnership | J312: NW/4 SE/4, S/2 SE/4, SW/4 NE/4 of 31-12N-24W | L312: 36 | M312: 160 | O312: 38443 | Q312: 0.25 | S312: F
A313: 205 | D313: Oil and Gas Lease | E313: 1676/379 | F313: 37354 | G313: 37372 | H313: Paul A, Prsnl Repres Albert | I313: Chesapeake Exploration Ltd. PTN | J313: SE/4 SW/4 of 31-12N-24W
A314: 2 | D314: Oil and Gas Lease | E314: 1676/379 | F314: 37354 | G314: 37372 | H314: Paul A, Personal Rep. Albert | I314: Chesapeake Exploration, Ltd. Partnership | J314: SE/4 SW/4 of 31-12N-24W | L314: 36 | M314: 40 | O314: 38450 | Q314: 0.25 | S314: F
A315: 1 | D315: Lease | E315: 1676/377 | F315: 37347 | G315: 37372 | H315: Myron V. Slobin | I315: Chesapeake Exploration Ltd. Ptn | J315: 31-12N-24W | L315: 36 | M315: 160 | O315: 38443 | Q315: 0.25 | S315: F
A316: 2 | D316: Lease | E316: 1676/379 | F316: 37354 | G316: 37372 | H316: Paul A. Prsnl Rep Albert | I316: Chesapeake Exploration Ltd. Ptn | J316: 31-12N-24W | L316: 36 | M316: 40 | O316: 38450 | Q316: 0.25 | S316: F
A317: 214 | D317: Oil and Gas Lease | E317: 1677/512 | F317: 37384 | G317: 37389 | H317: Hayhurst Oil Properties, Inc. | I317: Fleshman Agency, Inc. | J317: E/2 NW/4, N/2 NE/4 SW/4, NE/4 SE/4, SE/4 NE/4 of 31-12N-24W
A318: 7 | D318: Oil and Gas Lease | E318: 1677/512 | F318: 37384 | G318: 37389 | H318: Hayhurst Oil Properties, Inc. | I318: Fleshman Agency, Inc. | J318: E/2 NW/4, N/2 NE/4 SW/4, NE/4 SE/4, SE/4 NE/4 of 31-12N-24W | L318: 12 | M318: 180 | O318: 37749 | Q318: 0.25 | S318: F
A319: 210 | D319: Oil and Gas Lease | E319: 1677/516 | F319: 37364 | G319: 37389 | H319: Lyle T. Ibeling | I319: Chesapeake Exploration Ltd. PTN | J319: NW/4 SE/4, S/2 SE/4, SW/4 NE/4 of 31-12N-24W
A320: 5 | D320: Oil and Gas Lease | E320: 1677/516 | F320: 37364 | G320: 37389 | H320: Lyle T. Ibeling | I320: Chesapeake Exploration Co., Ltd. Partnership | J320: NW/4 SE/4, S/2 SE/4, SW/4 NE/4 of 31-12N-24W | L320: 36 | M320: 160 | O320: 38460 | Q320: 0.25 | S320: F
A321: 208 | D321: Oil and Gas Lease | E321: 1677/533 | F321: 37361 | G321: 37389 | H321: David S. Silverberg | I321: EOG Resources Inc. | J321: NW/4 SE/4, S/2 SE/4, SW/4 NE/4 of 31-12N-24W
A322: 4 | D322: Oil and Gas Lease | E322: 1677/533 | F322: 37361 | G322: 37389 | H322: David S. Silverberg | I322: EOG Resources, Inc. | J322: NW/4 SE/4, S/2 SE/4, SW/4 NE/4 of 31-12N-24W | L322: 36 | M322: 160 | O322: 38457 | Q322: 0.1875 | S322: F
A323: 209 | D323: Oil and Gas Lease | E323: 1677/535 | F323: 37361 | G323: 37389 | H323: Mary Ellen Silverberg | I323: EOG Resources Inc. | J323: NW/4 SE/4, S/2 SE/4, SW/4 NE/4 of 31-12N-24W
A324: 232 | D324: Oil and Gas Lease | E324: 1677/535 | F324: 37361 | G324: 37389 | H324: Mary Ellen Silverberg | I324: EOG Resources, Inc. | J324: NW/4 SE/4, S/2 SE/4, SW/4 NE/4 of 31-12N-24W
A325: 3 | D325: Lease | E325: 1677/512 | F325: 37384 | G325: 37389 | H325: Hayhurst Oil Properties Inc. | I325: Fleshman Agency Inc. | J325: 31-12N-24W | L325: 12 | M325: 180 | O325: 37749 | Q325: 0.25 | S325: F
A326: 4 | D326: Lease | E326: 1677/516 | F326: 37364 | G326: 37389 | H326: Lyle T. Ibeling | I326: Chesapeake Exploration Co. Ltd. Ptn | J326: 31-12N-24W | L326: 36 | M326: 160 | O326: 38460 | Q326: 0.25 | S326: F
A327: 5 | D327: Lease | E327: 1677/533 | F327: 37361 | G327: 37389 | H327: David S. Silverberg | I327: EOG Resources Inc. | J327: 31-12N-24W | L327: 36 | M327: 160 | O327: 38457 | Q327: 0.1875 | S327: F
A328: 212 | D328: Oil and Gas Lease | E328: 1678/554 | F328: 37381 | G328: 37399 | H328: Lyle T. Ibeling | I328: EOG Resources Inc. | J328: NW/4 SE/4, S/2 SE/4, SW/4 NE/4 of 31-12N-24W
A329: 234 | D329: Oil and Gas Lease | E329: 1678/554 | F329: 37381 | G329: 37399 | H329: Lyle T. Ibeling | I329: EOG Resources, Inc. | J329: NW/4 SE/4, S/2 SE/4, SW/4 NE/4 of 31-12N-24W
A330: 211 | D330: Oil and Gas Lease | E330: 1680/431 | F330: 37364 | G330: 37410 | H330: James E. Menchan | I330: Chesapeake Exploration Ltd. PTN | J330: E/2 SE/4, SW/4 NE/4 of 31-12N-24W
A331: 233 | D331: Oil and Gas Lease | E331: 1680/431 | F331: 37364 | G331: 37410 | H331: James E. Menchan | I331: Chesapeake Exploration, Ltd. Partnership | J331: E/2 SE/4, SW/4 NE/4 of 31-12N-24W
A332: 206 | D332: Oil and Gas Lease | E332: 1682/64 | F332: 37354 | G332: 37424 | H332: L. a. Persicke | I332: Chesapeake Exploration Ltd. PTN | J332: NW/4 SE/4, S/2 SE/4 of 31-12N-24W
A333: 231 | D333: Oil and Gas Lease | E333: 1682/64 | F333: 37354 | G333: 37424 | H333: L. A. Persicke | I333: Chesapeake Exploration, Ltd. Partnership | J333: NW/4 SE/4, S/2 SE/4 of 31-12N-24W
A334: 213 | D334: Oil and Gas Lease | E334: 1683/1 | F334: 37381 | G334: 37433 | H334: Deborah a. Deutsch, Paul R. Deutsch | I334: EOG Resources Inc. | J334: NW/4 SE/4, S/2 SE/4, SW/4 NE/4 of 31-12N-24W
A335: 6 | D335: Oil and Gas Lease | E335: 1683/1 | F335: 37381 | G335: 37433 | H335: Deborah A. Deutsch, Paul R. Deutsch | I335: EOG Resources, Inc. | J335: NW/4 SE/4, S/2 SE/4, SW/4 NE/4 of 31-12N-24W | L335: 36 | M335: 160 | O335: 38477 | Q335: 0.1875 | S335: F
A336: 6 | D336: Lease | E336: 1683/1 | F336: 37381 | G336: 37433 | H336: Paul R. & Deborah A. Deutseh | I336: EOG Resources | J336: 31-12N-24W | L336: 36 | M336: 160 | O336: 38477 | Q336: 0.1875 | S336: F
A337: 215 | D337: Oil and Gas Lease | E337: 1684/443 | F337: 37426 | G337: 37454 | H337: James F. Menehan | I337: EOG Resources Inc. | J337: NW/4 SE/4, S/2 SE/4, SW/4 NE/4 of 31-12N-24W
A338: 235 | D338: Oil and Gas Lease | E338: 1684/443 | F338: 37426 | G338: 37454 | H338: James F. Menehan | I338: EOG Resources, Inc. | J338: NW/4 SE/4, S/2 SE/4, SW/4 NE/4 of 31-12N-24W
A339: 216 | D339: Oil and Gas Lease | E339: 1686/580 | F339: 37426 | G339: 37484 | H339: William C, Bain, Jr., Peggy, Atty in Fact Brawner | I339: EOG Resources Inc. | J339: NW/4 SE/4, S/2 SE/4, SW/4 NE/4 of 31-12N-24W
A340: 8 | D340: Oil and Gas Lease | E340: 1686/580 | F340: 37426 | G340: 37484 | H340: William C, Bain, Jr., Peggy, Atty In Fact Brawner | I340: EOG Resources, Inc. | J340: NW/4 SE/4, S/2 SE/4, SW/4 NE/4 of 31-12N-24W | L340: 36 | M340: 160 | O340: 38522 | Q340: 0.125 | S340: F
A341: 7 | D341: Lease | E341: 1686/580 | F341: 37426 | G341: 37484 | H341: Peggy Atty For Bain William C. Jr Brawner | I341: EOG Resources | J341: 31-12N-24W | L341: 36 | M341: 160 | O341: 38522 | Q341: 0.125 | S341: F
A342: 207 | D342: Oil and Gas Lease | E342: 1688/108 | F342: 37354 | G342: 37503 | H342: L. a. Persicke | I342: Chesapeake Exploration Ltd. PTN | J342: NW/4 SE/4, S/2 SE/4, SW/4 NE/4 of 31-12N-24W
A343: 3 | D343: Oil and Gas Lease | E343: 1688/108 | F343: 37354 | G343: 37503 | H343: L. A. Persicke | I343: Chesapeake Exploration, Ltd. Partnership | J343: NW/4 SE/4, S/2 SE/4, SW/4 NE/4 of 31-12N-24W | L343: 36 | M343: 160 | O343: 38450 | Q343: 0.125 | S343: F
A344: 8 | D344: Lease | E344: 1688/108 | F344: 37354 | G344: 37503 | H344: L. A. Persicke | I344: Chesapeake Exploration Ltd. Ptn | J344: 31-12N-24W | L344: 36 | M344: 160 | O344: 38450 | Q344: 0.125 | S344: F
A345: 223 | D345: Oil and Gas Lease | E345: 1689/464 | F345: 37496 | G345: 37525 | H345: Gregory J. Winneke | I345: EOG Resources Inc. | J345: NW/4 SE/4, S/2 SE/4, SW/4 NE/4 of 31-12N-24W
A346: 9 | D346: Oil and Gas Lease | E346: 1689/464 | F346: 37496 | G346: 37525 | H346: Gregory J. Winneke | I346: EOG Resources, Inc. | J346: NW/4 SE/4, S/2 SE/4, SW/4 NE/4 of 31-12N-24W | L346: 36 | M346: 160 | O346: 38592 | Q346: 0.1875 | S346: F
A347: 222 | D347: Ratification | E347: 1689/519 | F347: 37490 | G347: 37525 | H347: Melvin F. Bain | I347: EOG Resources Inc. | J347: NW/4 SE/4, S/2 SE/4, SW/4 NE/4 of 31-12N-24W
A348: 241 | D348: Ratification | E348: 1689/519 | F348: 37490 | G348: 37525 | H348: Melvin F. Bain | I348: EOG Resources, Inc. | J348: NW/4 SE/4, S/2 SE/4, SW/4 NE/4 of 31-12N-24W
A349: 219 | D349: Ratification | E349: 1689/520 | F349: 37459 | G349: 37525 | H349: Leona I. Degrande | I349: EOG Resources Inc. | J349: NW/4 SE/4, S/2 SE/4, SW/4 NE/4 of 31-12N-24W
A350: 238 | D350: Ratification | E350: 1689/520 | F350: 37459 | G350: 37525 | H350: Leona I. Degrande | I350: EOG Resources, Inc. | J350: NW/4 SE/4, S/2 SE/4, SW/4 NE/4 of 31-12N-24W
A351: 218 | D351: Ratification | E351: 1689/521 | F351: 37455 | G351: 37525 | H351: William Cobal, Bain, Jr., Peggy, Atty in Fact Brawner | I351: EOG Resources Inc. | J351: NW/4 SE/4, S/2 SE/4, SW/4 NE/4 of 31-12N-24W
A352: 237 | D352: Ratification | E352: 1689/521 | F352: 37455 | G352: 37525 | H352: William Cobal, Bain, Jr., Peggy, Atty In Fact Brawner | I352: EOG Resources, Inc. | J352: NW/4 SE/4, S/2 SE/4, SW/4 NE/4 of 31-12N-24W
A353: 217 | D353: Ratification | E353: 1689/522 | F353: 37453 | G353: 37525 | H353: Peggy J. Brawner | I353: EOG Resources Inc. | J353: NW/4 SE/4, S/2 SE/4, SW/4 NE/4 of 31-12N-24W
A354: 236 | D354: Ratification | E354: 1689/522 | F354: 37453 | G354: 37525 | H354: Peggy J. Brawner | I354: EOG Resources, Inc. | J354: NW/4 SE/4, S/2 SE/4, SW/4 NE/4 of 31-12N-24W
A355: 220 | D355: Ratification | E355: 1689/523 | F355: 37461 | G355: 37525 | H355: Donald R. Bain | I355: EOG Resources Inc. | J355: NW/4 SE/4, S/2 SE/4, SW/4 NE/4 of 31-12N-24W
A356: 239 | D356: Ratification | E356: 1689/523 | F356: 37461 | G356: 37525 | H356: Donald R. Bain | I356: EOG Resources, Inc. | J356: NW/4 SE/4, S/2 SE/4, SW/4 NE/4 of 31-12N-24W
A357: 221 | D357: Ratification | E357: 1689/524 | F357: 37480 | G357: 37525 | H357: Charlotte F. Wilbert | I357: EOG Resources Inc. | J357: NW/4 SE/4, S/2 SE/4, SW/4 NE/4 of 31-12N-24W
A358: 240 | D358: Ratification | E358: 1689/524 | F358: 37480 | G358: 37525 | H358: Charlotte F. Wilbert | I358: EOG Resources, Inc. | J358: NW/4 SE/4, S/2 SE/4, SW/4 NE/4 of 31-12N-24W
A359: 9 | D359: Lease | E359: 1689/464 | F359: 37496 | G359: 37525 | H359: Gregory J. Winneke | I359: EOG Resources | J359: 31-12N-24W | L359: 36 | M359: 160 | O359: 38592 | Q359: 0.1875 | S359: F
A360: 228 | D360: Oil and Gas Lease | E360: 1736/193 | F360: 38001 | G360: 38020 | H360: Wilda E. Jensen | I360: R. Michael Lortz | J360: NW/4 SE/4, S/2 SE/4, SW/4 NE/4 of 31-12N-24W
A361: 245 | D361: Oil and Gas Lease | E361: 1736/193 | F361: 38001 | G361: 38020 | H361: Wilda E. Jensen | I361: R. Michael Lortz | J361: NW/4 SE/4, S/2 SE/4, SW/4 NE/4 of 31-12N-24W
A362: 229 | D362: Oil and Gas Lease | E362: 1736/195 | F362: 38001 | G362: 38020 | H362: Hans W. Jensen | I362: R. Michael Lortz | J362: NW/4 SE/4, S/2 SE/4, SW/4 NE/4 of 31-12N-24W
A363: 246 | D363: Oil and Gas Lease | E363: 1736/195 | F363: 38001 | G363: 38020 | H363: Hans W. Jensen | I363: R. Michael Lortz | J363: NW/4 SE/4, S/2 SE/4, SW/4 NE/4 of 31-12N-24W
A364: 236 | D364: Oil and Gas Lease | E364: 1736/197 | F364: 38007 | G364: 38020 | H364: A. C. Campbell | I364: R. Michael Lortz | J364: S/2 NE/4 SW/4, Lot 4, SE/4 SW/4, Lot 3 of 31-12N-24W
A365: 252 | D365: Oil and Gas Lease | E365: 1736/197 | F365: 38007 | G365: 38020 | H365: A. C. Campbell | I365: R. Michael Lortz | J365: S/2 NE/4 SW/4, Lot 4, SE/4 SW/4, Lot 3 of 31-12N-24W
A366: 230 | D366: Oil and Gas Lease | E366: 1736/199 | F366: 38001 | G366: 38020 | H366: Tim E. Jensen | I366: R. Michael Lortz | J366: NW/4 SE/4, S/2 SE/4, SW/4 NE/4 of 31-12N-24W
A367: 247 | D367: Oil and Gas Lease | E367: 1736/199 | F367: 38001 | G367: 38020 | H367: Tim E. Jensen | I367: R. Michael Lortz | J367: NW/4 SE/4, S/2 SE/4, SW/4 NE/4 of 31-12N-24W
A368: 240 | D368: Oil and Gas Lease | E368: 1736/473 | F368: 38025 | G368: 38027 | H368: Charles Allen Atha | I368: R. Michael Lortz | J368: All of 31-12N-24W
A369: 13 | D369: Oil and Gas Lease | E369: 1736/473 | F369: 38025 | G369: 38027 | H369: Charles Allen Atha | I369: R. Michael Lortz | J369: All of 31-12N-24W | L369: 36 | M369: 92.135002 | O369: 39121 | Q369: 0.1875 | S369: F
A370: 238 | D370: Oil and Gas Lease | E370: 1736/485 | F370: 38019 | G370: 38027 | H370: L. E. Thurman | I370: R. Michael Lortz | J370: E/2 NW/4, N/2 NE/4 SW/4, NE/4 SE/4, SE/4 NE/4 of 31-12N-24W
A371: 254 | D371: Oil and Gas Lease | E371: 1736/485 | F371: 38019 | G371: 38027 | H371: L. E. Thurman | I371: R. Michael Lortz | J371: E/2 NW/4, N/2 NE/4 SW/4, NE/4 SE/4, SE/4 NE/4 of 31-12N-24W
A372: 237 | D372: Oil and Gas Lease | E372: 1736/496 | F372: 38012 | G372: 38027 | H372: John W. Bain, Joseph a. Bain, Anna T. Gibson | I372: R. Michael Lortz | J372: NW/4 SE/4, S/2 SE/4, SW/4 NE/4 of 31-12N-24W
A373: 253 | D373: Oil and Gas Lease | E373: 1736/496 | F373: 38012 | G373: 38027 | H373: John W. Bain, Joseph A. Bain, Anna T. Gibson | I373: R. Michael Lortz | J373: NW/4 SE/4, S/2 SE/4, SW/4 NE/4 of 31-12N-24W
A374: 235 | D374: Oil and Gas Lease | E374: 1736/588 | F374: 38007 | G374: 38029 | H374: Clarence C. Bain | I374: R. Michael Lortz | J374: NW/4 SE/4, S/2 SE/4, SW/4 NE/4 of 31-12N-24W
A375: 11 | D375: Oil and Gas Lease | E375: 1736/588 | F375: 38007 | G375: 38029 | H375: Clarence C. Bain | I375: R. Michael Lortz | J375: NW/4 SE/4, S/2 SE/4, SW/4 NE/4 of 31-12N-24W | L375: 36 | M375: 160 | O375: 39103 | Q375: 0.1875 | S375: F
A376: 231 | D376: Oil and Gas Lease | E376: 1736/590 | F376: 38001 | G376: 38029 | H376: Juanita M. Wolff | I376: R. Michael Lortz | J376: NW/4 SE/4, S/2 SE/4, SW/4 NE/4 of 31-12N-24W
A377: 248 | D377: Oil and Gas Lease | E377: 1736/590 | F377: 38001 | G377: 38029 | H377: Juanita M. Wolff | I377: R. Michael Lortz | J377: NW/4 SE/4, S/2 SE/4, SW/4 NE/4 of 31-12N-24W
A378: 224 | D378: Oil and Gas Lease | E378: 1736/592 | F378: 37999 | G378: 38029 | H378: Nancy Mitchell Williams | I378: R. Michael Lortz | J378: E/2 NW/4, N/2 NE/4, N/2 NE/4 SW/4, Lot 4, NE/4 SE/4, S/2 NE/4 SW/4, SE/4 NE/4, SE/4 SW/4 of 31-12N-24W
A379: 10 | D379: Oil and Gas Lease | E379: 1736/592 | F379: 37999 | G379: 38029 | H379: Nancy Mitchell Williams | I379: R. Michael Lortz | J379: E/2 NW/4, N/2 NE/4, N/2 NE/4 SW/4, Lot 4, NE/4 SE/4, S/2 NE/4 SW/4, SE/4 NE/4, SE/4 SW/4 of 31-12N-24W | L379: 36 | M379: 375.33499 | O379: 39095 | Q379: 0.1875 | S379: F
A380: 225 | D380: Oil and Gas Lease | E380: 1736/594 | F380: 37999 | G380: 38029 | H380: Carrie Leeann Mitchell | I380: R. Michael Lortz | J380: E/2 NW/4, N/2 NE/4, N/2 NE/4 SW/4, Lot 4, NE/4 SE/4, S/2 NE/4 SW/4, SE/4 NE/4, SE/4 SW/4 of 31-12N-24W
A381: 242 | D381: Oil and Gas Lease | E381: 1736/594 | F381: 37999 | G381: 38029 | H381: Carrie Leeann Mitchell | I381: R. Michael Lortz | J381: E/2 NW/4, N/2 NE/4, N/2 NE/4 SW/4, Lot 4, NE/4 SE/4, S/2 NE/4 SW/4, SE/4 NE/4, SE/4 SW/4 of 31-12N-24W
A382: 232 | D382: Oil and Gas Lease | E382: 1736/596 | F382: 38001 | G382: 38029 | H382: Carl L. Bain | I382: R. Michael Lortz | J382: NW/4 SE/4, S/2 SE/4, SW/4 NE/4 of 31-12N-24W
A383: 249 | D383: Oil and Gas Lease | E383: 1736/596 | F383: 38001 | G383: 38029 | H383: Carl L. Bain | I383: R. Michael Lortz | J383: NW/4 SE/4, S/2 SE/4, SW/4 NE/4 of 31-12N-24W
A384: 233 | D384: Oil and Gas Lease | E384: 1736/598 | F384: 38001 | G384: 38029 | H384: Dow C. Etux Bain | I384: R. Michael Lortz | J384: NW/4 SE/4, S/2 SE/4, SW/4 NE/4 of 31-12N-24W
A385: 250 | D385: Oil and Gas Lease | E385: 1736/598 | F385: 38001 | G385: 38029 | H385: Dow C. Etux Bain | I385: R. Michael Lortz | J385: NW/4 SE/4, S/2 SE/4, SW/4 NE/4 of 31-12N-24W
A386: 226 | D386: Oil and Gas Lease | E386: 1736/600 | F386: 37999 | G386: 38029 | H386: Nancy Susan Mitchell | I386: R. Michael Lortz | J386: E/2 NW/4, N/2 NE/4, N/2 NE/4 SW/4, Lot 4, NE/4 SE/4, S/2 NE/4 SW/4, SE/4 NE/4, SE/4 SW/4 of 31-12N-24W
A387: 243 | D387: Oil and Gas Lease | E387: 1736/600 | F387: 37999 | G387: 38029 | H387: Nancy Susan Mitchell | I387: R. Michael Lortz | J387: E/2 NW/4, N/2 NE/4, N/2 NE/4 SW/4, Lot 4, NE/4 SE/4, S/2 NE/4 SW/4, SE/4 NE/4, SE/4 SW/4 of 31-12N-24W
A388: 227 | D388: Oil and Gas Lease | E388: 1736/602 | F388: 37999 | G388: 38029 | H388: Gena W. Moore | I388: R. Michael Lortz | J388: E/2 NW/4, N/2 NE/4, N/2 NE/4 SW/4, Lot 4, NE/4 SE/4, S/2 NE/4 SW/4, SE/4 NE/4, SE/4 SW/4 of 31-12N-24W
A389: 244 | D389: Oil and Gas Lease | E389: 1736/602 | F389: 37999 | G389: 38029 | H389: Gena W. Moore | I389: R. Michael Lortz | J389: E/2 NW/4, N/2 NE/4, N/2 NE/4 SW/4, Lot 4, NE/4 SE/4, S/2 NE/4 SW/4, SE/4 NE/4, SE/4 SW/4 of 31-12N-24W
A390: 10 | D390: Lease | E390: 1736/473 | F390: 38025 | G390: 38027 | H390: Charles Allen Atha | I390: R. Michael Lortz | J390: 31-12N-24W | L390: 36 | M390: 92.135002 | O390: 39121 | Q390: 0.1875 | S390: F
A391: 11 | D391: Lease | E391: 1736/588 | F391: 38007 | G391: 38029 | H391: Clarence C. Ttee Bain | I391: R. Michael Lortz | J391: 31-12N-24W | L391: 36 | M391: 160 | O391: 39103 | Q391: 0.1875 | S391: F
A392: 12 | D392: Lease | E392: 1736/592 | F392: 37999 | G392: 38029 | H392: Nancy Mitchell Williams | I392: R. Michael Lortz | J392: 31-12N-24W | L392: 36 | M392: 375.33499 | O392: 39095 | Q392: 0.1875 | S392: F
A393: 241 | D393: Oil and Gas Lease | E393: 1737/580 | F393: 38032 | G393: 38040 | H393: Sandra Lorrain York | I393: Kodiak Production Company | J393: All of 31-12N-24W
A394: 255 | D394: Oil and Gas Lease | E394: 1737/580 | F394: 38032 | G394: 38040 | H394: Sandra Lorrain York | I394: Kodiak Production Company | J394: All of 31-12N-24W
A395: 239 | D395: Oil and Gas Lease | E395: 1738/479 | F395: 38022 | G395: 38049 | H395: Lola F. Richards | I395: R. Michael Lortz | J395: NW/4 SE/4, S/2 SE/4, SW/4 NE/4 of 31-12N-24W
A396: 12 | D396: Oil and Gas Lease | E396: 1738/479 | F396: 38022 | G396: 38049 | H396: Lola F. Richards | I396: R. Michael Lortz | J396: NW/4 SE/4, S/2 SE/4, SW/4 NE/4 of 31-12N-24W | L396: 36 | M396: 100 | O396: 39118 | Q396: 0.1875 | S396: F
A397: 13 | D397: Lease | E397: 1738/479 | F397: 38022 | G397: 38049 | H397: Lola F. Richards | I397: R. Michael Lortz | J397: 31-12N-24W | L397: 36 | M397: 100 | O397: 39118 | Q397: 0.1875 | S397: F
...

Sheet Runsheet
A1: Instrument # | B1: OGL | C1: Doc Type | D1: Bk/Pg. | E1: Effective Date | F1: Recorded Date | G1: Grantor | H1: Grantee | I1: Legal Description | J1: Notes | K1: Document Link
A2: 1905-000429 | C2: Deed | D2: D6/206 | E2: 2062 | F2: 2063 | G2: Leo Kennett | H2: Mack Hawbrook | I2: E/2 NW/4, Lots 1, 2 of 31-12N-24W | J2: ARTI | K2: =HYPERLINK("https://okcountyrecords.com/detail/roger+mills/1905-000429","OKCountyRecords: 1905-000429") -> OKCountyRecords: 1905-000429
A3: 1907-000709 | C3: Deed | D3: D9/303 | E3: 2592 | F3: 2601 | G3: Charles T. Kennett and Sadie N. Kennett, HW | H3: John G. Lancaster | I3: SW/4 NE/4 SW/4 SE/4, SE/4 SE/4 of 31-12N-24W | J3: ARTI | K3: =HYPERLINK("https://okcountyrecords.com/detail/roger+mills/1907-000709","OKCountyRecords: 1907-000709") -> OKCountyRecords: 1907-000709
A4: 1913-000413 | C4: Deed | D4: D19/268 | E4: 4759 | F4: 4759 | G4: Ernest Brooks and Mary Brooks, HW | H4: Susie Danforth, W. C. Danforth | I4: SE/4 NE/4, NE/4 SE/4 of 31-12N-24W | J4: ARTI | K4: =HYPERLINK("https://okcountyrecords.com/detail/roger+mills/1913-000413","OKCountyRecords: 1913-000413") -> OKCountyRecords: 1913-000413
A5: 1916-001105 | C5: Lease | D5: MIS9/513 | E5: 5913 | F5: 5913 | G5: W. D. Wilson | H5: Olo Olson | I5: All of 31-12N-24W aol | J5: Leasehold / WI | K5: =HYPERLINK("https://okcountyrecords.com/detail/roger+mills/1916-001105","OKCountyRecords: 1916-001105") -> OKCountyRecords: 1916-001105
A6: 1917-003351 | C6: Oil and Gas Lease | D6: OGL4/61 | E6: 6333 | F6: 6333 | G6: H. E. Rupp, L. M. Rupp | H6: Reo Oil & Gas Company | I6: 31-12N-24W, aol | J6: Leasehold / WI | K6: =HYPERLINK("https://okcountyrecords.com/detail/roger+mills/1917-003351","OKCountyRecords: 1917-003351") -> OKCountyRecords: 1917-003351
A7: 1917-003354 | C7: Oil and Gas Lease | D7: OGL4/64 | E7: 6333 | F7: 6333 | G7: M. Hambrook | H7: Reo Oil & Gas Company | I7: 31-12N-24W | J7: Leasehold / WI | K7: =HYPERLINK("https://okcountyrecords.com/detail/roger+mills/1917-003354","OKCountyRecords: 1917-003354") -> OKCountyRecords: 1917-003354
A8: 1917-003731 | C8: Oil and Gas Lease | D8: OGL5/320 | E8: 6399 | F8: 6399 | G8: Claude J. McGuire, Herbert E. McGuire | H8: Empire Gas & Fuel Company | I8: 31-12N-24W | J8: Leasehold / WI | K8: =HYPERLINK("https://okcountyrecords.com/detail/roger+mills/1917-003731","OKCountyRecords: 1917-003731") -> OKCountyRecords: 1917-003731
A9: 1917-003743 | C9: Oil and Gas Lease | D9: OGL5/332 | E9: 6399 | F9: 6399 | G9: C. S. Repass, Sarah Repass | H9: Empire Gas & Fuel Company | I9: 31-12N-24W | J9: Leasehold / WI | K9: =HYPERLINK("https://okcountyrecords.com/detail/roger+mills/1917-003743","OKCountyRecords: 1917-003743") -> OKCountyRecords: 1917-003743
A10: 1918-002463 | C10: Release | D10: REL9/108 | E10: 6589 | F10: 6589 | G10: State Life Ins Co | H10: Claude J. McGuire, Herbert E. McGuire | I10: 31-12N-24W | J10: Leasehold / WI | K10: =HYPERLINK("https://okcountyrecords.com/detail/roger+mills/1918-002463","OKCountyRecords: 1918-002463") -> OKCountyRecords: 1918-002463
A11: 1918-002091 | C11: Release | D11: REL5/251 | E11: 6596 | F11: 6596 | G11: E. C. Thorne | H11: Claude McGuire, Herbert E. McGuire | I11: 31-12N-24W | J11: Leasehold / WI | K11: =HYPERLINK("https://okcountyrecords.com/detail/roger+mills/1918-002091","OKCountyRecords: 1918-002091") -> OKCountyRecords: 1918-002091
A12: 1919-002106 | C12: Oil and Gas Lease | D12: OGL4/401 | E12: 7090 | F12: 7090 | G12: Susie Danforth, W. C. Danforth | H12: John R. Williams | I12: 31-12N-24W | J12: Leasehold / WI | K12: =HYPERLINK("https://okcountyrecords.com/detail/roger+mills/1919-002106","OKCountyRecords: 1919-002106") -> OKCountyRecords: 1919-002106
A13: 1920-000012 | C13: Assignment | D13: ASN4/82 | E13: 7317 | F13: 7317 | G13: Martin Loan & Investment Company | H13: Florence Lewis | I13: 31-12N-24W | J13: Leasehold / WI | K13: =HYPERLINK("https://okcountyrecords.com/detail/roger+mills/1920-000012","OKCountyRecords: 1920-000012") -> OKCountyRecords: 1920-000012
A14: 1920-002046 | C14: Oil and Gas Lease | D14: OGL4/556 | E14: 7341 | F14: 7341 | G14: Margaret V. Black, William G. Black | H14: W. E. Thomas | I14: 31-12N-24W, aol | J14: Leasehold / WI | K14: =HYPERLINK("https://okcountyrecords.com/detail/roger+mills/1920-002046","OKCountyRecords: 1920-002046") -> OKCountyRecords: 1920-002046
A15: 1921-001533 | C15: Release | D15: REL11/342 | E15: 7682 | F15: 7682 | G15: H. L. Rowley | H15: H. E. Rupp, Lula M. Rupp | I15: 31-12N-24W, aol | J15: Leasehold / WI | K15: =HYPERLINK("https://okcountyrecords.com/detail/roger+mills/1921-001533","OKCountyRecords: 1921-001533") -> OKCountyRecords: 1921-001533
A16: 1923-002282 | C16: Oil and Gas Lease | D16: OGL6/484 | E16: 8513 | F16: 8513 | G16: E. T. Gamble, Zella Gamble | H16: Calvin M. Rosser | I16: 31-12N-24W | J16: Leasehold / WI | K16: =HYPERLINK("https://okcountyrecords.com/detail/roger+mills/1923-002282","OKCountyRecords: 1923-002282") -> OKCountyRecords: 1923-002282
A17: 1925-000406 | C17: Deed | D17: D34/104 | E17: 9137 | F17: 9137 | G17: E. T. Gamble and Zella M. Gamble, HW | H17: Leo Aulbert | I17: S/2 SW/4, S/2 N/2 SW/4 of 31-12N-24W | J17: ARTI | K17: =HYPERLINK("https://okcountyrecords.com/detail/roger+mills/1925-000406","OKCountyRecords: 1925-000406") -> OKCountyRecords: 1925-000406
A18: 1928-002014 | C18: Release | D18: REL15/588 | E18: 10238 | F18: 10238 | G18: E. C. Thorne | H18: Claude J. McGuire, Herbert E. McGuire | I18: 31-12N-24W | J18: Leasehold / WI | K18: =HYPERLINK("https://okcountyrecords.com/detail/roger+mills/1928-002014","OKCountyRecords: 1928-002014") -> OKCountyRecords: 1928-002014
A19: 1930-003190 | C19: Release | D19: REL16/331 | E19: 10964 | F19: 10964 | G19: Albert G. Frick | H19: H. E. Rupp, Lula Rupp | I19: 31-12N-24W, aol | J19: Leasehold / WI | K19: =HYPERLINK("https://okcountyrecords.com/detail/roger+mills/1930-003190","OKCountyRecords: 1930-003190") -> OKCountyRecords: 1930-003190
A20: 1930-002708 | C20: Oil and Gas Lease | D20: OGL8/649 | E20: 11164 | F20: 11164 | G20: Louis E. Jaques, Virginia Jaques | H20: Roy M. Johnson | I20: 31-12N-24W, aol | J20: Leasehold / WI | K20: =HYPERLINK("https://okcountyrecords.com/detail/roger+mills/1930-002708","OKCountyRecords: 1930-002708") -> OKCountyRecords: 1930-002708
A21: 1931-001768 | C21: Oil and Gas Lease | D21: OGL9/176 | E21: 11364 | F21: 11364 | G21: Swinburn J. Stewart | H21: Roy M. Johnson | I21: 31-12N-24W | J21: Leasehold / WI | K21: =HYPERLINK("https://okcountyrecords.com/detail/roger+mills/1931-001768","OKCountyRecords: 1931-001768") -> OKCountyRecords: 1931-001768
A22: 2005-008386 | C22: Order and Final Decree | D22: 1816/41 | E22: 12655 | F22: 38695 | G22: Roger Mills County Court RE: In the Matter of the Estate of Louis E. Jaques, deceased | H22: Virginia Jaques, widow, 1/2, Ethel Brister, 1/2 | I22: N/2 NE/4 of 31-12N-24W, aol | J22: ARTI | K22: =HYPERLINK("https://okcountyrecords.com/detail/roger+mills/2005-008386","OKCountyRecords: 2005-008386") -> OKCountyRecords: 2005-008386
A23: 1937-000416 | C23: Warranty Deed | D23: D48/72 | E23: 13545 | F23: 13545 | G23: Virginia Jaques and N. Virgina Jacques, one and the same person, a widow | H23: H. M. Carter | I23: N/2 NE/4 of 31-12N-24W, aol | J23: ARTI Subject to 1/2 of the royalty sold to Panhandle Co-Operative Royalty Company | K23: =HYPERLINK("https://okcountyrecords.com/detail/roger+mills/1937-000416","OKCountyRecords: 1937-000416") -> OKCountyRecords: 1937-000416
A24: 1945-000816 | C24: Final Decree | D24: MIS22/628 | E24: 16439 | F24: 16439 | G24: Beckham County Court, RE: In the Matter of the Estate of Benjamin H. Shotwell, Deceased | H24: Maggie Bennett, Eli L. Shotwell, Pearl L. Davis, Roy T. Shotwell, Ida M. Cuff | I24: SE/4 NE/4, NE/4 SE/4 of 31-12N-24W, aol | J24: ARTI | K24: =HYPERLINK("https://okcountyrecords.com/detail/roger+mills/1945-000816","OKCountyRecords: 1945-000816") -> OKCountyRecords: 1945-000816
A25: 1946-001487 | C25: Oil and Gas Lease | D25: OGL11/83 | E25: 16860 | F25: 16860 | G25: Lee Aulbert, Mollie Aulbert | H25: Tom R. Johnson Jr. | I25: 31-12N-24W | J25: Leasehold / WI | K25: =HYPERLINK("https://okcountyrecords.com/detail/roger+mills/1946-001487","OKCountyRecords: 1946-001487") -> OKCountyRecords: 1946-001487
A26: 1946-001492 | C26: Oil and Gas Lease | D26: OGL11/88 | E26: 16860 | F26: 16860 | G26: Eula Bain, William C. Bain | H26: O. C. Robinson | I26: 31-12N-24W | J26: Leasehold / WI | K26: =HYPERLINK("https://okcountyrecords.com/detail/roger+mills/1946-001492","OKCountyRecords: 1946-001492") -> OKCountyRecords: 1946-001492
A27: 1948-002010 | C27: Oil and Gas Lease | D27: OGL11/337 | E27: 17549 | F27: 17549 | G27: J. E. Campbell, Lillie A. Campbell | H27: C. L. Moss | I27: 31-12N-24W | J27: Leasehold / WI | K27: =HYPERLINK("https://okcountyrecords.com/detail/roger+mills/1948-002010","OKCountyRecords: 1948-002010") -> OKCountyRecords: 1948-002010
A28: 1948-000087 | C28: Assignment | D28: ASN14/269 | E28: 17554 | F28: 17554 | G28: J. B. Campbell, Lillie A. Campbell, Lillie A. Hambrook | H28: Commissioners of the Land Office | I28: 31-12N-24W | J28: Leasehold / WI | K28: =HYPERLINK("https://okcountyrecords.com/detail/roger+mills/1948-000087","OKCountyRecords: 1948-000087") -> OKCountyRecords: 1948-000087
A29: 1949-001867 | C29: Mineral Deed | D29: D63/97 | E29: 18170 | F29: 18170 | G29: H. M. Carter and Ethel Carter, HW | H29: G. C. Mitchel, Glenn D. Mitchel | I29: E/2 NW/4, SE/4 NE/4, NE/4 SE/4, N/2 NE/4 SW/4 of 31-12N-24W, aol | J29: 20/260 interest, being 20 NMA in 2 sections | K29: =HYPERLINK("https://okcountyrecords.com/detail/roger+mills/1949-001867","OKCountyRecords: 1949-001867") -> OKCountyRecords: 1949-001867
A30: 1950-000383 | C30: Warranty Deed | D30: D59/410 | E30: 18420 | F30: 18420 | G30: H. M. Carter and Ethel Carter, HW | H30: Marvin G. Mitchell and Carrie Lou Mitchell, HW, JTWROS | I30: E/2 NW/4, SE/4 NE/4, NE/4 SE/4, N/2 NE/4 SW/4 of 31-12N-24W, aol | J30: ARTI, Except 1/2 of the ogms in the N/2 NE/4 Corrects deed dated 2/21/1949 | K30: =HYPERLINK("https://okcountyrecords.com/detail/roger+mills/1950-000383","OKCountyRecords: 1950-000383") -> OKCountyRecords: 1950-000383
A31: 1951-001020 | C31: Surface Warranty Deed | D31: D65/63 | E31: 18680 | F31: 18680 | G31: Marvin G. Mitchell and Carrie Lou Mitchell, HW | H31: Elvin J. Ridling | I31: E/2 NW/4, SE/4 NE/4, NE/4 SE/4, N/2 NE/4 SW/4 of 31-12N-24W, aol | J31: Surface only, Grantors reserve all minerals | K31: =HYPERLINK("https://okcountyrecords.com/detail/roger+mills/1951-001020","OKCountyRecords: 1951-001020") -> OKCountyRecords: 1951-001020
A32: 1953-000493 | C32: Warranty Deed | D32: D67/154 | E32: 19396 | F32: 19396 | G32: Elvin J. Ridling and Dorothy Jean Ridling, HW | H32: M. G. Mitchell and Carrie Lou Mitchell, HW, JTWROS | I32: E/2 NW/4, SE/4 NE/4, NE/4 SE/4, N/2 NE/4 SW/4, Lot 4, S/2 SW/4, SE/4 SW/4 of 31-12N-24W | J32: ARTI | K32: =HYPERLINK("https://okcountyrecords.com/detail/roger+mills/1953-000493","OKCountyRecords: 1953-000493") -> OKCountyRecords: 1953-000493
A33: 1962-000500 | C33: Oil and Gas Lease | D33: MIS45/202 | E33: 22761 | F33: 22761 | G33: Joseph Devenas, Mary Margaret Devenas | H33: Robert O. Lister Jr. | I33: All of 31-12N-24W aol | J33: Leasehold / WI | K33: =HYPERLINK("https://okcountyrecords.com/detail/roger+mills/1962-000500","OKCountyRecords: 1962-000500") -> OKCountyRecords: 1962-000500
A34: 1962-000501 | C34: Oil and Gas Lease | D34: MIS45/204 | E34: 22761 | F34: 22761 | G34: Margaret Gray, Murrell Gray | H34: Robert O. Lister Jr. | I34: All of 31-12N-24W aol | J34: Leasehold / WI | K34: =HYPERLINK("https://okcountyrecords.com/detail/roger+mills/1962-000501","OKCountyRecords: 1962-000501") -> OKCountyRecords: 1962-000501
A35: 1962-000502 | C35: Oil and Gas Lease | D35: MIS45/206 | E35: 22761 | F35: 22761 | G35: Gladys Priest | H35: Robert O. Lister Jr. | I35: All of 31-12N-24W aol | J35: Leasehold / WI | K35: =HYPERLINK("https://okcountyrecords.com/detail/roger+mills/1962-000502","OKCountyRecords: 1962-000502") -> OKCountyRecords: 1962-000502
A36: 1962-000503 | C36: Oil and Gas Lease | D36: MIS45/208 | E36: 22761 | F36: 22761 | G36: Ethel I. Carter, H. M. Carter | H36: Robert O. Lister Jr. | I36: All of 31-12N-24W aol | J36: Leasehold / WI | K36: =HYPERLINK("https://okcountyrecords.com/detail/roger+mills/1962-000503","OKCountyRecords: 1962-000503") -> OKCountyRecords: 1962-000503
A37: 1962-000505 | C37: Oil and Gas Lease | D37: MIS45/212 | E37: 22761 | F37: 22761 | G37: Carrie Lou Mitchell, Marvin G. Mitchell | H37: Robert O. Lister Jr. | I37: All of 31-12N-24W | J37: Leasehold / WI | K37: =HYPERLINK("https://okcountyrecords.com/detail/roger+mills/1962-000505","OKCountyRecords: 1962-000505") -> OKCountyRecords: 1962-000505
A38: 1962-000506 | C38: Oil and Gas Lease | D38: MIS45/214 | E38: 22761 | F38: 22761 | G38: Carrie Lou Mitchell, Marvin G. Mitchell | H38: Robert O. Lister Jr. | I38: All of 31-12N-24W | J38: Leasehold / WI | K38: =HYPERLINK("https://okcountyrecords.com/detail/roger+mills/1962-000506","OKCountyRecords: 1962-000506") -> OKCountyRecords: 1962-000506
A39: 1962-000726 | C39: Oil and Gas Lease | D39: MIS45/598 | E39: 22816 | F39: 22816 | G39: Carrie Lou Mitchell, Marvin G. Mitchell | H39: Robert O. Lister Jr. | I39: All of 31-12N-24W | J39: Leasehold / WI | K39: =HYPERLINK("https://okcountyrecords.com/detail/roger+mills/1962-000726","OKCountyRecords: 1962-000726") -> OKCountyRecords: 1962-000726
A40: 1962-000727 | C40: Oil and Gas Lease | D40: MIS45/600 | E40: 22816 | F40: 22816 | G40: Carrie Lou Mitchell, Marvin G. Mitchell | H40: Robert O. Lister Jr. | I40: All of 31-12N-24W | J40: Leasehold / WI | K40: =HYPERLINK("https://okcountyrecords.com/detail/roger+mills/1962-000727","OKCountyRecords: 1962-000727") -> OKCountyRecords: 1962-000727
A41: 1962-001141 | C41: Mineral Deed | D41: MIS47/164 | E41: 22906 | F41: 22906 | G41: W. L. Ayers and Hazel Ayers, HW | H41: Robert O. Lister, Jr. | I41: Lot 4, S/2 of Lot 3, S/2 NE/4 SW/4, SE/4 SW/4 of 31-12N-24W | J41: 75/115.34 interest, 75 NMA | K41: =HYPERLINK("https://okcountyrecords.com/detail/roger+mills/1962-001141","OKCountyRecords: 1962-001141") -> OKCountyRecords: 1962-001141
A42: 1962-001142 | C42: Warranty Deed | D42: MIS47/165 | E42: 22906 | F42: 22906 | G42: W. L. Ayers and Hazel Ayers, HW | H42: Robert O. Lister, Jr. | I42: E/2 NW/4, SE/4 NE/4, NE/4 SE/4, N/2 NE/4 SW/4, Lot 4, S/2 SW/4, SE/4 SW/4, Lot 4, S/2 of Lot 3, S/2 NE/4 SW/4, SE/4 SW/4 of 31-12N-24W, aol | J42: Surface only, To correct contract dated 1/24/1957 | K42: =HYPERLINK("https://okcountyrecords.com/detail/roger+mills/1962-001142","OKCountyRecords: 1962-001142") -> OKCountyRecords: 1962-001142
A43: 1962-001143 | C43: Oil and Gas Lease | D43: MIS47/166 | E43: 22906 | F43: 22906 | G43: Marie Lister, Robert O. Lister Jr. | H43: W. V. Lister | I43: All of 31-12N-24W aol | J43: Leasehold / WI | K43: =HYPERLINK("https://okcountyrecords.com/detail/roger+mills/1962-001143","OKCountyRecords: 1962-001143") -> OKCountyRecords: 1962-001143
A44: 1962-001144 | C44: Joint Tenancy Warranty Deed | D44: MIS47/168 | E44: 22906 | F44: 22906 | G44: Robert O. Lister, Jr. and Marie Lister, HW | H44: Marvin G. Mitchell and Carrie Lou Mitchell, HW, JTWROS | I44: E/2 NW/4, SE/4 NE/4, NE/4 SE/4, N/2 NE/4 SW/4, Lot 4, S/2 SW/4, SE/4 SW/4, Lot 4, S/2 of Lot 3, S/2 NE/4 SW/4, SE/4 SW/4 of 31-12N-24W, aol | J44: Surface only | K44: =HYPERLINK("https://okcountyrecords.com/detail/roger+mills/1962-001144","OKCountyRecords: 1962-001144") -> OKCountyRecords: 1962-001144
A45: 1962-001145 | C45: Mineral Deed | D45: MIS47/169 | E45: 22906 | F45: 22906 | G45: Robert O. Lister, Jr. and Marie Lister, HW | H45: Carrie Lou Mitchell | I45: Lot 4, S/2 of Lot 3, S/2 NE/4 SW/4, SE/4 SW/4 of 31-12N-24W | J45: 55/115.34 interest, 55 NMA | K45: =HYPERLINK("https://okcountyrecords.com/detail/roger+mills/1962-001145","OKCountyRecords: 1962-001145") -> OKCountyRecords: 1962-001145
A46: 1962-001196 | C46: Oil and Gas Lease | D46: MIS47/240 | E46: 22913 | F46: 22913 | G46: Eula Bain, W. M. Bain | H46: Jack Campbell | I46: All of 31-12N-24W | J46: Leasehold / WI | K46: =HYPERLINK("https://okcountyrecords.com/detail/roger+mills/1962-001196","OKCountyRecords: 1962-001196") -> OKCountyRecords: 1962-001196
A47: 1962-001271 | C47: Release | D47: MIS47/367 | E47: 22927 | F47: 22927 | G47: Commissioners of the Land Office | H47: Eula Bain, William C. Bain | I47: 31-12N-24W | J47: Leasehold / WI | K47: =HYPERLINK("https://okcountyrecords.com/detail/roger+mills/1962-001271","OKCountyRecords: 1962-001271") -> OKCountyRecords: 1962-001271
A48: 1962-001281 | C48: Assignment | D48: MIS47/377 | E48: 22928 | F48: 22928 | G48: Jack Campbell | H48: Midwest Oil Corporation | I48: 31-12N-24W | J48: Leasehold / WI | K48: =HYPERLINK("https://okcountyrecords.com/detail/roger+mills/1962-001281","OKCountyRecords: 1962-001281") -> OKCountyRecords: 1962-001281
A49: 1962-001389 | C49: Mineral Deed | D49: MIS47/558 | E49: 22938 | F49: 22938 | G49: Robert O. Lister, Jr. | H49: A. C. Campbell | I49: Lot 4, S/2 of Lot 3, S/2 NE/4 SW/4, SE/4 SW/4 of 31-12N-24W | J49: 10/115.34 interest, 10 NMA | K49: =HYPERLINK("https://okcountyrecords.com/detail/roger+mills/1962-001389","OKCountyRecords: 1962-001389") -> OKCountyRecords: 1962-001389
A50: 1962-001390 | C50: Mineral Deed | D50: MIS47/559 | E50: 22938 | F50: 22938 | G50: Robert O. Lister, Jr. | H50: J. W. Klopfenstein | I50: Lot 4, S/2 of Lot 3, S/2 NE/4 SW/4, SE/4 SW/4 of 31-12N-24W | J50: 10/115.34 interest, 10 NMA | K50: =HYPERLINK("https://okcountyrecords.com/detail/roger+mills/1962-001390","OKCountyRecords: 1962-001390") -> OKCountyRecords: 1962-001390
A51: 1965-000770 | C51: Release | D51: MIS62/462 | E51: 23890 | F51: 23890 | G51: Hazel Ayers, W. L. Ayers | H51: Carrie Lou Mitchell | I51: 31-12N-24W, aol | J51: Leasehold / WI | K51: =HYPERLINK("https://okcountyrecords.com/detail/roger+mills/1965-000770","OKCountyRecords: 1965-000770") -> OKCountyRecords: 1965-000770
A52: 1965-000771 | C52: Joint Tenancy Warranty Deed | D52: MIS62/464 | E52: 23890 | F52: 23890 | G52: Carrie Lou Mitchell, Marvin G. Mitchell | H52: Clara Mae Bryan, George M. Bryan | I52: E/2 NW/4, SE/4 NE/4, NE/4 SE/4, N/2 NE/4 SW/4, Lot 4, S/2 SW/4, SE/4 SW/4, Lot 4, S/2 of Lot 3, S/2 NE/4 SW/4, SE/4 SW/4 of 31-12N-24W, aol | J52: Surface only | K52: =HYPERLINK("https://okcountyrecords.com/detail/roger+mills/1965-000771","OKCountyRecords: 1965-000771") -> OKCountyRecords: 1965-000771
A53: 1967-000241 | C53: Order | D53: MIS78/112 | E53: 24502 | F53: 24502 | G53: Oklahoma County Court, RE: In the Matter of the Estate of Kenneth A. Ellison, Deceased | H53: Robert O. Lister, Jr. | I53: 31-12N-24W, aol | J53: Confirms Sale of 1/32 of 7/8 ORRI in Oil and Gas Leases | K53: =HYPERLINK("https://okcountyrecords.com/detail/roger+mills/1967-000241","OKCountyRecords: 1967-000241") -> OKCountyRecords: 1967-000241
A54: 1967-000351 | C54: Oil and Gas Lease | D54: MIS78/309 | E54: 24512 | F54: 24512 | G54: J. B. Campbell, Lillie A. Campbell | H54: J. R. Groves | I54: All of 31-12N-24W | J54: Leasehold / WI | K54: =HYPERLINK("https://okcountyrecords.com/detail/roger+mills/1967-000351","OKCountyRecords: 1967-000351") -> OKCountyRecords: 1967-000351
A55: 1968-003144 | C55: Rental Division Order | D55: MIS97/120 | E55: 25176 | F55: 25176 | G55: J. B. Campbell, Lillie A. Campbell | H55: J. R. Groves | I55: 31-12N-24W | J55: Leasehold / WI | K55: =HYPERLINK("https://okcountyrecords.com/detail/roger+mills/1968-003144","OKCountyRecords: 1968-003144") -> OKCountyRecords: 1968-003144
A56: 1968-003045 | C56: Assignment | D56: MIS97/20 | E56: 25176 | F56: 25176 | G56: J. R. Groves | H56: Tenneco Oil Company | I56: 31-12N-24W, aol | J56: Leasehold / WI | K56: =HYPERLINK("https://okcountyrecords.com/detail/roger+mills/1968-003045","OKCountyRecords: 1968-003045") -> OKCountyRecords: 1968-003045
A57: 1970-001176 | C57: Oil and Gas Lease | D57: 110/54 | E57: 25743 | F57: 25743 | G57: Crystal Henson, O. K. Henson Jr. | H57: Union Oil Company of California | I57: All of 31-12N-24W aol | J57: Leasehold / WI | K57: =HYPERLINK("https://okcountyrecords.com/detail/roger+mills/1970-001176","OKCountyRecords: 1970-001176") -> OKCountyRecords: 1970-001176
A58: 1970-001971 | C58: Oil and Gas Lease | D58: 112/464 | E58: 25829 | F58: 25829 | G58: Gladys Priest | H58: Ghk Corporation | I58: All of 31-12N-24W aol | J58: Leasehold / WI | K58: =HYPERLINK("https://okcountyrecords.com/detail/roger+mills/1970-001971","OKCountyRecords: 1970-001971") -> OKCountyRecords: 1970-001971
A59: 1970-001972 | C59: Oil and Gas Lease | D59: 112/466 | E59: 25829 | F59: 25829 | G59: Joseph Devanas, Mary Margaret Devanas | H59: Ghk Corporation | I59: All of 31-12N-24W aol | J59: Leasehold / WI | OCR variant? 'Devanas' cf. 'Devenas' | K59: =HYPERLINK("https://okcountyrecords.com/detail/roger+mills/1970-001972","OKCountyRecords: 1970-001972") -> OKCountyRecords: 1970-001972
A60: 1970-001973 | C60: Oil and Gas Lease | D60: 112/468 | E60: 25829 | F60: 25829 | G60: Margaret Gray, Murrell Gray | H60: Ghk Corporation | I60: All of 31-12N-24W aol | J60: Leasehold / WI | K60: =HYPERLINK("https://okcountyrecords.com/detail/roger+mills/1970-001973","OKCountyRecords: 1970-001973") -> OKCountyRecords: 1970-001973
A61: 1970-002603 | C61: Oil and Gas Lease | D61: 114/483 | E61: 25884 | F61: 25884 | G61: Capitola Yell Harmon, Fred Harmon | H61: Kerr McGee Corporation | I61: All of 31-12N-24W aol | J61: Leasehold / WI | K61: =HYPERLINK("https://okcountyrecords.com/detail/roger+mills/1970-002603","OKCountyRecords: 1970-002603") -> OKCountyRecords: 1970-002603
A62: 1970-002661 | C62: Assignment | D62: 114/553 | E62: 25885 | F62: 25885 | G62: W. V. Lister | H62: Gasanadarko, Ltd. | I62: 31-12N-24W, aol | J62: Leasehold / WI | K62: =HYPERLINK("https://okcountyrecords.com/detail/roger+mills/1970-002661","OKCountyRecords: 1970-002661") -> OKCountyRecords: 1970-002661
A63: 1970-002662 | C63: Assignment | D63: 114/554 | E63: 25885 | F63: 25885 | G63: W. V. Lister | H63: Gasanadarko, Ltd. | I63: 31-12N-24W, aol | J63: Leasehold / WI | K63: =HYPERLINK("https://okcountyrecords.com/detail/roger+mills/1970-002662","OKCountyRecords: 1970-002662") -> OKCountyRecords: 1970-002662
A64: 1970-002663 | C64: Assignment | D64: 114/555 | E64: 25885 | F64: 25885 | G64: W. V. Lister | H64: Gasanadarko, Ltd. | I64: 31-12N-24W, aol | J64: Leasehold / WI | K64: =HYPERLINK("https://okcountyrecords.com/detail/roger+mills/1970-002663","OKCountyRecords: 1970-002663") -> OKCountyRecords: 1970-002663
A65: 1970-002664 | C65: Assignment | D65: 114/556 | E65: 25885 | F65: 25885 | G65: Ghk Corporation | H65: Gasanadarko, Ltd. | I65: 31-12N-24W, aol | J65: Leasehold / WI | K65: =HYPERLINK("https://okcountyrecords.com/detail/roger+mills/1970-002664","OKCountyRecords: 1970-002664") -> OKCountyRecords: 1970-002664
A66: 1970-002665 | C66: Assignment | D66: 114/557 | E66: 25885 | F66: 25885 | G66: Ghk Corporation | H66: Gasanadarko, Ltd. | I66: 31-12N-24W, aol | J66: Leasehold / WI | K66: =HYPERLINK("https://okcountyrecords.com/detail/roger+mills/1970-002665","OKCountyRecords: 1970-002665") -> OKCountyRecords: 1970-002665
A67: 1970-002666 | C67: Assignment | D67: 114/558 | E67: 25885 | F67: 25885 | G67: Ghk Corporation | H67: Gasanadarko, Ltd. | I67: 31-12N-24W, aol | J67: Leasehold / WI | K67: =HYPERLINK("https://okcountyrecords.com/detail/roger+mills/1970-002666","OKCountyRecords: 1970-002666") -> OKCountyRecords: 1970-002666
A68: 1970-002991 | C68: Assignment | D68: 115/456 | E68: 25905 | F68: 25905 | G68: W. V. Lister | H68: Ghk Corporation | I68: 31-12N-24W, aol | J68: Leasehold / WI | K68: =HYPERLINK("https://okcountyrecords.com/detail/roger+mills/1970-002991","OKCountyRecords: 1970-002991") -> OKCountyRecords: 1970-002991
A69: 1970-002992 | C69: Assignment | D69: 115/457 | E69: 25905 | F69: 25905 | G69: Ghk Corporation | H69: Gasanadarko, Ltd. | I69: 31-12N-24W, aol | J69: Leasehold / WI | K69: =HYPERLINK("https://okcountyrecords.com/detail/roger+mills/1970-002992","OKCountyRecords: 1970-002992") -> OKCountyRecords: 1970-002992
A70: 1970-003015 | C70: Rental Division Order | D70: 115/485 | E70: 25905 | F70: 25905 | G70: Marie Lister, Robert O. Lister Jr. | H70: W. V. Lister | I70: 31-12N-24W | J70: Leasehold / WI | K70: =HYPERLINK("https://okcountyrecords.com/detail/roger+mills/1970-003015","OKCountyRecords: 1970-003015") -> OKCountyRecords: 1970-003015
A71: 1970-003106 | C71: Oil and Gas Lease | D71: 116/44 | E71: 25910 | F71: 25910 | G71: L. E. Thurman | H71: Ghk Corporation | I71: All of 31-12N-24W aol | J71: Leasehold / WI | K71: =HYPERLINK("https://okcountyrecords.com/detail/roger+mills/1970-003106","OKCountyRecords: 1970-003106") -> OKCountyRecords: 1970-003106
A72: 1970-003107 | C72: Assignment | D72: 116/47 | E72: 25910 | F72: 25910 | G72: Ghk Corporation | H72: Gasanadarko, Ltd. | I72: 31-12N-24W, aol | J72: Leasehold / WI | K72: =HYPERLINK("https://okcountyrecords.com/detail/roger+mills/1970-003107","OKCountyRecords: 1970-003107") -> OKCountyRecords: 1970-003107
A73: 1971-001694 | C73: Release | D73: 122/46 | E73: 26071 | F73: 26071 | G73: Gasanadarko, Ltd. | H73: Marie Lister, Robert O. Lister Jr. | I73: 31-12N-24W | J73: Leasehold / WI | K73: =HYPERLINK("https://okcountyrecords.com/detail/roger+mills/1971-001694","OKCountyRecords: 1971-001694") -> OKCountyRecords: 1971-001694
A74: 1971-002243 | C74: Oil and Gas Lease | D74: 123/448 | E74: 26130 | F74: 26130 | G74: Eula M. Bain, William C. Bain | H74: W. V. Lister | I74: All of 31-12N-24W | J74: Leasehold / WI | K74: =HYPERLINK("https://okcountyrecords.com/detail/roger+mills/1971-002243","OKCountyRecords: 1971-002243") -> OKCountyRecords: 1971-002243
A75: 1971-002244 | C75: Assignment | D75: 123/450 | E75: 26130 | F75: 26130 | G75: W. V. Lister | H75: Gasanadarko, Ltd. | I75: 31-12N-24W | J75: Leasehold / WI | K75: =HYPERLINK("https://okcountyrecords.com/detail/roger+mills/1971-002244","OKCountyRecords: 1971-002244") -> OKCountyRecords: 1971-002244
A76: 1971-002664 | C76: Oil and Gas Lease | D76: 125/7 | E76: 26158 | F76: 26158 | G76: A. C. Campbell, Fern Campbell, J. W. Klopfenstein, Ruby M. Klopfenstein | H76: Chalfant Magee & Hansen, Inc. | I76: All of 31-12N-24W | J76: Leasehold / WI | K76: =HYPERLINK("https://okcountyrecords.com/detail/roger+mills/1971-002664","OKCountyRecords: 1971-002664") -> OKCountyRecords: 1971-002664
A77: 1971-003272 | C77: Assignment | D77: 127/28 | E77: 26193 | F77: 26193 | G77: A. C. Campbell, Fern Campbell, J. W. Klopfenstein, Ruby M. Klopfenstein | H77: Chalfant Magee and Hansen, Inc. | I77: 31-12N-24W | J77: Leasehold / WI | K77: =HYPERLINK("https://okcountyrecords.com/detail/roger+mills/1971-003272","OKCountyRecords: 1971-003272") -> OKCountyRecords: 1971-003272
A78: 1971-003746 | C78: Assignment | D78: 128/290 | E78: 26231 | F78: 26231 | G78: Gasanadarko, Ltd. | H78: El Paso Natural Gas Co | I78: All of 31-12N-24W, aol | J78: Leasehold / WI | K78: =HYPERLINK("https://okcountyrecords.com/detail/roger+mills/1971-003746","OKCountyRecords: 1971-003746") -> OKCountyRecords: 1971-003746
A79: 1971-004499 | C79: Assignment | D79: 130/483 | E79: 26287 | F79: 26287 | G79: Gasanadarko, Ltd. | H79: El Paso Natural Gas Co | I79: 31-12N-24W, aol | J79: Leasehold / WI | K79: =HYPERLINK("https://okcountyrecords.com/detail/roger+mills/1971-004499","OKCountyRecords: 1971-004499") -> OKCountyRecords: 1971-004499
A80: 1972-002543 | C80: Oil and Gas Lease | D80: 139/36 | E80: 26500 | F80: 26500 | G80: Gena (minor) Williams, Gene G. Guardian Williams, Marvin Mitchell (minor) Williams | H80: Chalfant Magee & Hansen, Inc. | I80: All of 31-12N-24W aol | J80: Leasehold / WI | K80: =HYPERLINK("https://okcountyrecords.com/detail/roger+mills/1972-002543","OKCountyRecords: 1972-002543") -> OKCountyRecords: 1972-002543
A81: 1972-002544 | C81: Assignment | D81: 139/38 | E81: 26500 | F81: 26500 | G81: Gena Williams, Gene C. Guard Williams, Marvin Mitchell Williams | H81: Chalfant Magee & Hansen, Inc. | I81: 31-12N-24W, aol | J81: Leasehold / WI | K81: =HYPERLINK("https://okcountyrecords.com/detail/roger+mills/1972-002544","OKCountyRecords: 1972-002544") -> OKCountyRecords: 1972-002544
A82: 1972-002545 | C82: Order Confirming Sale of Oil and Gas Leases | D82: 139/39 | E82: 26500 | F82: 26500 | G82: Kiowa County Court, RE: In the Matter of the Guardianship of the Estates of Marvin Mitchell Williams and Gena Williams, Minors | H82: Gene G. Williams | I82: E/2 NW/4, SE/4 NE/4, NE/4 SE/4, N/2 NE/4 SW/4, Lot 4, S/2 SW/4, SE/4 SW/4, S/2 of Lot 3, S/2 NE/4 SW/4, SE/4 SW/4 of 31-12N-24W, aol | J82: Confirms Sale of Oil and Gas Leases | K82: =HYPERLINK("https://okcountyrecords.com/detail/roger+mills/1972-002545","OKCountyRecords: 1972-002545") -> OKCountyRecords: 1972-002545
A83: 1972-002561 | C83: Oil and Gas Lease | D83: 139/70 | E83: 26500 | F83: 26500 | G83: Carrie Leeann (minor) Mitchell, John L. Guardian Mitchell, Nancy Susan (minor) Mitchell | H83: Chalfant Magee & Hansen, Inc. | I83: All of 31-12N-24W aol | J83: Leasehold / WI | K83: =HYPERLINK("https://okcountyrecords.com/detail/roger+mills/1972-002561","OKCountyRecords: 1972-002561") -> OKCountyRecords: 1972-002561
A84: 1972-002562 | C84: Order Confirming Sale of Oil and Gas Leases | D84: 139/72 | E84: 26500 | F84: 26500 | G84: Kiowa County Court, RE: In the Matter of the Guardianship of the Estates of Nancy Susan Mitchell and Carrie Lee Ann Mitchell, Minors | H84: John L. Mitchell | I84: E/2 NW/4, SE/4 NE/4, NE/4 SE/4, N/2 NE/4 SW/4, Lot 4, S/2 SW/4, SE/4 SW/4, S/2 of Lot 3, S/2 NE/4 SW/4, SE/4 SW/4 of 31-12N-24W, aol | J84: Confirms Sale of Oil and Gas Leases | K84: =HYPERLINK("https://okcountyrecords.com/detail/roger+mills/1972-002562","OKCountyRecords: 1972-002562") -> OKCountyRecords: 1972-002562
A85: 1972-002563 | C85: Assignment | D85: 139/73 | E85: 26500 | F85: 26500 | G85: Carrie Leeann Mitchell, John J. Guard Mitchell, Nancy Susqn Mitchell | H85: Chalfant Magee & Hansen, Inc. | I85: 31-12N-24W, aol | J85: Leasehold / WI | K85: =HYPERLINK("https://okcountyrecords.com/detail/roger+mills/1972-002563","OKCountyRecords: 1972-002563") -> OKCountyRecords: 1972-002563
A86: 1973-001367 | C86: Oil and Gas Lease | D86: 149/559 | E86: 26791 | F86: 26791 | G86: Oleta Florene Flanagan, Oleta Florene Wylie | H86: El Paso Natural Gas Company | I86: All of 31-12N-24W | J86: Leasehold / WI | K86: =HYPERLINK("https://okcountyrecords.com/detail/roger+mills/1973-001367","OKCountyRecords: 1973-001367") -> OKCountyRecords: 1973-001367
A87: 1973-002502 | C87: Oil and Gas Lease | D87: 153/344 | E87: 26882 | F87: 26882 | G87: Glen D. Mitchel, Hazel P. Mitchel | H87: El Paso Natural Gas Company | I87: All of 31-12N-24W | J87: Leasehold / WI | OCR variant? 'Mitchel' cf. 'Mitchell' | K87: =HYPERLINK("https://okcountyrecords.com/detail/roger+mills/1973-002502","OKCountyRecords: 1973-002502") -> OKCountyRecords: 1973-002502
A88: 1974-000130 | C88: Oil and Gas Lease | D88: 159/1 | E88: 27036 | F88: 27036 | G88: Annie E. Mitchel | H88: El Paso Natural Gas Company | I88: All of 31-12N-24W aol | J88: Leasehold / WI | OCR variant? 'Mitchel' cf. 'Mitchell' | K88: =HYPERLINK("https://okcountyrecords.com/detail/roger+mills/1974-000130","OKCountyRecords: 1974-000130") -> OKCountyRecords: 1974-000130
A89: 1974-001152 | C89: Joint Tenancy Warranty Deed | D89: 162/162 | E89: 27121 | F89: 27121 | G89: J. B. Campbell and Lillie A. Campbell, a/k/a Lillie Hambrook, a/k/a Lillie A. Hambrook, HW | H89: Elmo W. Kirk and Freeda Kirk, HW, JT | I89: Beginning at the NW Corner of the NW/4 of 31-12N-24W, thence East on Section line 18.20 chains (or 72 8/10 rods) thence South 50 chains (or 200 rods) thence West 18.20 chains (or 72 8/10 rods) to Range line between Ranges 24 and 25, thence North on Range line 50 chains (or 200 rods) to point of beginning, containing 91 acres, more or less, according to the Government Survey thereof, | J89: Surface only, EXCEPTING and reserving unto Lillie Campbell, her heirs, executors, administrators and assigns all interest in the oil, gas and other minerals in and under and that may be produced from said land with rights of ingress and egress. | K89: =HYPERLINK("https://okcountyrecords.com/detail/roger+mills/1974-001152","OKCountyRecords: 1974-001152") -> OKCountyRecords: 1974-001152
A90: 1974-001419 | C90: Oil and Gas Lease | D90: 163/132 | E90: 27148 | F90: 27148 | G90: R. O. Wilkin | H90: Exxon Corporation | I90: All of 31-12N-24W aol | J90: Leasehold / WI | K90: =HYPERLINK("https://okcountyrecords.com/detail/roger+mills/1974-001419","OKCountyRecords: 1974-001419") -> OKCountyRecords: 1974-001419
A91: 1974-001639 | C91: Mineral Deed | D91: 163/565 | E91: 27163 | F91: 27163 | G91: L. E. Thurman and Veronica Thurman, HW | H91: Marie Lister | I91: E/2 NW/4, SE/4 NE/4, NE/4 SE/4, N/2 NE/4 SW/4 of 31-12N-24W, aol | J91: 60/260 interest in 2 sections | K91: =HYPERLINK("https://okcountyrecords.com/detail/roger+mills/1974-001639","OKCountyRecords: 1974-001639") -> OKCountyRecords: 1974-001639
A92: 1974-001700 | C92: Mineral Deed | D92: 164/66 | E92: 27171 | F92: 27171 | G92: Marie Lister | H92: W. H. Sorenson | I92: E/2 NW/4, SE/4 NE/4, NE/4 SE/4, N/2 NE/4 SW/4 of 31-12N-24W, aol | J92: 40/260 interest in 2 sections | K92: =HYPERLINK("https://okcountyrecords.com/detail/roger+mills/1974-001700","OKCountyRecords: 1974-001700") -> OKCountyRecords: 1974-001700
A93: 1974-002044 | C93: Mineral Deed | D93: 165/87 | E93: 27207 | F93: 27207 | G93: Marie Lister | H93: Mann Childrens Trust | I93: E/2 NW/4, SE/4 NE/4, NE/4 SE/4, N/2 NE/4 SW/4 of 31-12N-24W, aol | J93: 10/260 interest in 2 sections | K93: =HYPERLINK("https://okcountyrecords.com/detail/roger+mills/1974-002044","OKCountyRecords: 1974-002044") -> OKCountyRecords: 1974-002044
A94: 1975-000869 | C94: Mineral Deed | D94: 176/144 | E94: 27481 | F94: 27481 | G94: Marie Lister | H94: J. E. Barnett | I94: E/2 NW/4, SE/4 NE/4, NE/4 SE/4, N/2 NE/4 SW/4 of 31-12N-24W, aol | J94: 10/260 interest in 2 sections | K94: =HYPERLINK("https://okcountyrecords.com/detail/roger+mills/1975-000869","OKCountyRecords: 1975-000869") -> OKCountyRecords: 1975-000869
A95: 1976-001369 | C95: Oil and Gas Lease | D95: 190/249 | E95: 27862 | F95: 27862 | G95: Flag Redfern Oil Company | H95: Apexco, Inc. | I95: All of 31-12N-24W | J95: Leasehold / WI | K95: =HYPERLINK("https://okcountyrecords.com/detail/roger+mills/1976-001369","OKCountyRecords: 1976-001369") -> OKCountyRecords: 1976-001369
A96: 1977-000812 | C96: Assignment | D96: 206/38 | E96: 27962 | F96: 28167 | G96: Apexco, Inc. | H96: El Paso Natural Gas Co | I96: W/2 NW/4 Lots 1-2 of 31-12N-24W, aol | J96: Leasehold / WI | K96: =HYPERLINK("https://okcountyrecords.com/detail/roger+mills/1977-000812","OKCountyRecords: 1977-000812") -> OKCountyRecords: 1977-000812
A97: 1976-003640 | C97: Assignment | D97: 198/182 | E97: 27964 | F97: 28026 | G97: Apexco, Inc. | H97: Entex Petroleum, Inc. | I97: W/2 NW/4 Lots 1-2 of 31-12N-24W, aol | J97: Leasehold / WI | K97: =HYPERLINK("https://okcountyrecords.com/detail/roger+mills/1976-003640","OKCountyRecords: 1976-003640") -> OKCountyRecords: 1976-003640
A98: 1980-004634 | C98: Assignment | D98: 298/320 | E98: 27964 | F98: 29388 | G98: Apexco, Inc. | H98: Bovaird Supply Co | I98: W/2 NW/4 Lots 1-2 of 31-12N-24W, aol | J98: Leasehold / WI | K98: =HYPERLINK("https://okcountyrecords.com/detail/roger+mills/1980-004634","OKCountyRecords: 1980-004634") -> OKCountyRecords: 1980-004634
A99: 1976-003251 | C99: Warranty Deed | D99: 197/116 | E99: 28005 | F99: 28005 | G99: Elmo W. Kirk and Freeda Kirk, HW | H99: Margie Kirk | I99: The South 51 acres in the following tract of land, to-wit: a tract of land in 31-12N-24W described as follows: Beginning at the NW Corner of the NW/4 of said Section 31, thence East on Section line 18.20 chains (or 72 8/10 rods) thence South 50 chains (or 200 rods) thence West 18.20 chains (or 72 8/10 rods) to Range line between Ranges 24 and 25, thence North on Range line 50 chains (or 200 rods) to point of beginning, containing 91 acres, more or less, according to the Government Survey thereof | J99: ARTI | K99: =HYPERLINK("https://okcountyrecords.com/detail/roger+mills/1976-003251","OKCountyRecords: 1976-003251") -> OKCountyRecords: 1976-003251
A100: 1977-000821 | C100: Oil and Gas Lease | D100: 206/58 | E100: 28167 | F100: 28167 | G100: Albert Fields Beaty, Lila Muriel Beaty | H100: Cities Service Company | I100: All of 31-12N-24W aol | J100: Leasehold / WI | K100: =HYPERLINK("https://okcountyrecords.com/detail/roger+mills/1977-000821","OKCountyRecords: 1977-000821") -> OKCountyRecords: 1977-000821
...

Sheet Tract 1
E1: Instrument | H1: Patent | I1: Deed | J1: Mineral Deed | K1: Mineral Deed | L1: Warranty Deed | M1: Mineral Deed | N1: Mineral Deed | O1: Quit Claim Deed | P1: Mineral Deed | Q1: Mineral Deed | R1: Decree | S1: Mineral Deed | T1: Warranty Deed | U1: Final Decree | V1: Mineral Deed | W1: Mineral Deed | X1: Mineral Deed | Y1: Final Decree | Z1: Quit Claim Deed | AA1: Joint Tenancy Warranty Deed | AB1: Trustees Mineral Deed | AC1: Trustees Mineral Deed | AD1: Trustees Mineral Deed | AE1: Final Decree | AF1: Mineral Deed | AG1: Mineral Deed | AH1: Quit Claim Mineral Deed | AI1: Mineral Deed | AJ1: Quit Claim Mineral Deed | AK1: Mineral Deed
A2: 1 | B2: TRACT | D2: N/2 NE/4, containing 80 acres | E2: Image Number | H2: 1930-002914 | I2: 1988-004185 | J2: 1994-006415 | K2: 1995-003404 | L2: 1996-002352 | M2: 2000-007685 | N2: 2001-000957 | O2: 2001-001092 | P2: 2001-001414 | Q2: 2001-001463 | R2: 2001-002342 | S2: 2002-004595 | T2: 2003-004945 | U2: 2004-000099 | V2: 2004-005901 | W2: 2005-000158 | X2: 2005-007551 | Y2: 2005-008386 | Z2: 2007-001848 | AA2: 2008-003157 | AB2: 2011-001007 | AC2: 2011-001008 | AD2: 2011-001009 | AE2: 2013-000518 | AF2: 2014-003089 | AG2: 2014-006293 | AH2: 2016-001882 | AJ2: 2018-002650 | AK2: 2021-001068
B3: DESCRIPTION | E3: Book / Page | H3: PAT010/234 | I3: 0981/0002 | J3: 1422/0009 | K3: 1457/0173 | L3: 1510/0491 | M3: 1611/0503 | N3: 1637/0026 | O3: 1637/0476 | P3: 1639/0206 | Q3: 1639/0426 | R3: 1643/0389 | S3: 1695/0238 | T3: 1724/0582 | U3: 1734/0014 | V3: 1765/0306 | W3: 1774/0309 | X3: 1812/0138 | Y3: 1816/0041 | Z3: 1872/0277 | AA3: 1914/0155 | AB3: 2063/0491 | AC3: 2063/0494 | AD3: 2063/0497 | AE3: 2177/0033 | AF3: 2251/0529 | AG3: 2273/0223 | AH3: 2342/0219 | AI3: 2376/0100 | AJ3: 2406/0228 | AK3: 2467/0476
E4: Date | H4: 11021 | I4: 32329 | J4: 34542 | K4: 34754 | L4: 35429 | M4: 36647 | N4: 36957 | O4: 36969 | P4: 36987 | Q4: 36991 | R4: 37034 | S4: 37592 | T4: 37897 | U4: 37994 | V4: 38281 | W4: 38365 | X4: 38658 | Y4: 38695 | Z4: 39197 | AA4: 39612 | AB4: 40592 | AC4: 40592 | AD4: 40592 | AE4: 41304 | AF4: 41774 | AG4: 41927 | AH4: 42593 | AI4: 42996 | AJ4: 43382 | AK4: 44377
B5: TRACT ACRES | D5: 80 | E5: Conveyance | H5: ARTI | I5: ARTI | J5: ARTI | K5: ARTI | L5: ARTI | M5: ARTI | N5: ARTI | O5: ARTI | P5: ARTI | Q5: ARTI | R5: ARTI | S5: ARTI | T5: ARTI | U5: ARTI | V5: ARTI | W5: ARTI | X5: ARTI | Y5: ARTI | Z5: ARTI | AA5: ARTI | AB5: ARTI | AC5: ARTI | AD5: ARTI | AE5: ARTI | AF5: ARTI | AG5: ARTI | AH5: ARTI | AI5: ARTI | AJ5: ARTI | AK5: ARTI
B6: BASE OGL | C6: 80 | D6: Tract 1 | E6: =SUBTOTAL(9,E9:E205) -> 0 | F6: SURFACE | H6: =IF(H7=0,"","RECHECK") | I6: =IF(I7=0,"","RECHECK") | J6: =IF(J7=0,"","RECHECK") | L6: =IF(L7=0,"","RECHECK") | M6: =IF(M7=0,"","RECHECK") | N6: =IF(N7=0,"","RECHECK") | O6: =IF(O7=0,"","RECHECK") | P6: =IF(P7=0,"","RECHECK") | Q6: =IF(Q7=0,"","RECHECK") | R6: =IF(R7=0,"","RECHECK") | S6: =IF(S7=0,"","RECHECK") | ... AF6: =IF(AF7=0,"","RECHECK") | AJ6: =IF(AJ7=0,"","RECHECK") | AK6: =IF(AK7=0,"","RECHECK") | AL6: =IF(AL7=0,"","RECHECK") | AM6: =IF(AM7=0,"","RECHECK") | AP6: =IF(AP7=0,"","RECHECK") | AQ6: =IF(AQ7=0,"","RECHECK") | AR6: =IF(AR7=0,"","RECHECK") | AS6: =IF(AS7=0,"","RECHECK") | AT6: =IF(AT7=0,"","RECHECK") | AU6: =IF(AU7=0,"","RECHECK") | AV6: =IF(AV7=0,"","RECHECK") | AW6: =IF(AW7=0,"","RECHECK") | ... FX6: =IF(FX7=0,"","RECHECK")
G7: =SUBTOTAL(9,G10:G206) -> 0 | H7: =SUBTOTAL(9,H10:H206) -> 0 | I7: =SUBTOTAL(9,I10:I206) -> 0 | J7: =SUBTOTAL(9,J10:J206) -> 0 | K7: =SUBTOTAL(9,K10:K206) -> 0 | L7: =SUBTOTAL(9,L10:L206) -> 0 | M7: =SUBTOTAL(9,M10:M206) -> 0 | N7: =SUBTOTAL(9,N10:N206) -> 0 | ... AJ7: =SUBTOTAL(9,AJ10:AJ206) -> 0 | AK7: 0 | AL7: =SUBTOTAL(9,AL10:AL206) -> 0 | AM7: =SUBTOTAL(9,AM10:AM206) -> 0 | AN7: =SUBTOTAL(9,AN10:AN201) -> 0 | AO7: =SUBTOTAL(9,AO10:AO195) -> 0 | AP7: =SUBTOTAL(9,AP10:AP195) -> 0 | AQ7: =SUBTOTAL(9,AQ10:AQ195) -> 0 | AR7: =SUBTOTAL(9,AR10:AR195) -> 0 | AS7: =SUBTOTAL(9,AS10:AS206) -> 0 | AT7: =SUBTOTAL(9,AT10:AT206) -> 0 | AU7: =SUBTOTAL(9,AU10:AU206) -> 0 | AV7: =SUBTOTAL(9,AV10:AV202) -> 0 | AW7: =SUBTOTAL(9,AW10:AW206) -> 0 | AX7: =SUBTOTAL(9,AX10:AX206) -> 0 | AY7: =SUBTOTAL(9,AY10:AY206) -> 0 | AZ7: =SUBTOTAL(9,AZ10:AZ206) -> 0 | BA7: =SUBTOTAL(9,BA10:BA206) -> 0 | BB7: =SUBTOTAL(9,BB10:BB206) -> 0 | BC7: =SUBTOTAL(9,BC10:BC206) -> 0 | BD7: =SUBTOTAL(9,BD10:BD206) -> 0 | ... FX7: =SUBTOTAL(9,FX10:FX206) -> 0
A8: NOTES | C8: NET ACRES | D8: OWNERS | E8: TOTAL
C10: =IFERROR(IF($E10>0,$E10/SUMIF($E$10:$E$75,">0")*$D$5,""),"") | D10: United States of America | E10: =SUM(G10:HQ10) -> -1 | H10: -1
C11: =IFERROR(IF($E11>0,$E11/SUMIF($E$10:$E$75,">0")*$D$5,""),"") -> 4.7058824 | D11: Roy A. Garrison | E11: =SUM(G11:HQ11) -> 1 | H11: 1
C12: =IFERROR(IF($E12>0,$E12/SUMIF($E$10:$E$75,">0")*$D$5,""),"") | D12: Flag-redfern Oil Company | E12: =SUM(G12:HQ12) -> 0
C13: =IFERROR(IF($E13>0,$E13/SUMIF($E$10:$E$75,">0")*$D$5,""),"") | D13: Eta-flag Royalty Trust | E13: =SUM(G13:HQ13) -> -1 | J13: -1
C14: =IFERROR(IF($E14>0,$E14/SUMIF($E$10:$E$75,">0")*$D$5,""),"") -> 4.7058824 | D14: First City National Bank of Midland Trustee | E14: =SUM(G14:HQ14) -> 1 | J14: 1
C15: =IFERROR(IF($E15>0,$E15/SUMIF($E$10:$E$75,">0")*$D$5,""),"") | D15: Hayhurst Oil Properties, Inc. | E15: =SUM(G15:HQ15) -> -1 | J15: -1
C16: =IFERROR(IF($E16>0,$E16/SUMIF($E$10:$E$75,">0")*$D$5,""),"") -> 4.7058824 | D16: Nam Corporation | E16: =SUM(G16:HQ16) -> 1 | J16: 1
C17: =IFERROR(IF($E17>0,$E17/SUMIF($E$10:$E$75,">0")*$D$5,""),"") | D17: Tripco, Inc. | E17: =SUM(G17:HQ17) -> -2 | K17: -1 | X17: -1
C18: =IFERROR(IF($E18>0,$E18/SUMIF($E$10:$E$75,">0")*$D$5,""),"") -> 4.7058824 | D18: Prudential Securities | E18: =SUM(G18:HQ18) -> 1 | K18: 1
C19: =IFERROR(IF($E19>0,$E19/SUMIF($E$10:$E$75,">0")*$D$5,""),"") | D19: Eula Cross | E19: =SUM(G19:HQ19) -> 0
C20: =IFERROR(IF($E20>0,$E20/SUMIF($E$10:$E$75,">0")*$D$5,""),"") | D20: Floyd W. Atha | E20: =SUM(G20:HQ20) -> 0
C21: =IFERROR(IF($E21>0,$E21/SUMIF($E$10:$E$75,">0")*$D$5,""),"") | D21: Nancy D. Atha | E21: =SUM(G21:HQ21) -> 0
C22: =IFERROR(IF($E22>0,$E22/SUMIF($E$10:$E$75,">0")*$D$5,""),"") | D22: Fer-scher Exploration, LLC | E22: =SUM(G22:HQ22) -> -1 | M22: -1
C23: =IFERROR(IF($E23>0,$E23/SUMIF($E$10:$E$75,">0")*$D$5,""),"") -> 4.7058824 | D23: Aspen Minerals Group | E23: =SUM(G23:HQ23) -> 1 | M23: 1
C24: =IFERROR(IF($E24>0,$E24/SUMIF($E$10:$E$75,">0")*$D$5,""),"") | D24: Nanalee Faye Barnett | E24: =SUM(G24:HQ24) -> -1 | N24: -1
C25: =IFERROR(IF($E25>0,$E25/SUMIF($E$10:$E$75,">0")*$D$5,""),"") -> 14.117647 | D25: Arrowhead Resources, Inc. | E25: =SUM(G25:HQ25) -> 3 | N25: 1 | P25: 1 | Q25: 1
C26: =IFERROR(IF($E26>0,$E26/SUMIF($E$10:$E$75,">0")*$D$5,""),"") | D26: Laurence L. Crouse, Trustee | E26: =SUM(G26:HQ26) -> -1 | O26: -1
C27: =IFERROR(IF($E27>0,$E27/SUMIF($E$10:$E$75,">0")*$D$5,""),"") -> 4.7058824 | D27: Crouse Family Limited Partnerhsip | E27: =SUM(G27:HQ27) -> 1 | O27: 1
C28: =IFERROR(IF($E28>0,$E28/SUMIF($E$10:$E$75,">0")*$D$5,""),"") | D28: Louise Ormand | E28: =SUM(G28:HQ28) -> -1 | P28: -1
C29: =IFERROR(IF($E29>0,$E29/SUMIF($E$10:$E$75,">0")*$D$5,""),"") | D29: Glenn D. Mitchel | E29: =SUM(G29:HQ29) -> -1 | Q29: -1
C30: =IFERROR(IF($E30>0,$E30/SUMIF($E$10:$E$75,">0")*$D$5,""),"") | D30: Jack E. Barnett, Deceased | E30: =SUM(G30:HQ30) -> -1 | R30: -1
C31: =IFERROR(IF($E31>0,$E31/SUMIF($E$10:$E$75,">0")*$D$5,""),"") -> 14.117647 | D31: The Public | E31: =SUM(G31:HQ31) -> 3 | R31: 1 | U31: 1 | Y31: 1
C32: =IFERROR(IF($E32>0,$E32/SUMIF($E$10:$E$75,">0")*$D$5,""),"") | D32: Hayhurst, Peggy J. Revoc Trust | E32: =SUM(G32:HQ32) -> 0
C33: =IFERROR(IF($E33>0,$E33/SUMIF($E$10:$E$75,">0")*$D$5,""),"") | D33: Peggy J. | E33: =SUM(G33:HQ33) -> 0
C34: =IFERROR(IF($E34>0,$E34/SUMIF($E$10:$E$75,">0")*$D$5,""),"") | D34: Bluebonnet Investments, Ltd. | E34: =SUM(G34:HQ34) -> -1 | T34: -1
C35: =IFERROR(IF($E35>0,$E35/SUMIF($E$10:$E$75,">0")*$D$5,""),"") -> 4.7058824 | D35: White Birch, LP | E35: =SUM(G35:HQ35) -> 1 | T35: 1
C36: =IFERROR(IF($E36>0,$E36/SUMIF($E$10:$E$75,">0")*$D$5,""),"") | D36: Evelyn Louise McLerran, Deceased | E36: =SUM(G36:HQ36) -> -1 | U36: -1
C37: =IFERROR(IF($E37>0,$E37/SUMIF($E$10:$E$75,">0")*$D$5,""),"") | D37: Aspen Energy Group, Inc. | E37: =SUM(G37:HQ37) -> -1 | V37: -1
C38: =IFERROR(IF($E38>0,$E38/SUMIF($E$10:$E$75,">0")*$D$5,""),"") -> 4.7058824 | D38: Crusader Energy Corporation | E38: =SUM(G38:HQ38) -> 1 | V38: 1
C39: =IFERROR(IF($E39>0,$E39/SUMIF($E$10:$E$75,">0")*$D$5,""),"") | D39: Minion Investment Co | E39: =SUM(G39:HQ39) -> 0
C40: =IFERROR(IF($E40>0,$E40/SUMIF($E$10:$E$75,">0")*$D$5,""),"") | D40: Brian L. Rice | E40: =SUM(G40:HQ40) -> 0
C41: =IFERROR(IF($E41>0,$E41/SUMIF($E$10:$E$75,">0")*$D$5,""),"") -> 4.7058824 | D41: Prism Energy, Inc. | E41: =SUM(G41:HQ41) -> 1 | X41: 1
C42: =IFERROR(IF($E42>0,$E42/SUMIF($E$10:$E$75,">0")*$D$5,""),"") | D42: Louis E. Jaques, Deceased | E42: =SUM(G42:HQ42) -> -1 | Y42: -1
C43: =IFERROR(IF($E43>0,$E43/SUMIF($E$10:$E$75,">0")*$D$5,""),"") | D43: Atha Nancy D. | E43: =SUM(G43:HQ43) -> 0
C44: =IFERROR(IF($E44>0,$E44/SUMIF($E$10:$E$75,">0")*$D$5,""),"") | D44: Atha Floyd Revoc Trust | E44: =SUM(G44:HQ44) -> 0
C45: =IFERROR(IF($E45>0,$E45/SUMIF($E$10:$E$75,">0")*$D$5,""),"") | D45: Floyd Atha, Trustee | E45: =SUM(G45:HQ45) -> 0
C46: =IFERROR(IF($E46>0,$E46/SUMIF($E$10:$E$75,">0")*$D$5,""),"") | D46: Floyd Co Atha, Trustee | E46: =SUM(G46:HQ46) -> 0
C47: =IFERROR(IF($E47>0,$E47/SUMIF($E$10:$E$75,">0")*$D$5,""),"") | D47: Nancy Co Atha, Trustee | E47: =SUM(G47:HQ47) -> 0
C48: =IFERROR(IF($E48>0,$E48/SUMIF($E$10:$E$75,">0")*$D$5,""),"") | D48: Danielle Delane Tucker | E48: =SUM(G48:HQ48) -> 0
C49: =IFERROR(IF($E49>0,$E49/SUMIF($E$10:$E$75,">0")*$D$5,""),"") | D49: Monte Earl Tucker | E49: =SUM(G49:HQ49) -> 0
C50: =IFERROR(IF($E50>0,$E50/SUMIF($E$10:$E$75,">0")*$D$5,""),"") | D50: Glenda Palmer | E50: =SUM(G50:HQ50) -> 0
C51: =IFERROR(IF($E51>0,$E51/SUMIF($E$10:$E$75,">0")*$D$5,""),"") | D51: Richard Palmer | E51: =SUM(G51:HQ51) -> 0
C52: =IFERROR(IF($E52>0,$E52/SUMIF($E$10:$E$75,">0")*$D$5,""),"") | D52: Palmer Family Trust | E52: =SUM(G52:HQ52) -> 0
C53: =IFERROR(IF($E53>0,$E53/SUMIF($E$10:$E$75,">0")*$D$5,""),"") | D53: Glenda Ann Palmer | E53: =SUM(G53:HQ53) -> 0
C54: =IFERROR(IF($E54>0,$E54/SUMIF($E$10:$E$75,">0")*$D$5,""),"") | D54: Mitchel, Glenn Douglas and Hazel Pearl Trust | E54: =SUM(G54:HQ54) -> 0
C55: =IFERROR(IF($E55>0,$E55/SUMIF($E$10:$E$75,">0")*$D$5,""),"") | D55: Mitchel, Jack D. and Shonna A. Family Trust | E55: =SUM(G55:HQ55) -> 0
C56: =IFERROR(IF($E56>0,$E56/SUMIF($E$10:$E$75,">0")*$D$5,""),"") | D56: Shonna Mitchel | E56: =SUM(G56:HD56) -> 0
C57: =IFERROR(IF($E57>0,$E57/SUMIF($E$10:$E$75,">0")*$D$5,""),"") | D57: Shonna A. Mitchel | E57: =SUM(G57:HD57) -> 0
C58: =IFERROR(IF($E58>0,$E58/SUMIF($E$10:$E$75,">0")*$D$5,""),"") | D58: Shonn | E58: =SUM(G58:HD58) -> 0
C59: =IFERROR(IF($E59>0,$E59/SUMIF($E$10:$E$75,">0")*$D$5,""),"") | D59: Gene G. Williams | E59: =SUM(G59:HD59) -> 0
C60: =IFERROR(IF($E60>0,$E60/SUMIF($E$10:$E$75,">0")*$D$5,""),"") | D60: Nancy Mitchell Dcd Williams | E60: =SUM(G60:HD60) -> 0
C61: =IFERROR(IF($E61>0,$E61/SUMIF($E$10:$E$75,">0")*$D$5,""),"") | D61: Luther Ervin Thurman | E61: =SUM(G61:HQ61) -> 0
C62: =IFERROR(IF($E62>0,$E62/SUMIF($E$10:$E$75,">0")*$D$5,""),"") | D62: Veronica Gentry Th | E62: =SUM(G62:HQ62) -> 0
C63: =IFERROR(IF($E63>0,$E63/SUMIF($E$10:$E$75,">0")*$D$5,""),"") | D63: Thurman, Luther and Veronica Liv Trust | E63: =SUM(G63:HQ63) -> 0
C64: =IFERROR(IF($E64>0,$E64/SUMIF($E$10:$E$75,">0")*$D$5,""),"") | D64: Etta Britton | E64: =SUM(G64:HH64) -> 0
C65: =IFERROR(IF($E65>0,$E65/SUMIF($E$10:$E$75,">0")*$D$5,""),"") | D65: Joe H. Britton | E65: =SUM(G65:HQ65) -> 0
C66: =IFERROR(IF($E66>0,$E66/SUMIF($E$10:$E$75,">0")*$D$5,""),"") | D66: Linda C. Browning | E66: =SUM(G66:HQ66) -> 0
C67: =IFERROR(IF($E67>0,$E67/SUMIF($E$10:$E$75,">0")*$D$5,""),"") | D67: Devon Energy Production Co | E67: =SUM(G67:HQ67) -> -1 | AH67: -1
C68: =IFERROR(IF($E68>0,$E68/SUMIF($E$10:$E$75,">0")*$D$5,""),"") -> 4.7058824 | D68: Tecolote Holdings | E68: =SUM(G68:HQ68) -> 1 | AH68: 1
C69: =IFERROR(IF($E69>0,$E69/SUMIF($E$10:$E$75,">0")*$D$5,""),"") | D69: Jon N. Wilkerson | E69: =SUM(G69:HQ69) -> -1 | AI69: -1
C70: =IFERROR(IF($E70>0,$E70/SUMIF($E$10:$E$75,">0")*$D$5,""),"") -> 4.7058824 | D70: Tamara K. Wilkerson | E70: =SUM(G70:HQ70) -> 1 | AI70: 1
C71: =IFERROR(IF($E71>0,$E71/SUMIF($E$10:$E$75,">0")*$D$5,""),"") | D71: Cindy Lou Vignal, Trustee | E71: =SUM(G71:HQ71) -> 0
C72: =IFERROR(IF($E72>0,$E72/SUMIF($E$10:$E$75,">0")*$D$5,""),"") | D72: Vignal, Gary | E72: =SUM(G72:HQ72) -> 0
C73: =IFERROR(IF($E73>0,$E73/SUMIF($E$10:$E$75,">0")*$D$5,""),"") | D73: Grizzly Operating, LLC | E73: =SUM(G73:HQ73) -> 0
C74: =IFERROR(IF($E74>0,$E74/SUMIF($E$10:$E$75,">0")*$D$5,""),"") | D74: Vanguard Operating, LLC | E74: =SUM(G74:HQ74) -> 0
C75: =IFERROR(IF($E75>0,$E75/SUMIF($E$10:$E$75,">0")*$D$5,""),"") | D75: Psi Lke, LLC | E75: =SUM(G75:HQ75) -> 0
C76: =E76*D$5 -> 0 | E76: =SUM(G76:HQ76) -> 0
C77: =E77*D$5 -> 0 | E77: =SUM(G77:HQ77) -> 0
C78: =E78*D$5 -> 0 | E78: =SUM(G78:HQ78) -> 0
C79: =E79*D$5 -> 0 | E79: =SUM(G79:HQ79) -> 0
C80: =E80*D$5 -> 0 | E80: =SUM(G80:HQ80) -> 0
C81: =E81*D$5 -> 0 | E81: =SUM(G81:HQ81) -> 0
C82: =E82*D$5 -> 0 | E82: =SUM(G82:HQ82) -> 0
C83: =E83*D$5 -> 0 | E83: =SUM(G83:HQ83) -> 0
C84: =E84*D$5 -> 0 | E84: =SUM(G84:HQ84) -> 0
C85: =E85*D$5 -> 0 | E85: =SUM(G85:HQ85) -> 0
C86: =E86*D$5 -> 0 | E86: =SUM(G86:HQ86) -> 0
C87: =E87*D$5 -> 0 | E87: =SUM(G87:HQ87) -> 0
... C205: =E205*D$5 -> 0 | E205: =SUM(G205:HQ205) -> 0

Sheet Tract 2
E1: Instrument | H1: Patent | I1: Quit Claim Deed | J1: Mineral Deed | K1: Final Decree | L1: Quit Claim Mineral Deed | M1: Quit Claim Mineral Deed | N1: Mineral Deed | O1: Mineral Deed | P1: Mineral Deed | Q1: Mineral Deed | R1: Mineral Deed | S1: Mineral Deed | T1: Mineral Deed | U1: Mineral Deed | V1: Mineral Deed | W1: Quit Claim Mineral Deed | X1: Mineral Deed | Y1: Mineral Deed | Z1: Mineral Deed | AA1: Mineral Deed | AB1: Mineral Deed | AC1: Quit Claim Deed | AD1: Deed | AE1: Mineral Deed | AF1: Mineral Deed | AG1: Mineral Deed | AH1: Mineral Deed | AI1: Mineral Deed | AJ1: Mineral Deed | AK1: Mineral Deed | AL1: Mineral Deed | AM1: Mineral Deed | AN1: Mineral Deed | AO1: Final Decree | AP1: Mineral Deed | AQ1: Mineral Deed | AR1: Quit Claim Mineral Deed | AS1: Mineral Deed | AT1: Mineral Deed | AU1: Mineral Deed | AV1: Mineral Deed | AW1: Deed | AX1: Mineral Deed | AY1: Mineral Deed | AZ1: Mineral Deed | BA1: Mineral Deed | BB1: Final Decree | BC1: Mineral Deed | BD1: Mineral Deed | BE1: Mineral Deed | BF1: Mineral Deed | BG1: Mineral Deed | BH1: Quit Claim Mineral Deed | BI1: Mineral Deed | BJ1: Mineral Deed | BK1: Mineral Deed | BL1: Mineral Deed | BM1: Mineral Deed | BN1: Mineral Deed | BO1: Final Decree
A2: 2 | B2: TRACT | D2: SW/4 SE/4, containing 40 acres | E2: Image Number | I2: 1995-004151 | J2: 1995-000396 | K2: 1995-001954 | L2: 1998-000584 | M2: 1998-000907 | N2: 1999-002219 | O2: 1999-002220 | P2: 1999-002739 | Q2: 1999-003363 | R2: 1999-003368 | S2: 1999-003364 | T2: 1999-003365 | U2: 1999-003366 | V2: 1999-003367 | W2: 2000-010180 | X2: 2001-000103 | Y2: 2001-000921 | Z2: 2001-000926 | AA2: 2001-000927 | AB2: 2002-004378 | AC2: 2003-003131 | AD2: 2005-000347 | AE2: 2005-001909 | AF2: 2005-003389 | AG2: 2005-007117 | AH2: 2005-007116 | AI2: 2005-007119 | AJ2: 2005-007120 | AK2: 2005-007540 | AL2: 2005-007541 | AM2: 2006-003765 | AN2: 2007-001374 | AO2: 2007-005167 | AP2: 2008-007325 | AQ2: 2009-000895 | AR2: 2010-002337 | AS2: 2010-005993 | AT2: 2010-007125 | AU2: 2010-008922 | AV2: 2011-003023 | AW2: 2011-007728 | AX2: 2011-007729 | AY2: 2012-002930 | AZ2: 2013-006083 | BA2: 2014-002935 | BB2: 2014-004286 | BC2: 2015-000877 | BD2: 2015-002791 | BE2: 2015-003284 | BG2: 2019-001747 | BH2: 2020-001650 | BI2: 2021-001774 | BJ2: 2023-002269 | BK2: 2025-002464 | BL2: 2025-002463 | BM2: 2025-005448 | BN2: 2025-005451 | BO2: 2026-003315
B3: DESCRIPTION | E3: Book / Page | H3: PAT006/74 | I3: 1462/0131 | J3: 1470/0059 | K3: 1479/0191 | L3: 1564/0310 | M3: 1567/0245 | N3: 1576/0219 | O3: 1576/0222 | P3: 1579/0358 | Q3: 1583/0391 | R3: 1583/0426 | S3: 1583/0398 | T3: 1583/0405 | U3: 1583/0412 | V3: 1583/0419 | W3: 1625/0440 | X3: 1631/0416 | Y3: 1636/0544 | Z3: 1636/0554 | AA3: 1636/0556 | AB3: 1694/0156 | AC3: 1714/0504 | AD3: 1775/0296 | AE3: 1783/0306 | AF3: 1790/0386 | AG3: 1810/0016 | AH3: 1810/0015 | AI3: 1810/0018 | AJ3: 1810/0019 | AK3: 1812/0120 | AL3: 1812/0121 | AM3: 1838/0136 | AN3: 1869/0351 | AO3: 1892/0567 | AP3: 1941/0550 | AQ3: 1949/0217 | AR3: 2002/0576 | AS3: 2022/0493 | AT3: 2031/0005 | AU3: 2041/0379 | AV3: 2074/0536 | AW3: 2104/0239 | AX3: 2104/0242 | AY3: 2131/0599 | AZ3: 2219/0516 | BA3: 2251/0022 | BB3: 2259/0397 | BC3: 2290/0178 | BD3: 2309/0236 | BE3: 2315/0042 | BF3: 2376/0100 | BG3: 2425/0225 | BH3: 2453/0219 | BI3: 2481/0287 | BJ3: 2529/0217 | BK3: 2625/0233 | BL3: 2625/0231 | BM3: 2649/0286 | BN3: 2649/0298 | BO3: 2704/0142
E4: Date | I4: 34806 | J4: 34920 | K4: 35038 | L4: 36026 | M4: 36059 | N4: 36175 | O4: 36175 | P4: 36215 | Q4: 36270 | R4: 36270 | S4: 36270 | T4: 36270 | U4: 36270 | V4: 36270 | W4: 36815 | X4: 36899 | Y4: 36956 | Z4: 36956 | AA4: 36956 | AB4: 37573 | AC4: 37797 | AD4: 38376 | AE4: 38446 | AF4: 38490 | AG4: 38642 | AH4: 38642 | AI4: 38642 | AJ4: 38642 | AK4: 38658 | AL4: 38658 | AM4: 38856 | AN4: 39167 | AO4: 39400 | AP4: 39783 | AQ4: 39874 | AR4: 40238 | AS4: 40336 | AT4: 40374 | AU4: 40438 | AV4: 40665 | AW4: 40869 | AX4: 40869 | AY4: 41015 | AZ4: 41592 | BA4: 41766 | BB4: 41821 | BC4: 42068 | BD4: 42255 | BE4: 42313 | BF4: 42996 | BG4: 43693 | BH4: 44133 | BI4: 44491 | BJ4: 45114 | BK4: 45771 | BL4: 45771 | BM4: 45908 | BN4: 45908 | BO4: 46178
B5: TRACT ACRES | D5: 40 | E5: Conveyance | H5: ARTI | I5: ARTI | J5: ARTI | K5: ARTI | L5: ARTI | M5: ARTI | N5: ARTI | O5: ARTI | P5: ARTI | Q5: ARTI | R5: ARTI | S5: ARTI | T5: ARTI | U5: ARTI | V5: ARTI | W5: ARTI | X5: ARTI | Y5: ARTI | Z5: ARTI | AA5: ARTI | AB5: ARTI | AC5: ARTI | AD5: ARTI | AE5: ARTI | AF5: ARTI | AG5: ARTI | AH5: ARTI | AI5: ARTI | AJ5: ARTI | AK5: ARTI | AL5: ARTI | AM5: ARTI | AN5: ARTI | AO5: ARTI | AP5: ARTI | AQ5: ARTI | AR5: ARTI | AS5: ARTI | AT5: ARTI | AU5: ARTI | AV5: ARTI | AW5: ARTI | AX5: ARTI | AY5: ARTI | AZ5: ARTI | BA5: ARTI | BB5: ARTI | BC5: ARTI | BD5: ARTI | BE5: ARTI | BF5: ARTI | BG5: ARTI | BH5: ARTI | BI5: ARTI | BJ5: ARTI | BK5: ARTI | BL5: ARTI | BM5: ARTI | BN5: ARTI | BO5: ARTI
B6: BASE OGL | C6: 40 | D6: Tract 2 | E6: =SUBTOTAL(9,E9:E205) -> 0 | F6: SURFACE | H6: =IF(H7=0,"","RECHECK") | I6: =IF(I7=0,"","RECHECK") | J6: =IF(J7=0,"","RECHECK") | K6: =IF(K7=0,"","RECHECK") | L6: =IF(L7=0,"","RECHECK") | M6: =IF(M7=0,"","RECHECK") | N6: =IF(N7=0,"","RECHECK") | O6: =IF(O7=0,"","RECHECK") | Q6: =IF(Q7=0,"","RECHECK") | R6: =IF(R7=0,"","RECHECK") | S6: =IF(S7=0,"","RECHECK") | T6: =IF(T7=0,"","RECHECK") | U6: =IF(U7=0,"","RECHECK") | V6: =IF(V7=0,"","RECHECK") | W6: =IF(W7=0,"","RECHECK") | X6: =IF(X7=0,"","RECHECK") | ... AA6: =IF(AA7=0,"","RECHECK") | AD6: =IF(AD7=0,"","RECHECK") | AE6: =IF(AE7=0,"","RECHECK") | AF6: =IF(AF7=0,"","RECHECK") | AG6: =IF(AG7=0,"","RECHECK") | AH6: =IF(AH7=0,"","RECHECK") | AI6: =IF(AI7=0,"","RECHECK") | AJ6: =IF(AJ7=0,"","RECHECK") | AK6: =IF(AK7=0,"","RECHECK") | ... GA6: =IF(GA7=0,"","RECHECK")
G7: =SUBTOTAL(9,G10:G206) -> 0 | H7: =SUBTOTAL(9,H10:H210) -> 0 | I7: =SUBTOTAL(9,I10:I210) -> 0 | J7: =SUBTOTAL(9,J10:J210) -> 0 | K7: =SUBTOTAL(9,K10:K210) -> 0 | L7: =SUBTOTAL(9,L10:L210) -> 0 | M7: =SUBTOTAL(9,M10:M206) -> 0 | N7: =SUBTOTAL(9,N10:N206) -> 0 | O7: =SUBTOTAL(9,O10:O206) -> 0 | P7: =SUBTOTAL(9,P10:P206) -> 0 | Q7: =SUBTOTAL(9,Q10:Q210) -> 0 | R7: =SUBTOTAL(9,R10:R206) -> 0 | S7: =SUBTOTAL(9,S10:S206) -> 0 | T7: =SUBTOTAL(9,T10:T206) -> 0 | U7: =SUBTOTAL(9,U10:U206) -> 0 | V7: =SUBTOTAL(9,V10:V206) -> 0 | W7: =SUBTOTAL(9,W10:W206) -> 0 | X7: =SUBTOTAL(9,X10:X206) -> 0 | Y7: =SUBTOTAL(9,Y10:Y206) -> 0 | Z7: 0 | AA7: =SUBTOTAL(9,AA10:AA210) -> 0 | AB7: =SUBTOTAL(9,AB10:AB207) -> 0 | AC7: =SUBTOTAL(9,AC10:AC201) -> 0 | AD7: =SUBTOTAL(9,AD10:AD201) -> 0 | AE7: =SUBTOTAL(9,AE10:AE201) -> 0 | AF7: =SUBTOTAL(9,AF10:AF201) -> 0 | AG7: =SUBTOTAL(9,AG10:AG206) -> 0 | AH7: =SUBTOTAL(9,AH10:AH202) -> 0 | AI7: =SUBTOTAL(9,AI10:AI206) -> 0 | AJ7: =SUBTOTAL(9,AJ10:AJ206) -> 0 | AK7: =SUBTOTAL(9,AK10:AK206) -> 0 | AL7: =SUBTOTAL(9,AL10:AL206) -> 0 | AM7: =SUBTOTAL(9,AM10:AM206) -> 0 | AN7: =SUBTOTAL(9,AN10:AN206) -> 0 | AO7: =SUBTOTAL(9,AO10:AO206) -> 0 | AP7: =SUBTOTAL(9,AP10:AP206) -> 0 | ... GA7: =SUBTOTAL(9,GA10:GA206) -> 0
A8: NOTES | C8: NET ACRES | D8: OWNERS | E8: TOTAL
C10: =IFERROR(IF($E10>0,$E10/SUMIF($E$10:$E$127,">0")*$D$5,""),"") | D10: United States of America | E10: =SUM(G10:HT10) -> -1 | H10: -1
C11: =IFERROR(IF($E11>0,$E11/SUMIF($E$10:$E$127,">0")*$D$5,""),"") | D11: Charles T. Kennett | E11: =SUM(G11:HT11) -> 0 | H11: 1 | I11: -1
C12: =IFERROR(IF($E12>0,$E12/SUMIF($E$10:$E$127,">0")*$D$5,""),"") -> 2.2222222 | D12: Barbara Bain | E12: =SUM(G12:HT12) -> 1 | I12: 1
C13: =IFERROR(IF($E13>0,$E13/SUMIF($E$10:$E$127,">0")*$D$5,""),"") | D13: Billy Wayne Bain | E13: =SUM(G13:HT13) -> -2 | J13: -1 | AO13: -1
C14: =IFERROR(IF($E14>0,$E14/SUMIF($E$10:$E$127,">0")*$D$5,""),"") | D14: Clarence C. Bain, Trustee | E14: =SUM(G14:HT14) -> 0 | J14: 1 | K14: -1 | L14: -1 | AC14: 1
C15: =IFERROR(IF($E15>0,$E15/SUMIF($E$10:$E$127,">0")*$D$5,""),"") -> 2.2222222 | D15: Dorothy J. Ba | E15: =SUM(G15:HT15) -> 1 | K15: 1
C16: =IFERROR(IF($E16>0,$E16/SUMIF($E$10:$E$127,">0")*$D$5,""),"") | D16: Alpine Oil and Royalty Co, Inc. | E16: =SUM(G16:HT16) -> 0 | J16: -1 | L16: 1
C17: =IFERROR(IF($E17>0,$E17/SUMIF($E$10:$E$127,">0")*$D$5,""),"") | D17: Melinda McCaul Mulvihill | E17: =SUM(G17:HT17) -> -1 | J17: 1 | P17: -1 | W17: -1
C18: =IFERROR(IF($E18>0,$E18/SUMIF($E$10:$E$127,">0")*$D$5,""),"") | D18: Wilson, Dwight J. Estate of | E18: =SUM(G18:HT18) -> -1 | K18: -1
C19: =IFERROR(IF($E19>0,$E19/SUMIF($E$10:$E$127,">0")*$D$5,""),"") -> 8.8888889 | D19: The Public | E19: =SUM(G19:HP19) -> 4 | K19: 1 | P19: 1 | AO19: 1 | BO19: 1
C20: =IFERROR(IF($E20>0,$E20/SUMIF($E$10:$E$127,">0")*$D$5,""),"") | D20: Jon T. Williams | E20: =SUM(G20:HP20) -> 0
C21: =IFERROR(IF($E21>0,$E21/SUMIF($E$10:$E$127,">0")*$D$5,""),"") | D21: Rogene E. Williams | E21: =SUM(G21:HT21) -> 0
C22: =IFERROR(IF($E22>0,$E22/SUMIF($E$10:$E$127,">0")*$D$5,""),"") | D22: Jon T. and Rogene E. Williams Trust | E22: =SUM(G22:HT22) -> 0
C23: =IFERROR(IF($E23>0,$E23/SUMIF($E$10:$E$127,">0")*$D$5,""),"") | D23: Jan A. Schroff | E23: =SUM(G23:HT23) -> 0
C24: =IFERROR(IF($E24>0,$E24/SUMIF($E$10:$E$127,">0")*$D$5,""),"") | D24: Jan A. Schroff, Trustee | E24: =SUM(G24:HT24) -> 0
C25: =IFERROR(IF($E25>0,$E25/SUMIF($E$10:$E$127,">0")*$D$5,""),"") | D25: David Slobin | E25: =SUM(G25:HT25) -> -2 | N25: -1 | O25: -1
C26: =IFERROR(IF($E26>0,$E26/SUMIF($E$10:$E$127,">0")*$D$5,""),"") -> 4.4444444 | D26: Myron Slobin | E26: =SUM(G26:HT26) -> 2 | N26: 1 | O26: 1
C27: =IFERROR(IF($E27>0,$E27/SUMIF($E$10:$E$127,">0")*$D$5,""),"") | D27: Eunice Evelyn Cook | E27: =SUM(G27:HT27) -> 0
C28: =IFERROR(IF($E28>0,$E28/SUMIF($E$10:$E$127,">0")*$D$5,""),"") | D28: Albert E. Fuchs | E28: =SUM(G28:HT28) -> 0
C29: =IFERROR(IF($E29>0,$E29/SUMIF($E$10:$E$127,">0")*$D$5,""),"") | D29: Aqu | E29: =SUM(G29:HT29) -> 0
C30: =IFERROR(IF($E30>0,$E30/SUMIF($E$10:$E$127,">0")*$D$5,""),"") | D30: Lola F. Richrads | E30: =SUM(G30:HT30) -> 0
C31: =IFERROR(IF($E31>0,$E31/SUMIF($E$10:$E$127,">0")*$D$5,""),"") | D31: Albert E. Fuchs, Trustee | E31: =SUM(G31:HT31) -> 0
C32: =IFERROR(IF($E32>0,$E32/SUMIF($E$10:$E$127,">0")*$D$5,""),"") | D32: Ocie H. Fuchs | E32: =SUM(G32:HT32) -> 0
C33: =IFERROR(IF($E33>0,$E33/SUMIF($E$10:$E$127,">0")*$D$5,""),"") | D33: Mark J. Fuchs | E33: =SUM(G33:HT33) -> 0
C34: =IFERROR(IF($E34>0,$E34/SUMIF($E$10:$E$127,">0")*$D$5,""),"") | D34: Jessie W. Fuchs | E34: =SUM(G34:HT34) -> 0
C35: =IFERROR(IF($E35>0,$E35/SUMIF($E$10:$E$127,">0")*$D$5,""),"") | D35: Raymond M. Fuchs | E35: =SUM(G35:HY35) -> 0
C36: =IFERROR(IF($E36>0,$E36/SUMIF($E$10:$E$127,">0")*$D$5,""),"") | D36: Isa May Smith | E36: =SUM(G36:HT36) -> 0
C37: =IFERROR(IF($E37>0,$E37/SUMIF($E$10:$E$127,">0")*$D$5,""),"") | D37: Melinda McCaul Mulvihill, Trustee | E37: =SUM(G37:HH37) -> 0
C38: =IFERROR(IF($E38>0,$E38/SUMIF($E$10:$E$127,">0")*$D$5,""),"") -> 2.2222222 | D38: Stephen M. Criser, Trustee | E38: =SUM(G38:HH38) -> 1 | W38: 1
C39: =IFERROR(IF($E39>0,$E39/SUMIF($E$10:$E$127,">0")*$D$5,""),"") | D39: William C. Bain Jr. | E39: =SUM(G39:HH39) -> 0
C40: =IFERROR(IF($E40>0,$E40/SUMIF($E$10:$E$127,">0")*$D$5,""),"") | D40: Donald R. Bain | E40: =SUM(G40:HH40) -> 0
C41: =IFERROR(IF($E41>0,$E41/SUMIF($E$10:$E$127,">0")*$D$5,""),"") | D41: Melvin F. Bain | E41: =SUM(G41:HH41) -> -1 | AK41: -1
C42: =IFERROR(IF($E42>0,$E42/SUMIF($E$10:$E$127,">0")*$D$5,""),"") | D42: Peggy J. | E42: =SUM(G42:HT42) -> 0
C43: =IFERROR(IF($E43>0,$E43/SUMIF($E$10:$E$127,">0")*$D$5,""),"") | D43: Dow C. Bain | E43: =SUM(G43:HP43) -> 0
C44: =IFERROR(IF($E44>0,$E44/SUMIF($E$10:$E$127,">0")*$D$5,""),"") | D44: Dow C. Bain, Trustee | E44: =SUM(G44:HT44) -> 0
C45: =IFERROR(IF($E45>0,$E45/SUMIF($E$10:$E$127,">0")*$D$5,""),"") | D45: Edris O. Bain, Trustee | E45: =SUM(G45:HT45) -> 0
C46: =IFERROR(IF($E46>0,$E46/SUMIF($E$10:$E$127,">0")*$D$5,""),"") | D46: Edris O. Bain | E46: =SUM(G46:HT46) -> 0
C47: =IFERROR(IF($E47>0,$E47/SUMIF($E$10:$E$127,">0")*$D$5,""),"") | D47: Billy Wayne Bain, Trustee | E47: =SUM(G47:HT47) -> 0
C48: =IFERROR(IF($E48>0,$E48/SUMIF($E$10:$E$127,">0")*$D$5,""),"") | D48: William Cobal | E48: =SUM(G48:HT48) -> 0
C49: =IFERROR(IF($E49>0,$E49/SUMIF($E$10:$E$127,">0")*$D$5,""),"") | D49: Deeanne Browning | E49: =SUM(G49:HT49) -> -1 | AC49: -1
C50: =IFERROR(IF($E50>0,$E50/SUMIF($E$10:$E$127,">0")*$D$5,""),"") | D50: Darrell E. Hamilton | E50: =SUM(G50:HT50) -> -1 | BO50: -1
C51: =IFERROR(IF($E51>0,$E51/SUMIF($E$10:$E$127,">0")*$D$5,""),"") | D51: S | E51: =SUM(G51:HT51) -> 0
C52: =IFERROR(IF($E52>0,$E52/SUMIF($E$10:$E$127,">0")*$D$5,""),"") | D52: Clarence Bain, Trustee | E52: =SUM(G52:HT52) -> 0
C53: =IFERROR(IF($E53>0,$E53/SUMIF($E$10:$E$127,">0")*$D$5,""),"") | D53: Norbert J. Co-prsnl Repres Dickman | E53: =SUM(G53:HT53) -> 0
C54: =IFERROR(IF($E54>0,$E54/SUMIF($E$10:$E$127,">0")*$D$5,""),"") | D54: Robe | E54: =SUM(G54:HT54) -> 0
C55: =IFERROR(IF($E55>0,$E55/SUMIF($E$10:$E$127,">0")*$D$5,""),"") | D55: Fasken Land and Minerals, Ltd. | E55: =SUM(G55:HT55) -> 0
C56: =IFERROR(IF($E56>0,$E56/SUMIF($E$10:$E$127,">0")*$D$5,""),"") | D56: John William Bain | E56: =SUM(G56:HT56) -> 0
C57: =IFERROR(IF($E57>0,$E57/SUMIF($E$10:$E$127,">0")*$D$5,""),"") | D57: G. & T. Partnership | E57: =SUM(G57:HT57) -> 0
C58: =IFERROR(IF($E58>0,$E58/SUMIF($E$10:$E$127,">0")*$D$5,""),"") | D58: Laura Snyder Robertson | E58: =SUM(G58:HT58) -> 0
C59: =IFERROR(IF($E59>0,$E59/SUMIF($E$10:$E$127,">0")*$D$5,""),"") | D59: James M. Robertson | E59: =SUM(G59:HT59) -> 0
C60: =IFERROR(IF($E60>0,$E60/SUMIF($E$10:$E$127,">0")*$D$5,""),"") | D60: Rose E. Robertson | E60: =SUM(G60:HT60) -> 0
C61: =IFERROR(IF($E61>0,$E61/SUMIF($E$10:$E$127,">0")*$D$5,""),"") | D61: Charlotte F. Willert | E61: =SUM(G61:HT61) -> -1 | AG61: -1
C62: =IFERROR(IF($E62>0,$E62/SUMIF($E$10:$E$127,">0")*$D$5,""),"") -> 11.111111 | D62: Mare Oil Company | E62: =SUM(G62:HT62) -> 5 | AG62: 1 | AH62: 1 | AI62: 1 | AJ62: 1 | AT62: 1
C63: =IFERROR(IF($E63>0,$E63/SUMIF($E$10:$E$127,">0")*$D$5,""),"") | D63: Peggy J. Brawner | E63: =SUM(G63:HT63) -> -1 | AH63: -1
C64: =IFERROR(IF($E64>0,$E64/SUMIF($E$10:$E$127,">0")*$D$5,""),"") | D64: Leona I. Degrande | E64: =SUM(G64:HT64) -> -3 | AI64: -1 | AJ64: -1 | AT64: -1
C65: =IFERROR(IF($E65>0,$E65/SUMIF($E$10:$E$127,">0")*$D$5,""),"") -> 2.2222222 | D65: Omega Royalty Co, LLC | E65: =SUM(G65:HT65) -> 1 | AK65: 1
C66: =IFERROR(IF($E66>0,$E66/SUMIF($E$10:$E$127,">0")*$D$5,""),"") | D66: Geotech Production, Inc. | E66: =SUM(G66:HT66) -> 0
C67: =IFERROR(IF($E67>0,$E67/SUMIF($E$10:$E$127,">0")*$D$5,""),"") | D67: Jack B. Searle | E67: =SUM(G67:HT67) -> 0
C68: =IFERROR(IF($E68>0,$E68/SUMIF($E$10:$E$127,">0")*$D$5,""),"") | D68: Datt Investment Company | E68: =SUM(G68:HT68) -> 0
C69: =IFERROR(IF($E69>0,$E69/SUMIF($E$10:$E$127,">0")*$D$5,""),"") | D69: Four A. Investments | E69: =SUM(G69:HT69) -> 0
C70: =IFERROR(IF($E70>0,$E70/SUMIF($E$10:$E$127,">0")*$D$5,""),"") | D70: Lola F. Ricards | E70: =SUM(G70:HT70) -> -1 | AN70: -1
C71: =IFERROR(IF($E71>0,$E71/SUMIF($E$10:$E$127,">0")*$D$5,""),"") -> 2.2222222 | D71: Arrowhead Resources, Inc. | E71: =SUM(G71:HT71) -> 1 | AN71: 1
C72: =IFERROR(IF($E72>0,$E72/SUMIF($E$10:$E$127,">0")*$D$5,""),"") | D72: Jan A. Indepedent Executor Schroff | E72: =SUM(G72:HT72) -> -1 | AP72: -1
C73: =IFERROR(IF($E73>0,$E73/SUMIF($E$10:$E$127,">0")*$D$5,""),"") -> 2.2222222 | D73: Williams , Rogene E. Revocable Living Tr | E73: =SUM(G73:HT73) -> 1 | AP73: 1
C74: =IFERROR(IF($E74>0,$E74/SUMIF($E$10:$E$127,">0")*$D$5,""),"") -> 2.2222222 | D74: Jesse W. Fuchs | E74: =SUM(G74:HT74) -> 1 | BA74: 1
C75: =IFERROR(IF($E75>0,$E75/SUMIF($E$10:$E$127,">0")*$D$5,""),"") | D75: Jinkee Acuero Fuchs | E75: =SUM(G75:HT75) -> 0
C76: =IFERROR(IF($E76>0,$E76/SUMIF($E$10:$E$127,">0")*$D$5,""),"") | D76: Jessica Corry Fuchs | E76: =SUM(G76:HT76) -> -1 | BA76: -1
C77: =IFERROR(IF($E77>0,$E77/SUMIF($E$10:$E$127,">0")*$D$5,""),"") | D77: Dwight J. Williams | E77: =SUM(G77:HT77) -> 0
C78: =IFERROR(IF($E78>0,$E78/SUMIF($E$10:$E$127,">0")*$D$5,""),"") | D78: Elizabeth M. Williams | E78: =SUM(G78:HT78) -> 0
C79: =IFERROR(IF($E79>0,$E79/SUMIF($E$10:$E$127,">0")*$D$5,""),"") | D79: Williams, Dwight J. Revocable Trust | E79: =SUM(G79:HT79) -> 0
C80: =IFERROR(IF($E80>0,$E80/SUMIF($E$10:$E$127,">0")*$D$5,""),"") | D80: Dwi | E80: =SUM(G80:HT80) -> 0
C81: =IFERROR(IF($E81>0,$E81/SUMIF($E$10:$E$127,">0")*$D$5,""),"") | D81: Wilda W. Jensen | E81: =SUM(G81:HT81) -> 0
C82: =IFERROR(IF($E82>0,$E82/SUMIF($E$10:$E$127,">0")*$D$5,""),"") | D82: Hans W. Jensen | E82: =SUM(G82:HT82) -> 0
C83: =IFERROR(IF($E83>0,$E83/SUMIF($E$10:$E$127,">0")*$D$5,""),"") | D83: Tim E. Jensen | E83: =SUM(G83:HT83) -> 0
C84: =IFERROR(IF($E84>0,$E84/SUMIF($E$10:$E$127,">0")*$D$5,""),"") | D84: Fausta J. Bish | E84: =SUM(G84:HT84) -> 0
C85: =IFERROR(IF($E85>0,$E85/SUMIF($E$10:$E$127,">0")*$D$5,""),"") | D85: Terry Bish | E85: =SUM(G85:HT85) -> 0
C86: =IFERROR(IF($E86>0,$E86/SUMIF($E$10:$E$127,">0")*$D$5,""),"") | D86: Tina Bish | E86: =SUM(G86:HT86) -> 0
C87: =IFERROR(IF($E87>0,$E87/SUMIF($E$10:$E$127,">0")*$D$5,""),"") | D87: D | E87: =SUM(G87:HT87) -> 0
C88: =IFERROR(IF($E88>0,$E88/SUMIF($E$10:$E$127,">0")*$D$5,""),"") | D88: Bish Family Trust | E88: =SUM(G88:HT88) -> 0
... C127: =IFERROR(IF($E127>0,$E127/SUMIF($E$10:$E$127,">0")*$D$5,""),"") | D127: Estate of Darrell Edward Hamilton | E127: =SUM(G127:HT127) -> 0
C128: =E128*D$5 -> 0 | E128: =SUM(G128:HT128) -> 0
C129: =E129*D$5 -> 0 | E129: =SUM(G129:HT129) -> 0
C130: =E130*D$5 -> 0 | E130: =SUM(G130:HT130) -> 0
C131: =E131*D$5 -> 0 | E131: =SUM(G131:HT131) -> 0
C132: =E132*D$5 -> 0 | E132: =SUM(G132:HT132) -> 0
C133: =E133*D$5 -> 0 | E133: =SUM(G133:HT133) -> 0
C134: =E134*D$5 -> 0 | E134: =SUM(G134:HT134) -> 0
C135: =E135*D$5 -> 0 | E135: =SUM(G135:HT135) -> 0
C136: =E136*D$5 -> 0 | E136: =SUM(G136:HT136) -> 0
C137: =E137*D$5 -> 0 | E137: =SUM(G137:HT137) -> 0
C138: =E138*D$5 -> 0 | E138: =SUM(G138:HT138) -> 0
C139: =E139*D$5 -> 0 | E139: =SUM(G139:HT139) -> 0
...

Sheet Tract 3
E1: Instrument | H1: Patent | I1: Mineral Deed | J1: Mineral Deed | K1: Warranty Deed | L1: Mineral Deed | M1: Mineral Deed | N1: Mineral Deed | O1: Mineral Deed | P1: Decree | Q1: Mineral Deed | R1: Warranty Deed | S1: Final Decree | T1: Final Decree | U1: Mineral Deed | V1: Mineral Deed | W1: Mineral Deed | X1: Quit Claim Deed | Y1: Joint Tenancy Warranty Deed | Z1: Trustees Mineral Deed | AA1: Trustees Mineral Deed | AB1: Trustees Mineral Deed | AC1: Mineral Deed | AD1: Mineral Deed | AE1: Final Decree | AF1: Mineral Deed | AG1: Mineral Deed | AH1: Mineral Deed | AI1: Quit Claim Mineral Deed | AJ1: Mineral Deed
A2: 3 | B2: TRACT | D2: SE/4 NE/4, containing 40 acres | E2: Image Number | H2: 1909-002932 | I2: 1994-006415 | J2: 1995-003404 | K2: 1996-002352 | L2: 2000-007685 | M2: 2001-000957 | N2: 2001-001414 | O2: 2001-001463 | P2: 2001-002342 | Q2: 2002-004595 | R2: 2003-004945 | S2: 2003-005699 | T2: 2004-000099 | U2: 2004-005901 | V2: 2005-000158 | W2: 2005-007551 | X2: 2007-001848 | Y2: 2008-003157 | Z2: 2011-001007 | AA2: 2011-001008 | AB2: 2011-001009 | AC2: 2011-008134 | AD2: 2012-004060 | AE2: 2013-000518 | AF2: 2014-003089 | AG2: 2014-006293 | AI2: 2018-002650 | AJ2: 2021-001068
B3: DESCRIPTION | E3: Book / Page | H3: PAT006/7 | I3: 1422/0009 | J3: 1457/0173 | K3: 1510/0491 | L3: 1611/0503 | M3: 1637/0026 | N3: 1639/0206 | O3: 1639/0426 | P3: 1643/0389 | Q3: 1695/0238 | R3: 1724/0582 | S3: 1728/0457 | T3: 1734/0014 | U3: 1765/0306 | V3: 1774/0309 | W3: 1812/0138 | X3: 1872/0277 | Y3: 1914/0155 | Z3: 2063/0491 | AA3: 2063/0494 | AB3: 2063/0497 | AC3: 2106/0387 | AD3: 2141/0003 | AE3: 2177/0033 | AF3: 2251/0529 | AG3: 2273/0223 | AH3: 2376/0100 | AI3: 2406/0228 | AJ3: 2467/0476
E4: Date | H4: 3652 | I4: 34542 | J4: 34754 | K4: 35429 | L4: 36647 | M4: 36957 | N4: 36987 | O4: 36991 | P4: 37034 | Q4: 37592 | R4: 37897 | S4: 37937 | T4: 37994 | U4: 38281 | V4: 38365 | W4: 38658 | X4: 39197 | Y4: 39612 | Z4: 40592 | AA4: 40592 | AB4: 40592 | AC4: 40886 | AD4: 41061 | AE4: 41304 | AF4: 41774 | AG4: 41927 | AH4: 42996 | AI4: 43382 | AJ4: 44377
B5: TRACT ACRES | D5: 40 | E5: Conveyance | H5: ARTI | I5: ARTI | J5: ARTI | K5: ARTI | L5: ARTI | M5: ARTI | N5: ARTI | O5: ARTI | P5: ARTI | Q5: ARTI | R5: ARTI | S5: ARTI | T5: ARTI | U5: ARTI | V5: ARTI | W5: ARTI | X5: ARTI | Y5: ARTI | Z5: ARTI | AA5: ARTI | AB5: ARTI | AC5: ARTI | AD5: ARTI | AE5: ARTI | AF5: ARTI | AG5: ARTI | AH5: ARTI | AI5: ARTI | AJ5: ARTI
B6: BASE OGL | C6: 40 | D6: Tract 3 | E6: =SUBTOTAL(9,E9:E203) -> 0 | F6: SURFACE | H6: =IF(H7=0,"","RECHECK") | I6: =IF(I7=0,"","RECHECK") | J6: =IF(J7=0,"","RECHECK") | L6: =IF(L7=0,"","RECHECK") | M6: =IF(M7=0,"","RECHECK") | N6: =IF(N7=0,"","RECHECK") | O6: =IF(O7=0,"","RECHECK") | P6: =IF(P7=0,"","RECHECK") | Q6: =IF(Q7=0,"","RECHECK") | R6: =IF(R7=0,"","RECHECK") | S6: =IF(S7=0,"","RECHECK") | ... X6: =IF(X7=0,"","RECHECK") | AA6: =IF(AA7=0,"","RECHECK") | AB6: =IF(AB7=0,"","RECHECK") | AC6: =IF(AC7=0,"","RECHECK") | AD6: =IF(AD7=0,"","RECHECK") | AE6: =IF(AE7=0,"","RECHECK") | AF6: =IF(AF7=0,"","RECHECK") | AG6: =IF(AG7=0,"","RECHECK") | AH6: =IF(AH7=0,"","RECHECK") | ... FS6: =IF(FS7=0,"","RECHECK")
G7: =SUBTOTAL(9,G10:G204) -> 0 | H7: =SUBTOTAL(9,H10:H212) -> 0 | I7: =SUBTOTAL(9,I10:I212) -> 0 | J7: =SUBTOTAL(9,J10:J212) -> 0 | K7: =SUBTOTAL(9,K10:K208) -> 0 | L7: =SUBTOTAL(9,L10:L204) -> 0 | M7: =SUBTOTAL(9,M10:M204) -> 0 | N7: =SUBTOTAL(9,N10:N204) -> 0 | O7: =SUBTOTAL(9,O10:O204) -> 0 | P7: =SUBTOTAL(9,P10:P204) -> 0 | Q7: =SUBTOTAL(9,Q10:Q204) -> 0 | R7: =SUBTOTAL(9,R10:R204) -> 0 | S7: =SUBTOTAL(9,S10:S204) -> 0 | ... V7: =SUBTOTAL(9,V10:V204) -> 0 | W7: 0 | X7: =SUBTOTAL(9,X10:X208) -> 0 | Y7: =SUBTOTAL(9,Y10:Y212) -> 0 | Z7: =SUBTOTAL(9,Z10:Z206) -> 0 | AA7: =SUBTOTAL(9,AA10:AA206) -> 0 | AB7: =SUBTOTAL(9,AB10:AB206) -> 0 | AC7: =SUBTOTAL(9,AC10:AC206) -> 0 | AD7: =SUBTOTAL(9,AD10:AD204) -> 0 | AE7: =SUBTOTAL(9,AE10:AE203) -> 0 | AF7: =SUBTOTAL(9,AF10:AF204) -> 0 | AG7: =SUBTOTAL(9,AG10:AG206) -> 0 | AH7: =SUBTOTAL(9,AH10:AH204) -> 0 | AI7: =SUBTOTAL(9,AI10:AI204) -> 0 | AJ7: =SUBTOTAL(9,AJ10:AJ204) -> 0 | AK7: =SUBTOTAL(9,AK10:AK204) -> 0 | AL7: =SUBTOTAL(9,AL10:AL204) -> 0 | AM7: =SUBTOTAL(9,AM10:AM204) -> 0 | AN7: =SUBTOTAL(9,AN10:AN204) -> 0 | AO7: =SUBTOTAL(9,AO10:AO204) -> 0 | ... FS7: =SUBTOTAL(9,FS10:FS204) -> 0
A8: NOTES | C8: NET ACRES | D8: OWNERS | E8: TOTAL
C10: =IFERROR(IF($E10>0,$E10/SUMIF($E$10:$E$74,">0")*$D$5,""),"") | D10: United States of America | E10: =SUM(G10:HL10) -> -1 | H10: -1
C11: =IFERROR(IF($E11>0,$E11/SUMIF($E$10:$E$74,">0")*$D$5,""),"") -> 2.6666667 | D11: Ernest Brooks | E11: =SUM(G11:HL11) -> 1 | H11: 1
C12: =IFERROR(IF($E12>0,$E12/SUMIF($E$10:$E$74,">0")*$D$5,""),"") | D12: Hayhurst Oil Properties, Inc. | E12: =SUM(G12:HL12) -> -1 | I12: -1
C13: =IFERROR(IF($E13>0,$E13/SUMIF($E$10:$E$74,">0")*$D$5,""),"") -> 2.6666667 | D13: Nam Corporation | E13: =SUM(G13:HL13) -> 1 | I13: 1
C14: =IFERROR(IF($E14>0,$E14/SUMIF($E$10:$E$74,">0")*$D$5,""),"") | D14: Tripco, Inc. | E14: =SUM(G14:HL14) -> -2 | J14: -1 | W14: -1
C15: =IFERROR(IF($E15>0,$E15/SUMIF($E$10:$E$74,">0")*$D$5,""),"") -> 2.6666667 | D15: Prudential Securities | E15: =SUM(G15:HL15) -> 1 | J15: 1
C16: =IFERROR(IF($E16>0,$E16/SUMIF($E$10:$E$74,">0")*$D$5,""),"") | D16: Eula Cross | E16: =SUM(G16:HL16) -> 0
C17: =IFERROR(IF($E17>0,$E17/SUMIF($E$10:$E$74,">0")*$D$5,""),"") | D17: Floyd W. Atha | E17: =SUM(G17:HL17) -> 0
C18: =IFERROR(IF($E18>0,$E18/SUMIF($E$10:$E$74,">0")*$D$5,""),"") | D18: Nancy D. Atha | E18: =SUM(G18:HL18) -> 0
C19: =IFERROR(IF($E19>0,$E19/SUMIF($E$10:$E$74,">0")*$D$5,""),"") | D19: Fer-scher Exploration, LLC | E19: =SUM(G19:HL19) -> -1 | L19: -1
C20: =IFERROR(IF($E20>0,$E20/SUMIF($E$10:$E$74,">0")*$D$5,""),"") -> 2.6666667 | D20: Aspen Minerals Group | E20: =SUM(G20:HL20) -> 1 | L20: 1
C21: =IFERROR(IF($E21>0,$E21/SUMIF($E$10:$E$74,">0")*$D$5,""),"") | D21: Nanalee Faye Barnett | E21: =SUM(G21:HL21) -> -1 | M21: -1
C22: =IFERROR(IF($E22>0,$E22/SUMIF($E$10:$E$74,">0")*$D$5,""),"") -> 8 | D22: Arrowhead Resources, Inc. | E22: =SUM(G22:HL22) -> 3 | M22: 1 | N22: 1 | O22: 1
C23: =IFERROR(IF($E23>0,$E23/SUMIF($E$10:$E$74,">0")*$D$5,""),"") | D23: Louise Ormand | E23: =SUM(G23:HL23) -> -1 | N23: -1
C24: =IFERROR(IF($E24>0,$E24/SUMIF($E$10:$E$74,">0")*$D$5,""),"") | D24: Glenn D. Mitchel | E24: =SUM(G24:HL24) -> -1 | O24: -1
C25: =IFERROR(IF($E25>0,$E25/SUMIF($E$10:$E$74,">0")*$D$5,""),"") | D25: Jack E. Barnett, Deceased | E25: =SUM(G25:HL25) -> -1 | P25: -1
C26: =IFERROR(IF($E26>0,$E26/SUMIF($E$10:$E$74,">0")*$D$5,""),"") -> 8 | D26: The Public | E26: =SUM(G26:HL26) -> 3 | P26: 1 | S26: 1 | T26: 1
C27: =IFERROR(IF($E27>0,$E27/SUMIF($E$10:$E$74,">0")*$D$5,""),"") | D27: Hayhurst, Peggy J. Revoc Trust | E27: =SUM(G27:HL27) -> 0
C28: =IFERROR(IF($E28>0,$E28/SUMIF($E$10:$E$74,">0")*$D$5,""),"") | D28: Peggy J. | E28: =SUM(G28:HL28) -> 0
C29: =IFERROR(IF($E29>0,$E29/SUMIF($E$10:$E$74,">0")*$D$5,""),"") | D29: Bluebonnet Investments, Ltd. | E29: =SUM(G29:HL29) -> -1 | R29: -1
C30: =IFERROR(IF($E30>0,$E30/SUMIF($E$10:$E$74,">0")*$D$5,""),"") -> 2.6666667 | D30: White Birch, LP | E30: =SUM(G30:HL30) -> 1 | R30: 1
C31: =IFERROR(IF($E31>0,$E31/SUMIF($E$10:$E$74,">0")*$D$5,""),"") | D31: Glenn Douglas Mitchell, Deceased | E31: =SUM(G31:HL31) -> -1 | S31: -1
C32: =IFERROR(IF($E32>0,$E32/SUMIF($E$10:$E$74,">0")*$D$5,""),"") | D32: Evelyn Louise McLerran, Deceased | E32: =SUM(G32:HL32) -> -1 | T32: -1
C33: =IFERROR(IF($E33>0,$E33/SUMIF($E$10:$E$74,">0")*$D$5,""),"") | D33: Aspen Energy Group, Inc. | E33: =SUM(G33:HL33) -> -1 | U33: -1
C34: =IFERROR(IF($E34>0,$E34/SUMIF($E$10:$E$74,">0")*$D$5,""),"") -> 2.6666667 | D34: Crusader Energy Corporation | E34: =SUM(G34:HL34) -> 1 | U34: 1
C35: =IFERROR(IF($E35>0,$E35/SUMIF($E$10:$E$74,">0")*$D$5,""),"") | D35: Minion Investment Co | E35: =SUM(G35:HL35) -> 0
C36: =IFERROR(IF($E36>0,$E36/SUMIF($E$10:$E$74,">0")*$D$5,""),"") | D36: Brian L. Rice | E36: =SUM(G36:HL36) -> 0
C37: =IFERROR(IF($E37>0,$E37/SUMIF($E$10:$E$74,">0")*$D$5,""),"") -> 2.6666667 | D37: Prism Energy, Inc. | E37: =SUM(G37:HQ37) -> 1 | W37: 1
C38: =IFERROR(IF($E38>0,$E38/SUMIF($E$10:$E$74,">0")*$D$5,""),"") | D38: Atha Nancy D. | E38: =SUM(G38:HL38) -> 0
C39: =IFERROR(IF($E39>0,$E39/SUMIF($E$10:$E$74,">0")*$D$5,""),"") | D39: Atha Floyd Revoc Trust | E39: =SUM(G39:GZ39) -> 0
C40: =IFERROR(IF($E40>0,$E40/SUMIF($E$10:$E$74,">0")*$D$5,""),"") | D40: Floyd Atha, Trustee | E40: =SUM(G40:GZ40) -> 0
C41: =IFERROR(IF($E41>0,$E41/SUMIF($E$10:$E$74,">0")*$D$5,""),"") | D41: Floyd Co Atha, Trustee | E41: =SUM(G41:GZ41) -> 0
C42: =IFERROR(IF($E42>0,$E42/SUMIF($E$10:$E$74,">0")*$D$5,""),"") | D42: Nancy Co Atha, Trustee | E42: =SUM(G42:GZ42) -> 0
C43: =IFERROR(IF($E43>0,$E43/SUMIF($E$10:$E$74,">0")*$D$5,""),"") | D43: Danielle Delane Tucker | E43: =SUM(G43:GZ43) -> 0
C44: =IFERROR(IF($E44>0,$E44/SUMIF($E$10:$E$74,">0")*$D$5,""),"") | D44: Monte Earl Tucker | E44: =SUM(G44:HL44) -> 0
C45: =IFERROR(IF($E45>0,$E45/SUMIF($E$10:$E$74,">0")*$D$5,""),"") | D45: Glenda Palmer | E45: =SUM(G45:HH45) -> 0
C46: =IFERROR(IF($E46>0,$E46/SUMIF($E$10:$E$74,">0")*$D$5,""),"") | D46: Richard Palmer | E46: =SUM(G46:HL46) -> 0
C47: =IFERROR(IF($E47>0,$E47/SUMIF($E$10:$E$74,">0")*$D$5,""),"") | D47: Palmer Family Trust | E47: =SUM(G47:HL47) -> 0
C48: =IFERROR(IF($E48>0,$E48/SUMIF($E$10:$E$74,">0")*$D$5,""),"") | D48: Glenda Ann Palmer | E48: =SUM(G48:HL48) -> 0
C49: =IFERROR(IF($E49>0,$E49/SUMIF($E$10:$E$74,">0")*$D$5,""),"") | D49: Mitchel, Glenn Douglas and Hazel Pearl Trust | E49: =SUM(G49:HL49) -> 0
C50: =IFERROR(IF($E50>0,$E50/SUMIF($E$10:$E$74,">0")*$D$5,""),"") | D50: Mitchel, Jack D. and Shonna A. Family Trust | E50: =SUM(G50:HL50) -> 0
C51: =IFERROR(IF($E51>0,$E51/SUMIF($E$10:$E$74,">0")*$D$5,""),"") | D51: Shonna Mitchel | E51: =SUM(G51:HL51) -> 0
C52: =IFERROR(IF($E52>0,$E52/SUMIF($E$10:$E$74,">0")*$D$5,""),"") | D52: Shonna A. Mitchel | E52: =SUM(G52:HL52) -> 0
C53: =IFERROR(IF($E53>0,$E53/SUMIF($E$10:$E$74,">0")*$D$5,""),"") | D53: Shonn | E53: =SUM(G53:HL53) -> 0
C54: =IFERROR(IF($E54>0,$E54/SUMIF($E$10:$E$74,">0")*$D$5,""),"") | D54: Myron V. Slobin | E54: =SUM(G54:HL54) -> -1 | AC54: -1
C55: =IFERROR(IF($E55>0,$E55/SUMIF($E$10:$E$74,">0")*$D$5,""),"") -> 2.6666667 | D55: Brian Herman Kortright | E55: =SUM(G55:HL55) -> 1 | AC55: 1
C56: =IFERROR(IF($E56>0,$E56/SUMIF($E$10:$E$74,">0")*$D$5,""),"") | D56: Joel R. Ibeling | E56: =SUM(G56:HL56) -> 0
C57: =IFERROR(IF($E57>0,$E57/SUMIF($E$10:$E$74,">0")*$D$5,""),"") | D57: Lyle T. Ibeling | E57: =SUM(G57:HL57) -> 0
C58: =IFERROR(IF($E58>0,$E58/SUMIF($E$10:$E$74,">0")*$D$5,""),"") | D58: Michel | E58: =SUM(G58:HL58) -> 0
C59: =IFERROR(IF($E59>0,$E59/SUMIF($E$10:$E$74,">0")*$D$5,""),"") | D59: Gregory J. Winneke | E59: =SUM(G59:HL59) -> 0
C60: =IFERROR(IF($E60>0,$E60/SUMIF($E$10:$E$74,">0")*$D$5,""),"") | D60: Gene G. Williams | E60: =SUM(G60:HL60) -> 0
C61: =IFERROR(IF($E61>0,$E61/SUMIF($E$10:$E$74,">0")*$D$5,""),"") | D61: Nancy Mitchell Dcd Williams | E61: =SUM(G61:HL61) -> 0
C62: =IFERROR(IF($E62>0,$E62/SUMIF($E$10:$E$74,">0")*$D$5,""),"") | D62: Luther Ervin Thurman | E62: =SUM(G62:HL62) -> 0
C63: =IFERROR(IF($E63>0,$E63/SUMIF($E$10:$E$74,">0")*$D$5,""),"") | D63: Veronica Gentry Th | E63: =SUM(G63:HL63) -> 0
C64: =IFERROR(IF($E64>0,$E64/SUMIF($E$10:$E$74,">0")*$D$5,""),"") | D64: Thurman, Luther and Veronica Liv Trust | E64: =SUM(G64:HL64) -> 0
C65: =IFERROR(IF($E65>0,$E65/SUMIF($E$10:$E$74,">0")*$D$5,""),"") | D65: Etta Britton | E65: =SUM(G65:HL65) -> 0
C66: =IFERROR(IF($E66>0,$E66/SUMIF($E$10:$E$74,">0")*$D$5,""),"") | D66: Joe H. Britton | E66: =SUM(G66:HL66) -> 0
C67: =IFERROR(IF($E67>0,$E67/SUMIF($E$10:$E$74,">0")*$D$5,""),"") | D67: Linda C. Browning | E67: =SUM(G67:HL67) -> 0
C68: =IFERROR(IF($E68>0,$E68/SUMIF($E$10:$E$74,">0")*$D$5,""),"") | D68: Jon N. Wilkerson | E68: =SUM(G68:HL68) -> -1 | AH68: -1
C69: =IFERROR(IF($E69>0,$E69/SUMIF($E$10:$E$74,">0")*$D$5,""),"") -> 2.6666667 | D69: Tamara K. Wilkerson | E69: =SUM(G69:HL69) -> 1 | AH69: 1
C70: =IFERROR(IF($E70>0,$E70/SUMIF($E$10:$E$74,">0")*$D$5,""),"") | D70: Cindy Lou Vignal, Trustee | E70: =SUM(G70:HL70) -> 0
C71: =IFERROR(IF($E71>0,$E71/SUMIF($E$10:$E$74,">0")*$D$5,""),"") | D71: Vignal, Gary | E71: =SUM(G71:HL71) -> 0
C72: =IFERROR(IF($E72>0,$E72/SUMIF($E$10:$E$74,">0")*$D$5,""),"") | D72: Grizzly Operating, LLC | E72: =SUM(G72:HL72) -> 0
C73: =IFERROR(IF($E73>0,$E73/SUMIF($E$10:$E$74,">0")*$D$5,""),"") | D73: Vanguard Operating, LLC | E73: =SUM(G73:HL73) -> 0
C74: =IFERROR(IF($E74>0,$E74/SUMIF($E$10:$E$74,">0")*$D$5,""),"") | D74: Psi Lke, LLC | E74: =SUM(G74:HL74) -> 0
C75: =E75*D$5 -> 0 | E75: =SUM(G75:HL75) -> 0
C76: =E76*D$5 -> 0 | E76: =SUM(G76:HL76) -> 0
C77: =E77*D$5 -> 0 | E77: =SUM(G77:HL77) -> 0
C78: =E78*D$5 -> 0 | E78: =SUM(G78:HL78) -> 0
C79: =E79*D$5 -> 0 | E79: =SUM(G79:HL79) -> 0
C80: =E80*D$5 -> 0 | E80: =SUM(G80:HL80) -> 0
C81: =E81*D$5 -> 0 | E81: =SUM(G81:HL81) -> 0
C82: =E82*D$5 -> 0 | E82: =SUM(G82:HL82) -> 0
C83: =E83*D$5 -> 0 | E83: =SUM(G83:HL83) -> 0
C84: =E84*D$5 -> 0 | E84: =SUM(G84:HL84) -> 0
C85: =E85*D$5 -> 0 | E85: =SUM(G85:HL85) -> 0
C86: =E86*D$5 -> 0 | E86: =SUM(G86:HL86) -> 0
... C203: =E203*D$5 -> 0 | E203: =SUM(G203:HL203) -> 0

Sheet Tract 4
E1: Instrument | H1: Patent | I1: Deed | J1: Deed | K1: Mineral Deed | L1: Mineral Deed | M1: Quit Claim Mineral Deed | N1: Mineral Deed | O1: Mineral Deed | P1: Mineral Deed | Q1: Mineral Deed | R1: Decree | S1: Mineral Deed | T1: Warranty Deed | U1: Final Decree | V1: Final Decree | W1: Mineral Deed | X1: Mineral Deed | Y1: Mineral Deed | Z1: Mineral Deed | AA1: Trustees Mineral Deed | AB1: Trustees Mineral Deed | AC1: Trustees Mineral Deed | AD1: Final Decree | AE1: Mineral Deed | AF1: Mineral Deed | AG1: Quit Claim Mineral Deed | AH1: Mineral Deed | AI1: Mineral Deed
A2: 4 | B2: TRACT | D2: E/2 NW/4, containing 80 acres | E2: Image Number | H2: 1907-005379 | I2: 1905-000429 | J2: 1927-000706 | K2: 1979-005655 | L2: 2014-003089 | M2: 2018-002650 | N2: 2017-000951 | O2: 2001-000957 | P2: 2001-001414 | Q2: 2001-001463 | R2: 2001-002342 | S2: 2002-004595 | T2: 2003-004945 | U2: 2003-005699 | V2: 2004-000099 | W2: 2004-005901 | X2: 2005-000158 | Y2: 2005-007551 | Z2: 2010-008934 | AA2: 2011-001007 | AB2: 2011-001008 | AC2: 2011-001009 | AD2: 2013-000518 | AE2: 2014-003089 | AF2: 2014-006293 | AG2: 2018-002650 | AH2: 2019-001855 | AI2: 2021-001068
B3: DESCRIPTION | E3: Book / Page | H3: PAT003/495 | I3: D00006/0206 | J3: D00038/0162 | K3: 0277/0064 | L3: 2251/0529 | M3: 2406/0228 | N3: 2365/0338 | O3: 1637/0026 | P3: 1639/0206 | Q3: 1639/0426 | R3: 1643/0389 | S3: 1695/0238 | T3: 1724/0582 | U3: 1728/0457 | V3: 1734/0014 | W3: 1765/0306 | X3: 1774/0309 | Y3: 1812/0138 | Z3: 2041/0406 | AA3: 2063/0491 | AB3: 2063/0494 | AC3: 2063/0497 | AD3: 2177/0033 | AE3: 2251/0529 | AF3: 2273/0223 | AG3: 2406/0228 | AH3: 2426/0154 | AI3: 2467/0476
E4: Date | H4: 2752 | I4: 2063 | J4: 10077 | K4: 29126 | L4: 41746 | M4: 43363 | N4: 42855 | O4: 36957 | P4: 36987 | Q4: 36991 | R4: 37034 | S4: 37592 | T4: 37897 | U4: 37937 | V4: 37994 | W4: 38281 | X4: 38365 | Y4: 38658 | Z4: 40441 | AA4: 40592 | AB4: 40592 | AC4: 40592 | AD4: 41304 | AE4: 41774 | AF4: 41927 | AG4: 43382 | AH4: 43711 | AI4: 44377
B5: TRACT ACRES | D5: 80 | E5: Conveyance | H5: ARTI | I5: ARTI | J5: ARTI | K5: ARTI | L5: ARTI | M5: ARTI | N5: ARTI | O5: ARTI | P5: ARTI | Q5: ARTI | R5: ARTI | S5: ARTI | T5: ARTI | U5: ARTI | V5: ARTI | W5: ARTI | X5: ARTI | Y5: ARTI | Z5: ARTI | AA5: ARTI | AB5: ARTI | AC5: ARTI | AD5: ARTI | AE5: ARTI | AF5: ARTI | AG5: ARTI | AH5: ARTI | AI5: ARTI
B6: BASE OGL | C6: 80 | D6: Tract 4 | E6: =SUBTOTAL(9,E9:E177) -> 1 | F6: SURFACE | H6: =IF(H7=0,"","RECHECK") | I6: =IF(I7=0,"","RECHECK") | J6: =IF(J7=0,"","RECHECK") | K6: =IF(K7=0,"","RECHECK") | L6: =IF(L7=0,"","RECHECK") | M6: =IF(M7=0,"","RECHECK") | N6: =IF(N7=0,"","RECHECK") | O6: =IF(O7=0,"","RECHECK") | ... FM6: =IF(FM7=0,"","RECHECK")
G7: =SUBTOTAL(9,G10:G178) -> 1 | H7: =SUBTOTAL(9,H10:H182) -> 0 | I7: =SUBTOTAL(9,I10:I182) -> 0 | J7: =SUBTOTAL(9,J10:J182) -> 0 | K7: =SUBTOTAL(9,K10:K182) -> 0 | L7: =SUBTOTAL(9,L10:L182) -> 0 | M7: =SUBTOTAL(9,M10:M182) -> 0 | N7: =SUBTOTAL(9,N10:N182) -> 0 | O7: =SUBTOTAL(9,O10:O182) -> 0 | P7: =SUBTOTAL(9,P10:P178) -> 0 | Q7: =SUBTOTAL(9,Q10:Q178) -> 0 | R7: =SUBTOTAL(9,R10:R178) -> 0 | S7: =SUBTOTAL(9,S10:S178) -> 0 | T7: =SUBTOTAL(9,T10:T178) -> 0 | U7: =SUBTOTAL(9,U10:U181) -> 0 | V7: =SUBTOTAL(9,V10:V178) -> 0 | W7: =SUBTOTAL(9,W10:W178) -> 0 | X7: =SUBTOTAL(9,X10:X178) -> 0 | Y7: =SUBTOTAL(9,Y10:Y178) -> 0 | Z7: =SUBTOTAL(9,Z10:Z178) -> 0 | AA7: =SUBTOTAL(9,AA10:AA178) -> 0 | AB7: =SUBTOTAL(9,AB10:AB181) -> 0 | AC7: =SUBTOTAL(9,AC10:AC181) -> 0 | AD7: =SUBTOTAL(9,AD10:AD178) -> 0 | AE7: =SUBTOTAL(9,AE10:AE178) -> 0 | AF7: =SUBTOTAL(9,AF10:AF178) -> 0 | AG7: =SUBTOTAL(9,AG10:AG178) -> 0 | AH7: =SUBTOTAL(9,AH10:AH178) -> 0 | AI7: =SUBTOTAL(9,AI10:AI178) -> 0 | AJ7: =SUBTOTAL(9,AJ10:AJ178) -> 0 | AK7: =SUBTOTAL(9,AK10:AK178) -> 0 | ... FM7: =SUBTOTAL(9,FM10:FM178) -> 0
A8: NOTES | C8: NET ACRES | D8: OWNERS | E8: TOTAL
C10: =IFERROR(IF($E10>0,$E10/SUMIF($E$10:$E$70,">0")*$D$5,""),"") | D10: United States of America | E10: =SUM(G10:HF10) -> 0 | G10: 1 | H10: -1
C11: =IFERROR(IF($E11>0,$E11/SUMIF($E$10:$E$70,">0")*$D$5,""),"") | D11: Leo Kennett | E11: =SUM(G11:HF11) -> 0 | H11: 1 | I11: -1
C12: =IFERROR(IF($E12>0,$E12/SUMIF($E$10:$E$70,">0")*$D$5,""),"") | D12: Leede Exploration | E12: =SUM(G12:HF12) -> 0 | I12: 1 | J12: -1
C13: =IFERROR(IF($E13>0,$E13/SUMIF($E$10:$E$70,">0")*$D$5,""),"") | D13: O. I. L. Energy, Inc. | E13: =SUM(G13:HF13) -> 0 | J13: 1 | K13: -1
C14: =IFERROR(IF($E14>0,$E14/SUMIF($E$10:$E$70,">0")*$D$5,""),"") -> 6.6666667 | D14: Robert H. Frazier | E14: =SUM(G14:HF14) -> 1 | K14: 1
C15: =IFERROR(IF($E15>0,$E15/SUMIF($E$10:$E$70,">0")*$D$5,""),"") | D15: Clyde A. Pine | E15: =SUM(G15:HF15) -> -1 | L15: -1
C16: =IFERROR(IF($E16>0,$E16/SUMIF($E$10:$E$70,">0")*$D$5,""),"") | D16: Charle | E16: =SUM(G16:HG16) -> 0 | L16: 1 | M16: -1
C17: =IFERROR(IF($E17>0,$E17/SUMIF($E$10:$E$70,">0")*$D$5,""),"") -> 6.6666667 | D17: Hayhurst Oil Properties, Inc. | E17: =SUM(G17:HG17) -> 1 | M17: 1
C18: =IFERROR(IF($E18>0,$E18/SUMIF($E$10:$E$70,">0")*$D$5,""),"") | D18: Nam Corporation | E18: =SUM(G18:HG18) -> -1 | N18: -1
C19: =IFERROR(IF($E19>0,$E19/SUMIF($E$10:$E$70,">0")*$D$5,""),"") | D19: Tripco, Inc. | E19: =SUM(G19:HG19) -> 0 | N19: 1 | Y19: -1
C20: =IFERROR(IF($E20>0,$E20/SUMIF($E$10:$E$70,">0")*$D$5,""),"") | D20: Prudential Securities | E20: =SUM(G20:HF20) -> -1 | O20: -1
C21: =IFERROR(IF($E21>0,$E21/SUMIF($E$10:$E$70,">0")*$D$5,""),"") -> 6.6666667 | D21: Fer-scher Exploration, LLC | E21: =SUM(G21:HF21) -> 1 | O21: 1
C22: =IFERROR(IF($E22>0,$E22/SUMIF($E$10:$E$70,">0")*$D$5,""),"") | D22: Aspen Minerals Group | E22: =SUM(G22:HF22) -> 0
C23: =IFERROR(IF($E23>0,$E23/SUMIF($E$10:$E$70,">0")*$D$5,""),"") | D23: Angale L. Best | E23: =SUM(G23:HF23) -> 0
C24: =IFERROR(IF($E24>0,$E24/SUMIF($E$10:$E$70,">0")*$D$5,""),"") | D24: Michael Best | E24: =SUM(G24:HF24) -> 0
C25: =IFERROR(IF($E25>0,$E25/SUMIF($E$10:$E$70,">0")*$D$5,""),"") | D25: Letha M. Crouse | E25: =SUM(G25:HF25) -> 0
C26: =IFERROR(IF($E26>0,$E26/SUMIF($E$10:$E$70,">0")*$D$5,""),"") | D26: Crouse Family Trust | E26: =SUM(G26:HF26) -> 0
C27: =IFERROR(IF($E27>0,$E27/SUMIF($E$10:$E$70,">0")*$D$5,""),"") | D27: Nanalee Faye Barnett | E27: =SUM(G27:HF27) -> -1 | O27: -1
C28: =IFERROR(IF($E28>0,$E28/SUMIF($E$10:$E$70,">0")*$D$5,""),"") -> 20 | D28: Arrowhead Resources, Inc. | E28: =SUM(G28:HF28) -> 3 | O28: 1 | P28: 1 | Q28: 1
C29: =IFERROR(IF($E29>0,$E29/SUMIF($E$10:$E$70,">0")*$D$5,""),"") | D29: Louise Ormand | E29: =SUM(G29:HF29) -> -1 | P29: -1
C30: =IFERROR(IF($E30>0,$E30/SUMIF($E$10:$E$70,">0")*$D$5,""),"") | D30: Glenn D. Mitchel | E30: =SUM(G30:HF30) -> -1 | Q30: -1
C31: =IFERROR(IF($E31>0,$E31/SUMIF($E$10:$E$70,">0")*$D$5,""),"") | D31: Jack E. Barnett, Deceased | E31: =SUM(G31:HF31) -> -1 | R31: -1
C32: =IFERROR(IF($E32>0,$E32/SUMIF($E$10:$E$70,">0")*$D$5,""),"") -> 20 | D32: The Public | E32: =SUM(G32:HF32) -> 3 | R32: 1 | U32: 1 | V32: 1
C33: =IFERROR(IF($E33>0,$E33/SUMIF($E$10:$E$70,">0")*$D$5,""),"") | D33: Hayhurst, Peggy J. Revoc Trust | E33: =SUM(G33:HF33) -> 0
C34: =IFERROR(IF($E34>0,$E34/SUMIF($E$10:$E$70,">0")*$D$5,""),"") | D34: Peggy J. | E34: =SUM(G34:HF34) -> 0
C35: =IFERROR(IF($E35>0,$E35/SUMIF($E$10:$E$70,">0")*$D$5,""),"") | D35: Bluebonnet Investments, Ltd. | E35: =SUM(G35:HF35) -> -1 | T35: -1
C36: =IFERROR(IF($E36>0,$E36/SUMIF($E$10:$E$70,">0")*$D$5,""),"") -> 6.6666667 | D36: White Birch, LP | E36: =SUM(G36:HF36) -> 1 | T36: 1
C37: =IFERROR(IF($E37>0,$E37/SUMIF($E$10:$E$70,">0")*$D$5,""),"") | D37: Glenn Douglas Mitchell, Deceased | E37: =SUM(G37:HF37) -> -1 | U37: -1
C38: =IFERROR(IF($E38>0,$E38/SUMIF($E$10:$E$70,">0")*$D$5,""),"") | D38: Evelyn Louise McLerran, Deceased | E38: =SUM(G38:HF38) -> -1 | V38: -1
C39: =IFERROR(IF($E39>0,$E39/SUMIF($E$10:$E$70,">0")*$D$5,""),"") | D39: Aspen Energy Group, Inc. | E39: =SUM(G39:HF39) -> -1 | W39: -1
C40: =IFERROR(IF($E40>0,$E40/SUMIF($E$10:$E$70,">0")*$D$5,""),"") -> 6.6666667 | D40: Crusader Energy Corporation | E40: =SUM(G40:HF40) -> 1 | W40: 1
C41: =IFERROR(IF($E41>0,$E41/SUMIF($E$10:$E$70,">0")*$D$5,""),"") | D41: Minion Investment Co | E41: =SUM(G41:HF41) -> 0
C42: =IFERROR(IF($E42>0,$E42/SUMIF($E$10:$E$70,">0")*$D$5,""),"") | D42: Brian L. Rice | E42: =SUM(G42:HF42) -> 0
C43: =IFERROR(IF($E43>0,$E43/SUMIF($E$10:$E$70,">0")*$D$5,""),"") -> 6.6666667 | D43: Prism Energy, Inc. | E43: =SUM(G43:HF43) -> 1 | Y43: 1
C44: =IFERROR(IF($E44>0,$E44/SUMIF($E$10:$E$70,">0")*$D$5,""),"") | D44: Petrohawk Energy Corporation | E44: =SUM(G44:HF44) -> 0
C45: =IFERROR(IF($E45>0,$E45/SUMIF($E$10:$E$70,">0")*$D$5,""),"") | D45: Petrohawk Properties, LP | E45: =SUM(G45:HF45) -> 0
C46: =IFERROR(IF($E46>0,$E46/SUMIF($E$10:$E$70,">0")*$D$5,""),"") | D46: Glenda Palmer | E46: =SUM(G46:HF46) -> 0
C47: =IFERROR(IF($E47>0,$E47/SUMIF($E$10:$E$70,">0")*$D$5,""),"") | D47: Richard Palmer | E47: =SUM(G47:HF47) -> 0
C48: =IFERROR(IF($E48>0,$E48/SUMIF($E$10:$E$70,">0")*$D$5,""),"") | D48: Palmer Family Trust | E48: =SUM(G48:HF48) -> 0
C49: =IFERROR(IF($E49>0,$E49/SUMIF($E$10:$E$70,">0")*$D$5,""),"") | D49: Glenda Ann Palmer | E49: =SUM(G49:HF49) -> 0
C50: =IFERROR(IF($E50>0,$E50/SUMIF($E$10:$E$70,">0")*$D$5,""),"") | D50: Mitchel, Glenn Douglas and Hazel Pearl Trust | E50: =SUM(G50:HF50) -> 0
C51: =IFERROR(IF($E51>0,$E51/SUMIF($E$10:$E$70,">0")*$D$5,""),"") | D51: Mitchel, Jack D. and Shonna A. Family Trust | E51: =SUM(G51:HF51) -> 0
C52: =IFERROR(IF($E52>0,$E52/SUMIF($E$10:$E$70,">0")*$D$5,""),"") | D52: Shonna Mitchel | E52: =SUM(G52:HF52) -> 0
C53: =IFERROR(IF($E53>0,$E53/SUMIF($E$10:$E$70,">0")*$D$5,""),"") | D53: Shonna A. Mitchel | E53: =SUM(G53:HF53) -> 0
C54: =IFERROR(IF($E54>0,$E54/SUMIF($E$10:$E$70,">0")*$D$5,""),"") | D54: Shonn | E54: =SUM(G54:HF54) -> 0
C55: =IFERROR(IF($E55>0,$E55/SUMIF($E$10:$E$70,">0")*$D$5,""),"") | D55: Gene G. Williams | E55: =SUM(G55:HF55) -> 0
... C70: =IFERROR(IF($E70>0,$E70/SUMIF($E$10:$E$70,">0")*$D$5,""),"") | D70: Psi Lke, LLC | E70: =SUM(G70:HF70) -> 0
C71: =E71*D$5 -> 0 | E71: =SUM(G71:HF71) -> 0
C72: =E72*D$5 -> 0 | E72: =SUM(G72:HF72) -> 0
C73: =E73*D$5 -> 0 | E73: =SUM(G73:HF73) -> 0
C74: =E74*D$5 -> 0 | E74: =SUM(G74:HF74) -> 0
C75: =E75*D$5 -> 0 | E75: =SUM(G75:HF75) -> 0
C76: =E76*D$5 -> 0 | E76: =SUM(G76:HF76) -> 0
C77: =E77*D$5 -> 0 | E77: =SUM(G77:HF77) -> 0
C78: =E78*D$5 -> 0 | E78: =SUM(G78:HF78) -> 0
C79: =E79*D$5 -> 0 | E79: =SUM(G79:HF79) -> 0
C80: =E80*D$5 -> 0 | E80: =SUM(G80:HF80) -> 0
C81: =E81*D$5 -> 0 | E81: =SUM(G81:HF81) -> 0
C82: =E82*D$5 -> 0 | E82: =SUM(G82:HF82) -> 0
... C177: =E177*D$5 -> 0 | E177: =SUM(G177:HF177) -> 0

Sheet Tract 5
E1: Instrument | H1: Patent | I1: Deed | J1: Final Decree | K1: Quit Claim Deed | L1: Quit Claim Mineral Deed | M1: Warranty Deed | N1: Warranty Deed | O1: Decree | P1: Quit Claim Deed | Q1: Joint Tenancy Warranty Deed | R1: Mineral Deed | S1: Warranty Deed | T1: Quit Claim Deed | U1: Mineral Deed | V1: Mineral Deed | W1: Mineral Deed | X1: Deed | Y1: Decree | Z1: Mineral Deed | AA1: Mineral Deed | AB1: Mineral Deed | AC1: Quit Claim Deed | AD1: Quit Claim Mineral Deed | AE1: Mineral Deed | AF1: Warranty Deed | AG1: Quit Claim | AH1: Quit Claim Deed | AI1: Warranty Deed | AJ1: Mineral Deed | AK1: Final Decree | AL1: Quit Claim Mineral Deed | AM1: Mineral Deed | AN1: Quit Claim Mineral Deed | AO1: Joint Tenancy Warranty Deed | AP1: Divorce Decree | AQ1: Quit Claim Deed | AR1: Quit Claim Mineral Deed | AS1: Quit Claim Mineral Deed | AT1: Joint Tenancy Quit Claim Mineral Deed | AU1: Warranty Deed | AV1: Mineral Deed | AW1: Mineral Deed | AX1: Final Decree
A2: 5 | B2: TRACT | D2: NW/4 partial, Lots 1 & 4, SE/4 SW/4 partial | E2: Image Number | H2: 1907-005379 | I2: 1988-004185 | J2: 1993-000918 | K2: 1995-003767 | L2: 1995-000748 | M2: 1996-002352 | N2: 1997-003023 | O2: 1999-005936 | P2: 2001-002190 | Q2: 2001-002496 | R2: 2002-003563 | S2: 2003-004685 | T2: 2004-000364 | U2: 2004-005738 | V2: 2004-005739 | W2: 2004-006577 | X2: 2005-000347 | Y2: 2005-002196 | Z2: 2005-004044 | AA2: 2005-004793 | AB2: 2005-005251 | AC2: 2007-001848 | AD2: 2008-004060 | AE2: 2008-006536 | AF2: 2009-002005 | AG2: 2009-002096 | AH2: 2009-002872 | AI2: 2009-002996 | AJ2: 2011-007826 | AK2: 2012-002191 | AL2: 2013-001724 | AM2: 2013-004163 | AN2: 2013-006129 | AO2: 2013-006415 | AP2: 2014-004525 | AQ2: 2016-001589 | AR2: 2016-001882 | AS2: 2020-001374 | AT2: 2025-001343 | AU2: 2025-003963 | AV2: 2026-000691 | AW2: 2026-001374 | AX2: 2026-002877
B3: DESCRIPTION | E3: Book / Page | H3: PAT003/495 | I3: 0981/0002 | J3: 1324/0022 | K3: 1459/0583 | L3: 1471/0574 | M3: 1510/0491 | N3: 1514/0525 | O3: 1600/0001 | P3: 1642/0532 | Q3: 1644/0460 | R3: 1688/0374 | S3: 1722/0449 | T3: 1735/0133 | U3: 1764/0344 | V3: 1764/0345 | W3: 1768/0339 | X3: 1775/0296 | Y3: 1784/0591 | Z3: 1794/0173 | AA3: 1797/0463 | AB3: 1800/0453 | AC3: 1872/0277 | AD3: 1919/0359 | AE3: 1937/0418 | AF3: 1956/0354 | AG3: 1958/0060 | AH3: 1963/0222 | AI3: 1964/0097 | AJ3: 2104/0537 | AK3: 2124/0117 | AL3: 2184/0570 | AM3: 2203/0395 | AN3: 2220/0118 | AO3: 2222/0536 | AP3: 2261/0255 | AQ3: 2337/0427 | AR3: 2342/0219 | AS3: 2450/0598 | AT3: 2617/0228 | AU3: 2638/0058 | AV3: 2682/0183 | AW3: 2688/0409 | AX3: 2700/0395
E4: Date | H4: 2752 | I4: 32329 | J4: 34032 | K4: 34778 | L4: 34950 | M4: 35429 | N4: 35479 | O4: 36511 | P4: 37029 | Q4: 37041 | R4: 37505 | S4: 37881 | T4: 38008 | U4: 38274 | V4: 38274 | W4: 38308 | X4: 38376 | Y4: 38455 | Z4: 38517 | AA4: 38548 | AB4: 38573 | AC4: 39197 | AD4: 39652 | AE4: 39748 | AF4: 39941 | AG4: 39947 | AH4: 40001 | AI4: 40011 | AJ4: 40876 | AK4: 40990 | AL4: 41372 | AM4: 41495 | AN4: 41596 | AO4: 41619 | AP4: 41834 | AQ4: 42556 | AR4: 42593 | AS4: 44076 | AT4: 45728 | AU4: 45840 | AV4: 46062 | AW4: 46092 | AX4: 46160
B5: TRACT ACRES | E5: Conveyance | H5: ARTI | I5: ARTI | J5: ARTI | K5: ARTI | L5: ARTI | M5: ARTI | N5: ARTI | O5: ARTI | P5: ARTI | Q5: ARTI | R5: ARTI | S5: ARTI | T5: ARTI | U5: ARTI | V5: ARTI | W5: ARTI | X5: ARTI | Y5: ARTI | Z5: ARTI | AA5: ARTI | AB5: ARTI | AC5: ARTI | AD5: ARTI | AE5: ARTI | AF5: ARTI | AG5: ARTI | AH5: ARTI | AI5: ARTI | AJ5: ARTI | AK5: ARTI | AL5: ARTI | AM5: ARTI | AN5: ARTI | AO5: ARTI | AP5: ARTI | AQ5: ARTI | AR5: ARTI | AS5: ARTI | AT5: ARTI | AU5: ARTI | AV5: ARTI | AW5: ARTI | AX5: ARTI
B6: BASE OGL | D6: Tract 5 | E6: =SUBTOTAL(9,E9:E203) -> 0 | F6: SURFACE | H6: =IF(H7=0,"","RECHECK") | I6: =IF(I7=0,"","RECHECK") | J6: =IF(J7=0,"","RECHECK") | K6: =IF(K7=0,"","RECHECK") | L6: =IF(L7=0,"","RECHECK") | M6: =IF(M7=0,"","RECHECK") | N6: =IF(N7=0,"","RECHECK") | O6: =IF(O7=0,"","RECHECK") | ... AB6: =IF(AB7=0,"","RECHECK") | AE6: =IF(AE7=0,"","RECHECK") | AF6: =IF(AF7=0,"","RECHECK") | AG6: =IF(AG7=0,"","RECHECK") | AH6: =IF(AH7=0,"","RECHECK") | AI6: =IF(AI7=0,"","RECHECK") | AJ6: =IF(AJ7=0,"","RECHECK") | AK6: =IF(AK7=0,"","RECHECK") | AL6: =IF(AL7=0,"","RECHECK") | ... FT6: =IF(FT7=0,"","RECHECK")
G7: =SUBTOTAL(9,G10:G204) -> 0 | H7: =SUBTOTAL(9,H10:H212) -> 0 | I7: =SUBTOTAL(9,I10:I212) -> 0 | J7: =SUBTOTAL(9,J10:J212) -> 0 | K7: =SUBTOTAL(9,K10:K212) -> 0 | L7: =SUBTOTAL(9,L10:L212) -> 0 | M7: =SUBTOTAL(9,M10:M212) -> 0 | N7: =SUBTOTAL(9,N10:N204) -> 0 | O7: =SUBTOTAL(9,O10:O204) -> 0 | P7: =SUBTOTAL(9,P10:P204) -> 0 | Q7: =SUBTOTAL(9,Q10:Q204) -> 0 | R7: =SUBTOTAL(9,R10:R204) -> 0 | S7: =SUBTOTAL(9,S10:S207) -> 0 | T7: =SUBTOTAL(9,T10:T204) -> 0 | U7: =SUBTOTAL(9,U10:U204) -> 0 | V7: =SUBTOTAL(9,V10:V204) -> 0 | W7: =SUBTOTAL(9,W10:W204) -> 0 | X7: =SUBTOTAL(9,X10:X204) -> 0 | Y7: =SUBTOTAL(9,Y10:Y204) -> 0 | Z7: =SUBTOTAL(9,Z10:Z207) -> 0 | AA7: 0 | AB7: =SUBTOTAL(9,AB10:AB209) -> 0 | AC7: =SUBTOTAL(9,AC10:AC212) -> 0 | AD7: =SUBTOTAL(9,AD10:AD206) -> 0 | AE7: =SUBTOTAL(9,AE10:AE206) -> 0 | AF7: =SUBTOTAL(9,AF10:AF206) -> 0 | AG7: =SUBTOTAL(9,AG10:AG206) -> 0 | AH7: =SUBTOTAL(9,AH10:AH207) -> 0 | AI7: =SUBTOTAL(9,AI10:AI203) -> 0 | AJ7: =SUBTOTAL(9,AJ10:AJ207) -> 0 | AK7: =SUBTOTAL(9,AK10:AK206) -> 0 | AL7: =SUBTOTAL(9,AL10:AL204) -> 0 | AM7: =SUBTOTAL(9,AM10:AM204) -> 0 | AN7: =SUBTOTAL(9,AN10:AN204) -> 0 | AO7: =SUBTOTAL(9,AO10:AO204) -> 0 | AP7: =SUBTOTAL(9,AP10:AP204) -> 0 | AQ7: =SUBTOTAL(9,AQ10:AQ204) -> 0 | AR7: =SUBTOTAL(9,AR10:AR204) -> 0 | AS7: =SUBTOTAL(9,AS10:AS204) -> 0 | ... FT7: =SUBTOTAL(9,FT10:FT204) -> 0
A8: NOTES | C8: NET ACRES | D8: OWNERS | E8: TOTAL
C10: =E10*D$5 -> 0 | D10: United States of America | E10: =SUM(G10:HM10) -> -1 | H10: -1
C11: =E11*D$5 -> 0 | D11: Leo Kennett | E11: =SUM(G11:HM11) -> 1 | H11: 1
C12: =E12*D$5 -> 0 | D12: Flag-redfern Oil Company | E12: =SUM(G12:HM12) -> 0
C13: =E13*D$5 -> 0 | D13: Eta-flag Royalty Trust | E13: =SUM(G13:HM13) -> 0
C14: =E14*D$5 -> 0 | D14: First City National Bank of Midland Trustee | E14: =SUM(G14:HM14) -> 0
C15: =E15*D$5 -> 0 | D15: Klopfenstein, John Estate of Dec | E15: =SUM(G15:HM15) -> 0
C16: =E16*D$5 -> 0 | D16: The Public | E16: =SUM(G16:HN16) -> 3 | O16: 1 | Y16: 1 | AK16: 1
C17: =E17*D$5 -> 0 | D17: Elanore Wheeler | E17: =SUM(G17:HN17) -> 0
C18: =E18*D$5 -> 0 | D18: Joseph Devenas | E18: =SUM(G18:HN18) -> 1 | AN18: 1
C19: =E19*D$5 -> 0 | D19: Joseph Devenas, Trustee | E19: =SUM(G19:HN19) -> 0
C20: =E20*D$5 -> 0 | D20: Charles R. Atha | E20: =SUM(G20:HN20) -> 0
C21: =E21*D$5 -> 0 | D21: Letty Atha | E21: =SUM(G21:HM21) -> 0
C22: =E22*D$5 -> 0 | D22: Charles E. Atha | E22: =SUM(G22:HM22) -> 0
C23: =E23*D$5 -> 0 | D23: Eula Cross | E23: =SUM(G23:HM23) -> 0
C24: =E24*D$5 -> 0 | D24: Floyd W. Atha | E24: =SUM(G24:HM24) -> 0
C25: =E25*D$5 -> 0 | D25: Nancy D. Atha | E25: =SUM(G25:HM25) -> 0
C26: =E26*D$5 -> 0 | D26: Leonard Herzperg | E26: =SUM(G26:HM26) -> 0
C27: =E27*D$5 -> 0 | D27: Mary Alice Herzperg | E27: =SUM(G27:HQ27) -> 0
C28: =E28*D$5 -> 0 | D28: Atha Letty Jane Deceased | E28: =SUM(G28:HQ28) -> -1 | O28: -1
C29: =E29*D$5 -> 0 | D29: Leonard Herzberg | E29: =SUM(G29:HQ29) -> 0
C30: =E30*D$5 -> 0 | D30: Mary Alice Herzberg | E30: =SUM(G30:HM30) -> 0
C31: =E31*D$5 -> 0 | D31: Carolyn Coots | E31: =SUM(G31:HM31) -> 0
C32: =E32*D$5 -> 0 | D32: Wendell Coots | E32: =SUM(G32:HM32) -> 0
C33: =E33*D$5 -> 0 | D33: Oleta Florene Flanagan | E33: =SUM(G33:HM33) -> -1 | R33: -1
C34: =E34*D$5 -> 0 | D34: Arrowhead Resources, Inc. | E34: =SUM(G34:HM34) -> 0 | R34: 1 | W34: 1 | AA34: -1 | AB34: -1
C35: =E35*D$5 -> 0 | D35: Kathy Bryant | E35: =SUM(G35:HM35) -> 0
C36: =E36*D$5 -> 0 | D36: William Bryant | E36: =SUM(G36:HM36) -> 0
C37: =E37*D$5 -> 0 | D37: John E. Mahoney, Trustee | E37: =SUM(G37:HV37) -> 0
C38: =E38*D$5 -> 0 | D38: Sandra Lorraine York | E38: =SUM(G38:HP38) -> -2 | U38: -1 | V38: -1
C39: =E39*D$5 -> 0 | D39: Koala Production Company | E39: =SUM(G39:HE39) -> 1 | U39: 1 | V39: 1 | AE39: -1
C40: =E40*D$5 -> 0 | D40: Sandra York | E40: =SUM(G40:HE40) -> -1 | W40: -1
C41: =E41*D$5 -> 0 | D41: Norbert J. Co-prsnl Repres Dickman | E41: =SUM(G41:HE41) -> 0
C42: =E42*D$5 -> 0 | D42: Robe | E42: =SUM(G42:HE42) -> 0
C43: =E43*D$5 -> 0 | D43: Fasken Land and Minerals, Ltd. | E43: =SUM(G43:HE43) -> 0
C44: =E44*D$5 -> 0 | D44: Virgil Mark Hambrook, Deceased | E44: =SUM(G44:HM44) -> -1 | Y44: -1
C45: =E45*D$5 -> 0 | D45: Koala Pordution Company | E45: =SUM(G45:HM45) -> -1 | Z45: -1
C46: =E46*D$5 -> 0 | D46: Chisholm Royalty Partners | E46: =SUM(G46:HM46) -> 1 | Z46: 1
C47: =E47*D$5 -> 0 | D47: Map2004-ok | E47: =SUM(G47:HM47) -> 2 | AA47: 1 | AB47: 1
C48: =E48*D$5 -> 0 | D48: Atha Nancy D. | E48: =SUM(G48:HM48) -> 0
C49: =E49*D$5 -> 0 | D49: Atha Floyd Revoc Trust | E49: =SUM(G49:HM49) -> 0
C50: =E50*D$5 -> 0 | D50: Floyd Atha, Trustee | E50: =SUM(G50:HM50) -> 0
C51: =E51*D$5 -> 0 | D51: Shawn S. Walters | E51: =SUM(G51:HM51) -> 0
C52: =E52*D$5 -> 0 | D52: Wayne A. Walters | E52: =SUM(G52:HM52) -> 0
C53: =E53*D$5 -> 0 | D53: Shawn S. Walters, Trustee | E53: =SUM(G53:HM53) -> 0
C54: =E54*D$5 -> 0 | D54: Wayne A. Walt | E54: =SUM(G54:HM54) -> 0
C55: =E55*D$5 -> 0 | D55: Koala Production Co | E55: =SUM(G55:HM55) -> 0
C56: =E56*D$5 -> 0 | D56: Fleshman Agency, Inc. | E56: =SUM(G56:HM56) -> -2 | AE56: 1 | AJ56: -1 | AL56: -1 | AM56: -1
C57: =E57*D$5 -> 0 | D57: Atha, Floyd and Nancy Rev Trust | E57: =SUM(G57:HM57) -> 0
C58: =E58*D$5 -> 0 | D58: Floyd C | E58: =SUM(G58:HM58) -> 0
C59: =E59*D$5 -> 0 | D59: Fuchs, Donnaleta Rev Trust | E59: =SUM(G59:HM59) -> 0
C60: =E60*D$5 -> 0 | D60: Donnaleta Fuchs, Trustee | E60: =SUM(G60:HM60) -> 0
C61: =E61*D$5 -> 0 | D61: Floyd Atha | E61: =SUM(G61:HM61) -> 0
C62: =E62*D$5 -> 0 | D62: Nancy Atha | E62: =SUM(G62:HM62) -> 0
C63: =E63*D$5 -> 0 | D63: Atha Revocable Trust, Floyd and Nancy | E63: =SUM(G63:HM63) -> 0
C64: =E64*D$5 -> 0 | D64: William E. Bryant | E64: =SUM(G64:HM64) -> 0
C65: =E65*D$5 -> 0 | D65: Clara Mae Bryan | E65: =SUM(G65:HM65) -> 0
C66: =E66*D$5 -> 0 | D66: George Kendall Bryan | E66: =SUM(G66:HM66) -> 0
C67: =E67*D$5 -> 0 | D67: G | E67: =SUM(G67:HM67) -> 0
C68: =E68*D$5 -> 0 | D68: Bryan Living Trust | E68: =SUM(G68:HM68) -> 0
... C73: =E73*D$5 -> 0 | D73: Fleshman Agency | E73: =SUM(G73:HM73) -> 0
C74: =E74*D$5 -> 0 | D74: Mekusukey Oil Company, LLC | E74: =SUM(G74:HM74) -> 3 | AJ74: 1 | AL74: 1 | AM74: 1
C75: =E75*D$5 -> 0 | D75: Fred A. Standiford | E75: =SUM(G75:HM75) -> -1 | AK75: -1
C76: =E76*D$5 -> 0 | D76: Martha Ann Devenas | E76: =SUM(G76:HM76) -> -1 | AN76: -1
C77: =E77*D$5 -> 0 | D77: Joseph A. Devenas Jr. | E77: =SUM(G77:HM77) -> 0
C78: =E78*D$5 -> 0 | D78: Barry Ross Kelley | E78: =SUM(G78:HM78) -> 0
C79: =E79*D$5 -> 0 | D79: Jill Ann Kelley | E79: =SUM(G79:HM79) -> 0
C80: =E80*D$5 -> 0 | D80: Rachael Elzabeth Newell | E80: =SUM(G80:HM80) -> 0
C81: =E81*D$5 -> 0 | D81: William Edgar Bryant | E81: =SUM(G81:HM81) -> -1 | AP81: -1
C82: =E82*D$5 -> 0 | D82: Kathy Lynn Bryant | E82: =SUM(G82:HM82) -> 1 | AP82: 1
C83: =E83*D$5 -> 0 | D83: Mariyln K. Bryan, Trustee | E83: =SUM(G83:HM83) -> 0
C84: =E84*D$5 -> 0 | D84: Katie C. Lucas | E84: =SUM(G84:HM84) -> 0
C85: =E85*D$5 -> 0 | D85: Matthew B. Lucas | E85: =SUM(G85:HM85) -> 0
C86: =E86*D$5 -> 0 | D86: Devon Energy Production Co | E86: =SUM(G86:HM86) -> 0
C87: =E87*D$5 -> 0 | D87: Tecolote Holdings | E87: =SUM(G87:HM87) -> 0
C88: =E88*D$5 -> 0 | D88: Janis Fern Campbell | E88: =SUM(G88:HM88) -> 0
C89: =E89*D$5 -> 0 | D89: Campbell Family Trust, Audy and Janis | E89: =SUM(G89:HM89) -> 0
C90: =E90*D$5 -> 0 | D90: Eleanor A/k/a Wheeler | E90: =SUM(G90:HM90) -> 0
C91: =E91*D$5 -> 0 | D91: Eleanore Wheeler | E91: =SUM(G91:HM91) -> 0
C92: =E92*D$5 -> 0 | D92: Shirley Wheeler | E92: =SUM(G92:HM92) -> 0
C93: =E93*D$5 -> 0 | D93: Rachael Elizabeth Newe | E93: =SUM(G93:HM93) -> 0
C94: =E94*D$5 -> 0 | D94: Newell Farms Trust | E94: =SUM(G94:HM94) -> 0
... C100: =E100*D$5 -> 0 | D100: Estate of Audy C. Campbell | E100: =SUM(G100:HM100) -> 0
C101: =E101*D$5 -> 0 | E101: =SUM(G101:HM101) -> 0
C102: =E102*D$5 -> 0 | E102: =SUM(G102:HM102) -> 0
C103: =E103*D$5 -> 0 | E103: =SUM(G103:HM103) -> 0
C104: =E104*D$5 -> 0 | E104: =SUM(G104:HM104) -> 0
C105: =E105*D$5 -> 0 | E105: =SUM(G105:HM105) -> 0
C106: =E106*D$5 -> 0 | E106: =SUM(G106:HM106) -> 0
C107: =E107*D$5 -> 0 | E107: =SUM(G107:HM107) -> 0
C108: =E108*D$5 -> 0 | E108: =SUM(G108:HM108) -> 0
C109: =E109*D$5 -> 0 | E109: =SUM(G109:HM109) -> 0
C110: =E110*D$5 -> 0 | E110: =SUM(G110:HM110) -> 0
...

Sheet Tract 6
E1: Instrument | H1: Deed | I1: Deed | J1: Deed | K1: Deed | L1: Mineral Deed | M1: Mineral Deed | N1: Mineral Deed | O1: Mineral Deed
A2: 6 | B2: TRACT | D2: W/2 SW/4, containing 80 acres, more or less | E2: Image Number | O2: 2015-002791
B3: DESCRIPTION | E3: Book / Page | H3: D00009/0303 | I3: D00011/0448 | J3: D00029/0382 | K3: 237/0370 | L3: 1583/0405 | M3: 1949/0217 | N3: 2251/0022 | O3: 2309/0236
E4: Date | H4: 2601 | I4: 3189 | J4: 7291 | K4: 28583 | L4: 36270 | M4: 39874 | N4: 41766 | O4: 42255
B5: TRACT ACRES | D5: 80 | E5: Conveyance | H5: ARTI | I5: ARTI | J5: ARTI | K5: ARTI | L5: ARTI | M5: ARTI | N5: ARTI | O5: ARTI
B6: BASE OGL | C6: 80 | D6: Tract 6 | E6: =SUBTOTAL(9,E9:E199) -> 0 | F6: SURFACE | AE6: =IF(AE7=0,"","RECHECK") | AF6: =IF(AF7=0,"","RECHECK") | AG6: =IF(AG7=0,"","RECHECK") | AH6: =IF(AH7=0,"","RECHECK") | AI6: =IF(AI7=0,"","RECHECK") | AJ6: =IF(AJ7=0,"","RECHECK") | AK6: =IF(AK7=0,"","RECHECK") | AL6: =IF(AL7=0,"","RECHECK") | ... FT6: =IF(FT7=0,"","RECHECK")
G7: =SUBTOTAL(9,G10:G200) -> 0 | H7: =IF(H9=0,"","RECHECK") | I7: =IF(I9=0,"","RECHECK") | J7: =IF(J9=0,"","RECHECK") | K7: =IF(K9=0,"","RECHECK") | L7: =IF(L9=0,"","RECHECK") | M7: =IF(M9=0,"","RECHECK") | N7: =IF(N9=0,"","RECHECK") | O7: =IF(O9=0,"","RECHECK") | AC7: =SUBTOTAL(9,AC10:AC208) -> 0 | AD7: =SUBTOTAL(9,AD10:AD202) -> 0 | AE7: =SUBTOTAL(9,AE10:AE202) -> 0 | AF7: =SUBTOTAL(9,AF10:AF202) -> 0 | AG7: =SUBTOTAL(9,AG10:AG202) -> 0 | AH7: =SUBTOTAL(9,AH10:AH203) -> 0 | AI7: =SUBTOTAL(9,AI10:AI199) -> 0 | AJ7: =SUBTOTAL(9,AJ10:AJ203) -> 0 | AK7: =SUBTOTAL(9,AK10:AK202) -> 0 | AL7: =SUBTOTAL(9,AL10:AL200) -> 0 | AM7: =SUBTOTAL(9,AM10:AM200) -> 0 | AN7: =SUBTOTAL(9,AN10:AN200) -> 0 | AO7: =SUBTOTAL(9,AO10:AO200) -> 0 | AP7: =SUBTOTAL(9,AP10:AP200) -> 0 | AQ7: =SUBTOTAL(9,AQ10:AQ200) -> 0 | AR7: =SUBTOTAL(9,AR10:AR200) -> 0 | AS7: =SUBTOTAL(9,AS10:AS200) -> 0 | ... FT7: =SUBTOTAL(9,FT10:FT200) -> 0
A8: NOTES | C8: NET ACRES | D8: OWNERS | E8: TOTAL
H9: =SUM(H10:H36) -> 0 | I9: =SUM(I10:I36) -> 0 | J9: =SUM(J10:J36) -> 0 | K9: =SUM(K10:K36) -> 0 | L9: =SUM(L10:L36) -> 0 | M9: =SUM(M10:M36) -> 0 | N9: =SUM(N10:N36) -> 0 | O9: =SUM(O10:O36) -> 0
C10: =IFERROR(IF($E10>0,$E10/SUMIF($E$10:$E$18,">0")*$D$5,""),"") | D10: Charles T. & Sadie N. Kennett | E10: =SUM(H10:O10) -> -1 | H10: -1
C11: =IFERROR(IF($E11>0,$E11/SUMIF($E$10:$E$18,">0")*$D$5,""),"") | D11: John G. Lancaster | E11: =SUM(H11:O11) -> 0 | H11: 1 | I11: -1
C12: =IFERROR(IF($E12>0,$E12/SUMIF($E$10:$E$18,">0")*$D$5,""),"") | D12: Eugene S. Repass | E12: =SUM(H12:O12) -> 0 | I12: 1 | J12: -1
C13: =IFERROR(IF($E13>0,$E13/SUMIF($E$10:$E$18,">0")*$D$5,""),"") | D13: William C. Bain | E13: =SUM(H13:O13) -> 0 | J13: 1 | K13: -1
C14: =IFERROR(IF($E14>0,$E14/SUMIF($E$10:$E$18,">0")*$D$5,""),"") | D14: Opal L. Fuchs | E14: =SUM(H14:O14) -> 0 | K14: 1 | L14: -1
C15: =IFERROR(IF($E15>0,$E15/SUMIF($E$10:$E$18,">0")*$D$5,""),"") | D15: Jesse W. Fuchs / Jinkee D. Acuero Fuchs | E15: =SUM(H15:O15) -> 0 | L15: 1 | M15: -1
C16: =IFERROR(IF($E16>0,$E16/SUMIF($E$10:$E$18,">0")*$D$5,""),"") | D16: Jessica Corry Fuchs | E16: =SUM(H16:O16) -> 0 | M16: 1 | N16: -1
C17: =IFERROR(IF($E17>0,$E17/SUMIF($E$10:$E$18,">0")*$D$5,""),"") -> 40 | D17: Jesse William (a/k/a William Jesse) Fuchs | E17: =SUM(H17:O17) -> 0.5 | N17: 1 | O17: -0.5
C18: =IFERROR(IF($E18>0,$E18/SUMIF($E$10:$E$18,">0")*$D$5,""),"") -> 40 | D18: Fuchs Trust — Jinkee D. Acuero Fuchs, Trustee | E18: =SUM(H18:O18) -> 0.5 | O18: 0.5
C19: =SUM(C10:C18) -> 80 | D19: TOTAL NET ACRES (= tract acres)

Sheet Tract 7
E1: Instrument | H1: Patent | I1: Mineral Deed | J1: Mineral Deed | K1: Warranty Deed | L1: Mineral Deed | M1: Mineral Deed | N1: Mineral Deed | O1: Mineral Deed | P1: Decree | Q1: Mineral Deed | R1: Warranty Deed | S1: Final Decree | T1: Mineral Deed | U1: Mineral Deed | V1: Mineral Deed | W1: Quit Claim Deed | X1: Joint Tenancy Warranty Deed | Y1: Trustees Mineral Deed | Z1: Trustees Mineral Deed | AA1: Trustees Mineral Deed | AB1: Final Decree | AC1: Mineral Deed | AD1: Mineral Deed | AE1: Quit Claim Mineral Deed | AF1: Mineral Deed
A2: 7 | B2: TRACT | D2: NE/4 SE/4, containing 40 acres, more or less | E2: Image Number | H2: 1909-002932 | I2: 1994-006415 | J2: 1995-003404 | K2: 1996-002352 | L2: 2000-007685 | M2: 2001-000957 | N2: 2001-001414 | O2: 2001-001463 | P2: 2001-002342 | Q2: 2002-004595 | R2: 2003-004945 | S2: 2004-000099 | T2: 2004-005901 | U2: 2005-000158 | V2: 2005-007551 | W2: 2007-001848 | X2: 2008-003157 | Y2: 2011-001007 | Z2: 2011-001008 | AA2: 2011-001009 | AB2: 2013-000518 | AC2: 2014-003089 | AD2: 2014-006293 | AE2: 2018-002650 | AF2: 2021-001068
B3: DESCRIPTION | E3: Book / Page | H3: PAT006/7 | I3: 1422/0009 | J3: 1457/0173 | K3: 1510/0491 | L3: 1611/0503 | M3: 1637/0026 | N3: 1639/0206 | O3: 1639/0426 | P3: 1643/0389 | Q3: 1695/0238 | R3: 1724/0582 | S3: 1734/0014 | T3: 1765/0306 | U3: 1774/0309 | V3: 1812/0138 | W3: 1872/0277 | X3: 1914/0155 | Y3: 2063/0491 | Z3: 2063/0494 | AA3: 2063/0497 | AB3: 2177/0033 | AC3: 2251/0529 | AD3: 2273/0223 | AE3: 2406/0228 | AF3: 2467/0476
E4: Date | H4: 3652 | I4: 34542 | J4: 34754 | K4: 35429 | L4: 36647 | M4: 36957 | N4: 36987 | O4: 36991 | P4: 37034 | Q4: 37592 | R4: 37897 | S4: 37994 | T4: 38281 | U4: 38365 | V4: 38658 | W4: 39197 | X4: 39612 | Y4: 40592 | Z4: 40592 | AA4: 40592 | AB4: 41304 | AC4: 41774 | AD4: 41927 | AE4: 43382 | AF4: 44377
B5: TRACT ACRES | D5: 40 | E5: Conveyance | H5: ARTI | I5: ARTI | J5: ARTI | K5: ARTI | L5: ARTI | M5: ARTI | N5: ARTI | O5: ARTI | P5: ARTI | Q5: ARTI | R5: ARTI | S5: ARTI | T5: ARTI | U5: ARTI | V5: ARTI | W5: ARTI | X5: ARTI | Y5: ARTI | Z5: ARTI | AA5: ARTI | AB5: ARTI | AC5: ARTI | AD5: ARTI | AE5: ARTI | AF5: ARTI
B6: BASE OGL | C6: 40 | D6: Tract 7 | E6: =SUBTOTAL(9,E9:E203) -> 0 | F6: SURFACE | H6: =IF(H7=0,"","RECHECK") | I6: =IF(I7=0,"","RECHECK") | J6: =IF(J7=0,"","RECHECK") | K6: =IF(K7=0,"","RECHECK") | L6: =IF(L7=0,"","RECHECK") | M6: =IF(M7=0,"","RECHECK") | N6: =IF(N7=0,"","RECHECK") | O6: =IF(O7=0,"","RECHECK") | ... AB6: =IF(AB7=0,"","RECHECK") | AE6: =IF(AE7=0,"","RECHECK") | AF6: =IF(AF7=0,"","RECHECK") | AG6: =IF(AG7=0,"","RECHECK") | AH6: =IF(AH7=0,"","RECHECK") | AI6: =IF(AI7=0,"","RECHECK") | AJ6: =IF(AJ7=0,"","RECHECK") | AK6: =IF(AK7=0,"","RECHECK") | AL6: =IF(AL7=0,"","RECHECK") | ... FT6: =IF(FT7=0,"","RECHECK")
G7: =SUBTOTAL(9,G10:G204) -> 0 | H7: =SUBTOTAL(9,H10:H212) -> 0 | I7: =SUBTOTAL(9,I10:I212) -> 0 | J7: =SUBTOTAL(9,J10:J212) -> 0 | K7: =SUBTOTAL(9,K10:K212) -> 0 | L7: =SUBTOTAL(9,L10:L212) -> 0 | M7: =SUBTOTAL(9,M10:M212) -> 0 | N7: =SUBTOTAL(9,N10:N204) -> 0 | O7: =SUBTOTAL(9,O10:O204) -> 0 | P7: =SUBTOTAL(9,P10:P204) -> 0 | Q7: =SUBTOTAL(9,Q10:Q204) -> 0 | R7: =SUBTOTAL(9,R10:R204) -> 0 | S7: =SUBTOTAL(9,S10:S207) -> 0 | T7: =SUBTOTAL(9,T10:T204) -> 0 | U7: =SUBTOTAL(9,U10:U204) -> 0 | V7: =SUBTOTAL(9,V10:V204) -> 0 | W7: =SUBTOTAL(9,W10:W204) -> 0 | X7: =SUBTOTAL(9,X10:X204) -> 0 | Y7: =SUBTOTAL(9,Y10:Y204) -> 0 | Z7: =SUBTOTAL(9,Z10:Z207) -> 0 | AA7: 0 | AB7: =SUBTOTAL(9,AB10:AB209) -> 0 | AC7: =SUBTOTAL(9,AC10:AC212) -> 0 | AD7: =SUBTOTAL(9,AD10:AD206) -> 0 | AE7: =SUBTOTAL(9,AE10:AE206) -> 0 | AF7: =SUBTOTAL(9,AF10:AF206) -> 0 | AG7: =SUBTOTAL(9,AG10:AG206) -> 0 | AH7: =SUBTOTAL(9,AH10:AH207) -> 0 | AI7: =SUBTOTAL(9,AI10:AI203) -> 0 | AJ7: =SUBTOTAL(9,AJ10:AJ207) -> 0 | AK7: =SUBTOTAL(9,AK10:AK206) -> 0 | AL7: =SUBTOTAL(9,AL10:AL204) -> 0 | AM7: =SUBTOTAL(9,AM10:AM204) -> 0 | AN7: =SUBTOTAL(9,AN10:AN204) -> 0 | AO7: =SUBTOTAL(9,AO10:AO204) -> 0 | AP7: =SUBTOTAL(9,AP10:AP204) -> 0 | AQ7: =SUBTOTAL(9,AQ10:AQ204) -> 0 | AR7: =SUBTOTAL(9,AR10:AR204) -> 0 | AS7: =SUBTOTAL(9,AS10:AS204) -> 0 | ... FT7: =SUBTOTAL(9,FT10:FT204) -> 0
A8: NOTES | C8: NET ACRES | D8: OWNERS | E8: TOTAL
H9: 1 | I9: 1 | J9: 1 | K9: 1 | L9: 1 | M9: 1 | N9: 1 | O9: 1 | P9: 1 | Q9: 1 | R9: 1 | S9: 1 | T9: 1 | U9: 1 | V9: 1 | W9: 1 | X9: 1 | Y9: 1 | Z9: 1 | AA9: 1 | AB9: 1 | AC9: 1 | AD9: 1 | AE9: 1 | AF9: 1
C10: =IFERROR(IF($E10>0,$E10/SUMIF($E$10:$E$65,">0")*$D$5,""),"") | D10: United States of America | E10: {=SUMPRODUCT(H$9:AF$9,IF(ISNUMBER(H10:AF10),H10:AF10,0))} -> -1 | H10: -1
C11: =IFERROR(IF($E11>0,$E11/SUMIF($E$10:$E$65,">0")*$D$5,""),"") -> 3.3333333 | D11: Ernest Brooks | E11: {=SUMPRODUCT(H$9:AF$9,IF(ISNUMBER(H11:AF11),H11:AF11,0))} -> 1 | H11: 1
C12: =IFERROR(IF($E12>0,$E12/SUMIF($E$10:$E$65,">0")*$D$5,""),"") | D12: Hayhurst Oil Properties, Inc. | E12: {=SUMPRODUCT(H$9:AF$9,IF(ISNUMBER(H12:AF12),H12:AF12,0))} -> -1 | I12: -1
C13: =IFERROR(IF($E13>0,$E13/SUMIF($E$10:$E$65,">0")*$D$5,""),"") -> 3.3333333 | D13: Nam Corporation | E13: {=SUMPRODUCT(H$9:AF$9,IF(ISNUMBER(H13:AF13),H13:AF13,0))} -> 1 | I13: 1
C14: =IFERROR(IF($E14>0,$E14/SUMIF($E$10:$E$65,">0")*$D$5,""),"") | D14: Tripco, Inc. | E14: {=SUMPRODUCT(H$9:AF$9,IF(ISNUMBER(H14:AF14),H14:AF14,0))} -> -2 | J14: -1 | V14: -1
C15: =IFERROR(IF($E15>0,$E15/SUMIF($E$10:$E$65,">0")*$D$5,""),"") -> 3.3333333 | D15: Prudential Securities | E15: {=SUMPRODUCT(H$9:AF$9,IF(ISNUMBER(H15:AF15),H15:AF15,0))} -> 1 | J15: 1
C16: =IFERROR(IF($E16>0,$E16/SUMIF($E$10:$E$65,">0")*$D$5,""),"") | D16: Eula Cross | E16: {=SUMPRODUCT(H$9:AF$9,IF(ISNUMBER(H16:AF16),H16:AF16,0))} -> 0
C17: =IFERROR(IF($E17>0,$E17/SUMIF($E$10:$E$65,">0")*$D$5,""),"") | D17: Floyd W. Atha | E17: {=SUMPRODUCT(H$9:AF$9,IF(ISNUMBER(H17:AF17),H17:AF17,0))} -> 0
C18: =IFERROR(IF($E18>0,$E18/SUMIF($E$10:$E$65,">0")*$D$5,""),"") | D18: Nancy D. Atha | E18: {=SUMPRODUCT(H$9:AF$9,IF(ISNUMBER(H18:AF18),H18:AF18,0))} -> 0
C19: =IFERROR(IF($E19>0,$E19/SUMIF($E$10:$E$65,">0")*$D$5,""),"") | D19: Fer-scher Exploration, LLC | E19: {=SUMPRODUCT(H$9:AF$9,IF(ISNUMBER(H19:AF19),H19:AF19,0))} -> -1 | L19: -1
C20: =IFERROR(IF($E20>0,$E20/SUMIF($E$10:$E$65,">0")*$D$5,""),"") -> 3.3333333 | D20: Aspen Minerals Group | E20: {=SUMPRODUCT(H$9:AF$9,IF(ISNUMBER(H20:AF20),H20:AF20,0))} -> 1 | L20: 1
C21: =IFERROR(IF($E21>0,$E21/SUMIF($E$10:$E$65,">0")*$D$5,""),"") | D21: Nanalee Faye Barnett | E21: {=SUMPRODUCT(H$9:AF$9,IF(ISNUMBER(H21:AF21),H21:AF21,0))} -> -1 | M21: -1
C22: =IFERROR(IF($E22>0,$E22/SUMIF($E$10:$E$65,">0")*$D$5,""),"") -> 10 | D22: Arrowhead Resources, Inc. | E22: {=SUMPRODUCT(H$9:AF$9,IF(ISNUMBER(H22:AF22),H22:AF22,0))} -> 3 | M22: 1 | N22: 1 | O22: 1
C23: =IFERROR(IF($E23>0,$E23/SUMIF($E$10:$E$65,">0")*$D$5,""),"") | D23: Louise Ormand | E23: {=SUMPRODUCT(H$9:AF$9,IF(ISNUMBER(H23:AF23),H23:AF23,0))} -> -1 | N23: -1
C24: =IFERROR(IF($E24>0,$E24/SUMIF($E$10:$E$65,">0")*$D$5,""),"") | D24: Glenn D. Mitchel | E24: {=SUMPRODUCT(H$9:AF$9,IF(ISNUMBER(H24:AF24),H24:AF24,0))} -> -1 | O24: -1
C25: =IFERROR(IF($E25>0,$E25/SUMIF($E$10:$E$65,">0")*$D$5,""),"") | D25: Jack E. Barnett, Deceased | E25: {=SUMPRODUCT(H$9:AF$9,IF(ISNUMBER(H25:AF25),H25:AF25,0))} -> -1 | P25: -1
C26: =IFERROR(IF($E26>0,$E26/SUMIF($E$10:$E$65,">0")*$D$5,""),"") -> 6.6666667 | D26: The Public | E26: {=SUMPRODUCT(H$9:AF$9,IF(ISNUMBER(H26:AF26),H26:AF26,0))} -> 2 | P26: 1 | S26: 1
C27: =IFERROR(IF($E27>0,$E27/SUMIF($E$10:$E$65,">0")*$D$5,""),"") | D27: Hayhurst, Peggy J. Revoc Trust | E27: {=SUMPRODUCT(H$9:AF$9,IF(ISNUMBER(H27:AF27),H27:AF27,0))} -> 0
C28: =IFERROR(IF($E28>0,$E28/SUMIF($E$10:$E$65,">0")*$D$5,""),"") | D28: Peggy J. | E28: {=SUMPRODUCT(H$9:AF$9,IF(ISNUMBER(H28:AF28),H28:AF28,0))} -> 0
C29: =IFERROR(IF($E29>0,$E29/SUMIF($E$10:$E$65,">0")*$D$5,""),"") | D29: Bluebonnet Investments, Ltd. | E29: {=SUMPRODUCT(H$9:AF$9,IF(ISNUMBER(H29:AF29),H29:AF29,0))} -> -1 | R29: -1
C30: =IFERROR(IF($E30>0,$E30/SUMIF($E$10:$E$65,">0")*$D$5,""),"") -> 3.3333333 | D30: White Birch, LP | E30: {=SUMPRODUCT(H$9:AF$9,IF(ISNUMBER(H30:AF30),H30:AF30,0))} -> 1 | R30: 1
C31: =IFERROR(IF($E31>0,$E31/SUMIF($E$10:$E$65,">0")*$D$5,""),"") | D31: Evelyn Louise McLerran, Deceased | E31: {=SUMPRODUCT(H$9:AF$9,IF(ISNUMBER(H31:AF31),H31:AF31,0))} -> -1 | S31: -1
C32: =IFERROR(IF($E32>0,$E32/SUMIF($E$10:$E$65,">0")*$D$5,""),"") | D32: Aspen Energy Group, Inc. | E32: {=SUMPRODUCT(H$9:AF$9,IF(ISNUMBER(H32:AF32),H32:AF32,0))} -> -1 | T32: -1
C33: =IFERROR(IF($E33>0,$E33/SUMIF($E$10:$E$65,">0")*$D$5,""),"") -> 3.3333333 | D33: Crusader Energy Corporation | E33: {=SUMPRODUCT(H$9:AF$9,IF(ISNUMBER(H33:AF33),H33:AF33,0))} -> 1 | T33: 1
C34: =IFERROR(IF($E34>0,$E34/SUMIF($E$10:$E$65,">0")*$D$5,""),"") | D34: Minion Investment Co | E34: {=SUMPRODUCT(H$9:AF$9,IF(ISNUMBER(H34:AF34),H34:AF34,0))} -> 0
C35: =IFERROR(IF($E35>0,$E35/SUMIF($E$10:$E$65,">0")*$D$5,""),"") | D35: Brian L. Rice | E35: {=SUMPRODUCT(H$9:AF$9,IF(ISNUMBER(H35:AF35),H35:AF35,0))} -> 0
C36: =IFERROR(IF($E36>0,$E36/SUMIF($E$10:$E$65,">0")*$D$5,""),"") -> 3.3333333 | D36: Prism Energy, Inc. | E36: {=SUMPRODUCT(H$9:AF$9,IF(ISNUMBER(H36:AF36),H36:AF36,0))} -> 1 | V36: 1
C37: =IFERROR(IF($E37>0,$E37/SUMIF($E$10:$E$65,">0")*$D$5,""),"") | D37: Atha Nancy D. | E37: {=SUMPRODUCT(H$9:AF$9,IF(ISNUMBER(H37:AF37),H37:AF37,0))} -> 0
C38: =IFERROR(IF($E38>0,$E38/SUMIF($E$10:$E$65,">0")*$D$5,""),"") | D38: Atha Floyd Revoc Trust | E38: {=SUMPRODUCT(H$9:AF$9,IF(ISNUMBER(H38:AF38),H38:AF38,0))} -> 0
C39: =IFERROR(IF($E39>0,$E39/SUMIF($E$10:$E$65,">0")*$D$5,""),"") | D39: Floyd Atha, Trustee | E39: {=SUMPRODUCT(H$9:AF$9,IF(ISNUMBER(H39:AF39),H39:AF39,0))} -> 0
C40: =IFERROR(IF($E40>0,$E40/SUMIF($E$10:$E$65,">0")*$D$5,""),"") | D40: Floyd Co Atha, Trustee | E40: {=SUMPRODUCT(H$9:AF$9,IF(ISNUMBER(H40:AF40),H40:AF40,0))} -> 0
C41: =IFERROR(IF($E41>0,$E41/SUMIF($E$10:$E$65,">0")*$D$5,""),"") | D41: Nancy Co Atha, Trustee | E41: {=SUMPRODUCT(H$9:AF$9,IF(ISNUMBER(H41:AF41),H41:AF41,0))} -> 0
C42: =IFERROR(IF($E42>0,$E42/SUMIF($E$10:$E$65,">0")*$D$5,""),"") | D42: Danielle Delane Tucker | E42: {=SUMPRODUCT(H$9:AF$9,IF(ISNUMBER(H42:AF42),H42:AF42,0))} -> 0
C43: =IFERROR(IF($E43>0,$E43/SUMIF($E$10:$E$65,">0")*$D$5,""),"") | D43: Monte Earl Tucker | E43: {=SUMPRODUCT(H$9:AF$9,IF(ISNUMBER(H43:AF43),H43:AF43,0))} -> 0
C44: =IFERROR(IF($E44>0,$E44/SUMIF($E$10:$E$65,">0")*$D$5,""),"") | D44: Glenda Palmer | E44: {=SUMPRODUCT(H$9:AF$9,IF(ISNUMBER(H44:AF44),H44:AF44,0))} -> 0
C45: =IFERROR(IF($E45>0,$E45/SUMIF($E$10:$E$65,">0")*$D$5,""),"") | D45: Richard Palmer | E45: {=SUMPRODUCT(H$9:AF$9,IF(ISNUMBER(H45:AF45),H45:AF45,0))} -> 0
C46: =IFERROR(IF($E46>0,$E46/SUMIF($E$10:$E$65,">0")*$D$5,""),"") | D46: Palmer Family Trust | E46: {=SUMPRODUCT(H$9:AF$9,IF(ISNUMBER(H46:AF46),H46:AF46,0))} -> 0
C47: =IFERROR(IF($E47>0,$E47/SUMIF($E$10:$E$65,">0")*$D$5,""),"") | D47: Glenda Ann Palmer | E47: {=SUMPRODUCT(H$9:AF$9,IF(ISNUMBER(H47:AF47),H47:AF47,0))} -> 0
C48: =IFERROR(IF($E48>0,$E48/SUMIF($E$10:$E$65,">0")*$D$5,""),"") | D48: Mitchel, Glenn Douglas and Hazel Pearl Trust | E48: {=SUMPRODUCT(H$9:AF$9,IF(ISNUMBER(H48:AF48),H48:AF48,0))} -> 0
... C65: =IFERROR(IF($E65>0,$E65/SUMIF($E$10:$E$65,">0")*$D$5,""),"") | D65: Psi Lke, LLC | E65: {=SUMPRODUCT(H$9:AF$9,IF(ISNUMBER(H65:AF65),H65:AF65,0))} -> 0
C66: =SUM(C10:C65) -> 40 | D66: TOTAL NET ACRES (= tract acres)

Sheet Tract 8
E1: Instrument | H1: Patent | I1: Quit Claim Deed | J1: Mineral Deed | K1: Final Decree | L1: Quit Claim Mineral Deed | M1: Quit Claim Mineral Deed | N1: Mineral Deed | O1: Mineral Deed | P1: Mineral Deed | Q1: Mineral Deed | R1: Mineral Deed | S1: Mineral Deed | T1: Mineral Deed | U1: Mineral Deed | V1: Mineral Deed | W1: Quit Claim Mineral Deed | X1: Mineral Deed | Y1: Mineral Deed | Z1: Mineral Deed | AA1: Mineral Deed | AB1: Mineral Deed | AC1: Quit Claim Deed | AD1: Deed | AE1: Mineral Deed | AF1: Mineral Deed | AG1: Mineral Deed | AH1: Mineral Deed | AI1: Mineral Deed | AJ1: Mineral Deed | AK1: Mineral Deed | AL1: Mineral Deed | AM1: Mineral Deed | AN1: Mineral Deed | AO1: Final Decree | AP1: Mineral Deed | AQ1: Mineral Deed | AR1: Quit Claim Mineral Deed | AS1: Mineral Deed | AT1: Mineral Deed | AU1: Mineral Deed | AV1: Mineral Deed | AW1: Deed | AX1: Mineral Deed | AY1: Mineral Deed | AZ1: Mineral Deed | BA1: Mineral Deed | BB1: Mineral Deed | BC1: Mineral Deed | BD1: Mineral Deed | BE1: Final Decree | BF1: Mineral Deed | BG1: Mineral Deed | BH1: Mineral Deed | BI1: Mineral Deed | BJ1: Quit Claim Mineral Deed | BK1: Mineral Deed | BL1: Mineral Deed | BM1: Mineral Deed | BN1: Mineral Deed | BO1: Mineral Deed | BP1: Mineral Deed | BQ1: Final Decree
A2: 8 | B2: TRACT | D2: W/2 SE/4, SE/4 SE/4, containing 120 acres, more or less | E2: Image Number | I2: 1995-004151 | J2: 1995-000396 | K2: 1995-001954 | L2: 1998-000584 | M2: 1998-000907 | N2: 1999-002219 | O2: 1999-002220 | P2: 1999-002739 | Q2: 1999-003363 | R2: 1999-003368 | S2: 1999-003364 | T2: 1999-003365 | U2: 1999-003366 | V2: 1999-003367 | W2: 2000-010180 | X2: 2001-000103 | Y2: 2001-000921 | Z2: 2001-000926 | AA2: 2001-000927 | AB2: 2002-004378 | AC2: 2003-003131 | AD2: 2005-000347 | AE2: 2005-001909 | AF2: 2005-003389 | AG2: 2005-007117 | AH2: 2005-007116 | AI2: 2005-007119 | AJ2: 2005-007120 | AK2: 2005-007540 | AL2: 2005-007541 | AM2: 2006-003765 | AN2: 2007-001374 | AO2: 2007-005167 | AP2: 2008-007325 | AQ2: 2009-000895 | AR2: 2010-002337 | AS2: 2010-005993 | AT2: 2010-007125 | AU2: 2010-008922 | AV2: 2011-003023 | AW2: 2011-007728 | AX2: 2011-007729 | AY2: 2011-008134 | AZ2: 2012-002930 | BA2: 2012-004060 | BB2: 2013-006083 | BC2: 2013-006585 | BD2: 2014-002935 | BE2: 2014-004286 | BF2: 2015-000877 | BG2: 2015-002791 | BH2: 2015-003284 | BI2: 2019-001747 | BJ2: 2020-001650 | BK2: 2021-001774 | BL2: 2023-002269 | BM2: 2025-002464 | BN2: 2025-002463 | BO2: 2025-005448 | BP2: 2025-005451 | BQ2: 2026-003315
B3: DESCRIPTION | E3: Book / Page | H3: PAT006/74 | I3: 1462/0131 | J3: 1470/0059 | K3: 1479/0191 | L3: 1564/0310 | M3: 1567/0245 | N3: 1576/0219 | O3: 1576/0222 | P3: 1579/0358 | Q3: 1583/0391 | R3: 1583/0426 | S3: 1583/0398 | T3: 1583/0405 | U3: 1583/0412 | V3: 1583/0419 | W3: 1625/0440 | X3: 1631/0416 | Y3: 1636/0544 | Z3: 1636/0554 | AA3: 1636/0556 | AB3: 1694/0156 | AC3: 1714/0504 | AD3: 1775/0296 | AE3: 1783/0306 | AF3: 1790/0386 | AG3: 1810/0016 | AH3: 1810/0015 | AI3: 1810/0018 | AJ3: 1810/0019 | AK3: 1812/0120 | AL3: 1812/0121 | AM3: 1838/0136 | AN3: 1869/0351 | AO3: 1892/0567 | AP3: 1941/0550 | AQ3: 1949/0217 | AR3: 2002/0576 | AS3: 2022/0493 | AT3: 2031/0005 | AU3: 2041/0379 | AV3: 2074/0536 | AW3: 2104/0239 | AX3: 2104/0242 | AY3: 2106/0387 | AZ3: 2131/0599 | BA3: 2141/0003 | BB3: 2219/0516 | BC3: 2224/0382 | BD3: 2251/0022 | BE3: 2259/0397 | BF3: 2290/0178 | BG3: 2309/0236 | BH3: 2315/0042 | BI3: 2425/0225 | BJ3: 2453/0219 | BK3: 2481/0287 | BL3: 2529/0217 | BM3: 2625/0233 | BN3: 2625/0231 | BO3: 2649/0286 | BP3: 2649/0298 | BQ3: 2704/0142
E4: Date | I4: 34806 | J4: 34920 | K4: 35038 | L4: 36026 | M4: 36059 | N4: 36175 | O4: 36175 | P4: 36215 | Q4: 36270 | R4: 36270 | S4: 36270 | T4: 36270 | U4: 36270 | V4: 36270 | W4: 36815 | X4: 36899 | Y4: 36956 | Z4: 36956 | AA4: 36956 | AB4: 37573 | AC4: 37797 | AD4: 38376 | AE4: 38446 | AF4: 38490 | AG4: 38642 | AH4: 38642 | AI4: 38642 | AJ4: 38642 | AK4: 38658 | AL4: 38658 | AM4: 38856 | AN4: 39167 | AO4: 39400 | AP4: 39783 | AQ4: 39874 | AR4: 40238 | AS4: 40336 | AT4: 40374 | AU4: 40438 | AV4: 40665 | AW4: 40869 | AX4: 40869 | AY4: 40886 | AZ4: 41015 | BA4: 41061 | BB4: 41592 | BC4: 41625 | BD4: 41766 | BE4: 41821 | BF4: 42068 | BG4: 42255 | BH4: 42313 | BI4: 43693 | BJ4: 44133 | BK4: 44491 | BL4: 45114 | BM4: 45771 | BN4: 45771 | BO4: 45908 | BP4: 45908 | BQ4: 46178
B5: TRACT ACRES | D5: 120 | E5: Conveyance | H5: ARTI | I5: ARTI | J5: ARTI | K5: ARTI | L5: ARTI | M5: ARTI | N5: ARTI | O5: ARTI | P5: ARTI | Q5: ARTI | R5: ARTI | S5: ARTI | T5: ARTI | U5: ARTI | V5: ARTI | W5: ARTI | X5: ARTI | Y5: ARTI | Z5: ARTI | AA5: ARTI | AB5: ARTI | AC5: ARTI | AD5: ARTI | AE5: ARTI | AF5: ARTI | AG5: ARTI | AH5: ARTI | AI5: ARTI | AJ5: ARTI | AK5: ARTI | AL5: ARTI | AM5: ARTI | AN5: ARTI | AO5: ARTI | AP5: ARTI | AQ5: ARTI | AR5: ARTI | AS5: ARTI | AT5: ARTI | AU5: ARTI | AV5: ARTI | AW5: ARTI | AX5: ARTI | AY5: ARTI | AZ5: ARTI | BA5: ARTI | BB5: ARTI | BC5: ARTI | BD5: ARTI | BE5: ARTI | BF5: ARTI | BG5: ARTI | BH5: ARTI | BI5: ARTI | BJ5: ARTI | BK5: ARTI | BL5: ARTI | BM5: ARTI | BN5: ARTI | BO5: ARTI | BP5: ARTI | BQ5: ARTI
B6: BASE OGL | C6: 120 | D6: Tract 8 | E6: =SUBTOTAL(9,E9:E203) -> 1 | F6: SURFACE | H6: =IF(H7=0,"","RECHECK") | I6: =IF(I7=0,"","RECHECK") | J6: =IF(J7=0,"","RECHECK") | K6: =IF(K7=0,"","RECHECK") | L6: =IF(L7=0,"","RECHECK") | M6: =IF(M7=0,"","RECHECK") | N6: =IF(N7=0,"","RECHECK") | O6: =IF(O7=0,"","RECHECK") | ... AB6: =IF(AB7=0,"","RECHECK") | AE6: =IF(AE7=0,"","RECHECK") | AF6: =IF(AF7=0,"","RECHECK") | AG6: =IF(AG7=0,"","RECHECK") | AH6: =IF(AH7=0,"","RECHECK") | AI6: =IF(AI7=0,"","RECHECK") | AJ6: =IF(AJ7=0,"","RECHECK") | AK6: =IF(AK7=0,"","RECHECK") | AL6: =IF(AL7=0,"","RECHECK") | ... FT6: =IF(FT7=0,"","RECHECK")
G7: =SUBTOTAL(9,G10:G204) -> 0 | H7: =SUBTOTAL(9,H10:H212) -> 0 | I7: =SUBTOTAL(9,I10:I212) -> 0 | J7: =SUBTOTAL(9,J10:J212) -> 0 | K7: =SUBTOTAL(9,K10:K212) -> 0 | L7: =SUBTOTAL(9,L10:L212) -> 0 | M7: =SUBTOTAL(9,M10:M212) -> 0 | N7: =SUBTOTAL(9,N10:N204) -> 0 | O7: =SUBTOTAL(9,O10:O204) -> 0 | P7: =SUBTOTAL(9,P10:P204) -> 0 | Q7: =SUBTOTAL(9,Q10:Q204) -> 0 | R7: =SUBTOTAL(9,R10:R204) -> 0 | S7: =SUBTOTAL(9,S10:S207) -> 0 | T7: =SUBTOTAL(9,T10:T204) -> 0 | U7: =SUBTOTAL(9,U10:U204) -> 0 | V7: =SUBTOTAL(9,V10:V204) -> 0 | W7: =SUBTOTAL(9,W10:W204) -> 0 | X7: =SUBTOTAL(9,X10:X204) -> 0 | Y7: =SUBTOTAL(9,Y10:Y204) -> 0 | Z7: =SUBTOTAL(9,Z10:Z207) -> 0 | AA7: 0 | AB7: =SUBTOTAL(9,AB10:AB209) -> 0 | AC7: =SUBTOTAL(9,AC10:AC212) -> 0 | AD7: =SUBTOTAL(9,AD10:AD206) -> 0 | AE7: =SUBTOTAL(9,AE10:AE206) -> 0 | AF7: =SUBTOTAL(9,AF10:AF206) -> 0 | AG7: =SUBTOTAL(9,AG10:AG206) -> 0 | AH7: =SUBTOTAL(9,AH10:AH207) -> 0 | AI7: =SUBTOTAL(9,AI10:AI203) -> 0 | AJ7: =SUBTOTAL(9,AJ10:AJ207) -> 0 | AK7: =SUBTOTAL(9,AK10:AK206) -> 0 | AL7: =SUBTOTAL(9,AL10:AL204) -> 0 | AM7: =SUBTOTAL(9,AM10:AM204) -> 0 | AN7: =SUBTOTAL(9,AN10:AN204) -> 0 | AO7: =SUBTOTAL(9,AO10:AO204) -> 0 | AP7: =SUBTOTAL(9,AP10:AP204) -> 0 | AQ7: =SUBTOTAL(9,AQ10:AQ204) -> 0 | AR7: =SUBTOTAL(9,AR10:AR204) -> 0 | AS7: =SUBTOTAL(9,AS10:AS204) -> 0 | ... FT7: =SUBTOTAL(9,FT10:FT204) -> 0
A8: NOTES | C8: NET ACRES | D8: OWNERS | E8: TOTAL
H9: 1 | I9: 1 | J9: 1 | K9: 1 | L9: 1 | M9: 1 | N9: 1 | O9: 1 | P9: 1 | Q9: 1 | R9: 1 | S9: 1 | T9: 1 | U9: 1 | V9: 1 | W9: 1 | X9: 1 | Y9: 1 | Z9: 1 | AA9: 1 | AB9: 1 | AC9: 1 | AD9: 1 | AE9: 1 | AF9: 1 | AG9: 1 | AH9: 1 | AI9: 1 | AJ9: 1 | AK9: 1 | AL9: 1 | AM9: 1 | AN9: 1 | AO9: 1 | AP9: 1 | AQ9: 1 | AR9: 1 | AS9: 1 | AT9: 1 | AU9: 1 | AV9: 1 | AW9: 1 | AX9: 1 | AY9: 1 | AZ9: 1 | BA9: 1 | BB9: 1 | BC9: 1 | BD9: 1 | BE9: 1 | BF9: 1 | BG9: 1 | BH9: 1 | BI9: 1 | BJ9: 1 | BK9: 1 | BL9: 1 | BM9: 1 | BN9: 1 | BO9: 1 | BP9: 1 | BQ9: 1
C10: =IFERROR(IF(AND($E10>0,$D10<>"The Public"),$E10/SUMIFS($E$10:$E$90,$E$10:$E$90,">0",$D$10:$D$90,"<>The Public")*$D$5,""),"") | D10: United States of America | E10: {=SUMPRODUCT(H$9:BQ$9,IF(ISNUMBER(H10:BQ10),H10:BQ10,0))} -> 0
C11: =IFERROR(IF(AND($E11>0,$D11<>"The Public"),$E11/SUMIFS($E$10:$E$90,$E$10:$E$90,">0",$D$10:$D$90,"<>The Public")*$D$5,""),"") | D11: Charles T. Kennett | E11: {=SUMPRODUCT(H$9:BQ$9,IF(ISNUMBER(H11:BQ11),H11:BQ11,0))} -> 0
C12: =IFERROR(IF(AND($E12>0,$D12<>"The Public"),$E12/SUMIFS($E$10:$E$90,$E$10:$E$90,">0",$D$10:$D$90,"<>The Public")*$D$5,""),"") | D12: Barbara Bain | E12: {=SUMPRODUCT(H$9:BQ$9,IF(ISNUMBER(H12:BQ12),H12:BQ12,0))} -> 0
C13: =IFERROR(IF(AND($E13>0,$D13<>"The Public"),$E13/SUMIFS($E$10:$E$90,$E$10:$E$90,">0",$D$10:$D$90,"<>The Public")*$D$5,""),"") | D13: Billy Wayne Bain | E13: {=SUMPRODUCT(H$9:BQ$9,IF(ISNUMBER(H13:BQ13),H13:BQ13,0))} -> -1 | AO13: -1
C14: =IFERROR(IF(AND($E14>0,$D14<>"The Public"),$E14/SUMIFS($E$10:$E$90,$E$10:$E$90,">0",$D$10:$D$90,"<>The Public")*$D$5,""),"") -> 9.2307692 | D14: Clarence C. Bain, Trustee | E14: {=SUMPRODUCT(H$9:BQ$9,IF(ISNUMBER(H14:BQ14),H14:BQ14,0))} -> 1 | AC14: 1
C15: =IFERROR(IF(AND($E15>0,$D15<>"The Public"),$E15/SUMIFS($E$10:$E$90,$E$10:$E$90,">0",$D$10:$D$90,"<>The Public")*$D$5,""),"") | D15: Dorothy J. Bain | E15: {=SUMPRODUCT(H$9:BQ$9,IF(ISNUMBER(H15:BQ15),H15:BQ15,0))} -> 0
C16: =IFERROR(IF(AND($E16>0,$D16<>"The Public"),$E16/SUMIFS($E$10:$E$90,$E$10:$E$90,">0",$D$10:$D$90,"<>The Public")*$D$5,""),"") | D16: Alpine Oil and Royalty Co, Inc. | E16: {=SUMPRODUCT(H$9:BQ$9,IF(ISNUMBER(H16:BQ16),H16:BQ16,0))} -> -1 | J16: -1
C17: =IFERROR(IF(AND($E17>0,$D17<>"The Public"),$E17/SUMIFS($E$10:$E$90,$E$10:$E$90,">0",$D$10:$D$90,"<>The Public")*$D$5,""),"") | D17: Melinda McCaul Mulvihill | E17: {=SUMPRODUCT(H$9:BQ$9,IF(ISNUMBER(H17:BQ17),H17:BQ17,0))} -> -1 | J17: 1 | P17: -1 | W17: -1
C18: =IFERROR(IF(AND($E18>0,$D18<>"The Public"),$E18/SUMIFS($E$10:$E$90,$E$10:$E$90,">0",$D$10:$D$90,"<>The Public")*$D$5,""),"") | D18: Wilson, Dwight J. Estate of | E18: {=SUMPRODUCT(H$9:BQ$9,IF(ISNUMBER(H18:BQ18),H18:BQ18,0))} -> -1 | K18: -1
C19: =IFERROR(IF(AND($E19>0,$D19<>"The Public"),$E19/SUMIFS($E$10:$E$90,$E$10:$E$90,">0",$D$10:$D$90,"<>The Public")*$D$5,""),"") | D19: The Public | E19: {=SUMPRODUCT(H$9:BQ$9,IF(ISNUMBER(H19:BQ19),H19:BQ19,0))} -> 4 | K19: 1 | P19: 1 | AO19: 1 | BQ19: 1
C20: =IFERROR(IF(AND($E20>0,$D20<>"The Public"),$E20/SUMIFS($E$10:$E$90,$E$10:$E$90,">0",$D$10:$D$90,"<>The Public")*$D$5,""),"") | D20: Jon T. Williams | E20: {=SUMPRODUCT(H$9:BQ$9,IF(ISNUMBER(H20:BQ20),H20:BQ20,0))} -> 0
C21: =IFERROR(IF(AND($E21>0,$D21<>"The Public"),$E21/SUMIFS($E$10:$E$90,$E$10:$E$90,">0",$D$10:$D$90,"<>The Public")*$D$5,""),"") | D21: Rogene E. Williams | E21: {=SUMPRODUCT(H$9:BQ$9,IF(ISNUMBER(H21:BQ21),H21:BQ21,0))} -> 0
C22: =IFERROR(IF(AND($E22>0,$D22<>"The Public"),$E22/SUMIFS($E$10:$E$90,$E$10:$E$90,">0",$D$10:$D$90,"<>The Public")*$D$5,""),"") | D22: Jon T. and Rogene E. Williams Trust | E22: {=SUMPRODUCT(H$9:BQ$9,IF(ISNUMBER(H22:BQ22),H22:BQ22,0))} -> 0
C23: =IFERROR(IF(AND($E23>0,$D23<>"The Public"),$E23/SUMIFS($E$10:$E$90,$E$10:$E$90,">0",$D$10:$D$90,"<>The Public")*$D$5,""),"") | D23: Jan A. Schroff | E23: {=SUMPRODUCT(H$9:BQ$9,IF(ISNUMBER(H23:BQ23),H23:BQ23,0))} -> 0
C24: =IFERROR(IF(AND($E24>0,$D24<>"The Public"),$E24/SUMIFS($E$10:$E$90,$E$10:$E$90,">0",$D$10:$D$90,"<>The Public")*$D$5,""),"") | D24: Jan A. Schroff, Trustee | E24: {=SUMPRODUCT(H$9:BQ$9,IF(ISNUMBER(H24:BQ24),H24:BQ24,0))} -> 0
C25: =IFERROR(IF(AND($E25>0,$D25<>"The Public"),$E25/SUMIFS($E$10:$E$90,$E$10:$E$90,">0",$D$10:$D$90,"<>The Public")*$D$5,""),"") | D25: David Slobin | E25: {=SUMPRODUCT(H$9:BQ$9,IF(ISNUMBER(H25:BQ25),H25:BQ25,0))} -> -2 | N25: -1 | O25: -1
C26: =IFERROR(IF(AND($E26>0,$D26<>"The Public"),$E26/SUMIFS($E$10:$E$90,$E$10:$E$90,">0",$D$10:$D$90,"<>The Public")*$D$5,""),"") -> 18.461538 | D26: Myron Slobin | E26: {=SUMPRODUCT(H$9:BQ$9,IF(ISNUMBER(H26:BQ26),H26:BQ26,0))} -> 2 | N26: 1 | O26: 1
C27: =IFERROR(IF(AND($E27>0,$D27<>"The Public"),$E27/SUMIFS($E$10:$E$90,$E$10:$E$90,">0",$D$10:$D$90,"<>The Public")*$D$5,""),"") | D27: Eunice Evelyn Cook | E27: {=SUMPRODUCT(H$9:BQ$9,IF(ISNUMBER(H27:BQ27),H27:BQ27,0))} -> 0
C28: =IFERROR(IF(AND($E28>0,$D28<>"The Public"),$E28/SUMIFS($E$10:$E$90,$E$10:$E$90,">0",$D$10:$D$90,"<>The Public")*$D$5,""),"") | D28: Albert E. Fuchs | E28: {=SUMPRODUCT(H$9:BQ$9,IF(ISNUMBER(H28:BQ28),H28:BQ28,0))} -> 0
C29: =IFERROR(IF(AND($E29>0,$D29<>"The Public"),$E29/SUMIFS($E$10:$E$90,$E$10:$E$90,">0",$D$10:$D$90,"<>The Public")*$D$5,""),"") | D29: Aqulla Fuchs | E29: {=SUMPRODUCT(H$9:BQ$9,IF(ISNUMBER(H29:BQ29),H29:BQ29,0))} -> 0
C30: =IFERROR(IF(AND($E30>0,$D30<>"The Public"),$E30/SUMIFS($E$10:$E$90,$E$10:$E$90,">0",$D$10:$D$90,"<>The Public")*$D$5,""),"") | D30: Lola F. Richards | E30: {=SUMPRODUCT(H$9:BQ$9,IF(ISNUMBER(H30:BQ30),H30:BQ30,0))} -> 0
C31: =IFERROR(IF(AND($E31>0,$D31<>"The Public"),$E31/SUMIFS($E$10:$E$90,$E$10:$E$90,">0",$D$10:$D$90,"<>The Public")*$D$5,""),"") | D31: Albert E. Fuchs, Trustee | E31: {=SUMPRODUCT(H$9:BQ$9,IF(ISNUMBER(H31:BQ31),H31:BQ31,0))} -> 0
C32: =IFERROR(IF(AND($E32>0,$D32<>"The Public"),$E32/SUMIFS($E$10:$E$90,$E$10:$E$90,">0",$D$10:$D$90,"<>The Public")*$D$5,""),"") | D32: Ocie H. Fuchs | E32: {=SUMPRODUCT(H$9:BQ$9,IF(ISNUMBER(H32:BQ32),H32:BQ32,0))} -> 0
C33: =IFERROR(IF(AND($E33>0,$D33<>"The Public"),$E33/SUMIFS($E$10:$E$90,$E$10:$E$90,">0",$D$10:$D$90,"<>The Public")*$D$5,""),"") | D33: Mark J. Fuchs | E33: {=SUMPRODUCT(H$9:BQ$9,IF(ISNUMBER(H33:BQ33),H33:BQ33,0))} -> 0
C34: =IFERROR(IF(AND($E34>0,$D34<>"The Public"),$E34/SUMIFS($E$10:$E$90,$E$10:$E$90,">0",$D$10:$D$90,"<>The Public")*$D$5,""),"") | D34: Jessie W. Fuchs | E34: {=SUMPRODUCT(H$9:BQ$9,IF(ISNUMBER(H34:BQ34),H34:BQ34,0))} -> 0
C35: =IFERROR(IF(AND($E35>0,$D35<>"The Public"),$E35/SUMIFS($E$10:$E$90,$E$10:$E$90,">0",$D$10:$D$90,"<>The Public")*$D$5,""),"") | D35: Raymond M. Fuchs | E35: {=SUMPRODUCT(H$9:BQ$9,IF(ISNUMBER(H35:BQ35),H35:BQ35,0))} -> 0
C36: =IFERROR(IF(AND($E36>0,$D36<>"The Public"),$E36/SUMIFS($E$10:$E$90,$E$10:$E$90,">0",$D$10:$D$90,"<>The Public")*$D$5,""),"") | D36: Isa May Smith | E36: {=SUMPRODUCT(H$9:BQ$9,IF(ISNUMBER(H36:BQ36),H36:BQ36,0))} -> 0
C37: =IFERROR(IF(AND($E37>0,$D37<>"The Public"),$E37/SUMIFS($E$10:$E$90,$E$10:$E$90,">0",$D$10:$D$90,"<>The Public")*$D$5,""),"") | D37: Melinda McCaul Mulvihill, Trustee | E37: {=SUMPRODUCT(H$9:BQ$9,IF(ISNUMBER(H37:BQ37),H37:BQ37,0))} -> 0
C38: =IFERROR(IF(AND($E38>0,$D38<>"The Public"),$E38/SUMIFS($E$10:$E$90,$E$10:$E$90,">0",$D$10:$D$90,"<>The Public")*$D$5,""),"") -> 9.2307692 | D38: Stephen M. Criser, Trustee | E38: {=SUMPRODUCT(H$9:BQ$9,IF(ISNUMBER(H38:BQ38),H38:BQ38,0))} -> 1 | W38: 1
C39: =IFERROR(IF(AND($E39>0,$D39<>"The Public"),$E39/SUMIFS($E$10:$E$90,$E$10:$E$90,">0",$D$10:$D$90,"<>The Public")*$D$5,""),"") | D39: William C. Bain Jr. | E39: {=SUMPRODUCT(H$9:BQ$9,IF(ISNUMBER(H39:BQ39),H39:BQ39,0))} -> 0
C40: =IFERROR(IF(AND($E40>0,$D40<>"The Public"),$E40/SUMIFS($E$10:$E$90,$E$10:$E$90,">0",$D$10:$D$90,"<>The Public")*$D$5,""),"") | D40: Donald R. Bain | E40: {=SUMPRODUCT(H$9:BQ$9,IF(ISNUMBER(H40:BQ40),H40:BQ40,0))} -> 0
C41: =IFERROR(IF(AND($E41>0,$D41<>"The Public"),$E41/SUMIFS($E$10:$E$90,$E$10:$E$90,">0",$D$10:$D$90,"<>The Public")*$D$5,""),"") | D41: Melvin F. Bain | E41: {=SUMPRODUCT(H$9:BQ$9,IF(ISNUMBER(H41:BQ41),H41:BQ41,0))} -> -1 | AK41: -1
C42: =IFERROR(IF(AND($E42>0,$D42<>"The Public"),$E42/SUMIFS($E$10:$E$90,$E$10:$E$90,">0",$D$10:$D$90,"<>The Public")*$D$5,""),"") | D42: Peggy J. | E42: {=SUMPRODUCT(H$9:BQ$9,IF(ISNUMBER(H42:BQ42),H42:BQ42,0))} -> 0
C43: =IFERROR(IF(AND($E43>0,$D43<>"The Public"),$E43/SUMIFS($E$10:$E$90,$E$10:$E$90,">0",$D$10:$D$90,"<>The Public")*$D$5,""),"") | D43: Dow C. Bain | E43: {=SUMPRODUCT(H$9:BQ$9,IF(ISNUMBER(H43:BQ43),H43:BQ43,0))} -> 0
C44: =IFERROR(IF(AND($E44>0,$D44<>"The Public"),$E44/SUMIFS($E$10:$E$90,$E$10:$E$90,">0",$D$10:$D$90,"<>The Public")*$D$5,""),"") | D44: Dow C. Bain, Trustee | E44: {=SUMPRODUCT(H$9:BQ$9,IF(ISNUMBER(H44:BQ44),H44:BQ44,0))} -> 0
C45: =IFERROR(IF(AND($E45>0,$D45<>"The Public"),$E45/SUMIFS($E$10:$E$90,$E$10:$E$90,">0",$D$10:$D$90,"<>The Public")*$D$5,""),"") | D45: Edris O. Bain, Trustee | E45: {=SUMPRODUCT(H$9:BQ$9,IF(ISNUMBER(H45:BQ45),H45:BQ45,0))} -> 0
C46: =IFERROR(IF(AND($E46>0,$D46<>"The Public"),$E46/SUMIFS($E$10:$E$90,$E$10:$E$90,">0",$D$10:$D$90,"<>The Public")*$D$5,""),"") | D46: Edris O. Bain | E46: {=SUMPRODUCT(H$9:BQ$9,IF(ISNUMBER(H46:BQ46),H46:BQ46,0))} -> 0
C47: =IFERROR(IF(AND($E47>0,$D47<>"The Public"),$E47/SUMIFS($E$10:$E$90,$E$10:$E$90,">0",$D$10:$D$90,"<>The Public")*$D$5,""),"") | D47: Billy Wayne Bain, Trustee | E47: {=SUMPRODUCT(H$9:BQ$9,IF(ISNUMBER(H47:BQ47),H47:BQ47,0))} -> 0
C48: =IFERROR(IF(AND($E48>0,$D48<>"The Public"),$E48/SUMIFS($E$10:$E$90,$E$10:$E$90,">0",$D$10:$D$90,"<>The Public")*$D$5,""),"") | D48: William Cobal Bain Jr. | E48: {=SUMPRODUCT(H$9:BQ$9,IF(ISNUMBER(H48:BQ48),H48:BQ48,0))} -> 0
C49: =IFERROR(IF(AND($E49>0,$D49<>"The Public"),$E49/SUMIFS($E$10:$E$90,$E$10:$E$90,">0",$D$10:$D$90,"<>The Public")*$D$5,""),"") | D49: Deeanne Browning | E49: {=SUMPRODUCT(H$9:BQ$9,IF(ISNUMBER(H49:BQ49),H49:BQ49,0))} -> -1 | AC49: -1
C50: =IFERROR(IF(AND($E50>0,$D50<>"The Public"),$E50/SUMIFS($E$10:$E$90,$E$10:$E$90,">0",$D$10:$D$90,"<>The Public")*$D$5,""),"") | D50: Darrell E. Hamilton | E50: {=SUMPRODUCT(H$9:BQ$9,IF(ISNUMBER(H50:BQ50),H50:BQ50,0))} -> -1 | BQ50: -1
C51: =IFERROR(IF(AND($E51>0,$D51<>"The Public"),$E51/SUMIFS($E$10:$E$90,$E$10:$E$90,">0",$D$10:$D$90,"<>The Public")*$D$5,""),"") | D51: S | E51: {=SUMPRODUCT(H$9:BQ$9,IF(ISNUMBER(H51:BQ51),H51:BQ51,0))} -> 0
C52: =IFERROR(IF(AND($E52>0,$D52<>"The Public"),$E52/SUMIFS($E$10:$E$90,$E$10:$E$90,">0",$D$10:$D$90,"<>The Public")*$D$5,""),"") | D52: Clarence Bain, Trustee | E52: {=SUMPRODUCT(H$9:BQ$9,IF(ISNUMBER(H52:BQ52),H52:BQ52,0))} -> 0
C53: =IFERROR(IF(AND($E53>0,$D53<>"The Public"),$E53/SUMIFS($E$10:$E$90,$E$10:$E$90,">0",$D$10:$D$90,"<>The Public")*$D$5,""),"") | D53: Norbert J. Co-prsnl Repres Dickman | E53: {=SUMPRODUCT(H$9:BQ$9,IF(ISNUMBER(H53:BQ53),H53:BQ53,0))} -> 0
C54: =IFERROR(IF(AND($E54>0,$D54<>"The Public"),$E54/SUMIFS($E$10:$E$90,$E$10:$E$90,">0",$D$10:$D$90,"<>The Public")*$D$5,""),"") | D54: Robe | E54: {=SUMPRODUCT(H$9:BQ$9,IF(ISNUMBER(H54:BQ54),H54:BQ54,0))} -> 0
C55: =IFERROR(IF(AND($E55>0,$D55<>"The Public"),$E55/SUMIFS($E$10:$E$90,$E$10:$E$90,">0",$D$10:$D$90,"<>The Public")*$D$5,""),"") | D55: Fasken Land and Minerals, Ltd. | E55: {=SUMPRODUCT(H$9:BQ$9,IF(ISNUMBER(H55:BQ55),H55:BQ55,0))} -> 0
C56: =IFERROR(IF(AND($E56>0,$D56<>"The Public"),$E56/SUMIFS($E$10:$E$90,$E$10:$E$90,">0",$D$10:$D$90,"<>The Public")*$D$5,""),"") | D56: John William Bain | E56: {=SUMPRODUCT(H$9:BQ$9,IF(ISNUMBER(H56:BQ56),H56:BQ56,0))} -> 0
C57: =IFERROR(IF(AND($E57>0,$D57<>"The Public"),$E57/SUMIFS($E$10:$E$90,$E$10:$E$90,">0",$D$10:$D$90,"<>The Public")*$D$5,""),"") | D57: G. & T. Partnership | E57: {=SUMPRODUCT(H$9:BQ$9,IF(ISNUMBER(H57:BQ57),H57:BQ57,0))} -> 0
C58: =IFERROR(IF(AND($E58>0,$D58<>"The Public"),$E58/SUMIFS($E$10:$E$90,$E$10:$E$90,">0",$D$10:$D$90,"<>The Public")*$D$5,""),"") | D58: Laura Snyder Robertson | E58: {=SUMPRODUCT(H$9:BQ$9,IF(ISNUMBER(H58:BQ58),H58:BQ58,0))} -> 0
C59: =IFERROR(IF(AND($E59>0,$D59<>"The Public"),$E59/SUMIFS($E$10:$E$90,$E$10:$E$90,">0",$D$10:$D$90,"<>The Public")*$D$5,""),"") | D59: James M. Robertson | E59: {=SUMPRODUCT(H$9:BQ$9,IF(ISNUMBER(H59:BQ59),H59:BQ59,0))} -> 0
C60: =IFERROR(IF(AND($E60>0,$D60<>"The Public"),$E60/SUMIFS($E$10:$E$90,$E$10:$E$90,">0",$D$10:$D$90,"<>The Public")*$D$5,""),"") | D60: Rose E. Robertson | E60: {=SUMPRODUCT(H$9:BQ$9,IF(ISNUMBER(H60:BQ60),H60:BQ60,0))} -> 0
C61: =IFERROR(IF(AND($E61>0,$D61<>"The Public"),$E61/SUMIFS($E$10:$E$90,$E$10:$E$90,">0",$D$10:$D$90,"<>The Public")*$D$5,""),"") | D61: Charlotte F. Willert | E61: {=SUMPRODUCT(H$9:BQ$9,IF(ISNUMBER(H61:BQ61),H61:BQ61,0))} -> -1 | AG61: -1
C62: =IFERROR(IF(AND($E62>0,$D62<>"The Public"),$E62/SUMIFS($E$10:$E$90,$E$10:$E$90,">0",$D$10:$D$90,"<>The Public")*$D$5,""),"") -> 46.153846 | D62: Mare Oil Company | E62: {=SUMPRODUCT(H$9:BQ$9,IF(ISNUMBER(H62:BQ62),H62:BQ62,0))} -> 5 | AG62: 1 | AH62: 1 | AI62: 1 | AJ62: 1 | AT62: 1
C63: =IFERROR(IF(AND($E63>0,$D63<>"The Public"),$E63/SUMIFS($E$10:$E$90,$E$10:$E$90,">0",$D$10:$D$90,"<>The Public")*$D$5,""),"") | D63: Peggy J. Brawner | E63: {=SUMPRODUCT(H$9:BQ$9,IF(ISNUMBER(H63:BQ63),H63:BQ63,0))} -> -1 | AH63: -1
C64: =IFERROR(IF(AND($E64>0,$D64<>"The Public"),$E64/SUMIFS($E$10:$E$90,$E$10:$E$90,">0",$D$10:$D$90,"<>The Public")*$D$5,""),"") | D64: Leona I. Degrande | E64: {=SUMPRODUCT(H$9:BQ$9,IF(ISNUMBER(H64:BQ64),H64:BQ64,0))} -> -3 | AI64: -1 | AJ64: -1 | AT64: -1
C65: =IFERROR(IF(AND($E65>0,$D65<>"The Public"),$E65/SUMIFS($E$10:$E$90,$E$10:$E$90,">0",$D$10:$D$90,"<>The Public")*$D$5,""),"") -> 9.2307692 | D65: Omega Royalty Co, LLC | E65: {=SUMPRODUCT(H$9:BQ$9,IF(ISNUMBER(H65:BQ65),H65:BQ65,0))} -> 1 | AK65: 1
C66: =IFERROR(IF(AND($E66>0,$D66<>"The Public"),$E66/SUMIFS($E$10:$E$90,$E$10:$E$90,">0",$D$10:$D$90,"<>The Public")*$D$5,""),"") | D66: Geotech Production, Inc. | E66: {=SUMPRODUCT(H$9:BQ$9,IF(ISNUMBER(H66:BQ66),H66:BQ66,0))} -> 0
C67: =IFERROR(IF(AND($E67>0,$D67<>"The Public"),$E67/SUMIFS($E$10:$E$90,$E$10:$E$90,">0",$D$10:$D$90,"<>The Public")*$D$5,""),"") | D67: Jack B. Searle | E67: {=SUMPRODUCT(H$9:BQ$9,IF(ISNUMBER(H67:BQ67),H67:BQ67,0))} -> 0
C68: =IFERROR(IF(AND($E68>0,$D68<>"The Public"),$E68/SUMIFS($E$10:$E$90,$E$10:$E$90,">0",$D$10:$D$90,"<>The Public")*$D$5,""),"") | D68: Datt Investment Company | E68: {=SUMPRODUCT(H$9:BQ$9,IF(ISNUMBER(H68:BQ68),H68:BQ68,0))} -> 0
C69: =IFERROR(IF(AND($E69>0,$D69<>"The Public"),$E69/SUMIFS($E$10:$E$90,$E$10:$E$90,">0",$D$10:$D$90,"<>The Public")*$D$5,""),"") | D69: Four A. Investments | E69: {=SUMPRODUCT(H$9:BQ$9,IF(ISNUMBER(H69:BQ69),H69:BQ69,0))} -> 0
C70: =IFERROR(IF(AND($E70>0,$D70<>"The Public"),$E70/SUMIFS($E$10:$E$90,$E$10:$E$90,">0",$D$10:$D$90,"<>The Public")*$D$5,""),"") | D70: Lola F. Ricards | E70: {=SUMPRODUCT(H$9:BQ$9,IF(ISNUMBER(H70:BQ70),H70:BQ70,0))} -> -1 | AN70: -1
C71: =IFERROR(IF(AND($E71>0,$D71<>"The Public"),$E71/SUMIFS($E$10:$E$90,$E$10:$E$90,">0",$D$10:$D$90,"<>The Public")*$D$5,""),"") -> 9.2307692 | D71: Arrowhead Resources, Inc. | E71: {=SUMPRODUCT(H$9:BQ$9,IF(ISNUMBER(H71:BQ71),H71:BQ71,0))} -> 1 | AN71: 1
C72: =IFERROR(IF(AND($E72>0,$D72<>"The Public"),$E72/SUMIFS($E$10:$E$90,$E$10:$E$90,">0",$D$10:$D$90,"<>The Public")*$D$5,""),"") | D72: Jan A. Indepedent Executor Schroff | E72: {=SUMPRODUCT(H$9:BQ$9,IF(ISNUMBER(H72:BQ72),H72:BQ72,0))} -> -1 | AP72: -1
C73: =IFERROR(IF(AND($E73>0,$D73<>"The Public"),$E73/SUMIFS($E$10:$E$90,$E$10:$E$90,">0",$D$10:$D$90,"<>The Public")*$D$5,""),"") -> 9.2307692 | D73: Williams, Rogene E. Revocable Living Trust | E73: {=SUMPRODUCT(H$9:BQ$9,IF(ISNUMBER(H73:BQ73),H73:BQ73,0))} -> 1 | AP73: 1
C74: =IFERROR(IF(AND($E74>0,$D74<>"The Public"),$E74/SUMIFS($E$10:$E$90,$E$10:$E$90,">0",$D$10:$D$90,"<>The Public")*$D$5,""),"") -> 9.2307692 | D74: Jesse W. Fuchs | E74: {=SUMPRODUCT(H$9:BQ$9,IF(ISNUMBER(H74:BQ74),H74:BQ74,0))} -> 1 | BD74: 1
C75: =IFERROR(IF(AND($E75>0,$D75<>"The Public"),$E75/SUMIFS($E$10:$E$90,$E$10:$E$90,">0",$D$10:$D$90,"<>The Public")*$D$5,""),"") | D75: Jinkee Acuero Fuchs | E75: {=SUMPRODUCT(H$9:BQ$9,IF(ISNUMBER(H75:BQ75),H75:BQ75,0))} -> 0
C76: =IFERROR(IF(AND($E76>0,$D76<>"The Public"),$E76/SUMIFS($E$10:$E$90,$E$10:$E$90,">0",$D$10:$D$90,"<>The Public")*$D$5,""),"") | D76: Jessica Corry Fuchs | E76: {=SUMPRODUCT(H$9:BQ$9,IF(ISNUMBER(H76:BQ76),H76:BQ76,0))} -> -1 | BD76: -1
C77: =IFERROR(IF(AND($E77>0,$D77<>"The Public"),$E77/SUMIFS($E$10:$E$90,$E$10:$E$90,">0",$D$10:$D$90,"<>The Public")*$D$5,""),"") | D77: Dwight J. Williams | E77: {=SUMPRODUCT(H$9:BQ$9,IF(ISNUMBER(H77:BQ77),H77:BQ77,0))} -> 0
C78: =IFERROR(IF(AND($E78>0,$D78<>"The Public"),$E78/SUMIFS($E$10:$E$90,$E$10:$E$90,">0",$D$10:$D$90,"<>The Public")*$D$5,""),"") | D78: Elizabeth M. Williams | E78: {=SUMPRODUCT(H$9:BQ$9,IF(ISNUMBER(H78:BQ78),H78:BQ78,0))} -> 0
C79: =IFERROR(IF(AND($E79>0,$D79<>"The Public"),$E79/SUMIFS($E$10:$E$90,$E$10:$E$90,">0",$D$10:$D$90,"<>The Public")*$D$5,""),"") | D79: Williams, Dwight J. Revocable Trust | E79: {=SUMPRODUCT(H$9:BQ$9,IF(ISNUMBER(H79:BQ79),H79:BQ79,0))} -> 0
C80: =IFERROR(IF(AND($E80>0,$D80<>"The Public"),$E80/SUMIFS($E$10:$E$90,$E$10:$E$90,">0",$D$10:$D$90,"<>The Public")*$D$5,""),"") | D80: Dwight J. Williams | E80: {=SUMPRODUCT(H$9:BQ$9,IF(ISNUMBER(H80:BQ80),H80:BQ80,0))} -> 0
C81: =IFERROR(IF(AND($E81>0,$D81<>"The Public"),$E81/SUMIFS($E$10:$E$90,$E$10:$E$90,">0",$D$10:$D$90,"<>The Public")*$D$5,""),"") | D81: Wilda W. Jensen | E81: {=SUMPRODUCT(H$9:BQ$9,IF(ISNUMBER(H81:BQ81),H81:BQ81,0))} -> 0
C82: =IFERROR(IF(AND($E82>0,$D82<>"The Public"),$E82/SUMIFS($E$10:$E$90,$E$10:$E$90,">0",$D$10:$D$90,"<>The Public")*$D$5,""),"") | D82: Hans W. Jensen | E82: {=SUMPRODUCT(H$9:BQ$9,IF(ISNUMBER(H82:BQ82),H82:BQ82,0))} -> 0
C83: =IFERROR(IF(AND($E83>0,$D83<>"The Public"),$E83/SUMIFS($E$10:$E$90,$E$10:$E$90,">0",$D$10:$D$90,"<>The Public")*$D$5,""),"") | D83: Tim E. Jensen | E83: {=SUMPRODUCT(H$9:BQ$9,IF(ISNUMBER(H83:BQ83),H83:BQ83,0))} -> 0
C84: =IFERROR(IF(AND($E84>0,$D84<>"The Public"),$E84/SUMIFS($E$10:$E$90,$E$10:$E$90,">0",$D$10:$D$90,"<>The Public")*$D$5,""),"") | D84: Fausta J. Bish | E84: {=SUMPRODUCT(H$9:BQ$9,IF(ISNUMBER(H84:BQ84),H84:BQ84,0))} -> 0
C85: =IFERROR(IF(AND($E85>0,$D85<>"The Public"),$E85/SUMIFS($E$10:$E$90,$E$10:$E$90,">0",$D$10:$D$90,"<>The Public")*$D$5,""),"") | D85: Terry Bish | E85: {=SUMPRODUCT(H$9:BQ$9,IF(ISNUMBER(H85:BQ85),H85:BQ85,0))} -> 0
C86: =IFERROR(IF(AND($E86>0,$D86<>"The Public"),$E86/SUMIFS($E$10:$E$90,$E$10:$E$90,">0",$D$10:$D$90,"<>The Public")*$D$5,""),"") | D86: Tina Bish | E86: {=SUMPRODUCT(H$9:BQ$9,IF(ISNUMBER(H86:BQ86),H86:BQ86,0))} -> 0
C87: =IFERROR(IF(AND($E87>0,$D87<>"The Public"),$E87/SUMIFS($E$10:$E$90,$E$10:$E$90,">0",$D$10:$D$90,"<>The Public")*$D$5,""),"") | D87: D | E87: {=SUMPRODUCT(H$9:BQ$9,IF(ISNUMBER(H87:BQ87),H87:BQ87,0))} -> 0
C88: =IFERROR(IF(AND($E88>0,$D88<>"The Public"),$E88/SUMIFS($E$10:$E$90,$E$10:$E$90,">0",$D$10:$D$90,"<>The Public")*$D$5,""),"") | D88: Bish Family Trust | E88: {=SUMPRODUCT(H$9:BQ$9,IF(ISNUMBER(H88:BQ88),H88:BQ88,0))} -> 0
... C90: =IFERROR(IF(AND($E90>0,$D90<>"The Public"),$E90/SUMIFS($E$10:$E$90,$E$10:$E$90,">0",$D$10:$D$90,"<>The Public")*$D$5,""),"") | D90: 4 A. Investments | E90: {=SUMPRODUCT(H$9:BQ$9,IF(ISNUMBER(H90:BQ90),H90:BQ90,0))} -> 0
C91: TBD | D91: Bryon A. Hetherington | E91: {=SUMPRODUCT(H$9:BQ$9,IF(ISNUMBER(H91:BQ91),H91:BQ91,0))} -> 0
C92: TBD | D92: Bryon A. Hetherington, Trustee | E92: {=SUMPRODUCT(H$9:BQ$9,IF(ISNUMBER(H92:BQ92),H92:BQ92,0))} -> 0
C93: TBD | D93: Hetherin | E93: {=SUMPRODUCT(H$9:BQ$9,IF(ISNUMBER(H93:BQ93),H93:BQ93,0))} -> 0
C94: TBD | D94: Michael L. Bain, Trustee | E94: {=SUMPRODUCT(H$9:BQ$9,IF(ISNUMBER(H94:BQ94),H94:BQ94,0))} -> 0
C95: TBD | D95: William C. Bai | E95: {=SUMPRODUCT(H$9:BQ$9,IF(ISNUMBER(H95:BQ95),H95:BQ95,0))} -> 0
C96: TBD | D96: Paul M. Bain | E96: {=SUMPRODUCT(H$9:BQ$9,IF(ISNUMBER(H96:BQ96),H96:BQ96,0))} -> 1 | AW96: 0.5 | AX96: 0.5
C97: TBD | D97: Myron V. Slobin | E97: {=SUMPRODUCT(H$9:BQ$9,IF(ISNUMBER(H97:BQ97),H97:BQ97,0))} -> -1.5 | AY97: -1 | BA97: 0.5 | BB97: -1
C98: TBD | D98: Brian Herman Kortright | E98: {=SUMPRODUCT(H$9:BQ$9,IF(ISNUMBER(H98:BQ98),H98:BQ98,0))} -> 2 | AY98: 1 | BB98: 1
C99: TBD | D99: Doris Bain | E99: {=SUMPRODUCT(H$9:BQ$9,IF(ISNUMBER(H99:BQ99),H99:BQ99,0))} -> -0.5 | AZ99: -0.5
C100: TBD | D100: Jospeh A. Bain | E100: {=SUMPRODUCT(H$9:BQ$9,IF(ISNUMBER(H100:BQ100),H100:BQ100,0))} -> -0.5 | AZ100: -0.5
C101: TBD | D101: Lighthouse Point, LLC | E101: {=SUMPRODUCT(H$9:BQ$9,IF(ISNUMBER(H101:BQ101),H101:BQ101,0))} -> 0 | AZ101: 1 | BH101: -1
...

Sheet WI 1
E1: Instrument | H1: Assignment | I1: Assignment | J1: Assignment | K1: Assignment | L1: Assignment | M1: Assignment | N1: Assignment | O1: Assignment | P1: Assignment | Q1: Assignment | R1: Assignment | S1: Assignment | T1: Wellbore Assignment | U1: Assignment | V1: Assignment | W1: Assignment | X1: Assignment | Y1: Wellbore Assignment
A2: 1 | B2: TRACT | D2: Lalexander 1-31 wellbore & Sec 31-12N-24W leasehold WI chain — exact WI/NRI TBD | E2: Image Number | H2: 1994-007065 | I2: 2007-008043 | J2: 2016-001883 | K2: 2016-002793 | L2: 2017-000083 | N2: 2019-001779 | O2: 2020-001283 | P2: 2020-001577 | R2: 2021-001561 | S2: 2021-001605 | T2: 2023-003590 | U2: 2024-002310 | V2: 2024-003107 | W2: 2024-004916 | Y2: 2025-006987
B3: DESCRIPTION | E3: Book / Page | H3: 1608/0038 | I3: 1567/0006 | J3: 2343/0001 | K3: 2354/0229 | L3: 2356/0399 | M3: 2385/0072 | N3: 2425/0380 | O3: 2449/0333 | P3: 2452/0235 | Q3: 2455/0446 | R3: 2479/0001 | S3: 2480/0297 | T3: 2542/0413 | U3: 2567/0102 | V3: 2571/0579 | W3: 2584/0149 | X3: 2604/0111 | Y3: 2664/0169
E4: Date | H4: 36600 | I4: 39336 | J4: 42593 | K4: 42719 | L4: 42752 | M4: 43119 | N4: 43698 | O4: 44060 | P4: 44118 | Q4: 44175 | R4: 44463 | S4: 44476 | T4: 45247 | U4: 45401 | V4: 45432 | W4: 45509 | X4: 45642 | Y4: 45975
B5: TRACT ACRES | D5: TBD | E5: Conveyance | H5: ARTI | I5: ARTI | J5: ARTI | K5: ARTI | L5: ARTI | M5: ARTI | N5: ARTI | O5: ARTI | P5: ARTI | Q5: ARTI | R5: ARTI | S5: ARTI | T5: Wellbore | U5: ARTI | V5: ARTI | W5: ARTI | X5: ARTI | Y5: Wellbore
B6: BASE OGL | D6: Working Interest 1 | E6: =SUBTOTAL(9,E9:E163) -> 0 | F6: SURFACE | H6: =IF(H7=0,"","RECHECK") | I6: =IF(I7=0,"","RECHECK") | J6: =IF(J7=0,"","RECHECK") | K6: =IF(K7=0,"","RECHECK") | L6: =IF(L7=0,"","RECHECK") | M6: =IF(M7=0,"","RECHECK") | N6: =IF(N7=0,"","RECHECK") | O6: =IF(O7=0,"","RECHECK") | ... Z6: =IF(Z7=0,"","RECHECK") | AB6: =IF(AB7=0,"","RECHECK") | AC6: =IF(AC7=0,"","RECHECK") | AD6: =IF(AD7=0,"","RECHECK") | AE6: =IF(AE7=0,"","RECHECK") | AF6: =IF(AF7=0,"","RECHECK") | AG6: =IF(AG7=0,"","RECHECK") | AH6: =IF(AH7=0,"","RECHECK") | AI6: =IF(AI7=0,"","RECHECK") | ... FQ6: =IF(FQ7=0,"","RECHECK")
G7: =SUBTOTAL(9,G10:G164) -> 0 | H7: =SUBTOTAL(9,H10:H164) -> 0 | I7: =SUBTOTAL(9,I10:I164) -> 0 | J7: =SUBTOTAL(9,J10:J164) -> 0 | K7: =SUBTOTAL(9,K10:K164) -> 0 | L7: =SUBTOTAL(9,L10:L164) -> 0 | M7: =SUBTOTAL(9,M10:M164) -> 0 | N7: =SUBTOTAL(9,N10:N164) -> 0 | ... FQ7: =SUBTOTAL(9,FQ10:FQ164) -> 0
A8: NOTES | C8: NET ACRES | D8: OWNERS | E8: TOTAL
C10: TBD | D10: R. Michael Lortz | E10: =SUM(G10:HJ10) -> -1 | H10: -1
C11: TBD | D11: Lariat Petroleum, Inc. | E11: =SUM(G11:HJ11) -> 1 | H11: 1
C12: TBD | D12: Ocean Energy, Inc. | E12: =SUM(G12:HJ12) -> -1 | I12: -1
C13: TBD | D13: Ocean Energy Resources, Inc. | E13: =SUM(G13:HJ13) -> 1 | I13: 1
C14: TBD | D14: Devon Energy Production Co. | E14: =SUM(G14:HJ14) -> -1 | J14: -1
C15: TBD | D15: Tecolote Holdings, LLC | E15: =SUM(G15:HJ15) -> 1 | J15: 1
C16: TBD | D16: Hefner Company, Inc. | E16: =SUM(G16:HJ16) -> -1 | K16: -1
C17: TBD | D17: Cheyenne Resources, LLC | E17: =SUM(G17:HJ17) -> 0 | K17: 1 | M17: -1
C18: TBD | D18: Geodyne / Samson | E18: =SUM(G18:HJ18) -> 0
C19: TBD | D19: Fairway Resources III, LLC | E19: =SUM(G19:HJ19) -> 0
C20: TBD | D20: Templar Energy, LLC | E20: =SUM(G20:HJ20) -> 1 | M20: 1
C21: TBD | D21: BHP Billiton Petroleum | E21: =SUM(G21:HJ21) -> -1 | N21: -1
C22: TBD | D22: Cohete Rojo, LLC | E22: =SUM(G22:HJ22) -> 1 | N22: 1
C23: TBD | D23: TE Holdco RP, LLC et al | E23: =SUM(G23:HJ23) -> 0
C24: TBD | D24: Presidio Wab, LLC | E24: =SUM(G24:HJ24) -> 0
C25: TBD | D25: Mustang Fuel Corporation | E25: =SUM(G25:HJ25) -> 0
C26: TBD | D26: Hani Tabally | E26: =SUM(G26:HJ26) -> -1 | Q26: -1
C27: TBD | D27: Santos J. Dominguez | E27: =SUM(G27:HJ27) -> 1 | Q27: 1
C28: TBD | D28: TLW Investments, LLC | E28: =SUM(G28:HJ28) -> -1 | S28: -1
C29: TBD | D29: Cannon Field Minerals Fund, LP | E29: =SUM(G29:HJ29) -> 1 | S29: 1
C30: TBD | D30: Unbridled Resources, LLC | E30: =SUM(G30:HJ30) -> -1 | T30: -1
C31: TBD | D31: MNR ABS Issuer I, LLC | E31: =SUM(G31:HJ31) -> 1 | T31: 1
C32: TBD | D32: Yale Oil Association, Inc. | E32: =SUM(G32:HJ32) -> -1 | U32: -1
C33: TBD | D33: K.C. Production, LLC | E33: =SUM(G33:HJ33) -> 1 | U33: 1
C34: TBD | D34: Greg et al CDX | E34: =SUM(G34:HJ34) -> 0
C35: TBD | D35: Chanas Partners, LLC | E35: =SUM(G35:HJ35) -> -1 | W35: -1
C36: TBD | D36: NWR Mineral Partners, LLC | E36: =SUM(G36:HJ36) -> 1 | W36: 1
C37: TBD | D37: Satherlie 1989 Rev. Trust | E37: =SUM(G37:HJ37) -> 0
C38: TBD | D38: Trison Holdings, LLC | E38: =SUM(G38:HJ38) -> 0
C39: TBD | D39: Presidio Finance, LLC | E39: =SUM(G39:HJ39) -> -1 | Y39: -1
C40: TBD | D40: Martins Empire, LLC | E40: =SUM(G40:HJ40) -> 1 | Y40: 1
D164: If additional Rows are needed,
D165: Insert them prior to the last row listed.
D166: Do NOT COPY the formulas below this line.

Sheet WI 2
A1: WORKING INTEREST 2 — LEASEHOLD SUMMARY (Sec. 31-12N-24W)
A2: All lease data linked live from the OGLs tab by OGL #. Status compares primary-term expiration to today; HBP/production can override — see notes at bottom.
A4: CURRENT TOP LEASES — Silver Oak Natural Resources, LLC (paid-up, 3/16, springing top leases)
A5: OGL # | B5: Book/Page | C5: Lessor (Mineral Owner) | D5: Lessee | E5: Exec Date | F5: Recorded | G5: Term (mo) | H5: Primary Exp | I5: Royalty | J5: Gross Ac | K5: Status | L5: Comments
A6: 292 | B6: =IFERROR(INDEX(OGLs!$E:$E,MATCH($A6,OGLs!$A:$A,0)),"") -> 2693/337 | C6: =IFERROR(INDEX(OGLs!$H:$H,MATCH($A6,OGLs!$A:$A,0)),"") -> James Gerard Buonaccorsi, Carrie Leeann Mitchell, Trustee of The Mitchell Buonaccorsi Living Trust | D6: =IFERROR(INDEX(OGLs!$I:$I,MATCH($A6,OGLs!$A:$A,0)),"") -> Silveroak Natural Resources, LLC | E6: =IFERROR(INDEX(OGLs!$F:$F,MATCH($A6,OGLs!$A:$A,0)),"") -> 46076 | F6: =IFERROR(INDEX(OGLs!$G:$G,MATCH($A6,OGLs!$A:$A,0)),"") -> 46122 | G6: =IFERROR(INDEX(OGLs!$L:$L,MATCH($A6,OGLs!$A:$A,0)),"") -> 36 | H6: =IFERROR(INDEX(OGLs!$O:$O,MATCH($A6,OGLs!$A:$A,0)),"") -> 47172 | I6: =IFERROR(INDEX(OGLs!$Q:$Q,MATCH($A6,OGLs!$A:$A,0)),"") -> 0.1875 | J6: =IFERROR(INDEX(OGLs!$M:$M,MATCH($A6,OGLs!$A:$A,0)),"") -> 0 | K6: =IF($H6="","",IF($H6<TODAY(),"Past primary term","Within primary term")) -> Within primary term | L6: Paid-up top lease (3/16); springing — effective only on prior-lease termination.
A7: 293 | B7: =IFERROR(INDEX(OGLs!$E:$E,MATCH($A7,OGLs!$A:$A,0)),"") -> 2693/345 | C7: =IFERROR(INDEX(OGLs!$H:$H,MATCH($A7,OGLs!$A:$A,0)),"") -> Kevin Johnson Johnson, Trustee of The Kevin Warner Johnson Trust | D7: =IFERROR(INDEX(OGLs!$I:$I,MATCH($A7,OGLs!$A:$A,0)),"") -> Silveroak Natural Resources, LLC | E7: =IFERROR(INDEX(OGLs!$F:$F,MATCH($A7,OGLs!$A:$A,0)),"") -> 46080 | F7: =IFERROR(INDEX(OGLs!$G:$G,MATCH($A7,OGLs!$A:$A,0)),"") -> 46122 | G7: =IFERROR(INDEX(OGLs!$L:$L,MATCH($A7,OGLs!$A:$A,0)),"") -> 60 | H7: =IFERROR(INDEX(OGLs!$O:$O,MATCH($A7,OGLs!$A:$A,0)),"") -> 47906 | I7: =IFERROR(INDEX(OGLs!$Q:$Q,MATCH($A7,OGLs!$A:$A,0)),"") -> 0.1875 | J7: =IFERROR(INDEX(OGLs!$M:$M,MATCH($A7,OGLs!$A:$A,0)),"") -> 0 | K7: =IF($H7="","",IF($H7<TODAY(),"Past primary term","Within primary term")) -> Within primary term | L7: Paid-up top lease (3/16); springing — effective only on prior-lease termination.
A8: 291 | B8: =IFERROR(INDEX(OGLs!$E:$E,MATCH($A8,OGLs!$A:$A,0)),"") -> 2693/349 | C8: =IFERROR(INDEX(OGLs!$H:$H,MATCH($A8,OGLs!$A:$A,0)),"") -> Mark Ashley Daigle, Trustee of The Mark Ashley Daigle Trust | D8: =IFERROR(INDEX(OGLs!$I:$I,MATCH($A8,OGLs!$A:$A,0)),"") -> Silveroak Natural Resources, LLC | E8: =IFERROR(INDEX(OGLs!$F:$F,MATCH($A8,OGLs!$A:$A,0)),"") -> 46076 | F8: =IFERROR(INDEX(OGLs!$G:$G,MATCH($A8,OGLs!$A:$A,0)),"") -> 46122 | G8: =IFERROR(INDEX(OGLs!$L:$L,MATCH($A8,OGLs!$A:$A,0)),"") -> 60 | H8: =IFERROR(INDEX(OGLs!$O:$O,MATCH($A8,OGLs!$A:$A,0)),"") -> 47902 | I8: =IFERROR(INDEX(OGLs!$Q:$Q,MATCH($A8,OGLs!$A:$A,0)),"") -> 0.1875 | J8: =IFERROR(INDEX(OGLs!$M:$M,MATCH($A8,OGLs!$A:$A,0)),"") -> 0 | K8: =IF($H8="","",IF($H8<TODAY(),"Past primary term","Within primary term")) -> Within primary term | L8: Paid-up top lease (3/16); springing — effective only on prior-lease termination.
A9: 290 | B9: =IFERROR(INDEX(OGLs!$E:$E,MATCH($A9,OGLs!$A:$A,0)),"") -> 2697/520 | C9: =IFERROR(INDEX(OGLs!$H:$H,MATCH($A9,OGLs!$A:$A,0)),"") -> Keri Lee Daigle Tucker, Trustee of The Keri Lee Daigle Tucker Trust | D9: =IFERROR(INDEX(OGLs!$I:$I,MATCH($A9,OGLs!$A:$A,0)),"") -> Silver Oak Natural Resources, LLC | E9: =IFERROR(INDEX(OGLs!$F:$F,MATCH($A9,OGLs!$A:$A,0)),"") -> 46070 | F9: =IFERROR(INDEX(OGLs!$G:$G,MATCH($A9,OGLs!$A:$A,0)),"") -> 46143 | G9: =IFERROR(INDEX(OGLs!$L:$L,MATCH($A9,OGLs!$A:$A,0)),"") -> 60 | H9: =IFERROR(INDEX(OGLs!$O:$O,MATCH($A9,OGLs!$A:$A,0)),"") -> 47896 | I9: =IFERROR(INDEX(OGLs!$Q:$Q,MATCH($A9,OGLs!$A:$A,0)),"") -> 0.1875 | J9: =IFERROR(INDEX(OGLs!$M:$M,MATCH($A9,OGLs!$A:$A,0)),"") -> 0 | K9: =IF($H9="","",IF($H9<TODAY(),"Past primary term","Within primary term")) -> Within primary term | L9: Paid-up top lease (3/16); springing — effective only on prior-lease termination.
A10: 294 | B10: =IFERROR(INDEX(OGLs!$E:$E,MATCH($A10,OGLs!$A:$A,0)),"") -> 2697/524 | C10: =IFERROR(INDEX(OGLs!$H:$H,MATCH($A10,OGLs!$A:$A,0)),"") -> Ronald Paul Dold | D10: =IFERROR(INDEX(OGLs!$I:$I,MATCH($A10,OGLs!$A:$A,0)),"") -> Silver Oak Natural Resources, LLC | E10: =IFERROR(INDEX(OGLs!$F:$F,MATCH($A10,OGLs!$A:$A,0)),"") -> 46112 | F10: =IFERROR(INDEX(OGLs!$G:$G,MATCH($A10,OGLs!$A:$A,0)),"") -> 46143 | G10: =IFERROR(INDEX(OGLs!$L:$L,MATCH($A10,OGLs!$A:$A,0)),"") -> 36 | H10: =IFERROR(INDEX(OGLs!$O:$O,MATCH($A10,OGLs!$A:$A,0)),"") -> 47208 | I10: =IFERROR(INDEX(OGLs!$Q:$Q,MATCH($A10,OGLs!$A:$A,0)),"") -> 0.1875 | J10: =IFERROR(INDEX(OGLs!$M:$M,MATCH($A10,OGLs!$A:$A,0)),"") -> 0 | K10: =IF($H10="","",IF($H10<TODAY(),"Past primary term","Within primary term")) -> Within primary term | L10: Paid-up top lease (3/16); springing — effective only on prior-lease termination.
A11: 289 | B11: =IFERROR(INDEX(OGLs!$E:$E,MATCH($A11,OGLs!$A:$A,0)),"") -> 2702/505 | C11: =IFERROR(INDEX(OGLs!$H:$H,MATCH($A11,OGLs!$A:$A,0)),"") -> a/k/a Gena Williams, a/k/a Gena Mitchell Williams, Gena W. Moore | D11: =IFERROR(INDEX(OGLs!$I:$I,MATCH($A11,OGLs!$A:$A,0)),"") -> Silver Oak Natural Resources, LLC | E11: =IFERROR(INDEX(OGLs!$F:$F,MATCH($A11,OGLs!$A:$A,0)),"") -> 46064 | F11: =IFERROR(INDEX(OGLs!$G:$G,MATCH($A11,OGLs!$A:$A,0)),"") -> 46170 | G11: =IFERROR(INDEX(OGLs!$L:$L,MATCH($A11,OGLs!$A:$A,0)),"") -> 60 | H11: =IFERROR(INDEX(OGLs!$O:$O,MATCH($A11,OGLs!$A:$A,0)),"") -> 47890 | I11: =IFERROR(INDEX(OGLs!$Q:$Q,MATCH($A11,OGLs!$A:$A,0)),"") -> 0.1875 | J11: =IFERROR(INDEX(OGLs!$M:$M,MATCH($A11,OGLs!$A:$A,0)),"") -> 0 | K11: =IF($H11="","",IF($H11<TODAY(),"Past primary term","Within primary term")) -> Within primary term | L11: Paid-up top lease (3/16); springing — effective only on prior-lease termination.
A13: HISTORIC LEASEHOLD — OGLs 1–27 (2002–2006; Chesapeake / EOG / Lortz / Jess Harris / Devon / TODCO)
A14: OGL # | B14: Book/Page | C14: Lessor (Mineral Owner) | D14: Lessee | E14: Exec Date | F14: Recorded | G14: Term (mo) | H14: Primary Exp | I14: Royalty | J14: Gross Ac | K14: Status | L14: Comments
A15: 1 | B15: =IFERROR(INDEX(OGLs!$E:$E,MATCH($A15,OGLs!$A:$A,0)),"") -> 1676/377 | C15: =IFERROR(INDEX(OGLs!$H:$H,MATCH($A15,OGLs!$A:$A,0)),"") -> Myron V. Slobin | D15: =IFERROR(INDEX(OGLs!$I:$I,MATCH($A15,OGLs!$A:$A,0)),"") -> Chesapeake Exploration, Ltd. Partnership | E15: =IFERROR(INDEX(OGLs!$F:$F,MATCH($A15,OGLs!$A:$A,0)),"") -> 37347 | F15: =IFERROR(INDEX(OGLs!$G:$G,MATCH($A15,OGLs!$A:$A,0)),"") -> 37372 | G15: =IFERROR(INDEX(OGLs!$L:$L,MATCH($A15,OGLs!$A:$A,0)),"") -> 36 | H15: =IFERROR(INDEX(OGLs!$O:$O,MATCH($A15,OGLs!$A:$A,0)),"") -> 38443 | I15: =IFERROR(INDEX(OGLs!$Q:$Q,MATCH($A15,OGLs!$A:$A,0)),"") -> 0.25 | J15: =IFERROR(INDEX(OGLs!$M:$M,MATCH($A15,OGLs!$A:$A,0)),"") -> 160 | K15: =IF($H15="","",IF($H15<TODAY(),"Past primary term","Within primary term")) -> Past primary term | L15: Primary term expired; HBP / release status unresolved — VERIFY production & releases.
A16: 2 | B16: =IFERROR(INDEX(OGLs!$E:$E,MATCH($A16,OGLs!$A:$A,0)),"") -> 4/61 | C16: =IFERROR(INDEX(OGLs!$H:$H,MATCH($A16,OGLs!$A:$A,0)),"") -> H. E. Rupp, L. M. Rupp | D16: =IFERROR(INDEX(OGLs!$I:$I,MATCH($A16,OGLs!$A:$A,0)),"") -> REO Oil & Gas Company | E16: =IFERROR(INDEX(OGLs!$F:$F,MATCH($A16,OGLs!$A:$A,0)),"") -> 6333 | F16: =IFERROR(INDEX(OGLs!$G:$G,MATCH($A16,OGLs!$A:$A,0)),"") -> 6333 | G16: =IFERROR(INDEX(OGLs!$L:$L,MATCH($A16,OGLs!$A:$A,0)),"") -> 0 | H16: =IFERROR(INDEX(OGLs!$O:$O,MATCH($A16,OGLs!$A:$A,0)),"") -> 0 | I16: =IFERROR(INDEX(OGLs!$Q:$Q,MATCH($A16,OGLs!$A:$A,0)),"") -> 0 | J16: =IFERROR(INDEX(OGLs!$M:$M,MATCH($A16,OGLs!$A:$A,0)),"") -> 0 | K16: =IF($H16="","",IF($H16<TODAY(),"Past primary term","Within primary term")) -> Past primary term | L16: Primary term expired; HBP / release status unresolved — VERIFY production & releases.
A17: 3 | B17: =IFERROR(INDEX(OGLs!$E:$E,MATCH($A17,OGLs!$A:$A,0)),"") -> 4/64 | C17: =IFERROR(INDEX(OGLs!$H:$H,MATCH($A17,OGLs!$A:$A,0)),"") -> M. Hambrook | D17: =IFERROR(INDEX(OGLs!$I:$I,MATCH($A17,OGLs!$A:$A,0)),"") -> REO Oil & Gas Company | E17: =IFERROR(INDEX(OGLs!$F:$F,MATCH($A17,OGLs!$A:$A,0)),"") -> 6333 | F17: =IFERROR(INDEX(OGLs!$G:$G,MATCH($A17,OGLs!$A:$A,0)),"") -> 6333 | G17: =IFERROR(INDEX(OGLs!$L:$L,MATCH($A17,OGLs!$A:$A,0)),"") -> 0 | H17: =IFERROR(INDEX(OGLs!$O:$O,MATCH($A17,OGLs!$A:$A,0)),"") -> 0 | I17: =IFERROR(INDEX(OGLs!$Q:$Q,MATCH($A17,OGLs!$A:$A,0)),"") -> 0 | J17: =IFERROR(INDEX(OGLs!$M:$M,MATCH($A17,OGLs!$A:$A,0)),"") -> 0 | K17: =IF($H17="","",IF($H17<TODAY(),"Past primary term","Within primary term")) -> Past primary term | L17: Primary term expired; HBP / release status unresolved — VERIFY production & releases.
A18: 4 | B18: =IFERROR(INDEX(OGLs!$E:$E,MATCH($A18,OGLs!$A:$A,0)),"") -> 5/320 | C18: =IFERROR(INDEX(OGLs!$H:$H,MATCH($A18,OGLs!$A:$A,0)),"") -> Claude J. McGuire, Herbert E. McGuire | D18: =IFERROR(INDEX(OGLs!$I:$I,MATCH($A18,OGLs!$A:$A,0)),"") -> Empire Gas & Fuel Company | E18: =IFERROR(INDEX(OGLs!$F:$F,MATCH($A18,OGLs!$A:$A,0)),"") -> 6399 | F18: =IFERROR(INDEX(OGLs!$G:$G,MATCH($A18,OGLs!$A:$A,0)),"") -> 6399 | G18: =IFERROR(INDEX(OGLs!$L:$L,MATCH($A18,OGLs!$A:$A,0)),"") -> 0 | H18: =IFERROR(INDEX(OGLs!$O:$O,MATCH($A18,OGLs!$A:$A,0)),"") -> 0 | I18: =IFERROR(INDEX(OGLs!$Q:$Q,MATCH($A18,OGLs!$A:$A,0)),"") -> 0 | J18: =IFERROR(INDEX(OGLs!$M:$M,MATCH($A18,OGLs!$A:$A,0)),"") -> 0 | K18: =IF($H18="","",IF($H18<TODAY(),"Past primary term","Within primary term")) -> Past primary term | L18: Primary term expired; HBP / release status unresolved — VERIFY production & releases.
